Workbook
Name Escalation_rate: [1]!COAL_TransitCost_Esc[#All]

Sheet PeriodMap
A1: Period | B1: Year (FY) | C1: Constraint (s) | D1: Notes
A2: 1 | B2: 2023 | C2: Capacity forced , no retirements, no new-builds | D2: This period is inserted only so that all existing capacity can be built. Using demand from 2024, as PIER2.0 does not provide a demand for 2023
A3: 2 | B3: 2024 | C3: Pipeline capacity forced, no retirements, no new-builds | D3: Demand = PIER2.0 2024, Calibration year for constrained model operation and comparison between Rumi+PIER2.0 & Macro case build on PIER2.0
A4: 3 | B4: 2025 | D4: Demand = PIER2.0 2025, Calibration year for less constraned model operaration
A5: 4 | B5: 2029 | D5: Using demand from 2029, as selected year for period , which spans 2026 to 2031, using constraints from PIER2.0 "8_REF_Unconstr" scenario
A6: 5 | B6: 2034 | D6: Using demand from 2034, as selected year for period, which spans 2032 to 2036, using constraints from PIER2.0 "8_REF_Unconstr" scenario
A7: 6 | B7: 2039 | D7: Using demand from 2039, as selected year for period, which spans 2037 to 2041, using constraints from PIER2.0 "8_REF_Unconstr" scenario
A8: 7 | B8: 2045
A9: 8 | B9: 2055
A10: 9 | B10: 2065
A11: 10 | B11: 2071

Sheet assets_gen_p1
A1: Source::File | G1: PIER::EnergyConvTechnologies.csv | H1: PIER::EnergyConvTechnologies.csv | I1: PIER::EnergyConvTechnologies.csv | J1: PIER::EnergyConvTechnologies.csv | K1: PIER2.0_ECT::EfficiencyCostMaxAnnual.csv | L1: PIER2.0_ECT::EfficiencyCostMaxAnnual.csv | M1: PIER2.0_ECT::EfficiencyCostMaxAnnual.csv | N1: PIER2.0_ECT::EfficiencyCostMaxAnnual.csv | O1: PIER2.0_ECT::EfficiencyCostMaxAnnual.csv | P1: PIER2.0::ECT_Lifetime.csv | Q1: PIER2.0::ECT_OperationalInfo.csv | R1: PIER2.0::ECT_OperationalInfo.csv | S1: PIER2.0::ECT_OperationalInfo.csv | T1: PIER2.0::ECT_LegacyCapacity.csv | V1: PIER2.0::ECT_CapAddBounds.csv | W1: PIER2.0::ECT_CapAddBounds.csv | X1: PIER2.0::PhysicalDerivedCarriers.csv | Y1: PIER2.0::PhysicalCarrierEmissions.csv or for coal, PIER2.0::ECT_EmissionDetails.csv | Z1: PIER2.0::ECT_EfficiencyCostMaxAnnualUF.xlsx | AA1: PIER2.0::ECT_EfficiencyCostMaxAnnualUF.xlsx
A2: PIER2.0 var name | B2: EnergyConvTech | C2: SubGeography1 | F2: ModelGeography | G2: CapacityUnit | H2: InputEC | I2: OutputDEC | J2: AnnualOutputPerUnitCapacity | K2: ConvEff | L2: MaxAnnualUF | M2: FixedCost | N2: FixedCost | O2: VarCost | P2: Lifetime | Q2: SelfCons | R2: MaxRampUpRate | S2: MaxRampDownRate | T2: LegacyCapacity | U2: RetCapacity | V2: MinCapacity | W2: MaxCapacity | X2: DomEnergyDensity | Y2: DomEmissionFactor
A3: Variable | K3: a | L3: b | M3: c | N3: d | O3: e | P3: f | Q3: g | R3: h | S3: i | T3: j | U3: k | V3: l | W3: m | X3: n | Y3: o | Z3: p | AA3: q | AC3: aa | AD3: bb | AE3: cc | AF3: dd | AG3: ee | AH3: ff | AI3: gg | AJ3: hh | AK3: ii | AL3: jj
A4: description | C4: model geography | G4: all units in macro are given in the selected value | H4: energy carrier | I4: energy carrier | J4: model granularity | K4: efficiency of conversion of energy input to output | L4: max utilization factor (over whole year) ** this must be considered alongside availability for technology provided in ECT_Max_CUF.csv to arrive at more granular availability profiles (see code) | M4: annuity on existiting capacity | N4: annuity on new capacity | O4: variable cost per Mt of input energy carrier | P4: lifetime of asset | Q4: % of energy input consumed by technology (not part of output) | T4: legacy/existing | U4: legacy capacity retired | V4: pipeline builds | W4: maximum additions | X4: given | Y4: given | Z4: given Fixed O&M (PIER or assumed), adjusted to 2024Rs from 2020Rs | AA4: given discount rate from PIER2.0 workbook, No adjustment made | AC4: self-consumption adjsuted fuel consumption of generating unit | AD4: self-consumption adjusted efficiency | AE4: doemstic only, need imported ! | AH4: This is without fixed O&M as expected by Macro | AI4: For existing infrastructure this is half operational lifetime, rounded to integer as Macro will fail if given decimal | AL4: legacy capacity
A5: Equation to Macro var | G5: given / 1000 | H5: given | M5: given/1000 | N5: given/1000 | P5: given | R5: given | S5: given | T5: = given*1000 | U5: = given*1000 | V5: = given*1000 | W5: = given*1000 | AA5: = given | AC5: = 1 / a / (1 -g) | AD5: = a - g | AE5: = ( n * conversion_if_not _MT) / (o * conversion_PJ_to_MWh) | AF5: = e / on/ conversion_PJ_to_MWh * aa | AG5: = p * 2020 to 2024 inflator | AH5: = d - ee | AI5: = round ( f / 2 , 0) | AJ5: = q / ( 1-(1+q)^(-gg)) | AK5: = ff / hh | AL5: = j - k
A6: Macro variable | C6: location | D6: type | E6: id | H6: fuel_commodity | M6: annualized_investment_cost | N6: annualized_investment_cost | P6: lifetime of asset | R6: ramp_up_fraction | S6: ramp_down_fraction | V6: min_capcity | W6: max_capacity | AA6: wacc | AC6: fuel_consumption | AD6: discharge_efficiency | AE6: emission_rate | AF6: variable_om_cost | AG6: fixed_om_cost | AH6: annualized_investment_cost | AI6: capital_recovery_period | AJ6: CRF | AK6: investment_cost | AL6: existing_capacity
A7: Unit | K7: % | L7: % | M7: million Rs2024/MW | N7: million Rs2024/MW | O7: million Rs / Mt | P7: years | Q7: % | R7: fraction of capacity | S7: fraction of capacity | T7: MW | U7: MW | V7: MW | W7: MW | X7: PJ/MT or PJ/BCM | Y7: tonnes CO2/MT (no BCM) | Z7: million 2020Rs/year | AA7: % | AC7: MWin per Mwout | AD7: % | AE7: tCO2/MWh input | AF7: millionRs/MWh-elec | AG7: million 2024Rs/year | AH7: million 2024Rs/year | AI7: years | AJ7: % total investment per capital recovery year | AK7: million 2024Rs | AL7: MW
B8: EG_COAL | C8: NR | D8: ThermalPower | E8: coal_legacy | F8: INDIA | G8: MW | H8: THERMAL_COAL | I8: ELECTRICITY | J8: 8760 | K8: 0.3809682 | L8: 0.85 | M8: =11751.5992748699/1000 -> 11.751599 | N8: =13721.03129/1000 -> 13.721031 | O8: 133.52302 | P8: 40 | Q8: 0.066 | R8: 0.3 | S8: 0.3 | T8: =Capacity!B5*1000 -> 67226.539 | U8: 0 | V8: 0 | W8: 0 | X8: =CarriersTech_characteristics!$G$2 -> 17.207188 | Y8: =CarriersTech_characteristics!$H$28*1000 -> 1942097.6 | Z8: 3 | AA8: 0.105 | AC8: =1/K8/(1-Q8) -> 2.8103758 | AE8: =Y8/(X8*Conversions!$D$2) -> 0.40631575 | AF8: =O8/X8/Conversions!$D$2*AC8 -> 7.850786e-05 | AG8: =Z8*Conversions!$D$4 -> 3.7167527 | AH8: =M8-AG8 -> 8.0348465 | AI8: =ROUND(P8/2,0) -> 20 | AJ8: =AA8/(1-(1+AA8)^-AI8) -> 0.12149327 | AK8: =AH8/AJ8 -> 66.13409 | AL8: =T8-U8 -> 67226.539
B9: EG_CCGT | C9: NR | D9: ThermalPower | E9: NG_CCGT_legacy | F9: INDIA | G9: MW | H9: NATGAS | I9: ELECTRICITY | J9: 8760 | K9: 0.40444272 | L9: 0.85 | M9: =8512.22780274884/1000 -> 8.5122278 | N9: =8512.227803/1000 -> 8.5122278 | O9: 0 | P9: 25 | Q9: 0.02 | R9: 0.9 | S9: 0.9 | T9: =Capacity!B6*1000 -> 7330.5467 | U9: 0 | V9: 0 | W9: 0 | X9: =CarriersTech_characteristics!$G$3 -> 37.6812 | Y9: =CarriersTech_characteristics!$H$3*1000 -> 3025024.5 | Z9: 2.9 | AA9: 0.105 | AC9: =1/K9/(1-Q9) -> 2.522998 | AE9: =(Y9*Conversions!$D$3)/(X9*Conversions!$D$2) -> 0.23958587 | AF9: 0 | AG9: =Z9*Conversions!$D$4 -> 3.592861 | AH9: =M9-AG9 -> 4.9193668 | AI9: =ROUND(P9/2,0) -> 13 | AJ9: =AA9/(1-(1+AA9)^-AI9) -> 0.14444512 | AK9: =AH9/AJ9 -> 34.056996 | AL9: =T9-U9 -> 7330.5467
B10: EG_OCGT | C10: NR | D10: ThermalPower | F10: INDIA | G10: MW | H10: NATGAS | I10: ELECTRICITY | J10: 8760 | K10: 0.28070163 | L10: 0.85 | M10: =6679.75064927145/1000 -> 6.6797506 | N10: =6679.750649/1000 -> 6.6797506 | O10: 0 | P10: 25 | Q10: 0.01 | R10: 1 | S10: 1 | T10: =Capacity!B7*1000 -> 0 | U10: 0 | V10: 0 | W10: 0 | X10: =CarriersTech_characteristics!$G$3 -> 37.6812 | Y10: =CarriersTech_characteristics!$H$3*1000 -> 3025024.5 | Z10: 0.7 | AA10: 0.105 | AC10: =1/K10/(1-Q10) -> 3.5984865 | AE10: =(Y10*Conversions!$D$3)/(X10*Conversions!$D$2) -> 0.23958587 | AF10: 0 | AG10: =Z10*Conversions!$D$4 -> 0.86724231 | AH10: =M10-AG10 -> 5.8125083 | AI10: =ROUND(P10/2,0) -> 13 | AJ10: =AA10/(1-(1+AA10)^-AI10) -> 0.14444512 | AK10: =AH10/AJ10 -> 40.240255 | AL10: =T10-U10 -> 0
B11: EG_PHWR | C11: NR | D11: ThermalPower | E11: nuclear_PHWR_legacy | F11: INDIA | G11: MW | H11: ATOMIC | I11: ELECTRICITY | J11: 8760 | K11: 1 | L11: 0.70916667 | M11: =20833.2103478327/1000 -> 20.83321 | N11: =20833.21035/1000 -> 20.83321 | O11: 0 | P11: 40 | Q11: 0.1078 | R11: 0.01 | S11: 0.01 | T11: =Capacity!B8*1000 -> 1603.5184 | U11: 0 | V11: 0 | W11: 0 | Z11: 4.3 | AA11: 0.105 | AC11: =1/K11/(1-Q11) -> 1.1208249 | AF11: 0 | AG11: =Z11*Conversions!$D$4 -> 5.3273456 | AH11: =M11-AG11 -> 15.505865 | AI11: =ROUND(P11/2,0) -> 20 | AJ11: =AA11/(1-(1+AA11)^-AI11) -> 0.12149327 | AK11: =AH11/AJ11 -> 127.62736 | AL11: =T11-U11 -> 1603.5184
B12: EG_SMR | C12: NR | D12: ThermalPower | F12: INDIA | G12: MW | H12: ATOMIC | I12: ELECTRICITY | J12: 8760 | K12: 1 | L12: 0.70916667 | M12: =N12 -> 35.289429 | N12: =35289.42939/1000 -> 35.289429 | O12: 0 | P12: 30 | Q12: 0.05 | R12: 0.01 | S12: 0.01 | T12: =Capacity!B9*1000 -> 0 | U12: 0 | V12: 0 | W12: 0 | Z12: 5 | AA12: 0.105 | AC12: =1/K12/(1-Q12) -> 1.0526316 | AF12: 0 | AG12: =Z12*Conversions!$D$4 -> 6.1945879 | AH12: =M12-AG12 -> 29.094841 | AI12: =ROUND(P12/2,0) -> 15 | AJ12: =AA12/(1-(1+AA12)^-AI12) -> 0.135248 | AK12: =AH12/AJ12 -> 215.12215 | AL12: =T12-U12 -> 0
B13: EG_LH | C13: NR | D13: HydroRes | E13: conventional_hydroelectric_legacy | F13: INDIA | G13: MW | H13: HYDEL | I13: ELECTRICITY | J13: 8760 | K13: 1 | L13: 1 | M13: =19631.8145207228/1000 -> 19.631815 | N13: =19631.81452/1000 -> 19.631815 | O13: 0 | P13: 40 | Q13: 0.006 | R13: 1 | S13: 1 | T13: =Capacity!B10*1000 -> 20527.317 | U13: 0 | V13: 0 | W13: 0 | Z13: 4.4 | AA13: 0.105 | AD13: =K13-Q13 -> 0.994 | AF13: 0 | AG13: =Z13*Conversions!$D$4 -> 5.4512374 | AH13: =M13-AG13 -> 14.180577 | AI13: =ROUND(P13/2,0) -> 20 | AJ13: =AA13/(1-(1+AA13)^-AI13) -> 0.12149327 | AK13: =AH13/AJ13 -> 116.71904 | AL13: =T13-U13 -> 20527.317
B14: EG_SH | C14: NR | D14: HydroRes | E14: conventional_hydroelectric_small_legacy | F14: INDIA | G14: MW | H14: HYDEL | I14: ELECTRICITY | J14: 8760 | K14: 1 | L14: 1 | M14: =11825.3487554956/1000 -> 11.825349 | N14: =11825.34876/1000 -> 11.825349 | O14: 0 | P14: 35 | Q14: 0.01 | R14: 1 | S14: 1 | T14: =Capacity!B11*1000 -> 1698.75 | U14: 0 | V14: 0 | W14: 0 | Z14: =2.4 -> 2.4 | AA14: 0.0835 | AD14: =K14-Q14 -> 0.99 | AF14: 0 | AG14: =Z14*Conversions!$D$4 -> 2.9734022 | AH14: =M14-AG14 -> 8.8519466 | AI14: =ROUND(P14/2,0) -> 18 | AJ14: =AA14/(1-(1+AA14)^-AI14) -> 0.10930622 | AK14: =AH14/AJ14 -> 80.983009 | AL14: =T14-U14 -> 1698.75
B15: EG_BIOMASS | C15: NR | D15: ThermalPower | E15: biomass_legacy | F15: INDIA | G15: MW | H15: BIOMASS_WASTE | I15: ELECTRICITY | J15: 8760 | K15: 0.2388459 | L15: 1 | M15: =7713.45723965334/1000 -> 7.7134572 | N15: =7713.45724/1000 -> 7.7134572 | O15: 0 | P15: 20 | Q15: 0.1 | R15: 0.06 | S15: 0.06 | T15: =Capacity!B12*1000 -> 3357.15 | U15: 0 | V15: 0 | W15: 0 | X15: =CarriersTech_characteristics!$G$7 -> 13.648968 | Y15: =CarriersTech_characteristics!$H$5*1000 -> 1656436.7 | Z15: 1 | AA15: 0.0835 | AC15: =1/K15/(1-Q15) -> 4.652 | AE15: =Y15/(X15*Conversions!$D$2) -> 0.43689545 | AF15: 0 | AG15: =Z15*Conversions!$D$4 -> 1.2389176 | AH15: =M15-AG15 -> 6.4745397 | AI15: =ROUND(P15/2,0) -> 10 | AJ15: =AA15/(1-(1+AA15)^-AI15) -> 0.15139063 | AK15: =AH15/AJ15 -> 42.767109 | AL15: =T15-U15 -> 3357.15
B16: EG_SOLARGM | C16: NR | D16: VRE | E16: solar_GM_legacy | F16: INDIA | G16: MW | H16: SUNLIGHT | I16: ELECTRICITY | J16: 8760 | K16: 1 | L16: 1 | M16: =5630.98419436319/1000 -> 5.6309842 | N16: =5439.705856/1000 -> 5.4397059 | O16: 0 | P16: 25 | Q16: 0.01 | R16: 1 | S16: 1 | T16: =Capacity!B13*1000 -> 19996.724 | U16: 0 | V16: 0 | W16: 0 | Z16: 0.35 | AA16: 0.105 | AC16: 1 | AF16: 0 | AG16: =Z16*Conversions!$D$4 -> 0.43362115 | AH16: =M16-AG16 -> 5.197363 | AI16: =ROUND(P16/2,0) -> 13 | AJ16: =AA16/(1-(1+AA16)^-AI16) -> 0.14444512 | AK16: =AH16/AJ16 -> 35.981577 | AL16: =T16-U16 -> 19996.724
B17: EG_SOLARRF | C17: NR | D17: VRE | E17: solar_RT_legacy | F17: INDIA | G17: MW | H17: SUNLIGHT | I17: ELECTRICITY | J17: 8760 | K17: 1 | L17: 1 | M17: =5542.18769541597/1000 -> 5.5421877 | N17: =5362.133837/1000 -> 5.3621338 | O17: 0 | P17: 25 | Q17: 0.006 | R17: 1 | S17: 1 | T17: =Capacity!B14*1000 -> 2666.3458 | U17: 0 | V17: 0 | W17: 0 | Z17: 0.51 | AA17: 0.104 | AC17: 1 | AF17: 0 | AG17: =Z17*Conversions!$D$4 -> 0.63184797 | AH17: =M17-AG17 -> 4.9103397 | AI17: =ROUND(P17/2,0) -> 13 | AJ17: =AA17/(1-(1+AA17)^-AI17) -> 0.14370863 | AK17: =AH17/AJ17 -> 34.168719 | AL17: =T17-U17 -> 2666.3458
B18: EG_WINDON | C18: NR | D18: VRE | E18: onshore_wind_legacy | F18: INDIA | G18: MW | H18: WIND | I18: ELECTRICITY | J18: 8760 | K18: 1 | L18: 1 | M18: =10659.4302732183/1000 -> 10.65943 | N18: =10586.96446/1000 -> 10.586964 | O18: 0 | P18: 25 | Q18: 0.005 | R18: 1 | S18: 1 | T18: =Capacity!B15*1000 -> 5301.42 | U18: 0 | V18: 0 | W18: 0 | Z18: 0.68 | AA18: 0.105 | AC18: 1 | AF18: 0 | AG18: =Z18*Conversions!$D$4 -> 0.84246396 | AH18: =M18-AG18 -> 9.8169663 | AI18: =ROUND(P18/2,0) -> 13 | AJ18: =AA18/(1-(1+AA18)^-AI18) -> 0.14444512 | AK18: =AH18/AJ18 -> 67.963296 | AL18: =T18-U18 -> 5301.42
B19: EG_WINDOFF | C19: NR | D19: VRE | F19: INDIA | G19: MW | H19: WIND | I19: ELECTRICITY | J19: 8760 | K19: 1 | L19: 1 | M19: =N19 -> 34.540362 | N19: =34540.36167/1000 -> 34.540362 | O19: 0 | P19: 25 | Q19: 0.005 | R19: 1 | S19: 1 | T19: =Capacity!B16*1000 -> 0 | U19: 0 | V19: 0 | W19: 0 | Z19: 6.7 | AA19: 0.112 | AC19: 1 | AF19: 0 | AG19: =Z19*Conversions!$D$4 -> 8.3007478 | AH19: =M19-AG19 -> 26.239614 | AI19: =ROUND(P19/2,0) -> 13 | AJ19: =AA19/(1-(1+AA19)^-AI19) -> 0.14964415 | AK19: =AH19/AJ19 -> 175.34674 | AL19: =T19-U19 -> 0
B20: EG_COAL | C20: NER | D20: ThermalPower | E20: coal_legacy | F20: INDIA | G20: MW | H20: THERMAL_COAL | I20: ELECTRICITY | J20: 8760 | K20: 0.3809682 | L20: 0.85 | M20: =26148.8463751508/1000 -> 26.148846 | N20: =13721.03129/1000 -> 13.721031 | O20: 133.52302 | P20: 40 | Q20: 0.066 | R20: 0.3 | S20: 0.3 | T20: =Capacity!B19*1000 -> 1010.9297 | U20: 0 | V20: 0 | W20: 0 | X20: =CarriersTech_characteristics!$G$2 -> 17.207188 | Y20: =CarriersTech_characteristics!$H$28*1000 -> 1942097.6 | Z20: 3 | AA20: 0.105 | AC20: =1/K20/(1-Q20) -> 2.8103758 | AE20: =Y20/(X20*Conversions!$D$2) -> 0.40631575 | AF20: =O20/CarriersTech_characteristics!$G$2/Conversions!$D$2*AC20 -> 7.850786e-05 | AG20: =Z20*Conversions!$D$4 -> 3.7167527 | AH20: =M20-AG20 -> 22.432094 | AI20: =ROUND(P20/2,0) -> 20 | AJ20: =AA20/(1-(1+AA20)^-AI20) -> 0.12149327 | AK20: =AH20/AJ20 -> 184.63652 | AL20: =T20-U20 -> 1010.9297
B21: EG_CCGT | C21: NER | D21: ThermalPower | E21: NG_CCGT_legacy | F21: INDIA | G21: MW | H21: NATGAS | I21: ELECTRICITY | J21: 8760 | K21: 0.40444272 | L21: 0.85 | M21: =8512.22780274884/1000 -> 8.5122278 | N21: =8512.227803/1000 -> 8.5122278 | O21: 0 | P21: 25 | Q21: 0.02 | R21: 0.9 | S21: 0.9 | T21: =Capacity!B20*1000 -> 2002.4569 | U21: 0 | V21: 0 | W21: 0 | X21: =CarriersTech_characteristics!$G$3 -> 37.6812 | Y21: =CarriersTech_characteristics!$H$3*1000 -> 3025024.5 | Z21: 2.9 | AA21: 0.105 | AC21: =1/K21/(1-Q21) -> 2.522998 | AE21: =(Y21*Conversions!$D$3)/(X21*Conversions!$D$2) -> 0.23958587 | AF21: 0 | AG21: =Z21*Conversions!$D$4 -> 3.592861 | AH21: =M21-AG21 -> 4.9193668 | AI21: =ROUND(P21/2,0) -> 13 | AJ21: =AA21/(1-(1+AA21)^-AI21) -> 0.14444512 | AK21: =AH21/AJ21 -> 34.056996 | AL21: =T21-U21 -> 2002.4569
B22: EG_OCGT | C22: NER | D22: ThermalPower | F22: INDIA | G22: MW | H22: NATGAS | I22: ELECTRICITY | J22: 8760 | K22: 0.28070163 | L22: 0.85 | M22: =6679.75064927145/1000 -> 6.6797506 | N22: =6679.750649/1000 -> 6.6797506 | O22: 0 | P22: 25 | Q22: 0.01 | R22: 1 | S22: 1 | T22: =Capacity!B21*1000 -> 0 | U22: 0 | V22: 0 | W22: 0 | X22: =CarriersTech_characteristics!$G$3 -> 37.6812 | Y22: =CarriersTech_characteristics!$H$3*1000 -> 3025024.5 | Z22: 0.7 | AA22: 0.105 | AC22: =1/K22/(1-Q22) -> 3.5984865 | AE22: =(Y22*Conversions!$D$3)/(X22*Conversions!$D$2) -> 0.23958587 | AF22: 0 | AG22: =Z22*Conversions!$D$4 -> 0.86724231 | AH22: =M22-AG22 -> 5.8125083 | AI22: =ROUND(P22/2,0) -> 13 | AJ22: =AA22/(1-(1+AA22)^-AI22) -> 0.14444512 | AK22: =AH22/AJ22 -> 40.240255 | AL22: =T22-U22 -> 0
B23: EG_PHWR | C23: NER | D23: ThermalPower | E23: nuclear_PHWR_legacy | F23: INDIA | G23: MW | H23: ATOMIC | I23: ELECTRICITY | J23: 8760 | K23: 1 | L23: 0.70916667 | M23: =20833.2103478327/1000 -> 20.83321 | N23: =20833.21035/1000 -> 20.83321 | O23: 0 | P23: 40 | Q23: 0.1078 | R23: 0.01 | S23: 0.01 | T23: =Capacity!B22*1000 -> 0 | U23: 0 | V23: 0 | W23: 0 | Z23: 4.3 | AA23: 0.105 | AC23: =1/K23/(1-Q23) -> 1.1208249 | AF23: 0 | AG23: =Z23*Conversions!$D$4 -> 5.3273456 | AH23: =M23-AG23 -> 15.505865 | AI23: =ROUND(P23/2,0) -> 20 | AJ23: =AA23/(1-(1+AA23)^-AI23) -> 0.12149327 | AK23: =AH23/AJ23 -> 127.62736 | AL23: =T23-U23 -> 0
B24: EG_SMR | C24: NER | D24: ThermalPower | F24: INDIA | G24: MW | H24: ATOMIC | I24: ELECTRICITY | J24: 8760 | K24: 1 | L24: 0.70916667 | M24: =N24 -> 35.289429 | N24: =35289.42939/1000 -> 35.289429 | O24: 0 | P24: 30 | Q24: 0.05 | R24: 0.01 | S24: 0.01 | T24: =Capacity!B23*1000 -> 0 | U24: 0 | V24: 0 | W24: 0 | Z24: 5 | AA24: 0.105 | AC24: =1/K24/(1-Q24) -> 1.0526316 | AF24: 0 | AG24: =Z24*Conversions!$D$4 -> 6.1945879 | AH24: =M24-AG24 -> 29.094841 | AI24: =ROUND(P24/2,0) -> 15 | AJ24: =AA24/(1-(1+AA24)^-AI24) -> 0.135248 | AK24: =AH24/AJ24 -> 215.12215 | AL24: =T24-U24 -> 0
B25: EG_LH | C25: NER | D25: HydroRes | E25: conventional_hydroelectric_legacy | F25: INDIA | G25: MW | H25: HYDEL | I25: ELECTRICITY | J25: 8760 | K25: 1 | L25: 1 | M25: =19631.8145207228/1000 -> 19.631815 | N25: =19631.81452/1000 -> 19.631815 | O25: 0 | P25: 40 | Q25: 0.006 | R25: 1 | S25: 1 | T25: =Capacity!B24*1000 -> 1842.8253 | U25: 0 | V25: 0 | W25: 0 | Z25: 4.4 | AA25: 0.105 | AD25: =K25-Q25 -> 0.994 | AF25: 0 | AG25: =Z25*Conversions!$D$4 -> 5.4512374 | AH25: =M25-AG25 -> 14.180577 | AI25: =ROUND(P25/2,0) -> 20 | AJ25: =AA25/(1-(1+AA25)^-AI25) -> 0.12149327 | AK25: =AH25/AJ25 -> 116.71904 | AL25: =T25-U25 -> 1842.8253
B26: EG_SH | C26: NER | D26: HydroRes | E26: conventional_hydroelectric_small_legacy | F26: INDIA | G26: MW | H26: HYDEL | I26: ELECTRICITY | J26: 8760 | K26: 1 | L26: 1 | M26: =11825.3487554956/1000 -> 11.825349 | N26: =11825.34876/1000 -> 11.825349 | O26: 0 | P26: 35 | Q26: 0.01 | R26: 1 | S26: 1 | T26: =Capacity!B25*1000 -> 299.35 | U26: 0 | V26: 0 | W26: 0 | Z26: =2.4 -> 2.4 | AA26: 0.0835 | AD26: =K26-Q26 -> 0.99 | AF26: 0 | AG26: =Z26*Conversions!$D$4 -> 2.9734022 | AH26: =M26-AG26 -> 8.8519466 | AI26: =ROUND(P26/2,0) -> 18 | AJ26: =AA26/(1-(1+AA26)^-AI26) -> 0.10930622 | AK26: =AH26/AJ26 -> 80.983009 | AL26: =T26-U26 -> 299.35
B27: EG_BIOMASS | C27: NER | D27: ThermalPower | E27: biomass_legacy | F27: INDIA | G27: MW | H27: BIOMASS_WASTE | I27: ELECTRICITY | J27: 8760 | K27: 0.2388459 | L27: 1 | M27: =7713.45723965334/1000 -> 7.7134572 | N27: =7713.45724/1000 -> 7.7134572 | O27: 0 | P27: 20 | Q27: 0.1 | R27: 0.06 | S27: 0.06 | T27: =Capacity!B26*1000 -> 15.8 | U27: 0 | V27: 0 | W27: 0 | X27: =CarriersTech_characteristics!$G$7 -> 13.648968 | Y27: =CarriersTech_characteristics!$H$5*1000 -> 1656436.7 | Z27: 1 | AA27: 0.0835 | AC27: =1/K27/(1-Q27) -> 4.652 | AE27: =Y27/(X27*Conversions!$D$2) -> 0.43689545 | AF27: 0 | AG27: =Z27*Conversions!$D$4 -> 1.2389176 | AH27: =M27-AG27 -> 6.4745397 | AI27: =ROUND(P27/2,0) -> 10 | AJ27: =AA27/(1-(1+AA27)^-AI27) -> 0.15139063 | AK27: =AH27/AJ27 -> 42.767109 | AL27: =T27-U27 -> 15.8
B28: EG_SOLARGM | C28: NER | D28: VRE | E28: solar_GM_legacy | F28: INDIA | G28: MW | H28: SUNLIGHT | I28: ELECTRICITY | J28: 8760 | K28: 1 | L28: 1 | M28: =5630.98419436319/1000 -> 5.6309842 | N28: =5439.705856/1000 -> 5.4397059 | O28: 0 | P28: 25 | Q28: 0.01 | R28: 1 | S28: 1 | T28: =Capacity!B27*1000 -> 171.48962 | U28: 0 | V28: 0 | W28: 0 | Z28: 0.35 | AA28: 0.105 | AC28: 1 | AF28: 0 | AG28: =Z28*Conversions!$D$4 -> 0.43362115 | AH28: =M28-AG28 -> 5.197363 | AI28: =ROUND(P28/2,0) -> 13 | AJ28: =AA28/(1-(1+AA28)^-AI28) -> 0.14444512 | AK28: =AH28/AJ28 -> 35.981577 | AL28: =T28-U28 -> 171.48962
B29: EG_SOLARRF | C29: NER | D29: VRE | E29: solar_RT_legacy | F29: INDIA | G29: MW | H29: SUNLIGHT | I29: ELECTRICITY | J29: 8760 | K29: 1 | L29: 1 | M29: =5542.18769541597/1000 -> 5.5421877 | N29: =5362.133837/1000 -> 5.3621338 | O29: 0 | P29: 25 | Q29: 0.006 | R29: 1 | S29: 1 | T29: =Capacity!B28*1000 -> 67.610378 | U29: 0 | V29: 0 | W29: 0 | Z29: 0.51 | AA29: 0.104 | AC29: 1 | AF29: 0 | AG29: =Z29*Conversions!$D$4 -> 0.63184797 | AH29: =M29-AG29 -> 4.9103397 | AI29: =ROUND(P29/2,0) -> 13 | AJ29: =AA29/(1-(1+AA29)^-AI29) -> 0.14370863 | AK29: =AH29/AJ29 -> 34.168719 | AL29: =T29-U29 -> 67.610378
B30: EG_WINDON | C30: NER | D30: VRE | E30: onshore_wind_legacy | F30: INDIA | G30: MW | H30: WIND | I30: ELECTRICITY | J30: 8760 | K30: 1 | L30: 1 | M30: =10659.4302732183/1000 -> 10.65943 | N30: =10586.96446/1000 -> 10.586964 | O30: 0 | P30: 25 | Q30: 0.005 | R30: 1 | S30: 1 | T30: =Capacity!B29*1000 -> 0 | U30: 0 | V30: 0 | W30: 0 | Z30: 0.68 | AA30: 0.105 | AC30: 1 | AF30: 0 | AG30: =Z30*Conversions!$D$4 -> 0.84246396 | AH30: =M30-AG30 -> 9.8169663 | AI30: =ROUND(P30/2,0) -> 13 | AJ30: =AA30/(1-(1+AA30)^-AI30) -> 0.14444512 | AK30: =AH30/AJ30 -> 67.963296 | AL30: =T30-U30 -> 0
B31: EG_WINDOFF | C31: NER | D31: VRE | F31: INDIA | G31: MW | H31: WIND | I31: ELECTRICITY | J31: 8760 | K31: 1 | L31: 1 | M31: =N31 -> 34.540362 | N31: =34540.36167/1000 -> 34.540362 | O31: 0 | P31: 25 | Q31: 0.005 | R31: 1 | S31: 1 | T31: =Capacity!B30*1000 -> 0 | U31: 0 | V31: 0 | W31: 0 | Z31: 6.7 | AA31: 0.112 | AC31: 1 | AF31: 0 | AG31: =Z31*Conversions!$D$4 -> 8.3007478 | AH31: =M31-AG31 -> 26.239614 | AI31: =ROUND(P31/2,0) -> 13 | AJ31: =AA31/(1-(1+AA31)^-AI31) -> 0.14964415 | AK31: =AH31/AJ31 -> 175.34674 | AL31: =T31-U31 -> 0
B32: EG_COAL | C32: ER | D32: ThermalPower | E32: coal_legacy | F32: INDIA | G32: MW | H32: THERMAL_COAL | I32: ELECTRICITY | J32: 8760 | K32: 0.3809682 | L32: 0.85 | M32: =6514.90571684157/1000 -> 6.5149057 | N32: =13721.03129/1000 -> 13.721031 | O32: 133.52302 | P32: 40 | Q32: 0.066 | R32: 0.3 | S32: 0.3 | T32: =Capacity!B33*1000 -> 41729.904 | U32: 0 | V32: 0 | W32: 0 | X32: =CarriersTech_characteristics!$G$2 -> 17.207188 | Y32: =CarriersTech_characteristics!$H$28*1000 -> 1942097.6 | Z32: 3 | AA32: 0.105 | AC32: =1/K32/(1-Q32) -> 2.8103758 | AE32: =Y32/(X32*Conversions!$D$2) -> 0.40631575 | AF32: =O32/CarriersTech_characteristics!$G$2/Conversions!$D$2*AC32 -> 7.850786e-05 | AG32: =Z32*Conversions!$D$4 -> 3.7167527 | AH32: =M32-AG32 -> 2.798153 | AI32: =ROUND(P32/2,0) -> 20 | AJ32: =AA32/(1-(1+AA32)^-AI32) -> 0.12149327 | AK32: =AH32/AJ32 -> 23.031342 | AL32: =T32-U32 -> 41729.904
B33: EG_CCGT | C33: ER | D33: ThermalPower | E33: NG_CCGT_legacy | F33: INDIA | G33: MW | H33: NATGAS | I33: ELECTRICITY | J33: 8760 | K33: 0.40444272 | L33: 0.85 | M33: =8512.22780274884/1000 -> 8.5122278 | N33: =8512.227803/1000 -> 8.5122278 | O33: 0 | P33: 25 | Q33: 0.02 | R33: 0.9 | S33: 0.9 | T33: =Capacity!B34*1000 -> 770.80433 | U33: 0 | V33: 0 | W33: 0 | X33: =CarriersTech_characteristics!$G$3 -> 37.6812 | Y33: =CarriersTech_characteristics!$H$3*1000 -> 3025024.5 | Z33: 2.9 | AA33: 0.105 | AC33: =1/K33/(1-Q33) -> 2.522998 | AE33: =(Y33*Conversions!$D$3)/(X33*Conversions!$D$2) -> 0.23958587 | AF33: 0 | AG33: =Z33*Conversions!$D$4 -> 3.592861 | AH33: =M33-AG33 -> 4.9193668 | AI33: =ROUND(P33/2,0) -> 13 | AJ33: =AA33/(1-(1+AA33)^-AI33) -> 0.14444512 | AK33: =AH33/AJ33 -> 34.056996 | AL33: =T33-U33 -> 770.80433
B34: EG_OCGT | C34: ER | D34: ThermalPower | F34: INDIA | G34: MW | H34: NATGAS | I34: ELECTRICITY | J34: 8760 | K34: 0.28070163 | L34: 0.85 | M34: =6679.75064927145/1000 -> 6.6797506 | N34: =6679.750649/1000 -> 6.6797506 | O34: 0 | P34: 25 | Q34: 0.01 | R34: 1 | S34: 1 | T34: =Capacity!B35*1000 -> 0 | U34: 0 | V34: 0 | W34: 0 | X34: =CarriersTech_characteristics!$G$3 -> 37.6812 | Y34: =CarriersTech_characteristics!$H$3*1000 -> 3025024.5 | Z34: 0.7 | AA34: 0.105 | AC34: =1/K34/(1-Q34) -> 3.5984865 | AE34: =(Y34*Conversions!$D$3)/(X34*Conversions!$D$2) -> 0.23958587 | AF34: 0 | AG34: =Z34*Conversions!$D$4 -> 0.86724231 | AH34: =M34-AG34 -> 5.8125083 | AI34: =ROUND(P34/2,0) -> 13 | AJ34: =AA34/(1-(1+AA34)^-AI34) -> 0.14444512 | AK34: =AH34/AJ34 -> 40.240255 | AL34: =T34-U34 -> 0
B35: EG_PHWR | C35: ER | D35: ThermalPower | E35: nuclear_PHWR_legacy | F35: INDIA | G35: MW | H35: ATOMIC | I35: ELECTRICITY | J35: 8760 | K35: 1 | L35: 0.70916667 | M35: =20833.2103478327/1000 -> 20.83321 | N35: =20833.21035/1000 -> 20.83321 | O35: 0 | P35: 40 | Q35: 0.1078 | R35: 0.01 | S35: 0.01 | T35: =Capacity!B36*1000 -> 0 | U35: 0 | V35: 0 | W35: 0 | Z35: 4.3 | AA35: 0.105 | AC35: =1/K35/(1-Q35) -> 1.1208249 | AF35: 0 | AG35: =Z35*Conversions!$D$4 -> 5.3273456 | AH35: =M35-AG35 -> 15.505865 | AI35: =ROUND(P35/2,0) -> 20 | AJ35: =AA35/(1-(1+AA35)^-AI35) -> 0.12149327 | AK35: =AH35/AJ35 -> 127.62736 | AL35: =T35-U35 -> 0
B36: EG_SMR | C36: ER | D36: ThermalPower | F36: INDIA | G36: MW | H36: ATOMIC | I36: ELECTRICITY | J36: 8760 | K36: 1 | L36: 0.70916667 | M36: =N36 -> 35.289429 | N36: =35289.42939/1000 -> 35.289429 | O36: 0 | P36: 30 | Q36: 0.05 | R36: 0.01 | S36: 0.01 | T36: =Capacity!B37*1000 -> 0 | U36: 0 | V36: 0 | W36: 0 | Z36: 5 | AA36: 0.105 | AC36: =1/K36/(1-Q36) -> 1.0526316 | AF36: 0 | AG36: =Z36*Conversions!$D$4 -> 6.1945879 | AH36: =M36-AG36 -> 29.094841 | AI36: =ROUND(P36/2,0) -> 15 | AJ36: =AA36/(1-(1+AA36)^-AI36) -> 0.135248 | AK36: =AH36/AJ36 -> 215.12215 | AL36: =T36-U36 -> 0
B37: EG_LH | C37: ER | D37: HydroRes | E37: conventional_hydroelectric_legacy | F37: INDIA | G37: MW | H37: HYDEL | I37: ELECTRICITY | J37: 8760 | K37: 1 | L37: 1 | M37: =19631.8145207228/1000 -> 19.631815 | N37: =19631.81452/1000 -> 19.631815 | O37: 0 | P37: 40 | Q37: 0.006 | R37: 1 | S37: 1 | T37: =Capacity!B38*1000 -> 4198.8603 | U37: 0 | V37: 0 | W37: 0 | Z37: 4.4 | AA37: 0.105 | AD37: =K37-Q37 -> 0.994 | AF37: 0 | AG37: =Z37*Conversions!$D$4 -> 5.4512374 | AH37: =M37-AG37 -> 14.180577 | AI37: =ROUND(P37/2,0) -> 20 | AJ37: =AA37/(1-(1+AA37)^-AI37) -> 0.12149327 | AK37: =AH37/AJ37 -> 116.71904 | AL37: =T37-U37 -> 4198.8603
B38: EG_SH | C38: ER | D38: HydroRes | E38: conventional_hydroelectric_small_legacy | F38: INDIA | G38: MW | H38: HYDEL | I38: ELECTRICITY | J38: 8760 | K38: 1 | L38: 1 | M38: =11825.3487554956/1000 -> 11.825349 | N38: =11825.34876/1000 -> 11.825349 | O38: 0 | P38: 35 | Q38: 0.01 | R38: 1 | S38: 1 | T38: =Capacity!B39*1000 -> 343.99 | U38: 0 | V38: 0 | W38: 0 | Z38: =2.4 -> 2.4 | AA38: 0.0835 | AD38: =K38-Q38 -> 0.99 | AF38: 0 | AG38: =Z38*Conversions!$D$4 -> 2.9734022 | AH38: =M38-AG38 -> 8.8519466 | AI38: =ROUND(P38/2,0) -> 18 | AJ38: =AA38/(1-(1+AA38)^-AI38) -> 0.10930622 | AK38: =AH38/AJ38 -> 80.983009 | AL38: =T38-U38 -> 343.99
B39: EG_BIOMASS | C39: ER | D39: ThermalPower | E39: biomass_legacy | F39: INDIA | G39: MW | H39: BIOMASS_WASTE | I39: ELECTRICITY | J39: 8760 | K39: 0.2388459 | L39: 1 | M39: =7713.45723965334/1000 -> 7.7134572 | N39: =7713.45724/1000 -> 7.7134572 | O39: 0 | P39: 20 | Q39: 0.1 | R39: 0.06 | S39: 0.06 | T39: =Capacity!B40*1000 -> 560.64 | U39: 0 | V39: 0 | W39: 0 | X39: =CarriersTech_characteristics!$G$7 -> 13.648968 | Y39: =CarriersTech_characteristics!$H$5*1000 -> 1656436.7 | Z39: 1 | AA39: 0.0835 | AC39: =1/K39/(1-Q39) -> 4.652 | AE39: =Y39/(X39*Conversions!$D$2) -> 0.43689545 | AF39: 0 | AG39: =Z39*Conversions!$D$4 -> 1.2389176 | AH39: =M39-AG39 -> 6.4745397 | AI39: =ROUND(P39/2,0) -> 10 | AJ39: =AA39/(1-(1+AA39)^-AI39) -> 0.15139063 | AK39: =AH39/AJ39 -> 42.767109 | AL39: =T39-U39 -> 560.64
B40: EG_SOLARGM | C40: ER | D40: VRE | E40: solar_GM_legacy | F40: INDIA | G40: MW | H40: SUNLIGHT | I40: ELECTRICITY | J40: 8760 | K40: 1 | L40: 1 | M40: =5630.98419436319/1000 -> 5.6309842 | N40: =5439.705856/1000 -> 5.4397059 | O40: 0 | P40: 25 | Q40: 0.01 | R40: 1 | S40: 1 | T40: =Capacity!B41*1000 -> 847.7259 | U40: 0 | V40: 0 | W40: 0 | Z40: 0.35 | AA40: 0.105 | AC40: 1 | AF40: 0 | AG40: =Z40*Conversions!$D$4 -> 0.43362115 | AH40: =M40-AG40 -> 5.197363 | AI40: =ROUND(P40/2,0) -> 13 | AJ40: =AA40/(1-(1+AA40)^-AI40) -> 0.14444512 | AK40: =AH40/AJ40 -> 35.981577 | AL40: =T40-U40 -> 847.7259
B41: EG_SOLARRF | C41: ER | D41: VRE | E41: solar_RT_legacy | F41: INDIA | G41: MW | H41: SUNLIGHT | I41: ELECTRICITY | J41: 8760 | K41: 1 | L41: 1 | M41: =5542.18769541597/1000 -> 5.5421877 | N41: =5362.133837/1000 -> 5.3621338 | O41: 0 | P41: 25 | Q41: 0.006 | R41: 1 | S41: 1 | T41: =Capacity!B42*1000 -> 200.0841 | U41: 0 | V41: 0 | W41: 0 | Z41: 0.51 | AA41: 0.104 | AC41: 1 | AF41: 0 | AG41: =Z41*Conversions!$D$4 -> 0.63184797 | AH41: =M41-AG41 -> 4.9103397 | AI41: =ROUND(P41/2,0) -> 13 | AJ41: =AA41/(1-(1+AA41)^-AI41) -> 0.14370863 | AK41: =AH41/AJ41 -> 34.168719 | AL41: =T41-U41 -> 200.0841
B42: EG_WINDON | C42: ER | D42: VRE | E42: onshore_wind_legacy | F42: INDIA | G42: MW | H42: WIND | I42: ELECTRICITY | J42: 8760 | K42: 1 | L42: 1 | M42: =10659.4302732183/1000 -> 10.65943 | N42: =10586.96446/1000 -> 10.586964 | O42: 0 | P42: 25 | Q42: 0.005 | R42: 1 | S42: 1 | T42: =Capacity!B43*1000 -> 46 | U42: 0 | V42: 0 | W42: 0 | Z42: 0.68 | AA42: 0.105 | AC42: 1 | AF42: 0 | AG42: =Z42*Conversions!$D$4 -> 0.84246396 | AH42: =M42-AG42 -> 9.8169663 | AI42: =ROUND(P42/2,0) -> 13 | AJ42: =AA42/(1-(1+AA42)^-AI42) -> 0.14444512 | AK42: =AH42/AJ42 -> 67.963296 | AL42: =T42-U42 -> 46
B43: EG_WINDOFF | C43: ER | D43: VRE | F43: INDIA | G43: MW | H43: WIND | I43: ELECTRICITY | J43: 8760 | K43: 1 | L43: 1 | M43: =N43 -> 34.540362 | N43: =34540.36167/1000 -> 34.540362 | O43: 0 | P43: 25 | Q43: 0.005 | R43: 1 | S43: 1 | T43: =Capacity!B44*1000 -> 0 | U43: 0 | V43: 0 | W43: 0 | Z43: 6.7 | AA43: 0.112 | AC43: 1 | AF43: 0 | AG43: =Z43*Conversions!$D$4 -> 8.3007478 | AH43: =M43-AG43 -> 26.239614 | AI43: =ROUND(P43/2,0) -> 13 | AJ43: =AA43/(1-(1+AA43)^-AI43) -> 0.14964415 | AK43: =AH43/AJ43 -> 175.34674 | AL43: =T43-U43 -> 0
B44: EG_COAL | C44: WR | D44: ThermalPower | E44: coal_legacy | F44: INDIA | G44: MW | H44: THERMAL_COAL | I44: ELECTRICITY | J44: 8760 | K44: 0.3809682 | L44: 0.85 | M44: =5794.65159561365/1000 -> 5.7946516 | N44: =13721.03129/1000 -> 13.721031 | O44: 133.52302 | P44: 40 | Q44: 0.066 | R44: 0.3 | S44: 0.3 | T44: =Capacity!B47*1000 -> 90475.826 | U44: 0 | V44: 0 | W44: 0 | X44: =CarriersTech_characteristics!$G$2 -> 17.207188 | Y44: =CarriersTech_characteristics!$H$28*1000 -> 1942097.6 | Z44: 3 | AA44: 0.105 | AC44: =1/K44/(1-Q44) -> 2.8103758 | AE44: =Y44/(X44*Conversions!$D$2) -> 0.40631575 | AF44: =O44/CarriersTech_characteristics!$G$2/Conversions!$D$2*AC44 -> 7.850786e-05 | AG44: =Z44*Conversions!$D$4 -> 3.7167527 | AH44: =M44-AG44 -> 2.0778989 | AI44: =ROUND(P44/2,0) -> 20 | AJ44: =AA44/(1-(1+AA44)^-AI44) -> 0.12149327 | AK44: =AH44/AJ44 -> 17.102996 | AL44: =T44-U44 -> 90475.826
B45: EG_CCGT | C45: WR | D45: ThermalPower | E45: NG_CCGT_legacy | F45: INDIA | G45: MW | H45: NATGAS | I45: ELECTRICITY | J45: 8760 | K45: 0.40444272 | L45: 0.85 | M45: =8512.22780274884/1000 -> 8.5122278 | N45: =8512.227803/1000 -> 8.5122278 | O45: 0 | P45: 25 | Q45: 0.02 | R45: 0.9 | S45: 0.9 | T45: =Capacity!B48*1000 -> 13563.175 | U45: 0 | V45: 0 | W45: 0 | X45: =CarriersTech_characteristics!$G$3 -> 37.6812 | Y45: =CarriersTech_characteristics!$H$3*1000 -> 3025024.5 | Z45: 2.9 | AA45: 0.105 | AC45: =1/K45/(1-Q45) -> 2.522998 | AE45: =(Y45*Conversions!$D$3)/(X45*Conversions!$D$2) -> 0.23958587 | AF45: 0 | AG45: =Z45*Conversions!$D$4 -> 3.592861 | AH45: =M45-AG45 -> 4.9193668 | AI45: =ROUND(P45/2,0) -> 13 | AJ45: =AA45/(1-(1+AA45)^-AI45) -> 0.14444512 | AK45: =AH45/AJ45 -> 34.056996 | AL45: =T45-U45 -> 13563.175
B46: EG_OCGT | C46: WR | D46: ThermalPower | F46: INDIA | G46: MW | H46: NATGAS | I46: ELECTRICITY | J46: 8760 | K46: 0.28070163 | L46: 0.85 | M46: =6679.75064927145/1000 -> 6.6797506 | N46: =6679.750649/1000 -> 6.6797506 | O46: 0 | P46: 25 | Q46: 0.01 | R46: 1 | S46: 1 | T46: =Capacity!B49*1000 -> 0 | U46: 0 | V46: 0 | W46: 0 | X46: =CarriersTech_characteristics!$G$3 -> 37.6812 | Y46: =CarriersTech_characteristics!$H$3*1000 -> 3025024.5 | Z46: 0.7 | AA46: 0.105 | AC46: =1/K46/(1-Q46) -> 3.5984865 | AE46: =(Y46*Conversions!$D$3)/(X46*Conversions!$D$2) -> 0.23958587 | AF46: 0 | AG46: =Z46*Conversions!$D$4 -> 0.86724231 | AH46: =M46-AG46 -> 5.8125083 | AI46: =ROUND(P46/2,0) -> 13 | AJ46: =AA46/(1-(1+AA46)^-AI46) -> 0.14444512 | AK46: =AH46/AJ46 -> 40.240255 | AL46: =T46-U46 -> 0
B47: EG_PHWR | C47: WR | D47: ThermalPower | E47: nuclear_PHWR_legacy | F47: INDIA | G47: MW | H47: ATOMIC | I47: ELECTRICITY | J47: 8760 | K47: 1 | L47: 0.70916667 | M47: =20833.2103478327/1000 -> 20.83321 | N47: =20833.21035/1000 -> 20.83321 | O47: 0 | P47: 40 | Q47: 0.1078 | R47: 0.01 | S47: 0.01 | T47: =Capacity!B50*1000 -> 3248.824 | U47: 0 | V47: 0 | W47: 0 | Z47: 4.3 | AA47: 0.105 | AC47: =1/K47/(1-Q47) -> 1.1208249 | AF47: 0 | AG47: =Z47*Conversions!$D$4 -> 5.3273456 | AH47: =M47-AG47 -> 15.505865 | AI47: =ROUND(P47/2,0) -> 20 | AJ47: =AA47/(1-(1+AA47)^-AI47) -> 0.12149327 | AK47: =AH47/AJ47 -> 127.62736 | AL47: =T47-U47 -> 3248.824
B48: EG_SMR | C48: WR | D48: ThermalPower | F48: INDIA | G48: MW | H48: ATOMIC | I48: ELECTRICITY | J48: 8760 | K48: 1 | L48: 0.70916667 | M48: =N48 -> 35.289429 | N48: =35289.42939/1000 -> 35.289429 | O48: 0 | P48: 30 | Q48: 0.05 | R48: 0.01 | S48: 0.01 | T48: =Capacity!B51*1000 -> 0 | U48: 0 | V48: 0 | W48: 0 | Z48: 5 | AA48: 0.105 | AC48: =1/K48/(1-Q48) -> 1.0526316 | AF48: 0 | AG48: =Z48*Conversions!$D$4 -> 6.1945879 | AH48: =M48-AG48 -> 29.094841 | AI48: =ROUND(P48/2,0) -> 15 | AJ48: =AA48/(1-(1+AA48)^-AI48) -> 0.135248 | AK48: =AH48/AJ48 -> 215.12215 | AL48: =T48-U48 -> 0
B49: EG_LH | C49: WR | D49: HydroRes | E49: conventional_hydroelectric_legacy | F49: INDIA | G49: MW | H49: HYDEL | I49: ELECTRICITY | J49: 8760 | K49: 1 | L49: 1 | M49: =19631.8145207228/1000 -> 19.631815 | N49: =19631.81452/1000 -> 19.631815 | O49: 0 | P49: 40 | Q49: 0.006 | R49: 1 | S49: 1 | T49: =Capacity!B52*1000 -> 7753.2156 | U49: 0 | V49: 0 | W49: 0 | Z49: 4.4 | AA49: 0.105 | AD49: =K49-Q49 -> 0.994 | AF49: 0 | AG49: =Z49*Conversions!$D$4 -> 5.4512374 | AH49: =M49-AG49 -> 14.180577 | AI49: =ROUND(P49/2,0) -> 20 | AJ49: =AA49/(1-(1+AA49)^-AI49) -> 0.12149327 | AK49: =AH49/AJ49 -> 116.71904 | AL49: =T49-U49 -> 7753.2156
B50: EG_SH | C50: WR | D50: HydroRes | E50: conventional_hydroelectric_small_legacy | F50: INDIA | G50: MW | H50: HYDEL | I50: ELECTRICITY | J50: 8760 | K50: 1 | L50: 1 | M50: =11825.3487554956/1000 -> 11.825349 | N50: =11825.34876/1000 -> 11.825349 | O50: 0 | P50: 35 | Q50: 0.01 | R50: 1 | S50: 1 | T50: =Capacity!B53*1000 -> 672.48 | U50: 0 | V50: 0 | W50: 0 | Z50: =2.4 -> 2.4 | AA50: 0.0835 | AD50: =K50-Q50 -> 0.99 | AF50: 0 | AG50: =Z50*Conversions!$D$4 -> 2.9734022 | AH50: =M50-AG50 -> 8.8519466 | AI50: =ROUND(P50/2,0) -> 18 | AJ50: =AA50/(1-(1+AA50)^-AI50) -> 0.10930622 | AK50: =AH50/AJ50 -> 80.983009 | AL50: =T50-U50 -> 672.48
B51: EG_BIOMASS | C51: WR | D51: ThermalPower | E51: biomass_legacy | F51: INDIA | G51: MW | H51: BIOMASS_WASTE | I51: ELECTRICITY | J51: 8760 | K51: 0.2388459 | L51: 1 | M51: =7713.45723965334/1000 -> 7.7134572 | N51: =7713.45724/1000 -> 7.7134572 | O51: 0 | P51: 20 | Q51: 0.1 | R51: 0.06 | S51: 0.06 | T51: =Capacity!B54*1000 -> 3161.7 | U51: 0 | V51: 0 | W51: 0 | X51: =CarriersTech_characteristics!$G$7 -> 13.648968 | Y51: =CarriersTech_characteristics!$H$5*1000 -> 1656436.7 | Z51: 1 | AA51: 0.0835 | AC51: =1/K51/(1-Q51) -> 4.652 | AE51: =Y51/(X51*Conversions!$D$2) -> 0.43689545 | AF51: 0 | AG51: =Z51*Conversions!$D$4 -> 1.2389176 | AH51: =M51-AG51 -> 6.4745397 | AI51: =ROUND(P51/2,0) -> 10 | AJ51: =AA51/(1-(1+AA51)^-AI51) -> 0.15139063 | AK51: =AH51/AJ51 -> 42.767109 | AL51: =T51-U51 -> 3161.7
B52: EG_SOLARGM | C52: WR | D52: VRE | E52: solar_GM_legacy | F52: INDIA | G52: MW | H52: SUNLIGHT | I52: ELECTRICITY | J52: 8760 | K52: 1 | L52: 1 | M52: =5630.98419436319/1000 -> 5.6309842 | N52: =5439.705856/1000 -> 5.4397059 | O52: 0 | P52: 25 | Q52: 0.01 | R52: 1 | S52: 1 | T52: =Capacity!B55*1000 -> 13221.936 | U52: 0 | V52: 0 | W52: 0 | Z52: 0.35 | AA52: 0.105 | AC52: 1 | AF52: 0 | AG52: =Z52*Conversions!$D$4 -> 0.43362115 | AH52: =M52-AG52 -> 5.197363 | AI52: =ROUND(P52/2,0) -> 13 | AJ52: =AA52/(1-(1+AA52)^-AI52) -> 0.14444512 | AK52: =AH52/AJ52 -> 35.981577 | AL52: =T52-U52 -> 13221.936
B53: EG_SOLARRF | C53: WR | D53: VRE | E53: solar_RT_legacy | F53: INDIA | G53: MW | H53: SUNLIGHT | I53: ELECTRICITY | J53: 8760 | K53: 1 | L53: 1 | M53: =5542.18769541597/1000 -> 5.5421877 | N53: =5362.133837/1000 -> 5.3621338 | O53: 0 | P53: 25 | Q53: 0.006 | R53: 1 | S53: 1 | T53: =Capacity!B56*1000 -> 4503.404 | U53: 0 | V53: 0 | W53: 0 | Z53: 0.51 | AA53: 0.104 | AC53: 1 | AF53: 0 | AG53: =Z53*Conversions!$D$4 -> 0.63184797 | AH53: =M53-AG53 -> 4.9103397 | AI53: =ROUND(P53/2,0) -> 13 | AJ53: =AA53/(1-(1+AA53)^-AI53) -> 0.14370863 | AK53: =AH53/AJ53 -> 34.168719 | AL53: =T53-U53 -> 4503.404
B54: EG_WINDON | C54: WR | D54: VRE | E54: onshore_wind_legacy | F54: INDIA | G54: MW | H54: WIND | I54: ELECTRICITY | J54: 8760 | K54: 1 | L54: 1 | M54: =10659.4302732183/1000 -> 10.65943 | N54: =10586.96446/1000 -> 10.586964 | O54: 0 | P54: 25 | Q54: 0.005 | R54: 1 | S54: 1 | T54: =Capacity!B57*1000 -> 18661.04 | U54: 0 | V54: 0 | W54: 0 | Z54: 0.68 | AA54: 0.105 | AC54: 1 | AF54: 0 | AG54: =Z54*Conversions!$D$4 -> 0.84246396 | AH54: =M54-AG54 -> 9.8169663 | AI54: =ROUND(P54/2,0) -> 13 | AJ54: =AA54/(1-(1+AA54)^-AI54) -> 0.14444512 | AK54: =AH54/AJ54 -> 67.963296 | AL54: =T54-U54 -> 18661.04
B55: EG_WINDOFF | C55: WR | D55: VRE | F55: INDIA | G55: MW | H55: WIND | I55: ELECTRICITY | J55: 8760 | K55: 1 | L55: 1 | M55: =N55 -> 34.540362 | N55: =34540.36167/1000 -> 34.540362 | O55: 0 | P55: 25 | Q55: 0.005 | R55: 1 | S55: 1 | T55: =Capacity!B58*1000 -> 0 | U55: 0 | V55: 0 | W55: 0 | Z55: 6.7 | AA55: 0.112 | AC55: 1 | AF55: 0 | AG55: =Z55*Conversions!$D$4 -> 8.3007478 | AH55: =M55-AG55 -> 26.239614 | AI55: =ROUND(P55/2,0) -> 13 | AJ55: =AA55/(1-(1+AA55)^-AI55) -> 0.14964415 | AK55: =AH55/AJ55 -> 175.34674 | AL55: =T55-U55 -> 0
B56: EG_COAL | C56: SR | D56: ThermalPower | E56: coal_legacy | F56: INDIA | G56: MW | H56: THERMAL_COAL | I56: ELECTRICITY | J56: 8760 | K56: 0.3809682 | L56: 0.85 | M56: =5822.44460147077/1000 -> 5.8224446 | N56: =13721.03129/1000 -> 13.721031 | O56: 133.52302 | P56: 40 | Q56: 0.066 | R56: 0.3 | S56: 0.3 | T56: =Capacity!B61*1000 -> 63929.271 | U56: 0 | V56: 0 | W56: 0 | X56: =CarriersTech_characteristics!$G$2 -> 17.207188 | Y56: =CarriersTech_characteristics!$H$28*1000 -> 1942097.6 | Z56: 3 | AA56: 0.105 | AC56: =1/K56/(1-Q56) -> 2.8103758 | AE56: =Y56/(X56*Conversions!$D$2) -> 0.40631575 | AF56: =O56/CarriersTech_characteristics!$G$2/Conversions!$D$2*AC56 -> 7.850786e-05 | AG56: =Z56*Conversions!$D$4 -> 3.7167527 | AH56: =M56-AG56 -> 2.1056919 | AI56: =ROUND(P56/2,0) -> 20 | AJ56: =AA56/(1-(1+AA56)^-AI56) -> 0.12149327 | AK56: =AH56/AJ56 -> 17.331758 | AL56: =T56-U56 -> 63929.271
B57: EG_CCGT | C57: SR | D57: ThermalPower | E57: NG_CCGT_legacy | F57: INDIA | G57: MW | H57: NATGAS | I57: ELECTRICITY | J57: 8760 | K57: 0.40444272 | L57: 0.85 | M57: =8512.22780274884/1000 -> 8.5122278 | N57: =8512.227803/1000 -> 8.5122278 | O57: 0 | P57: 25 | Q57: 0.02 | R57: 0.9 | S57: 0.9 | T57: =Capacity!B62*1000 -> 7730.2171 | U57: 0 | V57: 0 | W57: 0 | X57: =CarriersTech_characteristics!$G$3 -> 37.6812 | Y57: =CarriersTech_characteristics!$H$3*1000 -> 3025024.5 | Z57: 2.9 | AA57: 0.105 | AC57: =1/K57/(1-Q57) -> 2.522998 | AE57: =(Y57*Conversions!$D$3)/(X57*Conversions!$D$2) -> 0.23958587 | AF57: 0 | AG57: =Z57*Conversions!$D$4 -> 3.592861 | AH57: =M57-AG57 -> 4.9193668 | AI57: =ROUND(P57/2,0) -> 13 | AJ57: =AA57/(1-(1+AA57)^-AI57) -> 0.14444512 | AK57: =AH57/AJ57 -> 34.056996 | AL57: =T57-U57 -> 7730.2171
B58: EG_OCGT | C58: SR | D58: ThermalPower | F58: INDIA | G58: MW | H58: NATGAS | I58: ELECTRICITY | J58: 8760 | K58: 0.28070163 | L58: 0.85 | M58: =6679.75064927145/1000 -> 6.6797506 | N58: =6679.750649/1000 -> 6.6797506 | O58: 0 | P58: 25 | Q58: 0.01 | R58: 1 | S58: 1 | T58: =Capacity!B63*1000 -> 0 | U58: 0 | V58: 0 | W58: 0 | X58: =CarriersTech_characteristics!$G$3 -> 37.6812 | Y58: =CarriersTech_characteristics!$H$3*1000 -> 3025024.5 | Z58: 0.7 | AA58: 0.105 | AC58: =1/K58/(1-Q58) -> 3.5984865 | AE58: =(Y58*Conversions!$D$3)/(X58*Conversions!$D$2) -> 0.23958587 | AF58: 0 | AG58: =Z58*Conversions!$D$4 -> 0.86724231 | AH58: =M58-AG58 -> 5.8125083 | AI58: =ROUND(P58/2,0) -> 13 | AJ58: =AA58/(1-(1+AA58)^-AI58) -> 0.14444512 | AK58: =AH58/AJ58 -> 40.240255 | AL58: =T58-U58 -> 0
B59: EG_PHWR | C59: SR | D59: ThermalPower | E59: nuclear_PHWR_legacy | F59: INDIA | G59: MW | H59: ATOMIC | I59: ELECTRICITY | J59: 8760 | K59: 1 | L59: 0.70916667 | M59: =20833.2103478327/1000 -> 20.83321 | N59: =20833.21035/1000 -> 20.83321 | O59: 0 | P59: 40 | Q59: 0.1078 | R59: 0.01 | S59: 0.01 | T59: =Capacity!B64*1000 -> 3327.6676 | U59: 0 | V59: 0 | W59: 0 | Z59: 4.3 | AA59: 0.105 | AC59: =1/K59/(1-Q59) -> 1.1208249 | AF59: 0 | AG59: =Z59*Conversions!$D$4 -> 5.3273456 | AH59: =M59-AG59 -> 15.505865 | AI59: =ROUND(P59/2,0) -> 20 | AJ59: =AA59/(1-(1+AA59)^-AI59) -> 0.12149327 | AK59: =AH59/AJ59 -> 127.62736 | AL59: =T59-U59 -> 3327.6676
B60: EG_SMR | C60: SR | D60: ThermalPower | F60: INDIA | G60: MW | H60: ATOMIC | I60: ELECTRICITY | J60: 8760 | K60: 1 | L60: 0.70916667 | M60: =N60 -> 35.289429 | N60: =35289.42939/1000 -> 35.289429 | O60: 0 | P60: 30 | Q60: 0.05 | R60: 0.01 | S60: 0.01 | T60: =Capacity!B65*1000 -> 0 | U60: 0 | V60: 0 | W60: 0 | Z60: 5 | AA60: 0.105 | AC60: =1/K60/(1-Q60) -> 1.0526316 | AF60: 0 | AG60: =Z60*Conversions!$D$4 -> 6.1945879 | AH60: =M60-AG60 -> 29.094841 | AI60: =ROUND(P60/2,0) -> 15 | AJ60: =AA60/(1-(1+AA60)^-AI60) -> 0.135248 | AK60: =AH60/AJ60 -> 215.12215 | AL60: =T60-U60 -> 0
B61: EG_LH | C61: SR | D61: HydroRes | E61: conventional_hydroelectric_legacy | F61: INDIA | G61: MW | H61: HYDEL | I61: ELECTRICITY | J61: 8760 | K61: 1 | L61: 1 | M61: =19631.8145207228/1000 -> 19.631815 | N61: =19631.81452/1000 -> 19.631815 | O61: 0 | P61: 40 | Q61: 0.006 | R61: 1 | S61: 1 | T61: =Capacity!B66*1000 -> 12168.961 | U61: 0 | V61: 0 | W61: 0 | Z61: 4.4 | AA61: 0.105 | AD61: =K61-Q61 -> 0.994 | AF61: 0 | AG61: =Z61*Conversions!$D$4 -> 5.4512374 | AH61: =M61-AG61 -> 14.180577 | AI61: =ROUND(P61/2,0) -> 20 | AJ61: =AA61/(1-(1+AA61)^-AI61) -> 0.12149327 | AK61: =AH61/AJ61 -> 116.71904 | AL61: =T61-U61 -> 12168.961
B62: EG_SH | C62: SR | D62: HydroRes | E62: conventional_hydroelectric_small_legacy | F62: INDIA | G62: MW | H62: HYDEL | I62: ELECTRICITY | J62: 8760 | K62: 1 | L62: 1 | M62: =11825.3487554956/1000 -> 11.825349 | N62: =11825.34876/1000 -> 11.825349 | O62: 0 | P62: 35 | Q62: 0.01 | R62: 1 | S62: 1 | T62: =Capacity!B67*1000 -> 1924.48 | U62: 0 | V62: 0 | W62: 0 | Z62: =2.4 -> 2.4 | AA62: 0.0835 | AD62: =K62-Q62 -> 0.99 | AF62: 0 | AG62: =Z62*Conversions!$D$4 -> 2.9734022 | AH62: =M62-AG62 -> 8.8519466 | AI62: =ROUND(P62/2,0) -> 18 | AJ62: =AA62/(1-(1+AA62)^-AI62) -> 0.10930622 | AK62: =AH62/AJ62 -> 80.983009 | AL62: =T62-U62 -> 1924.48
B63: EG_BIOMASS | C63: SR | D63: ThermalPower | E63: biomass_legacy | F63: INDIA | G63: MW | H63: BIOMASS_WASTE | I63: ELECTRICITY | J63: 8760 | K63: 0.2388459 | L63: 1 | M63: =7713.45723965334/1000 -> 7.7134572 | N63: =7713.45724/1000 -> 7.7134572 | O63: 0 | P63: 20 | Q63: 0.1 | R63: 0.06 | S63: 0.06 | T63: =Capacity!B68*1000 -> 3734.75 | U63: 0 | V63: 0 | W63: 0 | X63: =CarriersTech_characteristics!$G$7 -> 13.648968 | Y63: =CarriersTech_characteristics!$H$5*1000 -> 1656436.7 | Z63: 1 | AA63: 0.0835 | AC63: =1/K63/(1-Q63) -> 4.652 | AE63: =Y63/(X63*Conversions!$D$2) -> 0.43689545 | AF63: 0 | AG63: =Z63*Conversions!$D$4 -> 1.2389176 | AH63: =M63-AG63 -> 6.4745397 | AI63: =ROUND(P63/2,0) -> 10 | AJ63: =AA63/(1-(1+AA63)^-AI63) -> 0.15139063 | AK63: =AH63/AJ63 -> 42.767109 | AL63: =T63-U63 -> 3734.75
B64: EG_SOLARGM | C64: SR | D64: VRE | E64: solar_GM_legacy | F64: INDIA | G64: MW | H64: SUNLIGHT | I64: ELECTRICITY | J64: 8760 | K64: 1 | L64: 1 | M64: =5630.98419436319/1000 -> 5.6309842 | N64: =5439.705856/1000 -> 5.4397059 | O64: 0 | P64: 25 | Q64: 0.01 | R64: 1 | S64: 1 | T64: =Capacity!B69*1000 -> 24128.917 | U64: 0 | V64: 0 | W64: 0 | Z64: 0.35 | AA64: 0.105 | AC64: 1 | AF64: 0 | AG64: =Z64*Conversions!$D$4 -> 0.43362115 | AH64: =M64-AG64 -> 5.197363 | AI64: =ROUND(P64/2,0) -> 13 | AJ64: =AA64/(1-(1+AA64)^-AI64) -> 0.14444512 | AK64: =AH64/AJ64 -> 35.981577 | AL64: =T64-U64 -> 24128.917
B65: EG_SOLARRF | C65: SR | D65: VRE | E65: solar_RT_legacy | F65: INDIA | G65: MW | H65: SUNLIGHT | I65: ELECTRICITY | J65: 8760 | K65: 1 | L65: 1 | M65: =5542.18769541597/1000 -> 5.5421877 | N65: =5362.133837/1000 -> 5.3621338 | O65: 0 | P65: 25 | Q65: 0.006 | R65: 1 | S65: 1 | T65: =Capacity!B70*1000 -> 2030.8232 | U65: 0 | V65: 0 | W65: 0 | Z65: 0.51 | AA65: 0.104 | AC65: 1 | AF65: 0 | AG65: =Z65*Conversions!$D$4 -> 0.63184797 | AH65: =M65-AG65 -> 4.9103397 | AI65: =ROUND(P65/2,0) -> 13 | AJ65: =AA65/(1-(1+AA65)^-AI65) -> 0.14370863 | AK65: =AH65/AJ65 -> 34.168719 | AL65: =T65-U65 -> 2030.8232
B66: EG_WINDON | C66: SR | D66: VRE | E66: onshore_wind_legacy | F66: INDIA | G66: MW | H66: WIND | I66: ELECTRICITY | J66: 8760 | K66: 1 | L66: 1 | M66: =10659.4302732183/1000 -> 10.65943 | N66: =10586.96446/1000 -> 10.586964 | O66: 0 | P66: 25 | Q66: 0.005 | R66: 1 | S66: 1 | T66: =Capacity!B71*1000 -> 22161.37 | U66: 0 | V66: 0 | W66: 0 | Z66: 0.68 | AA66: 0.105 | AC66: 1 | AF66: 0 | AG66: =Z66*Conversions!$D$4 -> 0.84246396 | AH66: =M66-AG66 -> 9.8169663 | AI66: =ROUND(P66/2,0) -> 13 | AJ66: =AA66/(1-(1+AA66)^-AI66) -> 0.14444512 | AK66: =AH66/AJ66 -> 67.963296 | AL66: =T66-U66 -> 22161.37
B67: EG_WINDOFF | C67: SR | D67: VRE | F67: INDIA | G67: MW | H67: WIND | I67: ELECTRICITY | J67: 8760 | K67: 1 | L67: 1 | M67: =N67 -> 34.540362 | N67: =34540.36167/1000 -> 34.540362 | O67: 0 | P67: 25 | Q67: 0.005 | R67: 1 | S67: 1 | T67: =Capacity!B72*1000 -> 0 | U67: 0 | V67: 0 | W67: 0 | Z67: 6.7 | AA67: 0.112 | AC67: 1 | AF67: 0 | AG67: =Z67*Conversions!$D$4 -> 8.3007478 | AH67: =M67-AG67 -> 26.239614 | AI67: =ROUND(P67/2,0) -> 13 | AJ67: =AA67/(1-(1+AA67)^-AI67) -> 0.14964415 | AK67: =AH67/AJ67 -> 175.34674 | AL67: =T67-U67 -> 0
B68: EG_COAL | C68: ALL | D68: ThermalPower | E68: coal_legacy | F68: INDIA | G68: MW | H68: THERMAL_COAL | I68: ELECTRICITY | J68: 8760 | K68: 0.3809682 | N68: =13721.03129/1000 -> 13.721031 | O68: 133.52302 | P68: 40 | Q68: 0.066 | T68: =T8+T20+T32+T44+T56 -> 264372.47 | U68: =U8+U20+U32+U44+U56 -> 0 | V68: =V8+V20+V32+V44+V56 -> 0 | W68: =W8+W20+W32+W44+W56 -> 0 | X68: =CarriersTech_characteristics!$G$2 -> 17.207188 | Y68: =CarriersTech_characteristics!$H$28*1000 -> 1942097.6 | AC68: =1/K68/(1-Q68) -> 2.8103758 | AE68: =Y68/(X68*Conversions!$D$2) -> 0.40631575
B69: EG_CCGT | C69: ALL | D69: ThermalPower | E69: NG_CCGT_legacy | F69: INDIA | G69: MW | H69: NATGAS | I69: ELECTRICITY | J69: 8760 | K69: 0.40444272 | L69: 0.85 | M69: =8512.22780274884/1000 -> 8.5122278 | N69: =8512.227803/1000 -> 8.5122278 | O69: 0 | P69: 25 | Q69: 0.02 | R69: 0.9 | S69: 0.9 | T69: =T9+T21+T33+T45+T57 -> 31397.2 | U69: =U9+U21+U33+U45+U57 -> 0 | V69: =V9+V21+V33+V45+V57 -> 0 | W69: =W9+W21+W33+W45+W57 -> 0 | X69: =CarriersTech_characteristics!$G$3 -> 37.6812 | Y69: =CarriersTech_characteristics!$H$3*1000 -> 3025024.5 | AC69: =1/K69/(1-Q69) -> 2.522998 | AE69: =(Y69*Conversions!$D$3)/(X69*Conversions!$D$2) -> 0.23958587
B70: EG_OCGT | C70: ALL | D70: ThermalPower | F70: INDIA | G70: MW | H70: NATGAS | I70: ELECTRICITY | J70: 8760 | K70: 0.28070163 | L70: 0.85 | M70: =6679.75064927145/1000 -> 6.6797506 | N70: =6679.750649/1000 -> 6.6797506 | O70: 0 | P70: 25 | Q70: 0.01 | R70: 1 | S70: 1 | T70: =T10+T22+T34+T46+T58 -> 0 | U70: =U10+U22+U34+U46+U58 -> 0 | V70: =V10+V22+V34+V46+V58 -> 0 | W70: =W10+W22+W34+W46+W58 -> 0 | X70: =CarriersTech_characteristics!$G$3 -> 37.6812 | Y70: =CarriersTech_characteristics!$H$3*1000 -> 3025024.5 | AC70: =1/K70/(1-Q70) -> 3.5984865 | AE70: =(Y70*Conversions!$D$3)/(X70*Conversions!$D$2) -> 0.23958587
B71: EG_PHWR | C71: ALL | D71: ThermalPower | E71: nuclear_PHWR_legacy | F71: INDIA | G71: MW | H71: ATOMIC | I71: ELECTRICITY | J71: 8760 | K71: 1 | L71: 0.70916667 | M71: =20833.2103478327/1000 -> 20.83321 | N71: =20833.21035/1000 -> 20.83321 | O71: 0 | P71: 40 | Q71: 0.1078 | R71: 0.01 | S71: 0.01 | T71: =T11+T23+T35+T47+T59 -> 8180.01 | U71: =U11+U23+U35+U47+U59 -> 0 | V71: =V11+V23+V35+V47+V59 -> 0 | W71: =W11+W23+W35+W47+W59 -> 0 | AC71: =1/K71/(1-Q71) -> 1.1208249
B72: EG_SMR | C72: ALL | D72: ThermalPower | F72: INDIA | G72: MW | H72: ATOMIC | I72: ELECTRICITY | J72: 8760 | K72: 1 | L72: 0.70916667 | N72: =35289.42939/1000 -> 35.289429 | O72: 0 | P72: 30 | Q72: 0.05 | R72: 0.01 | S72: 0.01 | T72: =T12+T24+T36+T48+T60 -> 0 | U72: =U12+U24+U36+U48+U60 -> 0 | V72: =V12+V24+V36+V48+V60 -> 0 | W72: =W12+W24+W36+W48+W60 -> 0 | AC72: =1/K72/(1-Q72) -> 1.0526316
B73: EG_LH | C73: ALL | D73: HydroRes | E73: conventional_hydroelectric_legacy | F73: INDIA | G73: MW | H73: HYDEL | I73: ELECTRICITY | J73: 8760 | K73: 1 | L73: 1 | M73: =19631.8145207228/1000 -> 19.631815 | N73: =19631.81452/1000 -> 19.631815 | O73: 0 | P73: 40 | Q73: 0.006 | R73: 1 | S73: 1 | T73: =T13+T25+T37+T49+T61 -> 46491.18 | U73: =U13+U25+U37+U49+U61 -> 0 | V73: =V13+V25+V37+V49+V61 -> 0 | W73: =W13+W25+W37+W49+W61 -> 0 | AD73: =K73-Q73 -> 0.994
B74: EG_SH | C74: ALL | D74: HydroRes | E74: conventional_hydroelectric_small_legacy | F74: INDIA | G74: MW | H74: HYDEL | I74: ELECTRICITY | J74: 8760 | K74: 1 | L74: 1 | M74: =11825.3487554956/1000 -> 11.825349 | N74: =11825.34876/1000 -> 11.825349 | O74: 0 | P74: 35 | Q74: 0.01 | R74: 1 | S74: 1 | T74: =T14+T26+T38+T50+T62 -> 4939.05 | U74: =U14+U26+U38+U50+U62 -> 0 | V74: =V14+V26+V38+V50+V62 -> 0 | W74: =W14+W26+W38+W50+W62 -> 0 | AD74: =K74-Q74 -> 0.99
B75: EG_BIOMASS | C75: ALL | D75: ThermalPower | E75: biomass_legacy | F75: INDIA | G75: MW | H75: BIOMASS_WASTE | I75: ELECTRICITY | J75: 8760 | K75: 0.2388459 | L75: 1 | M75: =7713.45723965334/1000 -> 7.7134572 | N75: =7713.45724/1000 -> 7.7134572 | O75: 0 | P75: 20 | Q75: 0.1 | R75: 0.06 | S75: 0.06 | T75: =T15+T27+T39+T51+T63 -> 10830.04 | U75: =U15+U27+U39+U51+U63 -> 0 | V75: =V15+V27+V39+V51+V63 -> 0 | W75: =W15+W27+W39+W51+W63 -> 0 | X75: =CarriersTech_characteristics!$G$7 -> 13.648968 | Y75: =CarriersTech_characteristics!$H$5*1000 -> 1656436.7 | AC75: =1/K75/(1-Q75) -> 4.652 | AE75: =Y75/(X75*Conversions!$D$2) -> 0.43689545
B76: EG_SOLARGM | C76: ALL | D76: VRE | E76: solar_GM_legacy | F76: INDIA | G76: MW | H76: SUNLIGHT | I76: ELECTRICITY | J76: 8760 | K76: 1 | L76: 1 | M76: =5630.98419436319/1000 -> 5.6309842 | N76: =5439.705856/1000 -> 5.4397059 | O76: 0 | P76: 25 | Q76: 0.01 | R76: 1 | S76: 1 | T76: =T16+T28+T40+T52+T64 -> 58366.793 | U76: =U16+U28+U40+U52+U64 -> 0 | V76: =V16+V28+V40+V52+V64 -> 0 | W76: =W16+W28+W40+W52+W64 -> 0 | AC76: 1
B77: EG_SOLARRF | C77: ALL | D77: VRE | E77: solar_RT_legacy | F77: INDIA | G77: MW | H77: SUNLIGHT | I77: ELECTRICITY | J77: 8760 | K77: 1 | L77: 1 | M77: =5542.18769541597/1000 -> 5.5421877 | N77: =5362.133837/1000 -> 5.3621338 | O77: 0 | P77: 25 | Q77: 0.006 | R77: 1 | S77: 1 | T77: =T17+T29+T41+T53+T65 -> 9468.2674 | U77: =U17+U29+U41+U53+U65 -> 0 | V77: =V17+V29+V41+V53+V65 -> 0 | W77: =W17+W29+W41+W53+W65 -> 0 | AC77: 1
B78: EG_WINDON | C78: ALL | D78: VRE | E78: onshore_wind_legacy | F78: INDIA | G78: MW | H78: WIND | I78: ELECTRICITY | J78: 8760 | K78: 1 | L78: 1 | M78: =10659.4302732183/1000 -> 10.65943 | N78: =10586.96446/1000 -> 10.586964 | O78: 0 | P78: 25 | Q78: 0.005 | R78: 1 | S78: 1 | T78: =T18+T30+T42+T54+T66 -> 46169.83 | U78: =U18+U30+U42+U54+U66 -> 0 | V78: =V18+V30+V42+V54+V66 -> 0 | W78: =W18+W30+W42+W54+W66 -> 0 | AC78: 1
B79: EG_WINDOFF | C79: ALL | D79: VRE | F79: INDIA | G79: MW | H79: WIND | I79: ELECTRICITY | J79: 8760 | K79: 1 | L79: 1 | N79: =34540.36167/1000 -> 34.540362 | O79: 0 | P79: 25 | Q79: 0.005 | R79: 1 | S79: 1 | T79: =T19+T31+T43+T55+T67 -> 0 | U79: =U19+U31+U43+U55+U67 -> 0 | V79: =V19+V31+V43+V55+V67 -> 0 | W79: =W19+W31+W43+W55+W67 -> 0 | AC79: 1

Sheet assets_gen_p2
A1: Source::File | G1: PIER::EnergyConvTechnologies.csv | H1: PIER::EnergyConvTechnologies.csv | I1: PIER::EnergyConvTechnologies.csv | J1: PIER::EnergyConvTechnologies.csv | K1: PIER2.0_ECT::EfficiencyCostMaxAnnual.csv | L1: PIER2.0_ECT::EfficiencyCostMaxAnnual.csv | M1: PIER2.0_ECT::EfficiencyCostMaxAnnual.csv | N1: PIER2.0_ECT::EfficiencyCostMaxAnnual.csv | O1: PIER2.0_ECT::EfficiencyCostMaxAnnual.csv | P1: PIER2.0::ECT_Lifetime.csv | Q1: PIER2.0::ECT_OperationalInfo.csv | R1: PIER2.0::ECT_OperationalInfo.csv | S1: PIER2.0::ECT_OperationalInfo.csv | T1: PIER2.0::ECT_LegacyCapacity.csv | V1: PIER2.0::ECT_CapAddBounds.csv | W1: PIER2.0::ECT_CapAddBounds.csv | X1: PIER2.0::PhysicalDerivedCarriers.csv | Y1: PIER2.0::PhysicalCarrierEmissions.csv | Z1: PIER2.0::ECT_EfficiencyCostMaxAnnualUF.xlsx | AA1: PIER2.0::ECT_EfficiencyCostMaxAnnualUF.xlsx
A2: PIER2.0 var name | B2: EnergyConvTech | C2: SubGeography1 | F2: ModelGeography | G2: CapacityUnit | H2: InputEC | I2: OutputDEC | J2: AnnualOutputPerUnitCapacity | K2: ConvEff | L2: MaxAnnualUF | M2: FixedCost | N2: FixedCost | O2: VarCost | P2: Lifetime | Q2: SelfCons | R2: MaxRampUpRate | S2: MaxRampDownRate | T2: LegacyCapacity | U2: RetCapacity | V2: MinCapacity | W2: MaxCapacity | X2: DomEnergyDensity | Y2: DomEmissionFactor
A3: Variable | K3: a | L3: b | M3: c | N3: d | O3: e | P3: f | Q3: g | R3: h | S3: i | T3: j | U3: k | V3: l | W3: m | X3: n | Y3: o | Z3: p | AA3: q | AC3: aa | AD3: bb | AE3: cc | AF3: dd | AG3: ee | AH3: ff | AI3: gg | AJ3: hh | AK3: ii | AL3: jj
A4: description | C4: model geography | G4: all units in macro are given in the selected value | H4: energy carrier | I4: energy carrier | J4: model granularity | K4: efficiency of conversion of energy input to output | L4: max utilization factor (over whole year) ** this must be considered alongside availability for technology provided in ECT_Max_CUF.csv to arrive at more granular availability profiles (see code) | M4: annuity on existiting capacity | N4: annuity on new capacity | O4: variable cost per Mt of input energy carrier | P4: lifetime of asset | Q4: % of energy input consumed by technology (not part of output) | T4: legacy/existing | U4: legacy capacity retired | V4: pipeline builds | W4: maximum additions | X4: given | Y4: given | Z4: given Fixed O&M (PIER or assumed), adjusted to 2024Rs from 2020Rs | AA4: given discount rate from PIER2.0 workbook, No adjustment made | AC4: self-consumption adjsuted fuel consumption of generating unit | AD4: self-consumption adjusted efficiency | AE4: doemstic only, need imported ! | AH4: This is without fixed O&M as expected by Macro | AI4: For existing infrastructure this is half operational lifetime, rounded to integer as Macro will fail if given decimal | AL4: legacy capacity
A5: Equation to Macro var | G5: given / 1000 | H5: given | M5: given/1000 | N5: given/1000 | P5: given | R5: given | S5: given | T5: = given*1000 | U5: = given*1000 | V5: = given*1000 | W5: = given*1000 | AA5: = given | AC5: = 1 / a / (1 -g) | AD5: = a - g | AE5: = ( n * conversion_if_not _MT) / (o * conversion_PJ_to_MWh) | AF5: = e / on/ conversion_PJ_to_MWh * aa | AG5: = p * 2020 to 2024 inflator | AH5: = d - ee | AI5: = round ( f / 2 , 0) | AJ5: = q / ( 1-(1+q)^(-gg)) | AK5: = ff / hh | AL5: = j - k
A6: Macro variable | C6: location | D6: type | E6: id | H6: fuel_commodity | M6: annualized_investment_cost | N6: annualized_investment_cost | P6: lifetime of asset | R6: ramp_up_fraction | S6: ramp_down_fraction | V6: min_capcity | W6: max_capacity | AA6: wacc | AC6: fuel_consumption | AD6: discharge_efficiency | AE6: emission_rate | AF6: variable_om_cost | AG6: fixed_om_cost | AH6: annualized_investment_cost | AI6: capital_recovery_period | AJ6: CRF | AK6: investment_cost | AL6: existing_capacity
A7: Unit | K7: % | L7: % | M7: million Rs2024/MW | N7: million Rs2024/MW | O7: million Rs / Mt | P7: years | Q7: % | R7: fraction of capacity | S7: fraction of capacity | T7: MW | U7: MW | V7: MW | W7: MW | X7: PJ/MT or PJ/BCM | Y7: tonnes CO2/MT (no BCM) | Z7: million 2020Rs/year | AA7: % | AC7: MWin per Mwout | AD7: % | AE7: tCO2/MWh input | AF7: millionRs/MWh-elec | AG7: million 2024Rs/year | AH7: million 2024Rs/year | AI7: years | AJ7: % total investment per capital recovery year | AK7: million 2024Rs | AL7: MW
B8: EG_COAL | C8: NR | D8: ThermalPower | E8: coal | F8: INDIA | G8: MW | H8: THERMAL_COAL | I8: ELECTRICITY | J8: 8760 | K8: 0.3809682 | L8: 0.85 | M8: =11751.5992748699/1000 -> 11.751599 | N8: =13721.03129/1000 -> 13.721031 | O8: 133.52302 | P8: 40 | Q8: 0.066 | R8: 0.3 | S8: 0.3 | T8: =Capacity!B5*1000 -> 67226.539 | U8: =Capacity!AR5*1000 -> 220 | V8: =Capacity!D5*1000 -> 0 | W8: =Capacity!X5*1000 -> 0 | X8: =CarriersTech_characteristics!$G$2 -> 17.207188 | Y8: =CarriersTech_characteristics!$H$28*1000 -> 1942097.6 | Z8: 3 | AA8: 0.105 | AC8: =1/K8/(1-Q8) -> 2.8103758 | AE8: =Y8/(X8*Conversions!$D$2) -> 0.40631575 | AF8: =O8/X8/Conversions!$D$2*AC8 -> 7.850786e-05 | AG8: =Z8*Conversions!$D$4 -> 3.7167527 | AH8: =M8-AG8 -> 8.0348465 | AI8: =P8 -> 40 | AJ8: =AA8/(1-(1+AA8)^-AI8) -> 0.10697141 | AK8: =AH8/AJ8 -> 75.112094 | AL8: =T8-U8 -> 67006.539
B9: EG_CCGT | C9: NR | D9: ThermalPower | E9: NG_CCGT | F9: INDIA | G9: MW | H9: NATGAS | I9: ELECTRICITY | J9: 8760 | K9: 0.40444272 | L9: 0.85 | M9: =8512.22780274884/1000 -> 8.5122278 | N9: =8512.227803/1000 -> 8.5122278 | O9: 0 | P9: 25 | Q9: 0.02 | R9: 0.9 | S9: 0.9 | T9: =Capacity!B6*1000 -> 7330.5467 | U9: =Capacity!AR6*1000 -> 0 | V9: =Capacity!D6*1000 -> 0 | W9: =Capacity!X6*1000 -> 0 | X9: =CarriersTech_characteristics!$G$3 -> 37.6812 | Y9: =CarriersTech_characteristics!$H$3*1000 -> 3025024.5 | Z9: 2.9 | AA9: 0.105 | AC9: =1/K9/(1-Q9) -> 2.522998 | AE9: =(Y9*Conversions!$D$3)/(X9*Conversions!$D$2) -> 0.23958587 | AF9: 0 | AG9: =Z9*Conversions!$D$4 -> 3.592861 | AH9: =M9-AG9 -> 4.9193668 | AI9: =P9 -> 25 | AJ9: =AA9/(1-(1+AA9)^-AI9) -> 0.11442932 | AK9: =AH9/AJ9 -> 42.99044 | AL9: =T9-U9 -> 7330.5467
B10: EG_OCGT | C10: NR | D10: ThermalPower | F10: INDIA | G10: MW | H10: NATGAS | I10: ELECTRICITY | J10: 8760 | K10: 0.28070163 | L10: 0.85 | M10: =6679.75064927145/1000 -> 6.6797506 | N10: =6679.750649/1000 -> 6.6797506 | O10: 0 | P10: 25 | Q10: 0.01 | R10: 1 | S10: 1 | T10: =Capacity!B7*1000 -> 0 | U10: =Capacity!AR7*1000 -> 0 | V10: =Capacity!D7*1000 -> 0 | W10: =Capacity!X7*1000 -> 0 | X10: =CarriersTech_characteristics!$G$3 -> 37.6812 | Y10: =CarriersTech_characteristics!$H$3*1000 -> 3025024.5 | Z10: 0.7 | AA10: 0.105 | AC10: =1/K10/(1-Q10) -> 3.5984865 | AE10: =(Y10*Conversions!$D$3)/(X10*Conversions!$D$2) -> 0.23958587 | AF10: 0 | AG10: =Z10*Conversions!$D$4 -> 0.86724231 | AH10: =M10-AG10 -> 5.8125083 | AI10: =P10 -> 25 | AJ10: =AA10/(1-(1+AA10)^-AI10) -> 0.11442932 | AK10: =AH10/AJ10 -> 50.795621 | AL10: =T10-U10 -> 0
B11: EG_PHWR | C11: NR | D11: ThermalPower | E11: nuclear_PHWR | F11: INDIA | G11: MW | H11: ATOMIC | I11: ELECTRICITY | J11: 8760 | K11: 1 | L11: 0.70916667 | M11: =20833.2103478327/1000 -> 20.83321 | N11: =20833.21035/1000 -> 20.83321 | O11: 0 | P11: 40 | Q11: 0.1078 | R11: 0.01 | S11: 0.01 | T11: =Capacity!B8*1000 -> 1603.5184 | U11: =Capacity!AR8*1000 -> 0 | V11: =Capacity!D8*1000 -> 0 | W11: =Capacity!X8*1000 -> 0 | Z11: 4.3 | AA11: 0.105 | AC11: =1/K11/(1-Q11) -> 1.1208249 | AF11: 0 | AG11: =Z11*Conversions!$D$4 -> 5.3273456 | AH11: =M11-AG11 -> 15.505865 | AI11: =P11 -> 40 | AJ11: =AA11/(1-(1+AA11)^-AI11) -> 0.10697141 | AK11: =AH11/AJ11 -> 144.95336 | AL11: =T11-U11 -> 1603.5184
B12: EG_SMR | C12: NR | D12: ThermalPower | F12: INDIA | G12: MW | H12: ATOMIC | I12: ELECTRICITY | J12: 8760 | K12: 1 | L12: 0.70916667 | M12: =N12 -> 35.289429 | N12: =35289.42939/1000 -> 35.289429 | O12: 0 | P12: 30 | Q12: 0.05 | R12: 0.01 | S12: 0.01 | T12: =Capacity!B9*1000 -> 0 | U12: =Capacity!AR9*1000 -> 0 | V12: =Capacity!D9*1000 -> 0 | W12: =Capacity!X9*1000 -> 0 | Z12: 5 | AA12: 0.105 | AC12: =1/K12/(1-Q12) -> 1.0526316 | AF12: 0 | AG12: =Z12*Conversions!$D$4 -> 6.1945879 | AH12: =M12-AG12 -> 29.094841 | AI12: =P12 -> 30 | AJ12: =AA12/(1-(1+AA12)^-AI12) -> 0.11052848 | AK12: =AH12/AJ12 -> 263.23388 | AL12: =T12-U12 -> 0
B13: EG_LH | C13: NR | D13: HydroRes | E13: conventional_hydroelectric | F13: INDIA | G13: MW | H13: HYDEL | I13: ELECTRICITY | J13: 8760 | K13: 1 | L13: 1 | M13: =19631.8145207228/1000 -> 19.631815 | N13: =19631.81452/1000 -> 19.631815 | O13: 0 | P13: 40 | Q13: 0.006 | R13: 1 | S13: 1 | T13: =Capacity!B10*1000 -> 20527.317 | U13: =Capacity!AR10*1000 -> 0 | V13: =Capacity!D10*1000 -> 0 | W13: =Capacity!X10*1000 -> 0 | Z13: 4.4 | AA13: 0.105 | AD13: =K13-Q13 -> 0.994 | AF13: 0 | AG13: =Z13*Conversions!$D$4 -> 5.4512374 | AH13: =M13-AG13 -> 14.180577 | AI13: =P13 -> 40 | AJ13: =AA13/(1-(1+AA13)^-AI13) -> 0.10697141 | AK13: =AH13/AJ13 -> 132.56418 | AL13: =T13-U13 -> 20527.317
B14: EG_SH | C14: NR | D14: HydroRes | E14: conventional_hydroelectric_small | F14: INDIA | G14: MW | H14: HYDEL | I14: ELECTRICITY | J14: 8760 | K14: 1 | L14: 1 | M14: =11825.3487554956/1000 -> 11.825349 | N14: =11825.34876/1000 -> 11.825349 | O14: 0 | P14: 35 | Q14: 0.01 | R14: 1 | S14: 1 | T14: =Capacity!B11*1000 -> 1698.75 | U14: =Capacity!AR11*1000 -> 0 | V14: =Capacity!D11*1000 -> 28 | W14: =Capacity!X11*1000 -> 28 | Z14: =2.4 -> 2.4 | AA14: 0.0835 | AD14: =K14-Q14 -> 0.99 | AF14: 0 | AG14: =Z14*Conversions!$D$4 -> 2.9734022 | AH14: =M14-AG14 -> 8.8519466 | AI14: =P14 -> 35 | AJ14: =AA14/(1-(1+AA14)^-AI14) -> 0.088866959 | AK14: =AH14/AJ14 -> 99.608974 | AL14: =T14-U14 -> 1698.75
B15: EG_BIOMASS | C15: NR | D15: ThermalPower | E15: biomass | F15: INDIA | G15: MW | H15: BIOMASS_WASTE | I15: ELECTRICITY | J15: 8760 | K15: 0.2388459 | L15: 1 | M15: =7713.45723965334/1000 -> 7.7134572 | N15: =7713.45724/1000 -> 7.7134572 | O15: 0 | P15: 20 | Q15: 0.1 | R15: 0.06 | S15: 0.06 | T15: =Capacity!B12*1000 -> 3357.15 | U15: =Capacity!AR12*1000 -> 0 | V15: =Capacity!D12*1000 -> 143 | W15: =Capacity!X12*1000 -> 143 | X15: =CarriersTech_characteristics!$G$7 -> 13.648968 | Y15: =CarriersTech_characteristics!$H$5*1000 -> 1656436.7 | Z15: 1 | AA15: 0.0835 | AC15: =1/K15/(1-Q15) -> 4.652 | AE15: =Y15/(X15*Conversions!$D$2) -> 0.43689545 | AF15: 0 | AG15: =Z15*Conversions!$D$4 -> 1.2389176 | AH15: =M15-AG15 -> 6.4745397 | AI15: =P15 -> 20 | AJ15: =AA15/(1-(1+AA15)^-AI15) -> 0.1045193 | AK15: =AH15/AJ15 -> 61.945879 | AL15: =T15-U15 -> 3357.15
B16: EG_SOLARGM | C16: NR | D16: VRE | E16: solar_GM | F16: INDIA | G16: MW | H16: SUNLIGHT | I16: ELECTRICITY | J16: 8760 | K16: 1 | L16: 1 | M16: =5630.98419436319/1000 -> 5.6309842 | N16: =5439.705856/1000 -> 5.4397059 | O16: 0 | P16: 25 | Q16: 0.01 | R16: 1 | S16: 1 | T16: =Capacity!B13*1000 -> 19996.724 | U16: =Capacity!AR13*1000 -> 0 | V16: =Capacity!D13*1000 -> 4791 | W16: =Capacity!X13*1000 -> 4791 | Z16: 0.35 | AA16: 0.105 | AC16: 1 | AF16: 0 | AG16: =Z16*Conversions!$D$4 -> 0.43362115 | AH16: =M16-AG16 -> 5.197363 | AI16: =P16 -> 25 | AJ16: =AA16/(1-(1+AA16)^-AI16) -> 0.11442932 | AK16: =AH16/AJ16 -> 45.419854 | AL16: =T16-U16 -> 19996.724
B17: EG_SOLARRF | C17: NR | D17: VRE | E17: solar_RT | F17: INDIA | G17: MW | H17: SUNLIGHT | I17: ELECTRICITY | J17: 8760 | K17: 1 | L17: 1 | M17: =5542.18769541597/1000 -> 5.5421877 | N17: =5362.133837/1000 -> 5.3621338 | O17: 0 | P17: 25 | Q17: 0.006 | R17: 1 | S17: 1 | T17: =Capacity!B14*1000 -> 2666.3458 | U17: =Capacity!AR14*1000 -> 0 | V17: =Capacity!D14*1000 -> 766 | W17: =Capacity!X14*1000 -> 766 | Z17: 0.51 | AA17: 0.104 | AC17: 1 | AF17: 0 | AG17: =Z17*Conversions!$D$4 -> 0.63184797 | AH17: =M17-AG17 -> 4.9103397 | AI17: =P17 -> 25 | AJ17: =AA17/(1-(1+AA17)^-AI17) -> 0.113573 | AK17: =AH17/AJ17 -> 43.235096 | AL17: =T17-U17 -> 2666.3458
B18: EG_WINDON | C18: NR | D18: VRE | E18: onshore_wind | F18: INDIA | G18: MW | H18: WIND | I18: ELECTRICITY | J18: 8760 | K18: 1 | L18: 1 | M18: =10659.4302732183/1000 -> 10.65943 | N18: =10586.96446/1000 -> 10.586964 | O18: 0 | P18: 25 | Q18: 0.005 | R18: 1 | S18: 1 | T18: =Capacity!B15*1000 -> 5301.42 | U18: =Capacity!AR15*1000 -> 0 | V18: =Capacity!D15*1000 -> 2 | W18: =Capacity!X15*1000 -> 2 | Z18: 0.68 | AA18: 0.105 | AC18: 1 | AF18: 0 | AG18: =Z18*Conversions!$D$4 -> 0.84246396 | AH18: =M18-AG18 -> 9.8169663 | AI18: =P18 -> 25 | AJ18: =AA18/(1-(1+AA18)^-AI18) -> 0.11442932 | AK18: =AH18/AJ18 -> 85.790655 | AL18: =T18-U18 -> 5301.42
B19: EG_WINDOFF | C19: NR | D19: VRE | F19: INDIA | G19: MW | H19: WIND | I19: ELECTRICITY | J19: 8760 | K19: 1 | L19: 1 | M19: =N19 -> 34.540362 | N19: =34540.36167/1000 -> 34.540362 | O19: 0 | P19: 25 | Q19: 0.005 | R19: 1 | S19: 1 | T19: =Capacity!B16*1000 -> 0 | U19: =Capacity!AR16*1000 -> 0 | V19: =Capacity!D16*1000 -> 0 | W19: =Capacity!X16*1000 -> 0 | Z19: 6.7 | AA19: 0.112 | AC19: 1 | AF19: 0 | AG19: =Z19*Conversions!$D$4 -> 8.3007478 | AH19: =M19-AG19 -> 26.239614 | AI19: =P19 -> 25 | AJ19: =AA19/(1-(1+AA19)^-AI19) -> 0.12047789 | AK19: =AH19/AJ19 -> 217.7961 | AL19: =T19-U19 -> 0
B20: EG_COAL | C20: NER | D20: ThermalPower | E20: coal | F20: INDIA | G20: MW | H20: THERMAL_COAL | I20: ELECTRICITY | J20: 8760 | K20: 0.3809682 | L20: 0.85 | M20: =26148.8463751508/1000 -> 26.148846 | N20: =13721.03129/1000 -> 13.721031 | O20: 133.52302 | P20: 40 | Q20: 0.066 | R20: 0.3 | S20: 0.3 | T20: =Capacity!B19*1000 -> 1010.9297 | U20: =Capacity!AR19*1000 -> 0 | V20: =Capacity!D19*1000 -> 0 | W20: =Capacity!X19*1000 -> 0 | X20: =CarriersTech_characteristics!$G$2 -> 17.207188 | Y20: =CarriersTech_characteristics!$H$28*1000 -> 1942097.6 | Z20: 3 | AA20: 0.105 | AC20: =1/K20/(1-Q20) -> 2.8103758 | AE20: =Y20/(X20*Conversions!$D$2) -> 0.40631575 | AF20: =O20/CarriersTech_characteristics!$G$2/Conversions!$D$2*AC20 -> 7.850786e-05 | AG20: =Z20*Conversions!$D$4 -> 3.7167527 | AH20: =M20-AG20 -> 22.432094 | AI20: =P20 -> 40 | AJ20: =AA20/(1-(1+AA20)^-AI20) -> 0.10697141 | AK20: =AH20/AJ20 -> 209.70177 | AL20: =T20-U20 -> 1010.9297
B21: EG_CCGT | C21: NER | D21: ThermalPower | E21: NG_CCGT | F21: INDIA | G21: MW | H21: NATGAS | I21: ELECTRICITY | J21: 8760 | K21: 0.40444272 | L21: 0.85 | M21: =8512.22780274884/1000 -> 8.5122278 | N21: =8512.227803/1000 -> 8.5122278 | O21: 0 | P21: 25 | Q21: 0.02 | R21: 0.9 | S21: 0.9 | T21: =Capacity!B20*1000 -> 2002.4569 | U21: =Capacity!AR20*1000 -> 0 | V21: =Capacity!D20*1000 -> 0 | W21: =Capacity!X20*1000 -> 0 | X21: =CarriersTech_characteristics!$G$3 -> 37.6812 | Y21: =CarriersTech_characteristics!$H$3*1000 -> 3025024.5 | Z21: 2.9 | AA21: 0.105 | AC21: =1/K21/(1-Q21) -> 2.522998 | AE21: =(Y21*Conversions!$D$3)/(X21*Conversions!$D$2) -> 0.23958587 | AF21: 0 | AG21: =Z21*Conversions!$D$4 -> 3.592861 | AH21: =M21-AG21 -> 4.9193668 | AI21: =P21 -> 25 | AJ21: =AA21/(1-(1+AA21)^-AI21) -> 0.11442932 | AK21: =AH21/AJ21 -> 42.99044 | AL21: =T21-U21 -> 2002.4569
B22: EG_OCGT | C22: NER | D22: ThermalPower | F22: INDIA | G22: MW | H22: NATGAS | I22: ELECTRICITY | J22: 8760 | K22: 0.28070163 | L22: 0.85 | M22: =6679.75064927145/1000 -> 6.6797506 | N22: =6679.750649/1000 -> 6.6797506 | O22: 0 | P22: 25 | Q22: 0.01 | R22: 1 | S22: 1 | T22: =Capacity!B21*1000 -> 0 | U22: =Capacity!AR21*1000 -> 0 | V22: =Capacity!D21*1000 -> 0 | W22: =Capacity!X21*1000 -> 0 | X22: =CarriersTech_characteristics!$G$3 -> 37.6812 | Y22: =CarriersTech_characteristics!$H$3*1000 -> 3025024.5 | Z22: 0.7 | AA22: 0.105 | AC22: =1/K22/(1-Q22) -> 3.5984865 | AE22: =(Y22*Conversions!$D$3)/(X22*Conversions!$D$2) -> 0.23958587 | AF22: 0 | AG22: =Z22*Conversions!$D$4 -> 0.86724231 | AH22: =M22-AG22 -> 5.8125083 | AI22: =P22 -> 25 | AJ22: =AA22/(1-(1+AA22)^-AI22) -> 0.11442932 | AK22: =AH22/AJ22 -> 50.795621 | AL22: =T22-U22 -> 0
B23: EG_PHWR | C23: NER | D23: ThermalPower | E23: nuclear_PHWR | F23: INDIA | G23: MW | H23: ATOMIC | I23: ELECTRICITY | J23: 8760 | K23: 1 | L23: 0.70916667 | M23: =20833.2103478327/1000 -> 20.83321 | N23: =20833.21035/1000 -> 20.83321 | O23: 0 | P23: 40 | Q23: 0.1078 | R23: 0.01 | S23: 0.01 | T23: =Capacity!B22*1000 -> 0 | U23: =Capacity!AR22*1000 -> 0 | V23: =Capacity!D22*1000 -> 0 | W23: =Capacity!X22*1000 -> 0 | Z23: 4.3 | AA23: 0.105 | AC23: =1/K23/(1-Q23) -> 1.1208249 | AF23: 0 | AG23: =Z23*Conversions!$D$4 -> 5.3273456 | AH23: =M23-AG23 -> 15.505865 | AI23: =P23 -> 40 | AJ23: =AA23/(1-(1+AA23)^-AI23) -> 0.10697141 | AK23: =AH23/AJ23 -> 144.95336 | AL23: =T23-U23 -> 0
B24: EG_SMR | C24: NER | D24: ThermalPower | F24: INDIA | G24: MW | H24: ATOMIC | I24: ELECTRICITY | J24: 8760 | K24: 1 | L24: 0.70916667 | M24: =N24 -> 35.289429 | N24: =35289.42939/1000 -> 35.289429 | O24: 0 | P24: 30 | Q24: 0.05 | R24: 0.01 | S24: 0.01 | T24: =Capacity!B23*1000 -> 0 | U24: =Capacity!AR23*1000 -> 0 | V24: =Capacity!D23*1000 -> 0 | W24: =Capacity!X23*1000 -> 0 | Z24: 5 | AA24: 0.105 | AC24: =1/K24/(1-Q24) -> 1.0526316 | AF24: 0 | AG24: =Z24*Conversions!$D$4 -> 6.1945879 | AH24: =M24-AG24 -> 29.094841 | AI24: =P24 -> 30 | AJ24: =AA24/(1-(1+AA24)^-AI24) -> 0.11052848 | AK24: =AH24/AJ24 -> 263.23388 | AL24: =T24-U24 -> 0
B25: EG_LH | C25: NER | D25: HydroRes | E25: conventional_hydroelectric | F25: INDIA | G25: MW | H25: HYDEL | I25: ELECTRICITY | J25: 8760 | K25: 1 | L25: 1 | M25: =19631.8145207228/1000 -> 19.631815 | N25: =19631.81452/1000 -> 19.631815 | O25: 0 | P25: 40 | Q25: 0.006 | R25: 1 | S25: 1 | T25: =Capacity!B24*1000 -> 1842.8253 | U25: =Capacity!AR24*1000 -> 0 | V25: =Capacity!D24*1000 -> 0 | W25: =Capacity!X24*1000 -> 0 | Z25: 4.4 | AA25: 0.105 | AD25: =K25-Q25 -> 0.994 | AF25: 0 | AG25: =Z25*Conversions!$D$4 -> 5.4512374 | AH25: =M25-AG25 -> 14.180577 | AI25: =P25 -> 40 | AJ25: =AA25/(1-(1+AA25)^-AI25) -> 0.10697141 | AK25: =AH25/AJ25 -> 132.56418 | AL25: =T25-U25 -> 1842.8253
B26: EG_SH | C26: NER | D26: HydroRes | E26: conventional_hydroelectric_small | F26: INDIA | G26: MW | H26: HYDEL | I26: ELECTRICITY | J26: 8760 | K26: 1 | L26: 1 | M26: =11825.3487554956/1000 -> 11.825349 | N26: =11825.34876/1000 -> 11.825349 | O26: 0 | P26: 35 | Q26: 0.01 | R26: 1 | S26: 1 | T26: =Capacity!B25*1000 -> 299.35 | U26: =Capacity!AR25*1000 -> 0 | V26: =Capacity!D25*1000 -> 10 | W26: =Capacity!X25*1000 -> 10 | Z26: =2.4 -> 2.4 | AA26: 0.0835 | AD26: =K26-Q26 -> 0.99 | AF26: 0 | AG26: =Z26*Conversions!$D$4 -> 2.9734022 | AH26: =M26-AG26 -> 8.8519466 | AI26: =P26 -> 35 | AJ26: =AA26/(1-(1+AA26)^-AI26) -> 0.088866959 | AK26: =AH26/AJ26 -> 99.608974 | AL26: =T26-U26 -> 299.35
B27: EG_BIOMASS | C27: NER | D27: ThermalPower | E27: biomass | F27: INDIA | G27: MW | H27: BIOMASS_WASTE | I27: ELECTRICITY | J27: 8760 | K27: 0.2388459 | L27: 1 | M27: =7713.45723965334/1000 -> 7.7134572 | N27: =7713.45724/1000 -> 7.7134572 | O27: 0 | P27: 20 | Q27: 0.1 | R27: 0.06 | S27: 0.06 | T27: =Capacity!B26*1000 -> 15.8 | U27: =Capacity!AR26*1000 -> 0 | V27: =Capacity!D26*1000 -> 1 | W27: =Capacity!X26*1000 -> 1 | X27: =CarriersTech_characteristics!$G$7 -> 13.648968 | Y27: =CarriersTech_characteristics!$H$5*1000 -> 1656436.7 | Z27: 1 | AA27: 0.0835 | AC27: =1/K27/(1-Q27) -> 4.652 | AE27: =Y27/(X27*Conversions!$D$2) -> 0.43689545 | AF27: 0 | AG27: =Z27*Conversions!$D$4 -> 1.2389176 | AH27: =M27-AG27 -> 6.4745397 | AI27: =P27 -> 20 | AJ27: =AA27/(1-(1+AA27)^-AI27) -> 0.1045193 | AK27: =AH27/AJ27 -> 61.945879 | AL27: =T27-U27 -> 15.8
B28: EG_SOLARGM | C28: NER | D28: VRE | E28: solar_GM | F28: INDIA | G28: MW | H28: SUNLIGHT | I28: ELECTRICITY | J28: 8760 | K28: 1 | L28: 1 | M28: =5630.98419436319/1000 -> 5.6309842 | N28: =5439.705856/1000 -> 5.4397059 | O28: 0 | P28: 25 | Q28: 0.01 | R28: 1 | S28: 1 | T28: =Capacity!B27*1000 -> 171.48962 | U28: =Capacity!AR27*1000 -> 0 | V28: =Capacity!D27*1000 -> 7 | W28: =Capacity!X27*1000 -> 7 | Z28: 0.35 | AA28: 0.105 | AC28: 1 | AF28: 0 | AG28: =Z28*Conversions!$D$4 -> 0.43362115 | AH28: =M28-AG28 -> 5.197363 | AI28: =P28 -> 25 | AJ28: =AA28/(1-(1+AA28)^-AI28) -> 0.11442932 | AK28: =AH28/AJ28 -> 45.419854 | AL28: =T28-U28 -> 171.48962
B29: EG_SOLARRF | C29: NER | D29: VRE | E29: solar_RT | F29: INDIA | G29: MW | H29: SUNLIGHT | I29: ELECTRICITY | J29: 8760 | K29: 1 | L29: 1 | M29: =5542.18769541597/1000 -> 5.5421877 | N29: =5362.133837/1000 -> 5.3621338 | O29: 0 | P29: 25 | Q29: 0.006 | R29: 1 | S29: 1 | T29: =Capacity!B28*1000 -> 67.610378 | U29: =Capacity!AR28*1000 -> 0 | V29: =Capacity!D28*1000 -> 8 | W29: =Capacity!X28*1000 -> 8 | Z29: 0.51 | AA29: 0.104 | AC29: 1 | AF29: 0 | AG29: =Z29*Conversions!$D$4 -> 0.63184797 | AH29: =M29-AG29 -> 4.9103397 | AI29: =P29 -> 25 | AJ29: =AA29/(1-(1+AA29)^-AI29) -> 0.113573 | AK29: =AH29/AJ29 -> 43.235096 | AL29: =T29-U29 -> 67.610378
B30: EG_WINDON | C30: NER | D30: VRE | E30: onshore_wind | F30: INDIA | G30: MW | H30: WIND | I30: ELECTRICITY | J30: 8760 | K30: 1 | L30: 1 | M30: =10659.4302732183/1000 -> 10.65943 | N30: =10586.96446/1000 -> 10.586964 | O30: 0 | P30: 25 | Q30: 0.005 | R30: 1 | S30: 1 | T30: =Capacity!B29*1000 -> 0 | U30: =Capacity!AR29*1000 -> 0 | V30: =Capacity!D29*1000 -> 0 | W30: =Capacity!X29*1000 -> 0 | Z30: 0.68 | AA30: 0.105 | AC30: 1 | AF30: 0 | AG30: =Z30*Conversions!$D$4 -> 0.84246396 | AH30: =M30-AG30 -> 9.8169663 | AI30: =P30 -> 25 | AJ30: =AA30/(1-(1+AA30)^-AI30) -> 0.11442932 | AK30: =AH30/AJ30 -> 85.790655 | AL30: =T30-U30 -> 0
B31: EG_WINDOFF | C31: NER | D31: VRE | F31: INDIA | G31: MW | H31: WIND | I31: ELECTRICITY | J31: 8760 | K31: 1 | L31: 1 | M31: =N31 -> 34.540362 | N31: =34540.36167/1000 -> 34.540362 | O31: 0 | P31: 25 | Q31: 0.005 | R31: 1 | S31: 1 | T31: =Capacity!B30*1000 -> 0 | U31: =Capacity!AR30*1000 -> 0 | V31: =Capacity!D30*1000 -> 0 | W31: =Capacity!X30*1000 -> 0 | Z31: 6.7 | AA31: 0.112 | AC31: 1 | AF31: 0 | AG31: =Z31*Conversions!$D$4 -> 8.3007478 | AH31: =M31-AG31 -> 26.239614 | AI31: =P31 -> 25 | AJ31: =AA31/(1-(1+AA31)^-AI31) -> 0.12047789 | AK31: =AH31/AJ31 -> 217.7961 | AL31: =T31-U31 -> 0
B32: EG_COAL | C32: ER | D32: ThermalPower | E32: coal | F32: INDIA | G32: MW | H32: THERMAL_COAL | I32: ELECTRICITY | J32: 8760 | K32: 0.3809682 | L32: 0.85 | M32: =6514.90571684157/1000 -> 6.5149057 | N32: =13721.03129/1000 -> 13.721031 | O32: 133.52302 | P32: 40 | Q32: 0.066 | R32: 0.3 | S32: 0.3 | T32: =Capacity!B33*1000 -> 41729.904 | U32: =Capacity!AR33*1000 -> 0 | V32: =Capacity!D33*1000 -> 0 | W32: =Capacity!X33*1000 -> 0 | X32: =CarriersTech_characteristics!$G$2 -> 17.207188 | Y32: =CarriersTech_characteristics!$H$28*1000 -> 1942097.6 | Z32: 3 | AA32: 0.105 | AC32: =1/K32/(1-Q32) -> 2.8103758 | AE32: =Y32/(X32*Conversions!$D$2) -> 0.40631575 | AF32: =O32/CarriersTech_characteristics!$G$2/Conversions!$D$2*AC32 -> 7.850786e-05 | AG32: =Z32*Conversions!$D$4 -> 3.7167527 | AH32: =M32-AG32 -> 2.798153 | AI32: =P32 -> 40 | AJ32: =AA32/(1-(1+AA32)^-AI32) -> 0.10697141 | AK32: =AH32/AJ32 -> 26.157952 | AL32: =T32-U32 -> 41729.904
B33: EG_CCGT | C33: ER | D33: ThermalPower | E33: NG_CCGT | F33: INDIA | G33: MW | H33: NATGAS | I33: ELECTRICITY | J33: 8760 | K33: 0.40444272 | L33: 0.85 | M33: =8512.22780274884/1000 -> 8.5122278 | N33: =8512.227803/1000 -> 8.5122278 | O33: 0 | P33: 25 | Q33: 0.02 | R33: 0.9 | S33: 0.9 | T33: =Capacity!B34*1000 -> 770.80433 | U33: =Capacity!AR34*1000 -> 0 | V33: =Capacity!D34*1000 -> 0 | W33: =Capacity!X34*1000 -> 0 | X33: =CarriersTech_characteristics!$G$3 -> 37.6812 | Y33: =CarriersTech_characteristics!$H$3*1000 -> 3025024.5 | Z33: 2.9 | AA33: 0.105 | AC33: =1/K33/(1-Q33) -> 2.522998 | AE33: =(Y33*Conversions!$D$3)/(X33*Conversions!$D$2) -> 0.23958587 | AF33: 0 | AG33: =Z33*Conversions!$D$4 -> 3.592861 | AH33: =M33-AG33 -> 4.9193668 | AI33: =P33 -> 25 | AJ33: =AA33/(1-(1+AA33)^-AI33) -> 0.11442932 | AK33: =AH33/AJ33 -> 42.99044 | AL33: =T33-U33 -> 770.80433
B34: EG_OCGT | C34: ER | D34: ThermalPower | F34: INDIA | G34: MW | H34: NATGAS | I34: ELECTRICITY | J34: 8760 | K34: 0.28070163 | L34: 0.85 | M34: =6679.75064927145/1000 -> 6.6797506 | N34: =6679.750649/1000 -> 6.6797506 | O34: 0 | P34: 25 | Q34: 0.01 | R34: 1 | S34: 1 | T34: =Capacity!B35*1000 -> 0 | U34: =Capacity!AR35*1000 -> 0 | V34: =Capacity!D35*1000 -> 0 | W34: =Capacity!X35*1000 -> 0 | X34: =CarriersTech_characteristics!$G$3 -> 37.6812 | Y34: =CarriersTech_characteristics!$H$3*1000 -> 3025024.5 | Z34: 0.7 | AA34: 0.105 | AC34: =1/K34/(1-Q34) -> 3.5984865 | AE34: =(Y34*Conversions!$D$3)/(X34*Conversions!$D$2) -> 0.23958587 | AF34: 0 | AG34: =Z34*Conversions!$D$4 -> 0.86724231 | AH34: =M34-AG34 -> 5.8125083 | AI34: =P34 -> 25 | AJ34: =AA34/(1-(1+AA34)^-AI34) -> 0.11442932 | AK34: =AH34/AJ34 -> 50.795621 | AL34: =T34-U34 -> 0
B35: EG_PHWR | C35: ER | D35: ThermalPower | E35: nuclear_PHWR | F35: INDIA | G35: MW | H35: ATOMIC | I35: ELECTRICITY | J35: 8760 | K35: 1 | L35: 0.70916667 | M35: =20833.2103478327/1000 -> 20.83321 | N35: =20833.21035/1000 -> 20.83321 | O35: 0 | P35: 40 | Q35: 0.1078 | R35: 0.01 | S35: 0.01 | T35: =Capacity!B36*1000 -> 0 | U35: =Capacity!AR36*1000 -> 0 | V35: =Capacity!D36*1000 -> 0 | W35: =Capacity!X36*1000 -> 0 | Z35: 4.3 | AA35: 0.105 | AC35: =1/K35/(1-Q35) -> 1.1208249 | AF35: 0 | AG35: =Z35*Conversions!$D$4 -> 5.3273456 | AH35: =M35-AG35 -> 15.505865 | AI35: =P35 -> 40 | AJ35: =AA35/(1-(1+AA35)^-AI35) -> 0.10697141 | AK35: =AH35/AJ35 -> 144.95336 | AL35: =T35-U35 -> 0
B36: EG_SMR | C36: ER | D36: ThermalPower | F36: INDIA | G36: MW | H36: ATOMIC | I36: ELECTRICITY | J36: 8760 | K36: 1 | L36: 0.70916667 | M36: =N36 -> 35.289429 | N36: =35289.42939/1000 -> 35.289429 | O36: 0 | P36: 30 | Q36: 0.05 | R36: 0.01 | S36: 0.01 | T36: =Capacity!B37*1000 -> 0 | U36: =Capacity!AR37*1000 -> 0 | V36: =Capacity!D37*1000 -> 0 | W36: =Capacity!X37*1000 -> 0 | Z36: 5 | AA36: 0.105 | AC36: =1/K36/(1-Q36) -> 1.0526316 | AF36: 0 | AG36: =Z36*Conversions!$D$4 -> 6.1945879 | AH36: =M36-AG36 -> 29.094841 | AI36: =P36 -> 30 | AJ36: =AA36/(1-(1+AA36)^-AI36) -> 0.11052848 | AK36: =AH36/AJ36 -> 263.23388 | AL36: =T36-U36 -> 0
B37: EG_LH | C37: ER | D37: HydroRes | E37: conventional_hydroelectric | F37: INDIA | G37: MW | H37: HYDEL | I37: ELECTRICITY | J37: 8760 | K37: 1 | L37: 1 | M37: =19631.8145207228/1000 -> 19.631815 | N37: =19631.81452/1000 -> 19.631815 | O37: 0 | P37: 40 | Q37: 0.006 | R37: 1 | S37: 1 | T37: =Capacity!B38*1000 -> 4198.8603 | U37: =Capacity!AR38*1000 -> 0 | V37: =Capacity!D38*1000 -> 0 | W37: =Capacity!X38*1000 -> 0 | Z37: 4.4 | AA37: 0.105 | AD37: =K37-Q37 -> 0.994 | AF37: 0 | AG37: =Z37*Conversions!$D$4 -> 5.4512374 | AH37: =M37-AG37 -> 14.180577 | AI37: =P37 -> 40 | AJ37: =AA37/(1-(1+AA37)^-AI37) -> 0.10697141 | AK37: =AH37/AJ37 -> 132.56418 | AL37: =T37-U37 -> 4198.8603
B38: EG_SH | C38: ER | D38: HydroRes | E38: conventional_hydroelectric_small | F38: INDIA | G38: MW | H38: HYDEL | I38: ELECTRICITY | J38: 8760 | K38: 1 | L38: 1 | M38: =11825.3487554956/1000 -> 11.825349 | N38: =11825.34876/1000 -> 11.825349 | O38: 0 | P38: 35 | Q38: 0.01 | R38: 1 | S38: 1 | T38: =Capacity!B39*1000 -> 343.99 | U38: =Capacity!AR39*1000 -> 0 | V38: =Capacity!D39*1000 -> 6 | W38: =Capacity!X39*1000 -> 6 | Z38: =2.4 -> 2.4 | AA38: 0.0835 | AD38: =K38-Q38 -> 0.99 | AF38: 0 | AG38: =Z38*Conversions!$D$4 -> 2.9734022 | AH38: =M38-AG38 -> 8.8519466 | AI38: =P38 -> 35 | AJ38: =AA38/(1-(1+AA38)^-AI38) -> 0.088866959 | AK38: =AH38/AJ38 -> 99.608974 | AL38: =T38-U38 -> 343.99
B39: EG_BIOMASS | C39: ER | D39: ThermalPower | E39: biomass | F39: INDIA | G39: MW | H39: BIOMASS_WASTE | I39: ELECTRICITY | J39: 8760 | K39: 0.2388459 | L39: 1 | M39: =7713.45723965334/1000 -> 7.7134572 | N39: =7713.45724/1000 -> 7.7134572 | O39: 0 | P39: 20 | Q39: 0.1 | R39: 0.06 | S39: 0.06 | T39: =Capacity!B40*1000 -> 560.64 | U39: =Capacity!AR40*1000 -> 0 | V39: =Capacity!D40*1000 -> 23 | W39: =Capacity!X40*1000 -> 23 | X39: =CarriersTech_characteristics!$G$7 -> 13.648968 | Y39: =CarriersTech_characteristics!$H$5*1000 -> 1656436.7 | Z39: 1 | AA39: 0.0835 | AC39: =1/K39/(1-Q39) -> 4.652 | AE39: =Y39/(X39*Conversions!$D$2) -> 0.43689545 | AF39: 0 | AG39: =Z39*Conversions!$D$4 -> 1.2389176 | AH39: =M39-AG39 -> 6.4745397 | AI39: =P39 -> 20 | AJ39: =AA39/(1-(1+AA39)^-AI39) -> 0.1045193 | AK39: =AH39/AJ39 -> 61.945879 | AL39: =T39-U39 -> 560.64
B40: EG_SOLARGM | C40: ER | D40: VRE | E40: solar_GM | F40: INDIA | G40: MW | H40: SUNLIGHT | I40: ELECTRICITY | J40: 8760 | K40: 1 | L40: 1 | M40: =5630.98419436319/1000 -> 5.6309842 | N40: =5439.705856/1000 -> 5.4397059 | O40: 0 | P40: 25 | Q40: 0.01 | R40: 1 | S40: 1 | T40: =Capacity!B41*1000 -> 847.7259 | U40: =Capacity!AR41*1000 -> 0 | V40: =Capacity!D41*1000 -> 40 | W40: =Capacity!X41*1000 -> 40 | Z40: 0.35 | AA40: 0.105 | AC40: 1 | AF40: 0 | AG40: =Z40*Conversions!$D$4 -> 0.43362115 | AH40: =M40-AG40 -> 5.197363 | AI40: =P40 -> 25 | AJ40: =AA40/(1-(1+AA40)^-AI40) -> 0.11442932 | AK40: =AH40/AJ40 -> 45.419854 | AL40: =T40-U40 -> 847.7259
B41: EG_SOLARRF | C41: ER | D41: VRE | E41: solar_RT | F41: INDIA | G41: MW | H41: SUNLIGHT | I41: ELECTRICITY | J41: 8760 | K41: 1 | L41: 1 | M41: =5542.18769541597/1000 -> 5.5421877 | N41: =5362.133837/1000 -> 5.3621338 | O41: 0 | P41: 25 | Q41: 0.006 | R41: 1 | S41: 1 | T41: =Capacity!B42*1000 -> 200.0841 | U41: =Capacity!AR42*1000 -> 0 | V41: =Capacity!D42*1000 -> 138 | W41: =Capacity!X42*1000 -> 138 | Z41: 0.51 | AA41: 0.104 | AC41: 1 | AF41: 0 | AG41: =Z41*Conversions!$D$4 -> 0.63184797 | AH41: =M41-AG41 -> 4.9103397 | AI41: =P41 -> 25 | AJ41: =AA41/(1-(1+AA41)^-AI41) -> 0.113573 | AK41: =AH41/AJ41 -> 43.235096 | AL41: =T41-U41 -> 200.0841
B42: EG_WINDON | C42: ER | D42: VRE | E42: onshore_wind | F42: INDIA | G42: MW | H42: WIND | I42: ELECTRICITY | J42: 8760 | K42: 1 | L42: 1 | M42: =10659.4302732183/1000 -> 10.65943 | N42: =10586.96446/1000 -> 10.586964 | O42: 0 | P42: 25 | Q42: 0.005 | R42: 1 | S42: 1 | T42: =Capacity!B43*1000 -> 46 | U42: =Capacity!AR43*1000 -> 0 | V42: =Capacity!D43*1000 -> 0 | W42: =Capacity!X43*1000 -> 0 | Z42: 0.68 | AA42: 0.105 | AC42: 1 | AF42: 0 | AG42: =Z42*Conversions!$D$4 -> 0.84246396 | AH42: =M42-AG42 -> 9.8169663 | AI42: =P42 -> 25 | AJ42: =AA42/(1-(1+AA42)^-AI42) -> 0.11442932 | AK42: =AH42/AJ42 -> 85.790655 | AL42: =T42-U42 -> 46
B43: EG_WINDOFF | C43: ER | D43: VRE | F43: INDIA | G43: MW | H43: WIND | I43: ELECTRICITY | J43: 8760 | K43: 1 | L43: 1 | M43: =N43 -> 34.540362 | N43: =34540.36167/1000 -> 34.540362 | O43: 0 | P43: 25 | Q43: 0.005 | R43: 1 | S43: 1 | T43: =Capacity!B44*1000 -> 0 | U43: =Capacity!AR44*1000 -> 0 | V43: =Capacity!D44*1000 -> 0 | W43: =Capacity!X44*1000 -> 0 | Z43: 6.7 | AA43: 0.112 | AC43: 1 | AF43: 0 | AG43: =Z43*Conversions!$D$4 -> 8.3007478 | AH43: =M43-AG43 -> 26.239614 | AI43: =P43 -> 25 | AJ43: =AA43/(1-(1+AA43)^-AI43) -> 0.12047789 | AK43: =AH43/AJ43 -> 217.7961 | AL43: =T43-U43 -> 0
B44: EG_COAL | C44: WR | D44: ThermalPower | E44: coal | F44: INDIA | G44: MW | H44: THERMAL_COAL | I44: ELECTRICITY | J44: 8760 | K44: 0.3809682 | L44: 0.85 | M44: =5794.65159561365/1000 -> 5.7946516 | N44: =13721.03129/1000 -> 13.721031 | O44: 133.52302 | P44: 40 | Q44: 0.066 | R44: 0.3 | S44: 0.3 | T44: =Capacity!B47*1000 -> 90475.826 | U44: =Capacity!AR47*1000 -> 0 | V44: =Capacity!D47*1000 -> 0 | W44: =Capacity!X47*1000 -> 0 | X44: =CarriersTech_characteristics!$G$2 -> 17.207188 | Y44: =CarriersTech_characteristics!$H$28*1000 -> 1942097.6 | Z44: 3 | AA44: 0.105 | AC44: =1/K44/(1-Q44) -> 2.8103758 | AE44: =Y44/(X44*Conversions!$D$2) -> 0.40631575 | AF44: =O44/CarriersTech_characteristics!$G$2/Conversions!$D$2*AC44 -> 7.850786e-05 | AG44: =Z44*Conversions!$D$4 -> 3.7167527 | AH44: =M44-AG44 -> 2.0778989 | AI44: =P44 -> 40 | AJ44: =AA44/(1-(1+AA44)^-AI44) -> 0.10697141 | AK44: =AH44/AJ44 -> 19.424806 | AL44: =T44-U44 -> 90475.826
B45: EG_CCGT | C45: WR | D45: ThermalPower | E45: NG_CCGT | F45: INDIA | G45: MW | H45: NATGAS | I45: ELECTRICITY | J45: 8760 | K45: 0.40444272 | L45: 0.85 | M45: =8512.22780274884/1000 -> 8.5122278 | N45: =8512.227803/1000 -> 8.5122278 | O45: 0 | P45: 25 | Q45: 0.02 | R45: 0.9 | S45: 0.9 | T45: =Capacity!B48*1000 -> 13563.175 | U45: =Capacity!AR48*1000 -> 0 | V45: =Capacity!D48*1000 -> 0 | W45: =Capacity!X48*1000 -> 0 | X45: =CarriersTech_characteristics!$G$3 -> 37.6812 | Y45: =CarriersTech_characteristics!$H$3*1000 -> 3025024.5 | Z45: 2.9 | AA45: 0.105 | AC45: =1/K45/(1-Q45) -> 2.522998 | AE45: =(Y45*Conversions!$D$3)/(X45*Conversions!$D$2) -> 0.23958587 | AF45: 0 | AG45: =Z45*Conversions!$D$4 -> 3.592861 | AH45: =M45-AG45 -> 4.9193668 | AI45: =P45 -> 25 | AJ45: =AA45/(1-(1+AA45)^-AI45) -> 0.11442932 | AK45: =AH45/AJ45 -> 42.99044 | AL45: =T45-U45 -> 13563.175
B46: EG_OCGT | C46: WR | D46: ThermalPower | F46: INDIA | G46: MW | H46: NATGAS | I46: ELECTRICITY | J46: 8760 | K46: 0.28070163 | L46: 0.85 | M46: =6679.75064927145/1000 -> 6.6797506 | N46: =6679.750649/1000 -> 6.6797506 | O46: 0 | P46: 25 | Q46: 0.01 | R46: 1 | S46: 1 | T46: =Capacity!B49*1000 -> 0 | U46: =Capacity!AR49*1000 -> 0 | V46: =Capacity!D49*1000 -> 0 | W46: =Capacity!X49*1000 -> 0 | X46: =CarriersTech_characteristics!$G$3 -> 37.6812 | Y46: =CarriersTech_characteristics!$H$3*1000 -> 3025024.5 | Z46: 0.7 | AA46: 0.105 | AC46: =1/K46/(1-Q46) -> 3.5984865 | AE46: =(Y46*Conversions!$D$3)/(X46*Conversions!$D$2) -> 0.23958587 | AF46: 0 | AG46: =Z46*Conversions!$D$4 -> 0.86724231 | AH46: =M46-AG46 -> 5.8125083 | AI46: =P46 -> 25 | AJ46: =AA46/(1-(1+AA46)^-AI46) -> 0.11442932 | AK46: =AH46/AJ46 -> 50.795621 | AL46: =T46-U46 -> 0
B47: EG_PHWR | C47: WR | D47: ThermalPower | E47: nuclear_PHWR | F47: INDIA | G47: MW | H47: ATOMIC | I47: ELECTRICITY | J47: 8760 | K47: 1 | L47: 0.70916667 | M47: =20833.2103478327/1000 -> 20.83321 | N47: =20833.21035/1000 -> 20.83321 | O47: 0 | P47: 40 | Q47: 0.1078 | R47: 0.01 | S47: 0.01 | T47: =Capacity!B50*1000 -> 3248.824 | U47: =Capacity!AR50*1000 -> 0 | V47: =Capacity!D50*1000 -> 1400 | W47: =Capacity!X50*1000 -> 1400 | Z47: 4.3 | AA47: 0.105 | AC47: =1/K47/(1-Q47) -> 1.1208249 | AF47: 0 | AG47: =Z47*Conversions!$D$4 -> 5.3273456 | AH47: =M47-AG47 -> 15.505865 | AI47: =P47 -> 40 | AJ47: =AA47/(1-(1+AA47)^-AI47) -> 0.10697141 | AK47: =AH47/AJ47 -> 144.95336 | AL47: =T47-U47 -> 3248.824
B48: EG_SMR | C48: WR | D48: ThermalPower | F48: INDIA | G48: MW | H48: ATOMIC | I48: ELECTRICITY | J48: 8760 | K48: 1 | L48: 0.70916667 | M48: =N48 -> 35.289429 | N48: =35289.42939/1000 -> 35.289429 | O48: 0 | P48: 30 | Q48: 0.05 | R48: 0.01 | S48: 0.01 | T48: =Capacity!B51*1000 -> 0 | U48: =Capacity!AR51*1000 -> 0 | V48: =Capacity!D51*1000 -> 0 | W48: =Capacity!X51*1000 -> 0 | Z48: 5 | AA48: 0.105 | AC48: =1/K48/(1-Q48) -> 1.0526316 | AF48: 0 | AG48: =Z48*Conversions!$D$4 -> 6.1945879 | AH48: =M48-AG48 -> 29.094841 | AI48: =P48 -> 30 | AJ48: =AA48/(1-(1+AA48)^-AI48) -> 0.11052848 | AK48: =AH48/AJ48 -> 263.23388 | AL48: =T48-U48 -> 0
B49: EG_LH | C49: WR | D49: HydroRes | E49: conventional_hydroelectric | F49: INDIA | G49: MW | H49: HYDEL | I49: ELECTRICITY | J49: 8760 | K49: 1 | L49: 1 | M49: =19631.8145207228/1000 -> 19.631815 | N49: =19631.81452/1000 -> 19.631815 | O49: 0 | P49: 40 | Q49: 0.006 | R49: 1 | S49: 1 | T49: =Capacity!B52*1000 -> 7753.2156 | U49: =Capacity!AR52*1000 -> 0 | V49: =Capacity!D52*1000 -> 0 | W49: =Capacity!X52*1000 -> 0 | Z49: 4.4 | AA49: 0.105 | AD49: =K49-Q49 -> 0.994 | AF49: 0 | AG49: =Z49*Conversions!$D$4 -> 5.4512374 | AH49: =M49-AG49 -> 14.180577 | AI49: =P49 -> 40 | AJ49: =AA49/(1-(1+AA49)^-AI49) -> 0.10697141 | AK49: =AH49/AJ49 -> 132.56418 | AL49: =T49-U49 -> 7753.2156
B50: EG_SH | C50: WR | D50: HydroRes | E50: conventional_hydroelectric_small | F50: INDIA | G50: MW | H50: HYDEL | I50: ELECTRICITY | J50: 8760 | K50: 1 | L50: 1 | M50: =11825.3487554956/1000 -> 11.825349 | N50: =11825.34876/1000 -> 11.825349 | O50: 0 | P50: 35 | Q50: 0.01 | R50: 1 | S50: 1 | T50: =Capacity!B53*1000 -> 672.48 | U50: =Capacity!AR53*1000 -> 0 | V50: =Capacity!D53*1000 -> 11 | W50: =Capacity!X53*1000 -> 11 | Z50: =2.4 -> 2.4 | AA50: 0.0835 | AD50: =K50-Q50 -> 0.99 | AF50: 0 | AG50: =Z50*Conversions!$D$4 -> 2.9734022 | AH50: =M50-AG50 -> 8.8519466 | AI50: =P50 -> 35 | AJ50: =AA50/(1-(1+AA50)^-AI50) -> 0.088866959 | AK50: =AH50/AJ50 -> 99.608974 | AL50: =T50-U50 -> 672.48
B51: EG_BIOMASS | C51: WR | D51: ThermalPower | E51: biomass | F51: INDIA | G51: MW | H51: BIOMASS_WASTE | I51: ELECTRICITY | J51: 8760 | K51: 0.2388459 | L51: 1 | M51: =7713.45723965334/1000 -> 7.7134572 | N51: =7713.45724/1000 -> 7.7134572 | O51: 0 | P51: 20 | Q51: 0.1 | R51: 0.06 | S51: 0.06 | T51: =Capacity!B54*1000 -> 3161.7 | U51: =Capacity!AR54*1000 -> 0 | V51: =Capacity!D54*1000 -> 136 | W51: =Capacity!X54*1000 -> 136 | X51: =CarriersTech_characteristics!$G$7 -> 13.648968 | Y51: =CarriersTech_characteristics!$H$5*1000 -> 1656436.7 | Z51: 1 | AA51: 0.0835 | AC51: =1/K51/(1-Q51) -> 4.652 | AE51: =Y51/(X51*Conversions!$D$2) -> 0.43689545 | AF51: 0 | AG51: =Z51*Conversions!$D$4 -> 1.2389176 | AH51: =M51-AG51 -> 6.4745397 | AI51: =P51 -> 20 | AJ51: =AA51/(1-(1+AA51)^-AI51) -> 0.1045193 | AK51: =AH51/AJ51 -> 61.945879 | AL51: =T51-U51 -> 3161.7
B52: EG_SOLARGM | C52: WR | D52: VRE | E52: solar_GM | F52: INDIA | G52: MW | H52: SUNLIGHT | I52: ELECTRICITY | J52: 8760 | K52: 1 | L52: 1 | M52: =5630.98419436319/1000 -> 5.6309842 | N52: =5439.705856/1000 -> 5.4397059 | O52: 0 | P52: 25 | Q52: 0.01 | R52: 1 | S52: 1 | T52: =Capacity!B55*1000 -> 13221.936 | U52: =Capacity!AR55*1000 -> 0 | V52: =Capacity!D55*1000 -> 5560 | W52: =Capacity!X55*1000 -> 5560 | Z52: 0.35 | AA52: 0.105 | AC52: 1 | AF52: 0 | AG52: =Z52*Conversions!$D$4 -> 0.43362115 | AH52: =M52-AG52 -> 5.197363 | AI52: =P52 -> 25 | AJ52: =AA52/(1-(1+AA52)^-AI52) -> 0.11442932 | AK52: =AH52/AJ52 -> 45.419854 | AL52: =T52-U52 -> 13221.936
B53: EG_SOLARRF | C53: WR | D53: VRE | E53: solar_RT | F53: INDIA | G53: MW | H53: SUNLIGHT | I53: ELECTRICITY | J53: 8760 | K53: 1 | L53: 1 | M53: =5542.18769541597/1000 -> 5.5421877 | N53: =5362.133837/1000 -> 5.3621338 | O53: 0 | P53: 25 | Q53: 0.006 | R53: 1 | S53: 1 | T53: =Capacity!B56*1000 -> 4503.404 | U53: =Capacity!AR56*1000 -> 0 | V53: =Capacity!D56*1000 -> 1704 | W53: =Capacity!X56*1000 -> 1704 | Z53: 0.51 | AA53: 0.104 | AC53: 1 | AF53: 0 | AG53: =Z53*Conversions!$D$4 -> 0.63184797 | AH53: =M53-AG53 -> 4.9103397 | AI53: =P53 -> 25 | AJ53: =AA53/(1-(1+AA53)^-AI53) -> 0.113573 | AK53: =AH53/AJ53 -> 43.235096 | AL53: =T53-U53 -> 4503.404
B54: EG_WINDON | C54: WR | D54: VRE | E54: onshore_wind | F54: INDIA | G54: MW | H54: WIND | I54: ELECTRICITY | J54: 8760 | K54: 1 | L54: 1 | M54: =10659.4302732183/1000 -> 10.65943 | N54: =10586.96446/1000 -> 10.586964 | O54: 0 | P54: 25 | Q54: 0.005 | R54: 1 | S54: 1 | T54: =Capacity!B57*1000 -> 18661.04 | U54: =Capacity!AR57*1000 -> 0 | V54: =Capacity!D57*1000 -> 1939 | W54: =Capacity!X57*1000 -> 1939 | Z54: 0.68 | AA54: 0.105 | AC54: 1 | AF54: 0 | AG54: =Z54*Conversions!$D$4 -> 0.84246396 | AH54: =M54-AG54 -> 9.8169663 | AI54: =P54 -> 25 | AJ54: =AA54/(1-(1+AA54)^-AI54) -> 0.11442932 | AK54: =AH54/AJ54 -> 85.790655 | AL54: =T54-U54 -> 18661.04
B55: EG_WINDOFF | C55: WR | D55: VRE | F55: INDIA | G55: MW | H55: WIND | I55: ELECTRICITY | J55: 8760 | K55: 1 | L55: 1 | M55: =N55 -> 34.540362 | N55: =34540.36167/1000 -> 34.540362 | O55: 0 | P55: 25 | Q55: 0.005 | R55: 1 | S55: 1 | T55: =Capacity!B58*1000 -> 0 | U55: =Capacity!AR58*1000 -> 0 | V55: =Capacity!D58*1000 -> 0 | W55: =Capacity!X58*1000 -> 0 | Z55: 6.7 | AA55: 0.112 | AC55: 1 | AF55: 0 | AG55: =Z55*Conversions!$D$4 -> 8.3007478 | AH55: =M55-AG55 -> 26.239614 | AI55: =P55 -> 25 | AJ55: =AA55/(1-(1+AA55)^-AI55) -> 0.12047789 | AK55: =AH55/AJ55 -> 217.7961 | AL55: =T55-U55 -> 0
B56: EG_COAL | C56: SR | D56: ThermalPower | E56: coal | F56: INDIA | G56: MW | H56: THERMAL_COAL | I56: ELECTRICITY | J56: 8760 | K56: 0.3809682 | L56: 0.85 | M56: =5822.44460147077/1000 -> 5.8224446 | N56: =13721.03129/1000 -> 13.721031 | O56: 133.52302 | P56: 40 | Q56: 0.066 | R56: 0.3 | S56: 0.3 | T56: =Capacity!B61*1000 -> 63929.271 | U56: =Capacity!AR61*1000 -> 0 | V56: =Capacity!D61*1000 -> 0 | W56: =Capacity!X61*1000 -> 0 | X56: =CarriersTech_characteristics!$G$2 -> 17.207188 | Y56: =CarriersTech_characteristics!$H$28*1000 -> 1942097.6 | Z56: 3 | AA56: 0.105 | AC56: =1/K56/(1-Q56) -> 2.8103758 | AE56: =Y56/(X56*Conversions!$D$2) -> 0.40631575 | AF56: =O56/CarriersTech_characteristics!$G$2/Conversions!$D$2*AC56 -> 7.850786e-05 | AG56: =Z56*Conversions!$D$4 -> 3.7167527 | AH56: =M56-AG56 -> 2.1056919 | AI56: =P56 -> 40 | AJ56: =AA56/(1-(1+AA56)^-AI56) -> 0.10697141 | AK56: =AH56/AJ56 -> 19.684623 | AL56: =T56-U56 -> 63929.271
B57: EG_CCGT | C57: SR | D57: ThermalPower | E57: NG_CCGT | F57: INDIA | G57: MW | H57: NATGAS | I57: ELECTRICITY | J57: 8760 | K57: 0.40444272 | L57: 0.85 | M57: =8512.22780274884/1000 -> 8.5122278 | N57: =8512.227803/1000 -> 8.5122278 | O57: 0 | P57: 25 | Q57: 0.02 | R57: 0.9 | S57: 0.9 | T57: =Capacity!B62*1000 -> 7730.2171 | U57: =Capacity!AR62*1000 -> 0 | V57: =Capacity!D62*1000 -> 370 | W57: =Capacity!X62*1000 -> 370 | X57: =CarriersTech_characteristics!$G$3 -> 37.6812 | Y57: =CarriersTech_characteristics!$H$3*1000 -> 3025024.5 | Z57: 2.9 | AA57: 0.105 | AC57: =1/K57/(1-Q57) -> 2.522998 | AE57: =(Y57*Conversions!$D$3)/(X57*Conversions!$D$2) -> 0.23958587 | AF57: 0 | AG57: =Z57*Conversions!$D$4 -> 3.592861 | AH57: =M57-AG57 -> 4.9193668 | AI57: =P57 -> 25 | AJ57: =AA57/(1-(1+AA57)^-AI57) -> 0.11442932 | AK57: =AH57/AJ57 -> 42.99044 | AL57: =T57-U57 -> 7730.2171
B58: EG_OCGT | C58: SR | D58: ThermalPower | F58: INDIA | G58: MW | H58: NATGAS | I58: ELECTRICITY | J58: 8760 | K58: 0.28070163 | L58: 0.85 | M58: =6679.75064927145/1000 -> 6.6797506 | N58: =6679.750649/1000 -> 6.6797506 | O58: 0 | P58: 25 | Q58: 0.01 | R58: 1 | S58: 1 | T58: =Capacity!B63*1000 -> 0 | U58: =Capacity!AR63*1000 -> 0 | V58: =Capacity!D63*1000 -> 0 | W58: =Capacity!X63*1000 -> 0 | X58: =CarriersTech_characteristics!$G$3 -> 37.6812 | Y58: =CarriersTech_characteristics!$H$3*1000 -> 3025024.5 | Z58: 0.7 | AA58: 0.105 | AC58: =1/K58/(1-Q58) -> 3.5984865 | AE58: =(Y58*Conversions!$D$3)/(X58*Conversions!$D$2) -> 0.23958587 | AF58: 0 | AG58: =Z58*Conversions!$D$4 -> 0.86724231 | AH58: =M58-AG58 -> 5.8125083 | AI58: =P58 -> 25 | AJ58: =AA58/(1-(1+AA58)^-AI58) -> 0.11442932 | AK58: =AH58/AJ58 -> 50.795621 | AL58: =T58-U58 -> 0
B59: EG_PHWR | C59: SR | D59: ThermalPower | E59: nuclear_PHWR | F59: INDIA | G59: MW | H59: ATOMIC | I59: ELECTRICITY | J59: 8760 | K59: 1 | L59: 0.70916667 | M59: =20833.2103478327/1000 -> 20.83321 | N59: =20833.21035/1000 -> 20.83321 | O59: 0 | P59: 40 | Q59: 0.1078 | R59: 0.01 | S59: 0.01 | T59: =Capacity!B64*1000 -> 3327.6676 | U59: =Capacity!AR64*1000 -> 0 | V59: =Capacity!D64*1000 -> 0 | W59: =Capacity!X64*1000 -> 0 | Z59: 4.3 | AA59: 0.105 | AC59: =1/K59/(1-Q59) -> 1.1208249 | AF59: 0 | AG59: =Z59*Conversions!$D$4 -> 5.3273456 | AH59: =M59-AG59 -> 15.505865 | AI59: =P59 -> 40 | AJ59: =AA59/(1-(1+AA59)^-AI59) -> 0.10697141 | AK59: =AH59/AJ59 -> 144.95336 | AL59: =T59-U59 -> 3327.6676
B60: EG_SMR | C60: SR | D60: ThermalPower | F60: INDIA | G60: MW | H60: ATOMIC | I60: ELECTRICITY | J60: 8760 | K60: 1 | L60: 0.70916667 | M60: =N60 -> 35.289429 | N60: =35289.42939/1000 -> 35.289429 | O60: 0 | P60: 30 | Q60: 0.05 | R60: 0.01 | S60: 0.01 | T60: =Capacity!B65*1000 -> 0 | U60: =Capacity!AR65*1000 -> 0 | V60: =Capacity!D65*1000 -> 0 | W60: =Capacity!X65*1000 -> 0 | Z60: 5 | AA60: 0.105 | AC60: =1/K60/(1-Q60) -> 1.0526316 | AF60: 0 | AG60: =Z60*Conversions!$D$4 -> 6.1945879 | AH60: =M60-AG60 -> 29.094841 | AI60: =P60 -> 30 | AJ60: =AA60/(1-(1+AA60)^-AI60) -> 0.11052848 | AK60: =AH60/AJ60 -> 263.23388 | AL60: =T60-U60 -> 0
B61: EG_LH | C61: SR | D61: HydroRes | E61: conventional_hydroelectric | F61: INDIA | G61: MW | H61: HYDEL | I61: ELECTRICITY | J61: 8760 | K61: 1 | L61: 1 | M61: =19631.8145207228/1000 -> 19.631815 | N61: =19631.81452/1000 -> 19.631815 | O61: 0 | P61: 40 | Q61: 0.006 | R61: 1 | S61: 1 | T61: =Capacity!B66*1000 -> 12168.961 | U61: =Capacity!AR66*1000 -> 0 | V61: =Capacity!D66*1000 -> 0 | W61: =Capacity!X66*1000 -> 0 | Z61: 4.4 | AA61: 0.105 | AD61: =K61-Q61 -> 0.994 | AF61: 0 | AG61: =Z61*Conversions!$D$4 -> 5.4512374 | AH61: =M61-AG61 -> 14.180577 | AI61: =P61 -> 40 | AJ61: =AA61/(1-(1+AA61)^-AI61) -> 0.10697141 | AK61: =AH61/AJ61 -> 132.56418 | AL61: =T61-U61 -> 12168.961
B62: EG_SH | C62: SR | D62: HydroRes | E62: conventional_hydroelectric_small | F62: INDIA | G62: MW | H62: HYDEL | I62: ELECTRICITY | J62: 8760 | K62: 1 | L62: 1 | M62: =11825.3487554956/1000 -> 11.825349 | N62: =11825.34876/1000 -> 11.825349 | O62: 0 | P62: 35 | Q62: 0.01 | R62: 1 | S62: 1 | T62: =Capacity!B67*1000 -> 1924.48 | U62: =Capacity!AR67*1000 -> 0 | V62: =Capacity!D67*1000 -> 17 | W62: =Capacity!X67*1000 -> 17 | Z62: =2.4 -> 2.4 | AA62: 0.0835 | AD62: =K62-Q62 -> 0.99 | AF62: 0 | AG62: =Z62*Conversions!$D$4 -> 2.9734022 | AH62: =M62-AG62 -> 8.8519466 | AI62: =P62 -> 35 | AJ62: =AA62/(1-(1+AA62)^-AI62) -> 0.088866959 | AK62: =AH62/AJ62 -> 99.608974 | AL62: =T62-U62 -> 1924.48
B63: EG_BIOMASS | C63: SR | D63: ThermalPower | E63: biomass | F63: INDIA | G63: MW | H63: BIOMASS_WASTE | I63: ELECTRICITY | J63: 8760 | K63: 0.2388459 | L63: 1 | M63: =7713.45723965334/1000 -> 7.7134572 | N63: =7713.45724/1000 -> 7.7134572 | O63: 0 | P63: 20 | Q63: 0.1 | R63: 0.06 | S63: 0.06 | T63: =Capacity!B68*1000 -> 3734.75 | U63: =Capacity!AR68*1000 -> 0 | V63: =Capacity!D68*1000 -> 160 | W63: =Capacity!X68*1000 -> 160 | X63: =CarriersTech_characteristics!$G$7 -> 13.648968 | Y63: =CarriersTech_characteristics!$H$5*1000 -> 1656436.7 | Z63: 1 | AA63: 0.0835 | AC63: =1/K63/(1-Q63) -> 4.652 | AE63: =Y63/(X63*Conversions!$D$2) -> 0.43689545 | AF63: 0 | AG63: =Z63*Conversions!$D$4 -> 1.2389176 | AH63: =M63-AG63 -> 6.4745397 | AI63: =P63 -> 20 | AJ63: =AA63/(1-(1+AA63)^-AI63) -> 0.1045193 | AK63: =AH63/AJ63 -> 61.945879 | AL63: =T63-U63 -> 3734.75
B64: EG_SOLARGM | C64: SR | D64: VRE | E64: solar_GM | F64: INDIA | G64: MW | H64: SUNLIGHT | I64: ELECTRICITY | J64: 8760 | K64: 1 | L64: 1 | M64: =5630.98419436319/1000 -> 5.6309842 | N64: =5439.705856/1000 -> 5.4397059 | O64: 0 | P64: 25 | Q64: 0.01 | R64: 1 | S64: 1 | T64: =Capacity!B69*1000 -> 24128.917 | U64: =Capacity!AR69*1000 -> 0 | V64: =Capacity!D69*1000 -> 1622 | W64: =Capacity!X69*1000 -> 1622 | Z64: 0.35 | AA64: 0.105 | AC64: 1 | AF64: 0 | AG64: =Z64*Conversions!$D$4 -> 0.43362115 | AH64: =M64-AG64 -> 5.197363 | AI64: =P64 -> 25 | AJ64: =AA64/(1-(1+AA64)^-AI64) -> 0.11442932 | AK64: =AH64/AJ64 -> 45.419854 | AL64: =T64-U64 -> 24128.917
B65: EG_SOLARRF | C65: SR | D65: VRE | E65: solar_RT | F65: INDIA | G65: MW | H65: SUNLIGHT | I65: ELECTRICITY | J65: 8760 | K65: 1 | L65: 1 | M65: =5542.18769541597/1000 -> 5.5421877 | N65: =5362.133837/1000 -> 5.3621338 | O65: 0 | P65: 25 | Q65: 0.006 | R65: 1 | S65: 1 | T65: =Capacity!B70*1000 -> 2030.8232 | U65: =Capacity!AR70*1000 -> 0 | V65: =Capacity!D70*1000 -> 618 | W65: =Capacity!X70*1000 -> 618 | Z65: 0.51 | AA65: 0.104 | AC65: 1 | AF65: 0 | AG65: =Z65*Conversions!$D$4 -> 0.63184797 | AH65: =M65-AG65 -> 4.9103397 | AI65: =P65 -> 25 | AJ65: =AA65/(1-(1+AA65)^-AI65) -> 0.113573 | AK65: =AH65/AJ65 -> 43.235096 | AL65: =T65-U65 -> 2030.8232
B66: EG_WINDON | C66: SR | D66: VRE | E66: onshore_wind | F66: INDIA | G66: MW | H66: WIND | I66: ELECTRICITY | J66: 8760 | K66: 1 | L66: 1 | M66: =10659.4302732183/1000 -> 10.65943 | N66: =10586.96446/1000 -> 10.586964 | O66: 0 | P66: 25 | Q66: 0.005 | R66: 1 | S66: 1 | T66: =Capacity!B71*1000 -> 22161.37 | U66: =Capacity!AR71*1000 -> 0 | V66: =Capacity!D71*1000 -> 1312 | W66: =Capacity!X71*1000 -> 1312 | Z66: 0.68 | AA66: 0.105 | AC66: 1 | AF66: 0 | AG66: =Z66*Conversions!$D$4 -> 0.84246396 | AH66: =M66-AG66 -> 9.8169663 | AI66: =P66 -> 25 | AJ66: =AA66/(1-(1+AA66)^-AI66) -> 0.11442932 | AK66: =AH66/AJ66 -> 85.790655 | AL66: =T66-U66 -> 22161.37
B67: EG_WINDOFF | C67: SR | D67: VRE | F67: INDIA | G67: MW | H67: WIND | I67: ELECTRICITY | J67: 8760 | K67: 1 | L67: 1 | M67: =N67 -> 34.540362 | N67: =34540.36167/1000 -> 34.540362 | O67: 0 | P67: 25 | Q67: 0.005 | R67: 1 | S67: 1 | T67: =Capacity!B72*1000 -> 0 | U67: =Capacity!AR72*1000 -> 0 | V67: =Capacity!D72*1000 -> 0 | W67: =Capacity!X72*1000 -> 0 | Z67: 6.7 | AA67: 0.112 | AC67: 1 | AF67: 0 | AG67: =Z67*Conversions!$D$4 -> 8.3007478 | AH67: =M67-AG67 -> 26.239614 | AI67: =P67 -> 25 | AJ67: =AA67/(1-(1+AA67)^-AI67) -> 0.12047789 | AK67: =AH67/AJ67 -> 217.7961 | AL67: =T67-U67 -> 0
B68: EG_COAL | C68: ALL | D68: ThermalPower | E68: coal | F68: INDIA | G68: MW | H68: THERMAL_COAL | I68: ELECTRICITY | J68: 8760 | K68: 0.3809682 | N68: =13721.03129/1000 -> 13.721031 | O68: 133.52302 | P68: 40 | Q68: 0.066 | T68: =T8+T20+T32+T44+T56 -> 264372.47 | U68: =U8+U20+U32+U44+U56 -> 220 | V68: =V8+V20+V32+V44+V56 -> 0 | W68: =W8+W20+W32+W44+W56 -> 0 | X68: =CarriersTech_characteristics!$G$2 -> 17.207188 | Y68: =CarriersTech_characteristics!$H$28*1000 -> 1942097.6 | AC68: =1/K68/(1-Q68) -> 2.8103758 | AE68: =Y68/(X68*Conversions!$D$2) -> 0.40631575 | AL68: =AL8+AL20+AL32+AL44+AL56 -> 264152.47
B69: EG_CCGT | C69: ALL | D69: ThermalPower | E69: NG_CCGT | F69: INDIA | G69: MW | H69: NATGAS | I69: ELECTRICITY | J69: 8760 | K69: 0.40444272 | L69: 0.85 | M69: =8512.22780274884/1000 -> 8.5122278 | N69: =8512.227803/1000 -> 8.5122278 | O69: 0 | P69: 25 | Q69: 0.02 | R69: 0.9 | S69: 0.9 | T69: =T9+T21+T33+T45+T57 -> 31397.2 | U69: =U9+U21+U33+U45+U57 -> 0 | V69: =V9+V21+V33+V45+V57 -> 370 | W69: =W9+W21+W33+W45+W57 -> 370 | X69: =CarriersTech_characteristics!$G$3 -> 37.6812 | Y69: =CarriersTech_characteristics!$H$3*1000 -> 3025024.5 | AC69: =1/K69/(1-Q69) -> 2.522998 | AE69: =(Y69*Conversions!$D$3)/(X69*Conversions!$D$2) -> 0.23958587 | AL69: =AL9+AL21+AL33+AL45+AL57 -> 31397.2
B70: EG_OCGT | C70: ALL | D70: ThermalPower | F70: INDIA | G70: MW | H70: NATGAS | I70: ELECTRICITY | J70: 8760 | K70: 0.28070163 | L70: 0.85 | M70: =6679.75064927145/1000 -> 6.6797506 | N70: =6679.750649/1000 -> 6.6797506 | O70: 0 | P70: 25 | Q70: 0.01 | R70: 1 | S70: 1 | T70: =T10+T22+T34+T46+T58 -> 0 | U70: =U10+U22+U34+U46+U58 -> 0 | V70: =V10+V22+V34+V46+V58 -> 0 | W70: =W10+W22+W34+W46+W58 -> 0 | X70: =CarriersTech_characteristics!$G$3 -> 37.6812 | Y70: =CarriersTech_characteristics!$H$3*1000 -> 3025024.5 | AC70: =1/K70/(1-Q70) -> 3.5984865 | AE70: =(Y70*Conversions!$D$3)/(X70*Conversions!$D$2) -> 0.23958587 | AL70: =AL10+AL22+AL34+AL46+AL58 -> 0
B71: EG_PHWR | C71: ALL | D71: ThermalPower | E71: nuclear_PHWR | F71: INDIA | G71: MW | H71: ATOMIC | I71: ELECTRICITY | J71: 8760 | K71: 1 | L71: 0.70916667 | M71: =20833.2103478327/1000 -> 20.83321 | N71: =20833.21035/1000 -> 20.83321 | O71: 0 | P71: 40 | Q71: 0.1078 | R71: 0.01 | S71: 0.01 | T71: =T11+T23+T35+T47+T59 -> 8180.01 | U71: =U11+U23+U35+U47+U59 -> 0 | V71: =V11+V23+V35+V47+V59 -> 1400 | W71: =W11+W23+W35+W47+W59 -> 1400 | AC71: =1/K71/(1-Q71) -> 1.1208249 | AL71: =AL11+AL23+AL35+AL47+AL59 -> 8180.01
B72: EG_SMR | C72: ALL | D72: ThermalPower | F72: INDIA | G72: MW | H72: ATOMIC | I72: ELECTRICITY | J72: 8760 | K72: 1 | L72: 0.70916667 | N72: =35289.42939/1000 -> 35.289429 | O72: 0 | P72: 30 | Q72: 0.05 | R72: 0.01 | S72: 0.01 | T72: =T12+T24+T36+T48+T60 -> 0 | U72: =U12+U24+U36+U48+U60 -> 0 | V72: =V12+V24+V36+V48+V60 -> 0 | W72: =W12+W24+W36+W48+W60 -> 0 | AC72: =1/K72/(1-Q72) -> 1.0526316 | AL72: =AL12+AL24+AL36+AL48+AL60 -> 0
B73: EG_LH | C73: ALL | D73: HydroRes | E73: conventional_hydroelectric | F73: INDIA | G73: MW | H73: HYDEL | I73: ELECTRICITY | J73: 8760 | K73: 1 | L73: 1 | M73: =19631.8145207228/1000 -> 19.631815 | N73: =19631.81452/1000 -> 19.631815 | O73: 0 | P73: 40 | Q73: 0.006 | R73: 1 | S73: 1 | T73: =T13+T25+T37+T49+T61 -> 46491.18 | U73: =U13+U25+U37+U49+U61 -> 0 | V73: =V13+V25+V37+V49+V61 -> 0 | W73: =W13+W25+W37+W49+W61 -> 0 | AD73: =K73-Q73 -> 0.994 | AL73: =AL13+AL25+AL37+AL49+AL61 -> 46491.18
B74: EG_SH | C74: ALL | D74: HydroRes | E74: conventional_hydroelectric_small | F74: INDIA | G74: MW | H74: HYDEL | I74: ELECTRICITY | J74: 8760 | K74: 1 | L74: 1 | M74: =11825.3487554956/1000 -> 11.825349 | N74: =11825.34876/1000 -> 11.825349 | O74: 0 | P74: 35 | Q74: 0.01 | R74: 1 | S74: 1 | T74: =T14+T26+T38+T50+T62 -> 4939.05 | U74: =U14+U26+U38+U50+U62 -> 0 | V74: =V14+V26+V38+V50+V62 -> 72 | W74: =W14+W26+W38+W50+W62 -> 72 | AD74: =K74-Q74 -> 0.99 | AL74: =AL14+AL26+AL38+AL50+AL62 -> 4939.05
B75: EG_BIOMASS | C75: ALL | D75: ThermalPower | E75: biomass | F75: INDIA | G75: MW | H75: BIOMASS_WASTE | I75: ELECTRICITY | J75: 8760 | K75: 0.2388459 | L75: 1 | M75: =7713.45723965334/1000 -> 7.7134572 | N75: =7713.45724/1000 -> 7.7134572 | O75: 0 | P75: 20 | Q75: 0.1 | R75: 0.06 | S75: 0.06 | T75: =T15+T27+T39+T51+T63 -> 10830.04 | U75: =U15+U27+U39+U51+U63 -> 0 | V75: =V15+V27+V39+V51+V63 -> 463 | W75: =W15+W27+W39+W51+W63 -> 463 | X75: =CarriersTech_characteristics!$G$7 -> 13.648968 | Y75: =CarriersTech_characteristics!$H$5*1000 -> 1656436.7 | AC75: =1/K75/(1-Q75) -> 4.652 | AE75: =Y75/(X75*Conversions!$D$2) -> 0.43689545 | AL75: =AL15+AL27+AL39+AL51+AL63 -> 10830.04
B76: EG_SOLARGM | C76: ALL | D76: VRE | E76: solar_GM | F76: INDIA | G76: MW | H76: SUNLIGHT | I76: ELECTRICITY | J76: 8760 | K76: 1 | L76: 1 | M76: =5630.98419436319/1000 -> 5.6309842 | N76: =5439.705856/1000 -> 5.4397059 | O76: 0 | P76: 25 | Q76: 0.01 | R76: 1 | S76: 1 | T76: =T16+T28+T40+T52+T64 -> 58366.793 | U76: =U16+U28+U40+U52+U64 -> 0 | V76: =V16+V28+V40+V52+V64 -> 12020 | W76: =W16+W28+W40+W52+W64 -> 12020 | AC76: 1 | AL76: =AL16+AL28+AL40+AL52+AL64 -> 58366.793
B77: EG_SOLARRF | C77: ALL | D77: VRE | E77: solar_RT | F77: INDIA | G77: MW | H77: SUNLIGHT | I77: ELECTRICITY | J77: 8760 | K77: 1 | L77: 1 | M77: =5542.18769541597/1000 -> 5.5421877 | N77: =5362.133837/1000 -> 5.3621338 | O77: 0 | P77: 25 | Q77: 0.006 | R77: 1 | S77: 1 | T77: =T17+T29+T41+T53+T65 -> 9468.2674 | U77: =U17+U29+U41+U53+U65 -> 0 | V77: =V17+V29+V41+V53+V65 -> 3234 | W77: =W17+W29+W41+W53+W65 -> 3234 | AC77: 1 | AL77: =AL17+AL29+AL41+AL53+AL65 -> 9468.2674
B78: EG_WINDON | C78: ALL | D78: VRE | E78: onshore_wind | F78: INDIA | G78: MW | H78: WIND | I78: ELECTRICITY | J78: 8760 | K78: 1 | L78: 1 | M78: =10659.4302732183/1000 -> 10.65943 | N78: =10586.96446/1000 -> 10.586964 | O78: 0 | P78: 25 | Q78: 0.005 | R78: 1 | S78: 1 | T78: =T18+T30+T42+T54+T66 -> 46169.83 | U78: =U18+U30+U42+U54+U66 -> 0 | V78: =V18+V30+V42+V54+V66 -> 3253 | W78: =W18+W30+W42+W54+W66 -> 3253 | AC78: 1 | AL78: =AL18+AL30+AL42+AL54+AL66 -> 46169.83
B79: EG_WINDOFF | C79: ALL | D79: VRE | F79: INDIA | G79: MW | H79: WIND | I79: ELECTRICITY | J79: 8760 | K79: 1 | L79: 1 | N79: =34540.36167/1000 -> 34.540362 | O79: 0 | P79: 25 | Q79: 0.005 | R79: 1 | S79: 1 | T79: =T19+T31+T43+T55+T67 -> 0 | U79: =U19+U31+U43+U55+U67 -> 0 | V79: =V19+V31+V43+V55+V67 -> 0 | W79: =W19+W31+W43+W55+W67 -> 0 | AC79: 1 | AL79: =AL19+AL31+AL43+AL55+AL67 -> 0

Sheet assets_stor_p1
A1: Source::File | G1: PIER::EnergyConvTechnologies.csv | H1: PIER::EnergyStorTechnologies.csv | I1: PIER::EnergyStorTechnologies.csv | J1: PIER::EnergyStorTechnologies.csv | K1: PIER::EnergyStorTechnologies.csv | L1: PIER::EnergyStorTechnologies.csv | M1: PIER2.0::EST_DeratingDepthOfDischarge.csv | N1: PIER2.0::EST_DeratingDepthOfDischarge.csv | O1: PIER2.0::EST_EfficiencyCost.csv | P1: PIER2.0::EST_Lifetime.csv or EST_LegacyDetails.csv | Q1: PIER2.0::EST_Lifetime.csv or EST_LegacyDetails.csv | R1: PIER2.0::EST_EfficiencyCost.csv | S1: PIER2.0::ECT_LegacyDetails.csv | T1: PIER2.0::EST_CapAddBounds.csv | U1: PIER2.0::EST_CapAddBounds.csv | V1: PIER2.0::EST_Parameters.xlsx | W1: PIER2.0::EST_Parameters.xlsx
A2: PIER2.0 var name | B2: EnergyConvTech | C2: SubGeography1 | F2: ModelGeography | G2: CapacityUnit | H2: StoredEC | I2: DomOrImp | J2: MaxChargeRate | K2: MaxDischargeRate | L2: StorPeriodicity | M2: CapacityDerating | N2: DepthOfDischarge | O2: Efficiency | P2: LifetimeYears | Q2: LifetimeCycles | R2: FixedCost | S2: LegacyCapacity | T2: MinCapacity | U2: MaxCapacity
A3: Variable | J3: a | K3: b | M3: c | N3: d | O3: e | P3: f | Q3: g | R3: h | S3: i | T3: j | U3: k | V3: l | W3: m | Y3: aa | Z3: bb | AA3: dd | AB3: ee | AC3: ff
A4: description | C4: model geography | G4: all units in macro are given in the selected value | H4: energy carrier | O4: overall efficiency | P4: lifetime of asset in years | Q4: lifetime of asset in cycles | R4: annuity on new capacity | S4: legacy/existing | T4: pipeline builds | U4: maximum additions | V4: given Fixed O&M (PIER or assumed), adjusted to 2024Rs from 2020Rs | W4: given discount rate from PIER2.0 workbook, No adjustment made | AA4: For existing infrastructure this is half operational lifetime, rounded to integer as Macro will fail if given decimal | AB4: CRF
A5: Equation to Macro var | G5: given / 1000 | H5: given | J5: given | K5: given | M5: given | N5: given | O5: given | P5: given | Q5: given | R5: given/1000 | S5: = given*1000 | T5: = given*1000 | U5: = given*1000 | W5: = given | Y5: = sqrt ( e ) | Z5: = sqrt ( e ) | AA5: = round ( f / 2 , 0) | AB5: = q / ( 1-(1+q)^(-gg)) | AC5: = ff / hh
A6: Macro variable | C6: location | D6: type | E6: id | J6: discharge_max_flow_fraction | P6: lifetime of asset | R6: annualized_investment_cost | T6: min_capcity | U6: max_capacity | W6: wacc | Y6: discharge_efficienc | Z6: charge_efficiency | AA6: capital_recovery_period | AC6: investment_cost
A7: Unit | J7: % | K7: % | M7: % | N7: fraction of capacity | O7: % | P7: years | Q7: cycles | R7: million Rs2024/MW | S7: MW | T7: MW | U7: MW | V7: million 2020Rs/year | W7: % | Y7: % | Z7: % | AA7: years | AC7: million 2024Rs
B8: TWOHR_BATTERY | C8: NR | D8: Battery | E8: 2-Hr | F8: INDIA | G8: MWh | H8: ELECTRICITY | I8: EC_DOM | J8: 0.5 | K8: 0.5 | L8: DAILY | M8: 0 | N8: 0.9 | O8: 0.8 | P8: 10 | Q8: 3873.4092 | R8: =Capacity!C103/1000 -> 2.2475151 | S8: 0 | T8: =S8 -> 0 | U8: =S8 -> 0 | V8: 0 | W8: 0.09 | Y8: =SQRT(O8) -> 0.89442719 | Z8: =Y8 -> 0.89442719 | AA8: =P8 -> 10 | AB8: =W8/(1-(1+W8)^(-AA8)) -> 0.15582009 | AC8: =R8/AB8 -> 14.423783
B9: FOURHR_BATTERY | C9: NR | D9: Battery | E9: 4-Hr | F9: INDIA | G9: MWh | H9: ELECTRICITY | I9: EC_DOM | J9: 0.25 | K9: 0.25 | L9: DAILY | M9: 0 | N9: 0.9 | O9: 0.8 | P9: 10 | Q9: 3873.4092 | R9: =Capacity!C123/1000 -> 1.9123593 | S9: 0 | T9: =S9 -> 0 | U9: =S9 -> 0 | V9: 0 | W9: 0.09 | Y9: =SQRT(O9) -> 0.89442719 | Z9: =Y9 -> 0.89442719 | AA9: =P9 -> 10 | AB9: =W9/(1-(1+W9)^-AA9) -> 0.15582009 | AC9: =R9/AB9 -> 12.272868
B10: SIXHR_BATTERY | C10: NR | D10: Battery | E10: 6-Hr | F10: INDIA | G10: MWh | H10: ELECTRICITY | I10: EC_DOM | J10: 0.166667 | K10: 0.166667 | L10: DAILY | M10: 0 | N10: 0.9 | O10: 0.8 | P10: 10 | Q10: 3873.4092 | R10: =Capacity!C143/1000 -> 1.8006408 | S10: 0 | T10: =S10 -> 0 | U10: =S10 -> 0 | V10: 0 | W10: 0.09 | Y10: =SQRT(O10) -> 0.89442719 | Z10: =Y10 -> 0.89442719 | AA10: =P10 -> 10 | AB10: =W10/(1-(1+W10)^-AA10) -> 0.15582009 | AC10: =R10/AB10 -> 11.555896
B11: PUMPED_STOR | C11: NR | D11: Battery | E11: pumpedhydro | F11: INDIA | G11: MWh | H11: ELECTRICITY | I11: EC_DOM | J11: 0.16666667 | K11: 0.16666667 | L11: DAILY | M11: 0 | N11: 0.9 | O11: 0.75 | P11: =Capacity!E85 -> 20 | Q11: =Capacity!F85 -> 50000 | R11: =Capacity!C163/1000 -> 1.9001303 | S11: =Capacity!D85*1000 -> 0 | T11: =S11 -> 0 | U11: =S11 -> 0 | V11: 0 | W11: 0.09 | Y11: =SQRT(O11) -> 0.8660254 | Z11: =Y11 -> 0.8660254 | AA11: =P11 -> 20 | AB11: =W11/(1-(1+W11)^-AA11) -> 0.10954648 | AC11: =R11/AB11 -> 17.345426
B12: TWOHR_BATTERY | C12: NER | D12: Battery | E12: 2-Hr | F12: INDIA | G12: MWh | H12: ELECTRICITY | I12: EC_DOM | J12: 0.5 | K12: 0.5 | L12: DAILY | M12: 0 | N12: 0.9 | O12: 0.8 | P12: 10 | Q12: 3873.4092 | R12: =$R$8 -> 2.2475151 | S12: 0 | T12: =S12 -> 0 | U12: =S12 -> 0 | V12: 0 | W12: 0.09 | Y12: =SQRT(O12) -> 0.89442719 | Z12: =Y12 -> 0.89442719 | AA12: =P12 -> 10 | AB12: =W12/(1-(1+W12)^-AA12) -> 0.15582009 | AC12: =R12/AB12 -> 14.423783
B13: FOURHR_BATTERY | C13: NER | D13: Battery | E13: 4-Hr | F13: INDIA | G13: MWh | H13: ELECTRICITY | I13: EC_DOM | J13: 0.25 | K13: 0.25 | L13: DAILY | M13: 0 | N13: 0.9 | O13: 0.8 | P13: 10 | Q13: 3873.4092 | R13: =$R$9 -> 1.9123593 | S13: 0 | T13: =S13 -> 0 | U13: =S13 -> 0 | V13: 0 | W13: 0.09 | Y13: =SQRT(O13) -> 0.89442719 | Z13: =Y13 -> 0.89442719 | AA13: =P13 -> 10 | AB13: =W13/(1-(1+W13)^-AA13) -> 0.15582009 | AC13: =R13/AB13 -> 12.272868
B14: SIXHR_BATTERY | C14: NER | D14: Battery | E14: 6-Hr | F14: INDIA | G14: MWh | H14: ELECTRICITY | I14: EC_DOM | J14: 0.166667 | K14: 0.166667 | L14: DAILY | M14: 0 | N14: 0.9 | O14: 0.8 | P14: 10 | Q14: 3873.4092 | R14: =$R$10 -> 1.8006408 | S14: 0 | T14: =S14 -> 0 | U14: =S14 -> 0 | V14: 0 | W14: 0.09 | Y14: =SQRT(O14) -> 0.89442719 | Z14: =Y14 -> 0.89442719 | AA14: =P14 -> 10 | AB14: =W14/(1-(1+W14)^-AA14) -> 0.15582009 | AC14: =R14/AB14 -> 11.555896
B15: PUMPED_STOR | C15: NER | D15: Battery | E15: pumpedhydro | F15: INDIA | G15: MWh | H15: ELECTRICITY | I15: EC_DOM | J15: 0.16666667 | K15: 0.16666667 | L15: DAILY | M15: 0 | N15: 0.9 | O15: 0.75 | P15: =Capacity!E86 -> 20 | Q15: =Capacity!F86 -> 50000 | R15: =$R$11 -> 1.9001303 | S15: =Capacity!D86*1000 -> 0 | T15: =S15 -> 0 | U15: =S15 -> 0 | V15: 0 | W15: 0.09 | Y15: =SQRT(O15) -> 0.8660254 | Z15: =Y15 -> 0.8660254 | AA15: =P15 -> 20 | AB15: =W15/(1-(1+W15)^-AA15) -> 0.10954648 | AC15: =R15/AB15 -> 17.345426
B16: TWOHR_BATTERY | C16: ER | D16: Battery | E16: 2-Hr | F16: INDIA | G16: MWh | H16: ELECTRICITY | I16: EC_DOM | J16: 0.5 | K16: 0.5 | L16: DAILY | M16: 0 | N16: 0.9 | O16: 0.8 | P16: 10 | Q16: 3873.4092 | R16: =$R$8 -> 2.2475151 | S16: 0 | T16: =S16 -> 0 | U16: =S16 -> 0 | V16: 0 | W16: 0.09 | Y16: =SQRT(O16) -> 0.89442719 | Z16: =Y16 -> 0.89442719 | AA16: =P16 -> 10 | AB16: =W16/(1-(1+W16)^-AA16) -> 0.15582009 | AC16: =R16/AB16 -> 14.423783
B17: FOURHR_BATTERY | C17: ER | D17: Battery | E17: 4-Hr | F17: INDIA | G17: MWh | H17: ELECTRICITY | I17: EC_DOM | J17: 0.25 | K17: 0.25 | L17: DAILY | M17: 0 | N17: 0.9 | O17: 0.8 | P17: 10 | Q17: 3873.4092 | R17: =$R$9 -> 1.9123593 | S17: 0 | T17: =S17 -> 0 | U17: =S17 -> 0 | V17: 0 | W17: 0.09 | Y17: =SQRT(O17) -> 0.89442719 | Z17: =Y17 -> 0.89442719 | AA17: =P17 -> 10 | AB17: =W17/(1-(1+W17)^-AA17) -> 0.15582009 | AC17: =R17/AB17 -> 12.272868
B18: SIXHR_BATTERY | C18: ER | D18: Battery | E18: 6-Hr | F18: INDIA | G18: MWh | H18: ELECTRICITY | I18: EC_DOM | J18: 0.166667 | K18: 0.166667 | L18: DAILY | M18: 0 | N18: 0.9 | O18: 0.8 | P18: 10 | Q18: 3873.4092 | R18: =$R$10 -> 1.8006408 | S18: 0 | T18: =S18 -> 0 | U18: =S18 -> 0 | V18: 0 | W18: 0.09 | Y18: =SQRT(O18) -> 0.89442719 | Z18: =Y18 -> 0.89442719 | AA18: =P18 -> 10 | AB18: =W18/(1-(1+W18)^-AA18) -> 0.15582009 | AC18: =R18/AB18 -> 11.555896
B19: PUMPED_STOR | C19: ER | D19: Battery | E19: pumpedhydro | F19: INDIA | G19: MWh | H19: ELECTRICITY | I19: EC_DOM | J19: 0.16666667 | K19: 0.16666667 | L19: DAILY | M19: 0 | N19: 0.9 | O19: 0.75 | P19: =Capacity!E87 -> 20 | Q19: =Capacity!F87 -> 50000 | R19: =$R$11 -> 1.9001303 | S19: =Capacity!D87*1000 -> 5400 | T19: =S19 -> 5400 | U19: =S19 -> 5400 | V19: 0 | W19: 0.09 | Y19: =SQRT(O19) -> 0.8660254 | Z19: =Y19 -> 0.8660254 | AA19: =P19 -> 20 | AB19: =W19/(1-(1+W19)^-AA19) -> 0.10954648 | AC19: =R19/AB19 -> 17.345426
B20: TWOHR_BATTERY | C20: WR | D20: Battery | E20: 2-Hr | F20: INDIA | G20: MWh | H20: ELECTRICITY | I20: EC_DOM | J20: 0.5 | K20: 0.5 | L20: DAILY | M20: 0 | N20: 0.9 | O20: 0.8 | P20: 10 | Q20: 3873.4092 | R20: =$R$8 -> 2.2475151 | S20: 0 | T20: =S20 -> 0 | U20: =S20 -> 0 | V20: 0 | W20: 0.09 | Y20: =SQRT(O20) -> 0.89442719 | Z20: =Y20 -> 0.89442719 | AA20: =P20 -> 10 | AB20: =W20/(1-(1+W20)^-AA20) -> 0.15582009 | AC20: =R20/AB20 -> 14.423783
B21: FOURHR_BATTERY | C21: WR | D21: Battery | E21: 4-Hr | F21: INDIA | G21: MWh | H21: ELECTRICITY | I21: EC_DOM | J21: 0.25 | K21: 0.25 | L21: DAILY | M21: 0 | N21: 0.9 | O21: 0.8 | P21: 10 | Q21: 3873.4092 | R21: =$R$9 -> 1.9123593 | S21: 0 | T21: =S21 -> 0 | U21: =S21 -> 0 | V21: 0 | W21: 0.09 | Y21: =SQRT(O21) -> 0.89442719 | Z21: =Y21 -> 0.89442719 | AA21: =P21 -> 10 | AB21: =W21/(1-(1+W21)^-AA21) -> 0.15582009 | AC21: =R21/AB21 -> 12.272868
B22: SIXHR_BATTERY | C22: WR | D22: Battery | E22: 6-Hr | F22: INDIA | G22: MWh | H22: ELECTRICITY | I22: EC_DOM | J22: 0.166667 | K22: 0.166667 | L22: DAILY | M22: 0 | N22: 0.9 | O22: 0.8 | P22: 10 | Q22: 3873.4092 | R22: =$R$10 -> 1.8006408 | S22: 0 | T22: =S22 -> 0 | U22: =S22 -> 0 | V22: 0 | W22: 0.09 | Y22: =SQRT(O22) -> 0.89442719 | Z22: =Y22 -> 0.89442719 | AA22: =P22 -> 10 | AB22: =W22/(1-(1+W22)^-AA22) -> 0.15582009 | AC22: =R22/AB22 -> 11.555896
B23: PUMPED_STOR | C23: WR | D23: Battery | E23: pumpedhydro | F23: INDIA | G23: MWh | H23: ELECTRICITY | I23: EC_DOM | J23: 0.16666667 | K23: 0.16666667 | L23: DAILY | M23: 0 | N23: 0.9 | O23: 0.75 | P23: =Capacity!E88 -> 20 | Q23: =Capacity!F88 -> 50000 | R23: =$R$11 -> 1.9001303 | S23: =Capacity!D88*1000 -> 11040 | T23: =S23 -> 11040 | U23: =S23 -> 11040 | V23: 0 | W23: 0.09 | Y23: =SQRT(O23) -> 0.8660254 | Z23: =Y23 -> 0.8660254 | AA23: =P23 -> 20 | AB23: =W23/(1-(1+W23)^-AA23) -> 0.10954648 | AC23: =R23/AB23 -> 17.345426
B24: TWOHR_BATTERY | C24: SR | D24: Battery | E24: 2-Hr | F24: INDIA | G24: MWh | H24: ELECTRICITY | I24: EC_DOM | J24: 0.5 | K24: 0.5 | L24: DAILY | M24: 0 | N24: 0.9 | O24: 0.8 | P24: 10 | Q24: 3873.4092 | R24: =$R$8 -> 2.2475151 | S24: 0 | T24: =S24 -> 0 | U24: =S24 -> 0 | V24: 0 | W24: 0.09 | Y24: =SQRT(O24) -> 0.89442719 | Z24: =Y24 -> 0.89442719 | AA24: =P24 -> 10 | AB24: =W24/(1-(1+W24)^-AA24) -> 0.15582009 | AC24: =R24/AB24 -> 14.423783
B25: FOURHR_BATTERY | C25: SR | D25: Battery | E25: 4-Hr | F25: INDIA | G25: MWh | H25: ELECTRICITY | I25: EC_DOM | J25: 0.25 | K25: 0.25 | L25: DAILY | M25: 0 | N25: 0.9 | O25: 0.8 | P25: 10 | Q25: 3873.4092 | R25: =$R$9 -> 1.9123593 | S25: 0 | T25: =S25 -> 0 | U25: =S25 -> 0 | V25: 0 | W25: 0.09 | Y25: =SQRT(O25) -> 0.89442719 | Z25: =Y25 -> 0.89442719 | AA25: =P25 -> 10 | AB25: =W25/(1-(1+W25)^-AA25) -> 0.15582009 | AC25: =R25/AB25 -> 12.272868
B26: SIXHR_BATTERY | C26: SR | D26: Battery | E26: 6-Hr | F26: INDIA | G26: MWh | H26: ELECTRICITY | I26: EC_DOM | J26: 0.166667 | K26: 0.166667 | L26: DAILY | M26: 0 | N26: 0.9 | O26: 0.8 | P26: 10 | Q26: 3873.4092 | R26: =$R$10 -> 1.8006408 | S26: 0 | T26: =S26 -> 0 | U26: =S26 -> 0 | V26: 0 | W26: 0.09 | Y26: =SQRT(O26) -> 0.89442719 | Z26: =Y26 -> 0.89442719 | AA26: =P26 -> 10 | AB26: =W26/(1-(1+W26)^-AA26) -> 0.15582009 | AC26: =R26/AB26 -> 11.555896
B27: PUMPED_STOR | C27: SR | D27: Battery | E27: pumpedhydro | F27: INDIA | G27: MWh | H27: ELECTRICITY | I27: EC_DOM | J27: 0.16666667 | K27: 0.16666667 | L27: DAILY | M27: 0 | N27: 0.9 | O27: 0.75 | P27: =Capacity!E89 -> 20 | Q27: =Capacity!F89 -> 50000 | R27: =$R$11 -> 1.9001303 | S27: =Capacity!D89*1000 -> 12033.6 | T27: =S27 -> 12033.6 | U27: =S27 -> 12033.6 | V27: 0 | W27: 0.09 | Y27: =SQRT(O27) -> 0.8660254 | Z27: =Y27 -> 0.8660254 | AA27: =P27 -> 20 | AB27: =W27/(1-(1+W27)^-AA27) -> 0.10954648 | AC27: =R27/AB27 -> 17.345426
B28: TWOHR_BATTERY | C28: ALL | D28: Battery | E28: 2-Hr | F28: INDIA | G28: MWh | H28: ELECTRICITY | I28: EC_DOM | J28: 0.5 | K28: 0.5 | L28: DAILY | M28: 0 | N28: 0.9 | O28: 0.8 | P28: =AVERAGE(P8,P12,P16,P20,P24) -> 10 | Q28: =AVERAGE(Q8,Q12,Q16,Q20,Q24) -> 3873.4092 | R28: =AVERAGE(R8,R12,R16,R20,R24) -> 2.2475151 | S28: =S8+S12+S16+S20+S24 -> 0 | T28: =S28 -> 0 | U28: =S28 -> 0 | V28: =AVERAGE(V8,V12,V16,V20,V24) -> 0 | W28: =AVERAGE(W8,W12,W16,W20,W24) -> 0.09 | Y28: =AVERAGE(Y8,Y12,Y16,Y20,Y24) -> 0.89442719 | Z28: =AVERAGE(Z8,Z12,Z16,Z20,Z24) -> 0.89442719 | AA28: =AVERAGE(AA8,AA12,AA16,AA20,AA24) -> 10 | AB28: =AVERAGE(AB8,AB12,AB16,AB20,AB24) -> 0.15582009 | AC28: =AVERAGE(AC8,AC12,AC16,AC20,AC24) -> 14.423783
B29: FOURHR_BATTERY | C29: ALL | D29: Battery | E29: 4-Hr | F29: INDIA | G29: MWh | H29: ELECTRICITY | I29: EC_DOM | J29: 0.25 | K29: 0.25 | L29: DAILY | M29: 0 | N29: 0.9 | O29: 0.8 | P29: =AVERAGE(P9,P13,P17,P21,P25) -> 10 | Q29: =AVERAGE(Q9,Q13,Q17,Q21,Q25) -> 3873.4092 | R29: =AVERAGE(R9,R13,R17,R21,R25) -> 1.9123593 | S29: =S9+S13+S17+S21+S25 -> 0 | T29: =S29 -> 0 | U29: =S29 -> 0 | V29: =AVERAGE(V9,V13,V17,V21,V25) -> 0 | W29: =AVERAGE(W9,W13,W17,W21,W25) -> 0.09 | Y29: =AVERAGE(Y9,Y13,Y17,Y21,Y25) -> 0.89442719 | Z29: =AVERAGE(Z9,Z13,Z17,Z21,Z25) -> 0.89442719 | AA29: =AVERAGE(AA9,AA13,AA17,AA21,AA25) -> 10 | AB29: =AVERAGE(AB9,AB13,AB17,AB21,AB25) -> 0.15582009 | AC29: =AVERAGE(AC9,AC13,AC17,AC21,AC25) -> 12.272868
B30: SIXHR_BATTERY | C30: ALL | D30: Battery | E30: 6-Hr | F30: INDIA | G30: MWh | H30: ELECTRICITY | I30: EC_DOM | J30: 0.166667 | K30: 0.166667 | L30: DAILY | M30: 0 | N30: 0.9 | O30: 0.8 | P30: =AVERAGE(P10,P14,P18,P22,P26) -> 10 | Q30: =AVERAGE(Q10,Q14,Q18,Q22,Q26) -> 3873.4092 | R30: =AVERAGE(R10,R14,R18,R22,R26) -> 1.8006408 | S30: =S10+S14+S18+S22+S26 -> 0 | T30: =S30 -> 0 | U30: =S30 -> 0 | V30: =AVERAGE(V10,V14,V18,V22,V26) -> 0 | W30: =AVERAGE(W10,W14,W18,W22,W26) -> 0.09 | Y30: =AVERAGE(Y10,Y14,Y18,Y22,Y26) -> 0.89442719 | Z30: =AVERAGE(Z10,Z14,Z18,Z22,Z26) -> 0.89442719 | AA30: =AVERAGE(AA10,AA14,AA18,AA22,AA26) -> 10 | AB30: =AVERAGE(AB10,AB14,AB18,AB22,AB26) -> 0.15582009 | AC30: =AVERAGE(AC10,AC14,AC18,AC22,AC26) -> 11.555896
B31: PUMPED_STOR | C31: ALL | D31: Battery | E31: pumpedhydro | F31: INDIA | G31: MWh | H31: ELECTRICITY | I31: EC_DOM | J31: 0.16666667 | K31: 0.16666667 | L31: DAILY | M31: 0 | N31: 0.9 | O31: 0.75 | P31: =AVERAGE(P11,P15,P19,P23,P27) -> 20 | Q31: =AVERAGE(Q11,Q15,Q19,Q23,Q27) -> 50000 | R31: =AVERAGE(R11,R15,R19,R23,R27) -> 1.9001303 | S31: =S11+S15+S19+S23+S27 -> 28473.6 | T31: =S31 -> 28473.6 | U31: =S31 -> 28473.6 | V31: =AVERAGE(V11,V15,V19,V23,V27) -> 0 | W31: =AVERAGE(W11,W15,W19,W23,W27) -> 0.09 | Y31: =AVERAGE(Y11,Y15,Y19,Y23,Y27) -> 0.8660254 | Z31: =AVERAGE(Z11,Z15,Z19,Z23,Z27) -> 0.8660254 | AA31: =AVERAGE(AA11,AA15,AA19,AA23,AA27) -> 20 | AB31: =AVERAGE(AB11,AB15,AB19,AB23,AB27) -> 0.10954648 | AC31: =AVERAGE(AC11,AC15,AC19,AC23,AC27) -> 17.345426

Sheet assets_stor_p2
A1: Source::File | G1: PIER::EnergyConvTechnologies.csv | H1: PIER::EnergyStorTechnologies.csv | I1: PIER::EnergyStorTechnologies.csv | J1: PIER::EnergyStorTechnologies.csv | K1: PIER::EnergyStorTechnologies.csv | L1: PIER::EnergyStorTechnologies.csv | M1: PIER2.0::EST_DeratingDepthOfDischarge.csv | N1: PIER2.0::EST_DeratingDepthOfDischarge.csv | O1: PIER2.0::EST_EfficiencyCost.csv | P1: PIER2.0::EST_Lifetime.csv or EST_LegacyDetails.csv | Q1: PIER2.0::EST_Lifetime.csv or EST_LegacyDetails.csv | R1: PIER2.0::EST_EfficiencyCost.csv | S1: PIER2.0::ECT_LegacyDetails.csv | T1: PIER2.0::EST_CapAddBounds.csv | U1: PIER2.0::EST_CapAddBounds.csv | V1: PIER2.0::EST_Parameters.xlsx | W1: PIER2.0::EST_Parameters.xlsx
A2: PIER2.0 var name | B2: EnergyConvTech | C2: SubGeography1 | F2: ModelGeography | G2: CapacityUnit | H2: StoredEC | I2: DomOrImp | J2: MaxChargeRate | K2: MaxDischargeRate | L2: StorPeriodicity | M2: CapacityDerating | N2: DepthOfDischarge | O2: Efficiency | P2: LifetimeYears | Q2: LifetimeCycles | R2: FixedCost | S2: LegacyCapacity | T2: MinCapacity | U2: MaxCapacity
A3: Variable | J3: a | K3: b | M3: c | N3: d | O3: e | P3: f | Q3: g | R3: h | S3: i | T3: j | U3: k | V3: l | W3: m | Y3: aa | Z3: bb | AA3: dd | AB3: ee | AC3: ff
A4: description | C4: model geography | G4: all units in macro are given in the selected value | H4: energy carrier | O4: overall efficiency | P4: lifetime of asset in years | Q4: lifetime of asset in cycles | R4: annuity on new capacity | S4: legacy/existing | T4: pipeline builds | U4: maximum additions | V4: given Fixed O&M (PIER or assumed), adjusted to 2024Rs from 2020Rs | W4: given discount rate from PIER2.0 workbook, No adjustment made | AA4: For existing infrastructure this is half operational lifetime, rounded to integer as Macro will fail if given decimal | AB4: CRF
A5: Equation to Macro var | G5: given / 1000 | H5: given | J5: given | K5: given | M5: given | N5: given | O5: given | P5: given | Q5: given | R5: given/1000 | S5: = given*1000 | T5: = given*1000 | U5: = given*1000 | W5: = given | Y5: = sqrt ( e ) | Z5: = sqrt ( e ) | AA5: = round ( f / 2 , 0) | AB5: = q / ( 1-(1+q)^(-gg)) | AC5: = ff / hh
A6: Macro variable | C6: location | D6: type | E6: id | J6: discharge_max_flow_fraction | P6: lifetime of asset | R6: annualized_investment_cost | T6: min_capcity | U6: max_capacity | W6: wacc | Y6: discharge_efficienc | Z6: charge_efficiency | AA6: capital_recovery_period | AC6: investment_cost
A7: Unit | J7: % | K7: % | M7: % | N7: fraction of capacity | O7: % | P7: years | Q7: cycles | R7: million Rs2024/MW | S7: MW | T7: MW | U7: MW | V7: million 2020Rs/year | W7: % | Y7: % | Z7: % | AA7: years | AC7: million 2024Rs
B8: TWOHR_BATTERY | C8: NR | D8: Battery | E8: 2-Hr | F8: INDIA | G8: MWh | H8: ELECTRICITY | I8: EC_DOM | J8: 0.5 | K8: 0.5 | L8: DAILY | M8: 0 | N8: 0.9 | O8: 0.8 | P8: 10 | Q8: =Capacity!D94 -> 3873.4092 | R8: =Capacity!$D$103/1000 -> 2.2475151 | S8: 0 | T8: =Capacity!C183*1000 -> 0 | U8: =Capacity!W183*1000 -> 89.882384 | V8: 0 | W8: 0.09 | Y8: =SQRT(O8) -> 0.89442719 | Z8: =Y8 -> 0.89442719 | AA8: =P8 -> 10 | AB8: =W8/(1-(1+W8)^(-AA8)) -> 0.15582009 | AC8: =R8/AB8 -> 14.423783
B9: FOURHR_BATTERY | C9: NR | D9: Battery | E9: 4-Hr | F9: INDIA | G9: MWh | H9: ELECTRICITY | I9: EC_DOM | J9: 0.25 | K9: 0.25 | L9: DAILY | M9: 0 | N9: 0.9 | O9: 0.8 | P9: 10 | Q9: =Capacity!D95 -> 3873.4092 | R9: =Capacity!$D$123/1000 -> 1.9123593 | S9: 0 | T9: =Capacity!C184*1000 -> 0 | U9: =Capacity!W184*1000 -> 179.76477 | V9: 0 | W9: 0.09 | Y9: =SQRT(O9) -> 0.89442719 | Z9: =Y9 -> 0.89442719 | AA9: =P9 -> 10 | AB9: =W9/(1-(1+W9)^-AA9) -> 0.15582009 | AC9: =R9/AB9 -> 12.272868
B10: SIXHR_BATTERY | C10: NR | D10: Battery | E10: 6-Hr | F10: INDIA | G10: MWh | H10: ELECTRICITY | I10: EC_DOM | J10: 0.166667 | K10: 0.166667 | L10: DAILY | M10: 0 | N10: 0.9 | O10: 0.8 | P10: 10 | Q10: =Capacity!D96 -> 3873.4092 | R10: =Capacity!$D$143/1000 -> 1.8006408 | S10: 0 | T10: =Capacity!C185*1000 -> 0 | U10: =Capacity!W185*1000 -> 269.64715 | V10: 0 | W10: 0.09 | Y10: =SQRT(O10) -> 0.89442719 | Z10: =Y10 -> 0.89442719 | AA10: =P10 -> 10 | AB10: =W10/(1-(1+W10)^-AA10) -> 0.15582009 | AC10: =R10/AB10 -> 11.555896
B11: PUMPED_STOR | C11: NR | D11: Battery | E11: pumpedhydro | F11: INDIA | G11: MWh | H11: ELECTRICITY | I11: EC_DOM | J11: 0.16666667 | K11: 0.16666667 | L11: DAILY | M11: 0 | N11: 0.9 | O11: 0.75 | P11: 40 | Q11: =Capacity!D97 -> 50000 | R11: =Capacity!$D$163/1000 -> 1.9001303 | S11: =Capacity!D85*1000 -> 0 | T11: =Capacity!C186*1000 -> 0 | U11: =Capacity!W186*1000 -> 0 | V11: 0 | W11: 0.09 | Y11: =SQRT(O11) -> 0.8660254 | Z11: =Y11 -> 0.8660254 | AA11: =P11 -> 40 | AB11: =W11/(1-(1+W11)^-AA11) -> 0.092959609 | AC11: =R11/AB11 -> 20.440386
B12: TWOHR_BATTERY | C12: NER | D12: Battery | E12: 2-Hr | F12: INDIA | G12: MWh | H12: ELECTRICITY | I12: EC_DOM | J12: 0.5 | K12: 0.5 | L12: DAILY | M12: 0 | N12: 0.9 | O12: 0.8 | P12: 10 | Q12: =$Q$8 -> 3873.4092 | R12: =$R$8 -> 2.2475151 | S12: 0 | T12: =Capacity!C187*1000 -> 0 | U12: =Capacity!W187*1000 -> 15.332799 | V12: 0 | W12: 0.09 | Y12: =SQRT(O12) -> 0.89442719 | Z12: =Y12 -> 0.89442719 | AA12: =P12 -> 10 | AB12: =W12/(1-(1+W12)^-AA12) -> 0.15582009 | AC12: =R12/AB12 -> 14.423783
B13: FOURHR_BATTERY | C13: NER | D13: Battery | E13: 4-Hr | F13: INDIA | G13: MWh | H13: ELECTRICITY | I13: EC_DOM | J13: 0.25 | K13: 0.25 | L13: DAILY | M13: 0 | N13: 0.9 | O13: 0.8 | P13: 10 | Q13: =$Q$9 -> 3873.4092 | R13: =$R$9 -> 1.9123593 | S13: 0 | T13: =Capacity!C188*1000 -> 0 | U13: =Capacity!W188*1000 -> 30.665598 | V13: 0 | W13: 0.09 | Y13: =SQRT(O13) -> 0.89442719 | Z13: =Y13 -> 0.89442719 | AA13: =P13 -> 10 | AB13: =W13/(1-(1+W13)^-AA13) -> 0.15582009 | AC13: =R13/AB13 -> 12.272868
B14: SIXHR_BATTERY | C14: NER | D14: Battery | E14: 6-Hr | F14: INDIA | G14: MWh | H14: ELECTRICITY | I14: EC_DOM | J14: 0.166667 | K14: 0.166667 | L14: DAILY | M14: 0 | N14: 0.9 | O14: 0.8 | P14: 10 | Q14: =$Q$10 -> 3873.4092 | R14: =$R$10 -> 1.8006408 | S14: 0 | T14: =Capacity!C189*1000 -> 0 | U14: =Capacity!W189*1000 -> 45.998396 | V14: 0 | W14: 0.09 | Y14: =SQRT(O14) -> 0.89442719 | Z14: =Y14 -> 0.89442719 | AA14: =P14 -> 10 | AB14: =W14/(1-(1+W14)^-AA14) -> 0.15582009 | AC14: =R14/AB14 -> 11.555896
B15: PUMPED_STOR | C15: NER | D15: Battery | E15: pumpedhydro | F15: INDIA | G15: MWh | H15: ELECTRICITY | I15: EC_DOM | J15: 0.16666667 | K15: 0.16666667 | L15: DAILY | M15: 0 | N15: 0.9 | O15: 0.75 | P15: 40 | Q15: =$Q$11 -> 50000 | R15: =$R$11 -> 1.9001303 | S15: =Capacity!D86*1000 -> 0 | T15: =Capacity!C190*1000 -> 0 | U15: =Capacity!W190*1000 -> 0 | V15: 0 | W15: 0.09 | Y15: =SQRT(O15) -> 0.8660254 | Z15: =Y15 -> 0.8660254 | AA15: =P15 -> 40 | AB15: =W15/(1-(1+W15)^-AA15) -> 0.092959609 | AC15: =R15/AB15 -> 20.440386
B16: TWOHR_BATTERY | C16: ER | D16: Battery | E16: 2-Hr | F16: INDIA | G16: MWh | H16: ELECTRICITY | I16: EC_DOM | J16: 0.5 | K16: 0.5 | L16: DAILY | M16: 0 | N16: 0.9 | O16: 0.8 | P16: 10 | Q16: =$Q$8 -> 3873.4092 | R16: =$R$8 -> 2.2475151 | S16: 0 | T16: =Capacity!C191*1000 -> 0 | U16: =Capacity!W191*1000 -> 17.738573 | V16: 0 | W16: 0.09 | Y16: =SQRT(O16) -> 0.89442719 | Z16: =Y16 -> 0.89442719 | AA16: =P16 -> 10 | AB16: =W16/(1-(1+W16)^-AA16) -> 0.15582009 | AC16: =R16/AB16 -> 14.423783
B17: FOURHR_BATTERY | C17: ER | D17: Battery | E17: 4-Hr | F17: INDIA | G17: MWh | H17: ELECTRICITY | I17: EC_DOM | J17: 0.25 | K17: 0.25 | L17: DAILY | M17: 0 | N17: 0.9 | O17: 0.8 | P17: 10 | Q17: =$Q$9 -> 3873.4092 | R17: =$R$9 -> 1.9123593 | S17: 0 | T17: =Capacity!C192*1000 -> 0 | U17: =Capacity!W192*1000 -> 35.477145 | V17: 0 | W17: 0.09 | Y17: =SQRT(O17) -> 0.89442719 | Z17: =Y17 -> 0.89442719 | AA17: =P17 -> 10 | AB17: =W17/(1-(1+W17)^-AA17) -> 0.15582009 | AC17: =R17/AB17 -> 12.272868
B18: SIXHR_BATTERY | C18: ER | D18: Battery | E18: 6-Hr | F18: INDIA | G18: MWh | H18: ELECTRICITY | I18: EC_DOM | J18: 0.166667 | K18: 0.166667 | L18: DAILY | M18: 0 | N18: 0.9 | O18: 0.8 | P18: 10 | Q18: =$Q$10 -> 3873.4092 | R18: =$R$10 -> 1.8006408 | S18: 0 | T18: =Capacity!C193*1000 -> 0 | U18: =Capacity!W193*1000 -> 53.215719 | V18: 0 | W18: 0.09 | Y18: =SQRT(O18) -> 0.89442719 | Z18: =Y18 -> 0.89442719 | AA18: =P18 -> 10 | AB18: =W18/(1-(1+W18)^-AA18) -> 0.15582009 | AC18: =R18/AB18 -> 11.555896
B19: PUMPED_STOR | C19: ER | D19: Battery | E19: pumpedhydro | F19: INDIA | G19: MWh | H19: ELECTRICITY | I19: EC_DOM | J19: 0.16666667 | K19: 0.16666667 | L19: DAILY | M19: 0 | N19: 0.9 | O19: 0.75 | P19: 40 | Q19: =$Q$11 -> 50000 | R19: =$R$11 -> 1.9001303 | S19: =Capacity!D87*1000 -> 5400 | T19: =Capacity!C194*1000 -> 0 | U19: =Capacity!W194*1000 -> 0 | V19: 0 | W19: 0.09 | Y19: =SQRT(O19) -> 0.8660254 | Z19: =Y19 -> 0.8660254 | AA19: =P19 -> 40 | AB19: =W19/(1-(1+W19)^-AA19) -> 0.092959609 | AC19: =R19/AB19 -> 20.440386
B20: TWOHR_BATTERY | C20: WR | D20: Battery | E20: 2-Hr | F20: INDIA | G20: MWh | H20: ELECTRICITY | I20: EC_DOM | J20: 0.5 | K20: 0.5 | L20: DAILY | M20: 0 | N20: 0.9 | O20: 0.8 | P20: 10 | Q20: =$Q$8 -> 3873.4092 | R20: =$R$8 -> 2.2475151 | S20: 0 | T20: =Capacity!C195*1000 -> 0 | U20: =Capacity!W195*1000 -> 48.356055 | V20: 0 | W20: 0.09 | Y20: =SQRT(O20) -> 0.89442719 | Z20: =Y20 -> 0.89442719 | AA20: =P20 -> 10 | AB20: =W20/(1-(1+W20)^-AA20) -> 0.15582009 | AC20: =R20/AB20 -> 14.423783
B21: FOURHR_BATTERY | C21: WR | D21: Battery | E21: 4-Hr | F21: INDIA | G21: MWh | H21: ELECTRICITY | I21: EC_DOM | J21: 0.25 | K21: 0.25 | L21: DAILY | M21: 0 | N21: 0.9 | O21: 0.8 | P21: 10 | Q21: =$Q$9 -> 3873.4092 | R21: =$R$9 -> 1.9123593 | S21: 0 | T21: =Capacity!C196*1000 -> 0 | U21: =Capacity!W196*1000 -> 96.712109 | V21: 0 | W21: 0.09 | Y21: =SQRT(O21) -> 0.89442719 | Z21: =Y21 -> 0.89442719 | AA21: =P21 -> 10 | AB21: =W21/(1-(1+W21)^-AA21) -> 0.15582009 | AC21: =R21/AB21 -> 12.272868
B22: SIXHR_BATTERY | C22: WR | D22: Battery | E22: 6-Hr | F22: INDIA | G22: MWh | H22: ELECTRICITY | I22: EC_DOM | J22: 0.166667 | K22: 0.166667 | L22: DAILY | M22: 0 | N22: 0.9 | O22: 0.8 | P22: 10 | Q22: =$Q$10 -> 3873.4092 | R22: =$R$10 -> 1.8006408 | S22: 0 | T22: =Capacity!C197*1000 -> 0 | U22: =Capacity!W197*1000 -> 145.06816 | V22: 0 | W22: 0.09 | Y22: =SQRT(O22) -> 0.89442719 | Z22: =Y22 -> 0.89442719 | AA22: =P22 -> 10 | AB22: =W22/(1-(1+W22)^-AA22) -> 0.15582009 | AC22: =R22/AB22 -> 11.555896
B23: PUMPED_STOR | C23: WR | D23: Battery | E23: pumpedhydro | F23: INDIA | G23: MWh | H23: ELECTRICITY | I23: EC_DOM | J23: 0.16666667 | K23: 0.16666667 | L23: DAILY | M23: 0 | N23: 0.9 | O23: 0.75 | P23: 40 | Q23: =$Q$11 -> 50000 | R23: =$R$11 -> 1.9001303 | S23: =Capacity!D88*1000 -> 11040 | T23: =Capacity!C198*1000 -> 0 | U23: =Capacity!W198*1000 -> 0 | V23: 0 | W23: 0.09 | Y23: =SQRT(O23) -> 0.8660254 | Z23: =Y23 -> 0.8660254 | AA23: =P23 -> 40 | AB23: =W23/(1-(1+W23)^-AA23) -> 0.092959609 | AC23: =R23/AB23 -> 20.440386
B24: TWOHR_BATTERY | C24: SR | D24: Battery | E24: 2-Hr | F24: INDIA | G24: MWh | H24: ELECTRICITY | I24: EC_DOM | J24: 0.5 | K24: 0.5 | L24: DAILY | M24: 0 | N24: 0.9 | O24: 0.8 | P24: 10 | Q24: =$Q$8 -> 3873.4092 | R24: =$R$8 -> 2.2475151 | S24: 0 | T24: =Capacity!C199*1000 -> 0 | U24: =Capacity!W199*1000 -> 28.690189 | V24: 0 | W24: 0.09 | Y24: =SQRT(O24) -> 0.89442719 | Z24: =Y24 -> 0.89442719 | AA24: =P24 -> 10 | AB24: =W24/(1-(1+W24)^-AA24) -> 0.15582009 | AC24: =R24/AB24 -> 14.423783
B25: FOURHR_BATTERY | C25: SR | D25: Battery | E25: 4-Hr | F25: INDIA | G25: MWh | H25: ELECTRICITY | I25: EC_DOM | J25: 0.25 | K25: 0.25 | L25: DAILY | M25: 0 | N25: 0.9 | O25: 0.8 | P25: 10 | Q25: =$Q$9 -> 3873.4092 | R25: =$R$9 -> 1.9123593 | S25: 0 | T25: =Capacity!C200*1000 -> 0 | U25: =Capacity!W200*1000 -> 57.380379 | V25: 0 | W25: 0.09 | Y25: =SQRT(O25) -> 0.89442719 | Z25: =Y25 -> 0.89442719 | AA25: =P25 -> 10 | AB25: =W25/(1-(1+W25)^-AA25) -> 0.15582009 | AC25: =R25/AB25 -> 12.272868
B26: SIXHR_BATTERY | C26: SR | D26: Battery | E26: 6-Hr | F26: INDIA | G26: MWh | H26: ELECTRICITY | I26: EC_DOM | J26: 0.166667 | K26: 0.166667 | L26: DAILY | M26: 0 | N26: 0.9 | O26: 0.8 | P26: 10 | Q26: =$Q$10 -> 3873.4092 | R26: =$R$10 -> 1.8006408 | S26: 0 | T26: =Capacity!C201*1000 -> 0 | U26: =Capacity!W201*1000 -> 86.070568 | V26: 0 | W26: 0.09 | Y26: =SQRT(O26) -> 0.89442719 | Z26: =Y26 -> 0.89442719 | AA26: =P26 -> 10 | AB26: =W26/(1-(1+W26)^-AA26) -> 0.15582009 | AC26: =R26/AB26 -> 11.555896
B27: PUMPED_STOR | C27: SR | D27: Battery | E27: pumpedhydro | F27: INDIA | G27: MWh | H27: ELECTRICITY | I27: EC_DOM | J27: 0.16666667 | K27: 0.16666667 | L27: DAILY | M27: 0 | N27: 0.9 | O27: 0.75 | P27: 40 | Q27: =$Q$11 -> 50000 | R27: =$R$11 -> 1.9001303 | S27: =Capacity!D89*1000 -> 12033.6 | T27: =Capacity!C202*1000 -> 0 | U27: =Capacity!W202*1000 -> 0 | V27: 0 | W27: 0.09 | Y27: =SQRT(O27) -> 0.8660254 | Z27: =Y27 -> 0.8660254 | AA27: =P27 -> 40 | AB27: =W27/(1-(1+W27)^-AA27) -> 0.092959609 | AC27: =R27/AB27 -> 20.440386
B28: TWOHR_BATTERY | C28: ALL | D28: Battery | E28: 2-Hr | F28: INDIA | G28: MWh | H28: ELECTRICITY | I28: EC_DOM | J28: 0.5 | K28: 0.5 | L28: DAILY | M28: 0 | N28: 0.9 | O28: 0.8 | P28: =AVERAGE(P8,P12,P16,P20,P24) -> 10 | Q28: =AVERAGE(Q8,Q12,Q16,Q20,Q24) -> 3873.4092 | R28: =AVERAGE(R8,R12,R16,R20,R24) -> 2.2475151 | S28: =S8+S12+S16+S20+S24 -> 0 | T28: =T8+T12+T16+T20+T24 -> 0 | U28: =U8+U12+U16+U20+U24 -> 200 | V28: =AVERAGE(V8,V12,V16,V20,V24) -> 0 | W28: =AVERAGE(W8,W12,W16,W20,W24) -> 0.09 | Y28: =AVERAGE(Y8,Y12,Y16,Y20,Y24) -> 0.89442719 | Z28: =AVERAGE(Z8,Z12,Z16,Z20,Z24) -> 0.89442719 | AA28: =AVERAGE(AA8,AA12,AA16,AA20,AA24) -> 10 | AB28: =AVERAGE(AB8,AB12,AB16,AB20,AB24) -> 0.15582009 | AC28: =AVERAGE(AC8,AC12,AC16,AC20,AC24) -> 14.423783
B29: FOURHR_BATTERY | C29: ALL | D29: Battery | E29: 4-Hr | F29: INDIA | G29: MWh | H29: ELECTRICITY | I29: EC_DOM | J29: 0.25 | K29: 0.25 | L29: DAILY | M29: 0 | N29: 0.9 | O29: 0.8 | P29: =AVERAGE(P9,P13,P17,P21,P25) -> 10 | Q29: =AVERAGE(Q9,Q13,Q17,Q21,Q25) -> 3873.4092 | R29: =AVERAGE(R9,R13,R17,R21,R25) -> 1.9123593 | S29: =S9+S13+S17+S21+S25 -> 0 | T29: =T9+T13+T17+T21+T25 -> 0 | U29: =U9+U13+U17+U21+U25 -> 400 | V29: =AVERAGE(V9,V13,V17,V21,V25) -> 0 | W29: =AVERAGE(W9,W13,W17,W21,W25) -> 0.09 | Y29: =AVERAGE(Y9,Y13,Y17,Y21,Y25) -> 0.89442719 | Z29: =AVERAGE(Z9,Z13,Z17,Z21,Z25) -> 0.89442719 | AA29: =AVERAGE(AA9,AA13,AA17,AA21,AA25) -> 10 | AB29: =AVERAGE(AB9,AB13,AB17,AB21,AB25) -> 0.15582009 | AC29: =AVERAGE(AC9,AC13,AC17,AC21,AC25) -> 12.272868
B30: SIXHR_BATTERY | C30: ALL | D30: Battery | E30: 6-Hr | F30: INDIA | G30: MWh | H30: ELECTRICITY | I30: EC_DOM | J30: 0.166667 | K30: 0.166667 | L30: DAILY | M30: 0 | N30: 0.9 | O30: 0.8 | P30: =AVERAGE(P10,P14,P18,P22,P26) -> 10 | Q30: =AVERAGE(Q10,Q14,Q18,Q22,Q26) -> 3873.4092 | R30: =AVERAGE(R10,R14,R18,R22,R26) -> 1.8006408 | S30: =S10+S14+S18+S22+S26 -> 0 | T30: =T10+T14+T18+T22+T26 -> 0 | U30: =U10+U14+U18+U22+U26 -> 600 | V30: =AVERAGE(V10,V14,V18,V22,V26) -> 0 | W30: =AVERAGE(W10,W14,W18,W22,W26) -> 0.09 | Y30: =AVERAGE(Y10,Y14,Y18,Y22,Y26) -> 0.89442719 | Z30: =AVERAGE(Z10,Z14,Z18,Z22,Z26) -> 0.89442719 | AA30: =AVERAGE(AA10,AA14,AA18,AA22,AA26) -> 10 | AB30: =AVERAGE(AB10,AB14,AB18,AB22,AB26) -> 0.15582009 | AC30: =AVERAGE(AC10,AC14,AC18,AC22,AC26) -> 11.555896
B31: PUMPED_STOR | C31: ALL | D31: Battery | E31: pumpedhydro | F31: INDIA | G31: MWh | H31: ELECTRICITY | I31: EC_DOM | J31: 0.16666667 | K31: 0.16666667 | L31: DAILY | M31: 0 | N31: 0.9 | O31: 0.75 | P31: =AVERAGE(P11,P15,P19,P23,P27) -> 40 | Q31: =AVERAGE(Q11,Q15,Q19,Q23,Q27) -> 50000 | R31: =AVERAGE(R11,R15,R19,R23,R27) -> 1.9001303 | S31: =S11+S15+S19+S23+S27 -> 28473.6 | T31: =T11+T15+T19+T23+T27 -> 0 | U31: =U11+U15+U19+U23+U27 -> 0 | V31: =AVERAGE(V11,V15,V19,V23,V27) -> 0 | W31: =AVERAGE(W11,W15,W19,W23,W27) -> 0.09 | Y31: =AVERAGE(Y11,Y15,Y19,Y23,Y27) -> 0.8660254 | Z31: =AVERAGE(Z11,Z15,Z19,Z23,Z27) -> 0.8660254 | AA31: =AVERAGE(AA11,AA15,AA19,AA23,AA27) -> 40 | AB31: =AVERAGE(AB11,AB15,AB19,AB23,AB27) -> 0.092959609 | AC31: =AVERAGE(AC11,AC15,AC19,AC23,AC27) -> 20.440386

Sheet Nodes_P1
A1: Source::File | B1: PIER2.0::PEC_ProdImpConstraints.csv | C1: PIER2.0::PEC_ProdImpConstraints.csv | D1: PIER2.0::PEC_ProdImpConstraints.csv | E1: PIER2.0::PEC_ProdImpConstraints.csv | F1: PIER2.0::PEC_ProdImpConstraints.csv | G1: PIER2.0::PEC_ProdImpConstraints.csv | H1: PIER2.0::PEC_Info.csv | I1: PIER2.0::PEC_Info.csv | J1: PIER2.0::PEC_Info.csv | K1: PIER2.0::PEC_Info.csv | L1: PIER2.0::PEC_Info.csv | M1: PIER2.0::PEC_Info.csv | N1: PIER2.0::PEC_Info.csv
A2: PIER2.0 var name | B2: EnergyCarrier | C2: ModelGeography | D2: SubGeography1 | E2: Year | F2: MaxDomesticProd | G2: MaxImport | H2: NonEnergyShare | I2: DomesticPrice (mRs/ktonne) | J2: AVTaxOHDom | K2: FixedTaxOHDom | L2: ImportPrice | M2: AVTaxOHImp | N2: FixedTaxOHImp
A3: Variable | F3: a | G3: b | H3: c | I3: d | J3: e | K3: f | L3: g | M3: h | N3: i | P3: aa | Q3: bb | R3: cc | S3: dd
A4: description | P4: Seg1 - domestic price with taxes applied | Q4: Seg 1 - domestic resource | R4: Seg 2 - import price with taxes applied | S4: Seg 2 - import resource
A5: Equation to Macro var | P5: = ( d * 1e3 * (1 + e) + f * 1e3 ) / conversion_if_not _MT / conversion from MT to PJ / conversion from PJ to MWh | Q5: = a * conversion_if_not _MT * conversion from MT to PJ * conversion from PJ to MWh | R5: = ( g * 1e3 * (1 + h) + i * 1e3 ) / conversion_if_not _MT / conversion from MT to PJ / conversion from PJ to MWh | S5: = b * conversion_if_not _MT * conversion from MT to PJ * conversion from PJ to MWh
A6: Macro variable | D6: location | P6: price | Q6: max | R6: price | S6: max
A7: Unit | F7: MT or BCM | G7: MT or BCF | H7: % | I7: mRs/mT or kRs/BCM | J7: % | K7: mRs/mT ork Rs/BCM | L7: mRs/mT or kRs/BCM | M7: % | N7: mRs/mT or kRs/BCM | P7: mRs/MWh | Q7: MWh | R7: mRs/mWh
B8: BIOMASS | C8: INDIA | E8: 2023 | F8: 270 | G8: 0 | H8: 0 | I8: 5449.5727 | J8: 0 | K8: 0 | L8: 5449.5727 | M8: 0 | N8: 0 | P8: =(I8*(1+J8)+K8*1000)/CarriersTech_characteristics!$G$5/Conversions!$D$2 -> 0.0012608266 | Q8: =F8*CarriersTech_characteristics!$G$5*Conversions!$D$2 -> 1.167e+09 | R8: =(L8*(1+M8)+N8*1000)/CarriersTech_characteristics!$J$5/Conversions!$D$2 -> 0.0012608266 | S8: =G8*CarriersTech_characteristics!$J$5*Conversions!$D$2 -> 0
B9: BIOMASS_WASTE | C9: INDIA | E9: 2023 | F9: 175 | G9: 0 | H9: 0 | I9: 9000 | J9: 0.05 | K9: 0 | L9: 9000 | M9: 0.05 | N9: 0 | P9: =(I9*(1+J9)+K9*1000)/CarriersTech_characteristics!$G$7/Conversions!$D$2 -> 0.0024924961 | Q9: =F9*CarriersTech_characteristics!$G$7*Conversions!$D$2 -> 6.6349151e+08 | R9: =(L9*(1+M9)+N9*1000)/CarriersTech_characteristics!$J$7/Conversions!$D$2 -> 0.0024924961 | S9: =G9*CarriersTech_characteristics!$J$7*Conversions!$D$2 -> 0
B10: NATGAS | C10: INDIA | E10: 2023 | F10: 33.648 | G10: 200 | H10: 0.36749121 | I10: 23859.031 | J10: 0.24 | K10: 0 | L10: 54880.306 | M10: 0.349 | N10: 0 | P10: =(I10*(1+J10)+K10*1000)/Conversions!$D$3/CarriersTech_characteristics!$G$3/Conversions!$D$2 -> 0.0034095552 | Q10: =F10*CarriersTech_characteristics!$G$3*Conversions!$D$2*(1-H10) -> 2.2276556e+08 | R10: =(L10*(1+M10)+N10*1000)/Conversions!$D$3/CarriersTech_characteristics!$J$3/Conversions!$D$2 -> 0.008532017 | S10: =G10*CarriersTech_characteristics!$J$3*Conversions!$D$2 -> 2.0934e+09
B11: THERMAL_COAL | C11: INDIA | D11: NR | E11: 2023 | F11: 30.747 | G11: 0 | H11: 0 | I11: 1156.3734 | J11: 0.3508 | K11: 0 | L11: 13197.141 | M11: 0.205 | N11: 0 | P11: =(I11*(1+J11)+K11*1000)/CarriersTech_characteristics!$G$2/Conversions!$D$2 -> 0.00032679978 | Q11: =F11*CarriersTech_characteristics!$G$2*Conversions!$D$2 -> 1.4696372e+08 | R11: =(L11*(1+M11)+N11*1000)/CarriersTech_characteristics!$J$2/Conversions!$D$2 -> 0.0025321733 | S11: =G11*CarriersTech_characteristics!$J$2*Conversions!$D$2 -> 0
B12: THERMAL_COAL | C12: INDIA | D12: NER | E12: 2023 | F12: 0 | G12: 0 | H12: 0 | I12: 1156.3734 | J12: 0.3508 | K12: 0 | L12: 13197.141 | M12: 0.205 | N12: 0 | P12: =(I12*(1+J12)+K12*1000)/CarriersTech_characteristics!$G$2/Conversions!$D$2 -> 0.00032679978 | Q12: =F12*CarriersTech_characteristics!$G$2*Conversions!$D$2 -> 0 | R12: =(L12*(1+M12)+N12*1000)/CarriersTech_characteristics!$J$2/Conversions!$D$2 -> 0.0025321733 | S12: =G12*CarriersTech_characteristics!$J$2*Conversions!$D$2 -> 0
B13: THERMAL_COAL | C13: INDIA | D13: ER | E13: 2023 | F13: 395.289 | G13: 150 | H13: 0 | I13: 1156.3734 | J13: 0.3508 | K13: 0 | L13: 13197.141 | M13: 0.205 | N13: 0 | P13: =(I13*(1+J13)+K13*1000)/CarriersTech_characteristics!$G$2/Conversions!$D$2 -> 0.00032679978 | Q13: =F13*CarriersTech_characteristics!$G$2*Conversions!$D$2 -> 1.8893922e+09 | R13: =(L13*(1+M13)+N13*1000)/CarriersTech_characteristics!$J$2/Conversions!$D$2 -> 0.0025321733 | S13: =G13*CarriersTech_characteristics!$J$2*Conversions!$D$2 -> 9.4203001e+08
B14: THERMAL_COAL | C14: INDIA | D14: WR | E14: 2023 | F14: 406.857 | G14: 150 | H14: 0 | I14: 1156.3734 | J14: 0.3508 | K14: 0 | L14: 13197.141 | M14: 0.205 | N14: 0 | P14: =(I14*(1+J14)+K14*1000)/CarriersTech_characteristics!$G$2/Conversions!$D$2 -> 0.00032679978 | Q14: =F14*CarriersTech_characteristics!$G$2*Conversions!$D$2 -> 1.9446847e+09 | R14: =(L14*(1+M14)+N14*1000)/CarriersTech_characteristics!$J$2/Conversions!$D$2 -> 0.0025321733 | S14: =G14*CarriersTech_characteristics!$J$2*Conversions!$D$2 -> 9.4203001e+08
B15: THERMAL_COAL | C15: INDIA | D15: SR | E15: 2023 | F15: 91.156 | G15: 150 | H15: 0 | I15: 1156.3734 | J15: 0.3508 | K15: 0 | L15: 13197.141 | M15: 0.205 | N15: 0 | P15: =(I15*(1+J15)+K15*1000)/CarriersTech_characteristics!$G$2/Conversions!$D$2 -> 0.00032679978 | Q15: =F15*CarriersTech_characteristics!$G$2*Conversions!$D$2 -> 4.3570511e+08 | R15: =(L15*(1+M15)+N15*1000)/CarriersTech_characteristics!$J$2/Conversions!$D$2 -> 0.0025321733 | S15: =G15*CarriersTech_characteristics!$J$2*Conversions!$D$2 -> 9.4203001e+08
B16: THERMAL_COAL | C16: INDIA | D16: ALL | E16: 2023 | Q16: =SUM(Q11:Q15) -> 4.4167457e+09 | S16: =SUM(S11:S15) -> 2.82609e+09

Sheet Nodes_P2
A1: Source::File | B1: PIER2.0::PEC_ProdImpConstraints.csv | C1: PIER2.0::PEC_ProdImpConstraints.csv | D1: PIER2.0::PEC_ProdImpConstraints.csv | E1: PIER2.0::PEC_ProdImpConstraints.csv | F1: PIER2.0::PEC_ProdImpConstraints.csv | G1: PIER2.0::PEC_ProdImpConstraints.csv | H1: PIER2.0::PEC_Info.csv | I1: PIER2.0::PEC_Info.csv | J1: PIER2.0::PEC_Info.csv | K1: PIER2.0::PEC_Info.csv | L1: PIER2.0::PEC_Info.csv | M1: PIER2.0::PEC_Info.csv | N1: PIER2.0::PEC_Info.csv
A2: PIER2.0 var name | B2: EnergyCarrier | C2: ModelGeography | D2: SubGeography1 | E2: Year | F2: MaxDomesticProd | G2: MaxImport | H2: NonEnergyShare | I2: DomesticPrice (mRs/ktonne) | J2: AVTaxOHDom | K2: FixedTaxOHDom | L2: ImportPrice | M2: AVTaxOHImp | N2: FixedTaxOHImp
A3: Variable | F3: a | G3: b | H3: c | I3: d | J3: e | K3: f | L3: g | M3: h | N3: i | P3: aa | Q3: bb | R3: cc | S3: dd
A4: description | P4: Seg1 - domestic price with taxes applied | Q4: Seg 1 - domestic resource | R4: Seg 2 - import price with taxes applied | S4: Seg 2 - import resource
A5: Equation to Macro var | P5: = ( d * 1e3 * (1 + e) + f * 1e3 ) / conversion_if_not _MT / conversion from MT to PJ / conversion from PJ to MWh | Q5: = a * conversion_if_not _MT * conversion from MT to PJ * conversion from PJ to MWh | R5: = ( g * 1e3 * (1 + h) + i * 1e3 ) / conversion_if_not _MT / conversion from MT to PJ / conversion from PJ to MWh | S5: = b * conversion_if_not _MT * conversion from MT to PJ * conversion from PJ to MWh
A6: Macro variable | D6: location | P6: price | Q6: max | R6: price | S6: max
A7: Unit | F7: MT or BCM | G7: MT or BCF | H7: % | I7: mRs/mT or kRs/BCM | J7: % | K7: mRs/mT ork Rs/BCM | L7: mRs/mT or kRs/BCM | M7: % | N7: mRs/mT or kRs/BCM | P7: mRs/MWh | Q7: MWh | R7: mRs/mWh
B8: BIOMASS | C8: INDIA | E8: 2024 | F8: 270 | G8: 0 | H8: 0 | I8: 5683.2536 | J8: 0 | K8: 0 | L8: 5683.2536 | M8: 0 | N8: 0 | P8: =(I8*(1+J8)+K8*1000)/CarriersTech_characteristics!$G$5/Conversions!$D$2 -> 0.0013148916 | Q8: =F8*CarriersTech_characteristics!$G$5*Conversions!$D$2 -> 1.167e+09 | R8: =(L8*(1+M8)+N8*1000)/CarriersTech_characteristics!$J$5/Conversions!$D$2 -> 0.0013148916 | S8: =G8*CarriersTech_characteristics!$J$5*Conversions!$D$2 -> 0
B9: BIOMASS_WASTE | C9: INDIA | E9: 2024 | F9: 175 | G9: 0 | H9: 0 | I9: 9000 | J9: 0.05 | K9: 0 | L9: 9000 | M9: 0.05 | N9: 0 | P9: =(I9*(1+J9)+K9*1000)/CarriersTech_characteristics!$G$7/Conversions!$D$2 -> 0.0024924961 | Q9: =F9*CarriersTech_characteristics!$G$7*Conversions!$D$2 -> 6.6349151e+08 | R9: =(L9*(1+M9)+N9*1000)/CarriersTech_characteristics!$J$7/Conversions!$D$2 -> 0.0024924961 | S9: =G9*CarriersTech_characteristics!$J$7*Conversions!$D$2 -> 0
B10: NATGAS | C10: INDIA | E10: 2024 | F10: 34.32096 | G10: 200 | H10: 0.36749121 | I10: 24102 | J10: 0.24 | K10: 0 | L10: 35195.967 | M10: 0.349 | N10: 0 | P10: =(I10*(1+J10)+K10*1000)/Conversions!$D$3/CarriersTech_characteristics!$G$3/Conversions!$D$2 -> 0.0034442765 | Q10: =F10*CarriersTech_characteristics!$G$3*Conversions!$D$2*(1-H10) -> 2.2722087e+08 | R10: =(L10*(1+M10)+N10*1000)/Conversions!$D$3/CarriersTech_characteristics!$J$3/Conversions!$D$2 -> 0.0054717732 | S10: =G10*CarriersTech_characteristics!$J$3*Conversions!$D$2 -> 2.0934e+09
B11: THERMAL_COAL | C11: INDIA | D11: NR | E11: 2024 | F11: 31.9232 | G11: 0 | H11: 0 | I11: 1156.3734 | J11: 0.3508 | K11: 0 | L11: 10095.813 | M11: 0.205 | N11: 0 | P11: =(I11*(1+J11)+K11*1000)/CarriersTech_characteristics!$G$2/Conversions!$D$2 -> 0.00032679978 | Q11: =F11*CarriersTech_characteristics!$G$2*Conversions!$D$2 -> 1.5258569e+08 | R11: =(L11*(1+M11)+N11*1000)/CarriersTech_characteristics!$J$2/Conversions!$D$2 -> 0.0019371126 | S11: =G11*CarriersTech_characteristics!$J$2*Conversions!$D$2 -> 0
B12: THERMAL_COAL | C12: INDIA | D12: NER | E12: 2024 | F12: 0 | G12: 0 | H12: 0 | I12: 1156.3734 | J12: 0.3508 | K12: 0 | L12: 10095.813 | M12: 0.205 | N12: 0 | P12: =(I12*(1+J12)+K12*1000)/CarriersTech_characteristics!$G$2/Conversions!$D$2 -> 0.00032679978 | Q12: =F12*CarriersTech_characteristics!$G$2*Conversions!$D$2 -> 0 | R12: =(L12*(1+M12)+N12*1000)/CarriersTech_characteristics!$J$2/Conversions!$D$2 -> 0.0019371126 | S12: =G12*CarriersTech_characteristics!$J$2*Conversions!$D$2 -> 0
B13: THERMAL_COAL | C13: INDIA | D13: ER | E13: 2024 | F13: 417.84809 | G13: 150 | H13: 0 | I13: 1156.3734 | J13: 0.3508 | K13: 0 | L13: 10095.813 | M13: 0.205 | N13: 0 | P13: =(I13*(1+J13)+K13*1000)/CarriersTech_characteristics!$G$2/Conversions!$D$2 -> 0.00032679978 | Q13: =F13*CarriersTech_characteristics!$G$2*Conversions!$D$2 -> 1.9972196e+09 | R13: =(L13*(1+M13)+N13*1000)/CarriersTech_characteristics!$J$2/Conversions!$D$2 -> 0.0019371126 | S13: =G13*CarriersTech_characteristics!$J$2*Conversions!$D$2 -> 9.4203001e+08
B14: THERMAL_COAL | C14: INDIA | D14: WR | E14: 2024 | F14: 429.33807 | G14: 150 | H14: 0 | I14: 1156.3734 | J14: 0.3508 | K14: 0 | L14: 10095.813 | M14: 0.205 | N14: 0 | P14: =(I14*(1+J14)+K14*1000)/CarriersTech_characteristics!$G$2/Conversions!$D$2 -> 0.00032679978 | Q14: =F14*CarriersTech_characteristics!$G$2*Conversions!$D$2 -> 2.0521391e+09 | R14: =(L14*(1+M14)+N14*1000)/CarriersTech_characteristics!$J$2/Conversions!$D$2 -> 0.0019371126 | S14: =G14*CarriersTech_characteristics!$J$2*Conversions!$D$2 -> 9.4203001e+08
B15: THERMAL_COAL | C15: INDIA | D15: SR | E15: 2024 | F15: 91.773025 | G15: 150 | H15: 0 | I15: 1156.3734 | J15: 0.3508 | K15: 0 | L15: 10095.813 | M15: 0.205 | N15: 0 | P15: =(I15*(1+J15)+K15*1000)/CarriersTech_characteristics!$G$2/Conversions!$D$2 -> 0.00032679978 | Q15: =F15*CarriersTech_characteristics!$G$2*Conversions!$D$2 -> 4.3865435e+08 | R15: =(L15*(1+M15)+N15*1000)/CarriersTech_characteristics!$J$2/Conversions!$D$2 -> 0.0019371126 | S15: =G15*CarriersTech_characteristics!$J$2*Conversions!$D$2 -> 9.4203001e+08
B16: THERMAL_COAL | C16: INDIA | D16: ALL | E16: 2024 | P16: =AVERAGE(P11:P15) -> 0.00032679978 | Q16: =SUM(Q11:Q15) -> 4.6405988e+09 | R16: =AVERAGE(R11:R15) -> 0.0019371126 | S16: =SUM(S11:S15) -> 2.82609e+09

Sheet Capacity
A1: ECT_LegacyCapacity.csv | C1: PIER2.0::ECT_CapAddBounds.csv | W1: PIER2.0::ECT_CapAddBounds.csv | AQ1: ECT_LegacyRetirement.csv
A2: Sum of LegacyCapacity | B2: Column Labels | C2: Sum of MinCapacity | D2: Column Labels | W2: Sum of MaxCapacity | X2: Column Labels | AQ2: Sum of RetCapacity | AR2: Column Labels
A3: Row Labels | B3: 2023 | C3: Row Labels | D3: 2024 | E3: 2025 | F3: 2026 | G3: 2027 | H3: 2028 | I3: 2029 | J3: 2030 | K3: 2031 | L3: 2032 | M3: 2033 | N3: 2034 | O3: 2035 | P3: 2036 | Q3: 2037 | R3: 2038 | S3: 2039 | T3: 2040 | U3: 2041 | V3: Grand Total | W3: Row Labels | X3: 2024 | Y3: 2025 | Z3: 2026 | AA3: 2027 | AB3: 2028 | AC3: 2029 | AD3: 2030 | AE3: 2031 | AF3: 2032 | AG3: 2033 | AH3: 2034 | AI3: 2035 | AJ3: 2036 | AK3: 2037 | AL3: 2038 | AM3: 2039 | AN3: 2040 | AO3: 2041 | AP3: Grand Total | AQ3: Row Labels | AR3: 2024 | AS3: 2025 | AT3: 2026 | AU3: 2027 | AV3: 2028 | AW3: 2029 | AX3: 2030 | AY3: 2031 | AZ3: 2032 | BA3: 2033 | BB3: 2034 | BC3: 2035 | BD3: 2036 | BE3: 2037 | BF3: 2038 | BG3: 2039 | BH3: 2040 | BI3: 2041 | BJ3: Grand Total
A4: NR | C4: NR | D4: 5.7302851 | E4: 12.310682 | F4: 18.219754 | G4: 17.552791 | H4: 1.6012732 | I4: 2.9927801 | J4: 2.1219236 | K4: 1.8943604 | L4: 1.563 | M4: 0.43 | N4: 0.3 | O4: 0.8 | P4: 0 | Q4: 0 | R4: 0 | S4: 0 | T4: 0 | U4: 0 | V4: 65.51685 | W4: NR | X4: 5.7302851 | Y4: 12.390225 | Z4: 18.411873 | AA4: 18.58281 | AB4: 30.456714 | AC4: 33.839687 | AD4: 37.599498 | AE4: 42.6684 | AF4: 45.5034 | AG4: 44.68843 | AH4: 44.17943 | AI4: 44.39643 | AJ4: 44.220088 | AK4: 46.964088 | AL4: 47.627088 | AM4: 47.627088 | AN4: 47.627088 | AO4: 47.627088 | AP4: 660.13971 | AQ4: NR | AR4: 0.22 | AS4: 0 | AT4: 0 | AU4: 0.21 | AV4: 2.27 | AW4: 0.21 | AX4: 2.315 | AY4: 0 | AZ4: 0.86 | BA4: 1.55 | BB4: 1.17417 | BC4: 1.59417 | BD4: 1.17417 | BE4: 0.72768 | BF4: 0.72768 | BG4: 0.72768 | BH4: 0.95942 | BI4: 1.356425 | BJ4: 16.076395
A5: EG_COAL | B5: 67.226539 | C5: EG_COAL | D5: 0 | E5: 1.32 | F5: 0 | G5: 2.64 | H5: 0 | I5: 0 | J5: 0 | K5: 0 | L5: 0 | M5: 0 | N5: 0 | O5: 0.8 | P5: 0 | Q5: 0 | R5: 0 | S5: 0 | T5: 0 | U5: 0 | V5: 4.76 | W5: EG_COAL | X5: 0 | Y5: 1.32 | Z5: 0 | AA5: 2.64 | AB5: 0 | AC5: 2.543 | AD5: 2.36 | AE5: 2.341 | AF5: 2.515 | AG5: 2.515 | AH5: 1.874 | AI5: 2.199 | AJ5: 2.148 | AK5: 2.41 | AL5: 2.543 | AM5: 2.543 | AN5: 2.543 | AO5: 2.543 | AP5: 35.037 | AQ5: EG_COAL | AR5: 0.22 | AS5: 0 | AT5: 0 | AU5: 0 | AV5: 2.06 | AW5: 0 | AX5: 2.105 | AY5: 0 | AZ5: 0.86 | BA5: 1.55 | BB5: 0.71 | BC5: 1.13 | BD5: 0.71 | BE5: 0 | BF5: 0 | BG5: 0 | BH5: 0 | BI5: 0 | BJ5: 9.345
A6: EG_CCGT | B6: 7.3305467 | C6: EG_CCGT | D6: 0 | E6: 0 | F6: 0 | G6: 0 | H6: 0 | I6: 0 | J6: 0 | K6: 0 | L6: 0 | M6: 0 | N6: 0 | O6: 0 | P6: 0 | Q6: 0 | R6: 0 | S6: 0 | T6: 0 | U6: 0 | V6: 0 | W6: EG_CCGT | X6: 0 | Y6: 0 | Z6: 0 | AA6: 0 | AB6: 0.234 | AC6: 0.234 | AD6: 0.234 | AE6: 0.234 | AF6: 0.234 | AG6: 0.234 | AH6: 0.234 | AI6: 0.234 | AJ6: 0.234 | AK6: 0.234 | AL6: 0.234 | AM6: 0.234 | AN6: 0.234 | AO6: 0.234 | AP6: 3.276 | AQ6: EG_CCGT | AR6: 0 | AS6: 0 | AT6: 0 | AU6: 0.21 | AV6: 0.21 | AW6: 0.21 | AX6: 0.21 | AY6: 0 | AZ6: 0 | BA6: 0 | BB6: 0 | BC6: 0 | BD6: 0 | BE6: 0 | BF6: 0 | BG6: 0 | BH6: 0 | BI6: 0 | BJ6: 0.84
A7: EG_OCGT | B7: 0 | C7: EG_OCGT | D7: 0 | E7: 0 | F7: 0 | G7: 0 | H7: 0 | I7: 0 | J7: 0 | K7: 0 | L7: 0 | M7: 0 | N7: 0 | O7: 0 | P7: 0 | Q7: 0 | R7: 0 | S7: 0 | T7: 0 | U7: 0 | V7: 0 | W7: EG_OCGT | X7: 0 | Y7: 0 | Z7: 0 | AA7: 0.7 | AB7: 0.7 | AC7: 0.7 | AD7: 0.7 | AE7: 0.7 | AF7: 0.7 | AG7: 0.7 | AH7: 0.7 | AI7: 0.7 | AJ7: 0.7 | AK7: 0.7 | AL7: 0.7 | AM7: 0.7 | AN7: 0.7 | AO7: 0.7 | AP7: 10.5
A8: EG_PHWR | B8: 1.6035184 | C8: EG_PHWR | D8: 0 | E8: 0.7 | F8: 0.7 | G8: 0 | H8: 0 | I8: 0 | J8: 1.4 | K8: 0 | L8: 0 | M8: 0 | N8: 0 | O8: 0 | P8: 0 | Q8: 0 | R8: 0 | S8: 0 | T8: 0 | U8: 0 | V8: 2.8 | W8: EG_PHWR | X8: 0 | Y8: 0.7 | Z8: 0.7 | AA8: 0 | AB8: 0 | AC8: 0 | AD8: 1.4 | AE8: 0 | AF8: 0 | AG8: 0 | AH8: 0.196 | AI8: 0.196 | AJ8: 0.196 | AK8: 0.196 | AL8: 0.196 | AM8: 0.196 | AN8: 0.196 | AO8: 0.196 | AP8: 4.368
A9: EG_SMR | B9: 0 | C9: EG_SMR | D9: 0 | E9: 0 | F9: 0 | G9: 0 | H9: 0 | I9: 0 | J9: 0 | K9: 0 | L9: 0 | M9: 0 | N9: 0 | O9: 0 | P9: 0 | Q9: 0 | R9: 0 | S9: 0 | T9: 0 | U9: 0 | V9: 0 | W9: EG_SMR | X9: 0 | Y9: 0 | Z9: 0 | AA9: 0 | AB9: 0 | AC9: 0 | AD9: 0 | AE9: 0 | AF9: 0 | AG9: 0.048 | AH9: 0.048 | AI9: 0.048 | AJ9: 0.048 | AK9: 0.048 | AL9: 0.048 | AM9: 0.048 | AN9: 0.048 | AO9: 0.048 | AP9: 0.432
A10: EG_LH | B10: 20.527317 | C10: EG_LH | D10: 0 | E10: 0.56 | F10: 1.55 | G10: 0 | H10: 1.004 | I10: 0.72 | J10: 0.45 | K10: 1.624 | L10: 1.39 | M10: 0.43 | N10: 0.3 | O10: 0 | P10: 0 | Q10: 0 | R10: 0 | S10: 0 | T10: 0 | U10: 0 | V10: 8.028 | W10: EG_LH | X10: 0 | Y10: 0.56 | Z10: 1.55 | AA10: 0 | AB10: 1.004 | AC10: 0.72 | AD10: 0.45 | AE10: 1.624 | AF10: 1.455 | AG10: 0.702 | AH10: 0.638 | AI10: 0.53 | AJ10: 0.53 | AK10: 0 | AL10: 0.53 | AM10: 0.53 | AN10: 0.53 | AO10: 0.53 | AP10: 11.883
A11: EG_SH | B11: 1.69875 | C11: EG_SH | D11: 0.028 | E11: 0.028 | F11: 0.028 | G11: 0.028 | H11: 0.018 | I11: 0.018 | J11: 0.018 | K11: 0.018 | L11: 0.018 | M11: 0 | N11: 0 | O11: 0 | P11: 0 | Q11: 0 | R11: 0 | S11: 0 | T11: 0 | U11: 0 | V11: 0.202 | W11: EG_SH | X11: 0.028 | Y11: 0.028 | Z11: 0.028 | AA11: 0.028 | AB11: 0.018 | AC11: 0.018 | AD11: 0.38 | AE11: 0.38 | AF11: 0.38 | AG11: 0.38 | AH11: 0.38 | AI11: 0.38 | AJ11: 0.38 | AK11: 0.38 | AL11: 0.38 | AM11: 0.38 | AN11: 0.38 | AO11: 0.38 | AP11: 4.708
A12: EG_BIOMASS | B12: 3.35715 | C12: EG_BIOMASS | D12: 0.143 | E12: 0.143 | F12: 0.143 | G12: 0.143 | H12: 0.155 | I12: 0.155 | J12: 0.155 | K12: 0.155 | L12: 0.155 | M12: 0 | N12: 0 | O12: 0 | P12: 0 | Q12: 0 | R12: 0 | S12: 0 | T12: 0 | U12: 0 | V12: 1.347 | W12: EG_BIOMASS | X12: 0.143 | Y12: 0.143 | Z12: 0.143 | AA12: 0.143 | AB12: 0.155 | AC12: 0.155 | AD12: 0.155 | AE12: 0.199 | AF12: 0.288 | AG12: 0.318 | AH12: 0.318 | AI12: 0.318 | AJ12: 0.318 | AK12: 0.318 | AL12: 0.318 | AM12: 0.318 | AN12: 0.318 | AO12: 0.318 | AP12: 4.386 | AQ12: EG_BIOMASS | AR12: 0 | AS12: 0 | AT12: 0 | AU12: 0 | AV12: 0 | AW12: 0 | AX12: 0 | AY12: 0 | AZ12: 0 | BA12: 0 | BB12: 0 | BC12: 0 | BD12: 0 | BE12: 0 | BF12: 0 | BG12: 0 | BH12: 0 | BI12: 0 | BJ12: 0
A13: EG_SOLARGM | B13: 19.996724 | C13: EG_SOLARGM | D13: 4.791 | E13: 4.85 | F13: 12.938 | G13: 11.7 | H13: 0.329 | I13: 1.881 | J13: 0 | K13: 0 | L13: 0 | M13: 0 | N13: 0 | O13: 0 | P13: 0 | Q13: 0 | R13: 0 | S13: 0 | T13: 0 | U13: 0 | V13: 36.489 | W13: EG_SOLARGM | X13: 4.791 | Y13: 4.85 | Z13: 12.938 | AA13: 11.7 | AB13: 17.977 | AC13: 17.977 | AD13: 17.977 | AE13: 17.977 | AF13: 19.775 | AG13: 19.775 | AH13: 19.775 | AI13: 19.775 | AJ13: 19.775 | AK13: 21.753 | AL13: 21.753 | AM13: 21.753 | AN13: 21.753 | AO13: 21.753 | AP13: 313.827 | AQ13: EG_SOLARGM | AR13: 0 | AS13: 0 | AT13: 0 | AU13: 0 | AV13: 0 | AW13: 0 | AX13: 0 | AY13: 0 | AZ13: 0 | BA13: 0 | BB13: 0 | BC13: 0 | BD13: 0 | BE13: 0.24338879 | BF13: 0.24338879 | BG13: 0.24338879 | BH13: 0.3712446 | BI13: 0.55789485 | BJ13: 1.6593058
A14: EG_SOLARRF | B14: 2.6663458 | C14: EG_SOLARRF | D14: 0.766 | E14: 4.679 | F14: 2.242 | G14: 2.233 | H14: 0.021 | I14: 0.119 | J14: 0 | K14: 0 | L14: 0 | M14: 0 | N14: 0 | O14: 0 | P14: 0 | Q14: 0 | R14: 0 | S14: 0 | T14: 0 | U14: 0 | V14: 10.06 | W14: EG_SOLARRF | X14: 0.766 | Y14: 4.679 | Z14: 2.242 | AA14: 2.233 | AB14: 4.494 | AC14: 4.494 | AD14: 4.494 | AE14: 4.494 | AF14: 4.944 | AG14: 4.944 | AH14: 4.944 | AI14: 4.944 | AJ14: 4.944 | AK14: 5.437 | AL14: 5.437 | AM14: 5.437 | AN14: 5.437 | AO14: 5.437 | AP14: 79.801 | AQ14: EG_SOLARRF | AR14: 0 | AS14: 0 | AT14: 0 | AU14: 0 | AV14: 0 | AW14: 0 | AX14: 0 | AY14: 0 | AZ14: 0 | BA14: 0 | BB14: 0 | BC14: 0 | BD14: 0 | BE14: 0.020121213 | BF14: 0.020121213 | BG14: 0.020121213 | BH14: 0.064675397 | BI14: 0.11303015 | BJ14: 0.23806918
A15: EG_WINDON | B15: 5.30142 | C15: EG_WINDON | D15: 0.002 | E15: 0.029 | F15: 0.616 | G15: 0.705 | H15: 0 | I15: 0 | J15: 0 | K15: 0 | L15: 0 | M15: 0 | N15: 0 | O15: 0 | P15: 0 | Q15: 0 | R15: 0 | S15: 0 | T15: 0 | U15: 0 | V15: 1.352 | W15: EG_WINDON | X15: 0.002 | Y15: 0.029 | Z15: 0.616 | AA15: 0.705 | AB15: 4.921 | AC15: 4.921 | AD15: 4.921 | AE15: 4.921 | AF15: 5.414 | AG15: 5.414 | AH15: 5.414 | AI15: 5.414 | AJ15: 5.414 | AK15: 5.955 | AL15: 5.955 | AM15: 5.955 | AN15: 5.955 | AO15: 5.955 | AP15: 77.881 | AQ15: EG_WINDON | AR15: 0 | AS15: 0 | AT15: 0 | AU15: 0 | AV15: 0 | AW15: 0 | AX15: 0 | AY15: 0 | AZ15: 0 | BA15: 0 | BB15: 0.46417 | BC15: 0.46417 | BD15: 0.46417 | BE15: 0.46417 | BF15: 0.46417 | BG15: 0.46417 | BH15: 0.5235 | BI15: 0.6855 | BJ15: 3.99402
A16: EG_WINDOFF | B16: 0 | C16: EG_WINDOFF | D16: 0 | E16: 0 | F16: 0 | G16: 0 | H16: 0 | I16: 0 | J16: 0 | K16: 0 | L16: 0 | M16: 0 | N16: 0 | O16: 0 | P16: 0 | Q16: 0 | R16: 0 | S16: 0 | T16: 0 | U16: 0 | V16: 0 | W16: EG_WINDOFF | X16: 0 | Y16: 0 | Z16: 0 | AA16: 0 | AB16: 0 | AC16: 0 | AD16: 0 | AE16: 0 | AF16: 0 | AG16: 0 | AH16: 0 | AI16: 0 | AJ16: 0 | AK16: 0 | AL16: 0 | AM16: 0 | AN16: 0 | AO16: 0 | AP16: 0
A17: GH_ELECTROLYSIS | B17: 0.06863464 | C17: GH_ELECTROLYSIS | D17: 0.0002850662 | E17: 0.001682276 | F17: 0.002753779 | G17: 0.1037915 | H17: 0.074273203 | I17: 0.099780123 | J17: 0.098923584 | K17: 0.097360442 | L17: 0 | M17: 0 | N17: 0 | O17: 0 | P17: 0 | Q17: 0 | R17: 0 | S17: 0 | T17: 0 | U17: 0 | V17: 0.47884997 | W17: GH_ELECTROLYSIS | X17: 0.0002850662 | Y17: 0.081225473 | Z17: 0.1948728 | AA17: 0.43381032 | AB17: 0.95371397 | AC17: 2.077687 | AD17: 4.5284981 | AE17: 9.7983996 | AF17: 9.7983996 | AG17: 9.6584305 | AH17: 9.6584305 | AI17: 9.6584305 | AJ17: 9.5330884 | AK17: 9.5330884 | AL17: 9.5330884 | AM17: 9.5330884 | AN17: 9.5330884 | AO17: 9.5330884 | AP17: 114.04071
A18: NER | C18: NER | D18: 0.026021154 | E18: 0.62318206 | F18: 1.5422626 | G18: 0.051700517 | H18: 0.13494169 | I18: 0.017185507 | J18: 0.016974035 | K18: 0.016588109 | L18: 0.008 | M18: 0 | N18: 0 | O18: 0 | P18: 0 | Q18: 2.88 | R18: 0 | S18: 0 | T18: 0 | U18: 0 | V18: 5.3168556 | W18: NER | X18: 0.026021154 | Y18: 0.63179034 | Z18: 1.5605806 | AA18: 0.2735446 | AB18: 4.3191356 | AC18: 4.3392666 | AD18: 4.6918111 | AE18: 5.1453112 | AF18: 5.6373112 | AG18: 6.024754 | AH18: 6.052754 | AI18: 6.110754 | AJ18: 6.0888081 | AK18: 8.7658081 | AL18: 6.5168081 | AM18: 6.5168081 | AN18: 6.5168081 | AO18: 6.5168081 | AP18: 85.734883 | AQ18: NER | AR18: 0 | AS18: 0 | AT18: 0 | AU18: 0 | AV18: 0 | AW18: 0 | AX18: 0 | AY18: 0 | AZ18: 0 | BA18: 0 | BB18: 0 | BC18: 0 | BD18: 0 | BE18: 1e-05 | BF18: 1e-05 | BG18: 1e-05 | BH18: 0.005 | BI18: 0.00034 | BJ18: 0.00537
A19: EG_COAL | B19: 1.0109297 | C19: EG_COAL | D19: 0 | E19: 0 | F19: 0 | G19: 0 | H19: 0 | I19: 0 | J19: 0 | K19: 0 | L19: 0 | M19: 0 | N19: 0 | O19: 0 | P19: 0 | Q19: 0 | R19: 0 | S19: 0 | T19: 0 | U19: 0 | V19: 0 | W19: EG_COAL | X19: 0 | Y19: 0 | Z19: 0 | AA19: 0 | AB19: 0 | AC19: 0.038 | AD19: 0.036 | AE19: 0.036 | AF19: 0.037 | AG19: 0.037 | AH19: 0.028 | AI19: 0.024 | AJ19: 0.033 | AK19: 0.036 | AL19: 0.038 | AM19: 0.038 | AN19: 0.038 | AO19: 0.038 | AP19: 0.457 | AQ19: EG_COAL | AR19: 0 | AS19: 0 | AT19: 0 | AU19: 0 | AV19: 0 | AW19: 0 | AX19: 0 | AY19: 0 | AZ19: 0 | BA19: 0 | BB19: 0 | BC19: 0 | BD19: 0 | BE19: 0 | BF19: 0 | BG19: 0 | BH19: 0 | BI19: 0 | BJ19: 0
A20: EG_CCGT | B20: 2.0024569 | C20: EG_CCGT | D20: 0 | E20: 0 | F20: 0 | G20: 0 | H20: 0 | I20: 0 | J20: 0 | K20: 0 | L20: 0 | M20: 0 | N20: 0 | O20: 0 | P20: 0 | Q20: 0 | R20: 0 | S20: 0 | T20: 0 | U20: 0 | V20: 0 | W20: EG_CCGT | X20: 0 | Y20: 0 | Z20: 0 | AA20: 0 | AB20: 0.064 | AC20: 0.064 | AD20: 0.064 | AE20: 0.064 | AF20: 0.064 | AG20: 0.064 | AH20: 0.064 | AI20: 0.064 | AJ20: 0.064 | AK20: 0.064 | AL20: 0.064 | AM20: 0.064 | AN20: 0.064 | AO20: 0.064 | AP20: 0.896 | AQ20: EG_CCGT | AR20: 0 | AS20: 0 | AT20: 0 | AU20: 0 | AV20: 0 | AW20: 0 | AX20: 0 | AY20: 0 | AZ20: 0 | BA20: 0 | BB20: 0 | BC20: 0 | BD20: 0 | BE20: 0 | BF20: 0 | BG20: 0 | BH20: 0 | BI20: 0 | BJ20: 0
A21: EG_OCGT | B21: 0 | C21: EG_OCGT | D21: 0 | E21: 0 | F21: 0 | G21: 0 | H21: 0 | I21: 0 | J21: 0 | K21: 0 | L21: 0 | M21: 0 | N21: 0 | O21: 0 | P21: 0 | Q21: 0 | R21: 0 | S21: 0 | T21: 0 | U21: 0 | V21: 0 | W21: EG_OCGT | X21: 0 | Y21: 0 | Z21: 0 | AA21: 0.191 | AB21: 0.191 | AC21: 0.191 | AD21: 0.191 | AE21: 0.191 | AF21: 0.191 | AG21: 0.191 | AH21: 0.191 | AI21: 0.191 | AJ21: 0.191 | AK21: 0.191 | AL21: 0.191 | AM21: 0.191 | AN21: 0.191 | AO21: 0.191 | AP21: 2.865
A22: EG_PHWR | B22: 0 | C22: EG_PHWR | D22: 0 | E22: 0 | F22: 0 | G22: 0 | H22: 0 | I22: 0 | J22: 0 | K22: 0 | L22: 0 | M22: 0 | N22: 0 | O22: 0 | P22: 0 | Q22: 0 | R22: 0 | S22: 0 | T22: 0 | U22: 0 | V22: 0 | W22: EG_PHWR | X22: 0 | Y22: 0 | Z22: 0 | AA22: 0 | AB22: 0 | AC22: 0 | AD22: 0 | AE22: 0 | AF22: 0 | AG22: 0 | AH22: 0 | AI22: 0 | AJ22: 0 | AK22: 0 | AL22: 0 | AM22: 0 | AN22: 0 | AO22: 0 | AP22: 0
A23: EG_SMR | B23: 0 | C23: EG_SMR | D23: 0 | E23: 0 | F23: 0 | G23: 0 | H23: 0 | I23: 0 | J23: 0 | K23: 0 | L23: 0 | M23: 0 | N23: 0 | O23: 0 | P23: 0 | Q23: 0 | R23: 0 | S23: 0 | T23: 0 | U23: 0 | V23: 0 | W23: EG_SMR | X23: 0 | Y23: 0 | Z23: 0 | AA23: 0 | AB23: 0 | AC23: 0 | AD23: 0 | AE23: 0 | AF23: 0 | AG23: 0 | AH23: 0 | AI23: 0 | AJ23: 0 | AK23: 0 | AL23: 0 | AM23: 0 | AN23: 0 | AO23: 0 | AP23: 0
A24: EG_LH | B24: 1.8428253 | C24: EG_LH | D24: 0 | E24: 0.5 | F24: 1.5 | G24: 0 | H24: 0.12 | I24: 0 | J24: 0 | K24: 0 | L24: 0 | M24: 0 | N24: 0 | O24: 0 | P24: 0 | Q24: 2.88 | R24: 0 | S24: 0 | T24: 0 | U24: 0 | V24: 5 | W24: EG_LH | X24: 0 | Y24: 0.5 | Z24: 1.5 | AA24: 0 | AB24: 0.12 | AC24: 0 | AD24: 0 | AE24: 0 | AF24: 0.107 | AG24: 0.53 | AH24: 0.567 | AI24: 0.629 | AJ24: 0.629 | AK24: 2.88 | AL24: 0.629 | AM24: 0.629 | AN24: 0.629 | AO24: 0.629 | AP24: 9.978
A25: EG_SH | B25: 0.29935 | C25: EG_SH | D25: 0.01 | E25: 0.01 | F25: 0.01 | G25: 0.01 | H25: 0.007 | I25: 0.007 | J25: 0.007 | K25: 0.007 | L25: 0.007 | M25: 0 | N25: 0 | O25: 0 | P25: 0 | Q25: 0 | R25: 0 | S25: 0 | T25: 0 | U25: 0 | V25: 0.075 | W25: EG_SH | X25: 0.01 | Y25: 0.01 | Z25: 0.01 | AA25: 0.01 | AB25: 0.007 | AC25: 0.007 | AD25: 0.142 | AE25: 0.142 | AF25: 0.142 | AG25: 0.142 | AH25: 0.142 | AI25: 0.142 | AJ25: 0.142 | AK25: 0.142 | AL25: 0.142 | AM25: 0.142 | AN25: 0.142 | AO25: 0.142 | AP25: 1.758
A26: EG_BIOMASS | B26: 0.0158 | C26: EG_BIOMASS | D26: 0.001 | E26: 0.001 | F26: 0.001 | G26: 0.001 | H26: 0.001 | I26: 0.001 | J26: 0.001 | K26: 0.001 | L26: 0.001 | M26: 0 | N26: 0 | O26: 0 | P26: 0 | Q26: 0 | R26: 0 | S26: 0 | T26: 0 | U26: 0 | V26: 0.009 | W26: EG_BIOMASS | X26: 0.001 | Y26: 0.001 | Z26: 0.001 | AA26: 0.001 | AB26: 0.001 | AC26: 0.001 | AD26: 0.001 | AE26: 0.001 | AF26: 0.001 | AG26: 0 | AH26: 0 | AI26: 0 | AJ26: 0 | AK26: 0 | AL26: 0 | AM26: 0 | AN26: 0 | AO26: 0 | AP26: 0.009 | AQ26: EG_BIOMASS | AR26: 0 | AS26: 0 | AT26: 0 | AU26: 0 | AV26: 0 | AW26: 0 | AX26: 0 | AY26: 0 | AZ26: 0 | BA26: 0 | BB26: 0 | BC26: 0 | BD26: 0 | BE26: 0 | BF26: 0 | BG26: 0 | BH26: 0 | BI26: 0 | BJ26: 0
A27: EG_SOLARGM | B27: 0.17148962 | C27: EG_SOLARGM | D27: 0.007 | E27: 0.007 | F27: 0 | G27: 0 | H27: 0 | I27: 0 | J27: 0 | K27: 0 | L27: 0 | M27: 0 | N27: 0 | O27: 0 | P27: 0 | Q27: 0 | R27: 0 | S27: 0 | T27: 0 | U27: 0 | V27: 0.014 | W27: EG_SOLARGM | X27: 0.007 | Y27: 0.007 | Z27: 0 | AA27: 0 | AB27: 3.067 | AC27: 3.067 | AD27: 3.067 | AE27: 3.067 | AF27: 3.373 | AG27: 3.373 | AH27: 3.373 | AI27: 3.373 | AJ27: 3.373 | AK27: 3.71 | AL27: 3.71 | AM27: 3.71 | AN27: 3.71 | AO27: 3.71 | AP27: 47.697 | AQ27: EG_SOLARGM | AR27: 0 | AS27: 0 | AT27: 0 | AU27: 0 | AV27: 0 | AW27: 0 | AX27: 0 | AY27: 0 | AZ27: 0 | BA27: 0 | BB27: 0 | BC27: 0 | BD27: 0 | BE27: 5.90991e-06 | BF27: 5.90991e-06 | BG27: 5.90991e-06 | BH27: 0.002954953 | BI27: 0.000200937 | BJ27: 0.0031736197
A28: EG_SOLARRF | B28: 0.067610378 | C28: EG_SOLARRF | D28: 0.008 | E28: 0.105 | F28: 0.031 | G28: 0.031 | H28: 0 | I28: 0 | J28: 0 | K28: 0 | L28: 0 | M28: 0 | N28: 0 | O28: 0 | P28: 0 | Q28: 0 | R28: 0 | S28: 0 | T28: 0 | U28: 0 | V28: 0.175 | W28: EG_SOLARRF | X28: 0.008 | Y28: 0.105 | Z28: 0.031 | AA28: 0.031 | AB28: 0.767 | AC28: 0.767 | AD28: 0.767 | AE28: 0.767 | AF28: 0.843 | AG28: 0.843 | AH28: 0.843 | AI28: 0.843 | AJ28: 0.843 | AK28: 0.928 | AL28: 0.928 | AM28: 0.928 | AN28: 0.928 | AO28: 0.928 | AP28: 12.098 | AQ28: EG_SOLARRF | AR28: 0 | AS28: 0 | AT28: 0 | AU28: 0 | AV28: 0 | AW28: 0 | AX28: 0 | AY28: 0 | AZ28: 0 | BA28: 0 | BB28: 0 | BC28: 0 | BD28: 0 | BE28: 4.09009e-06 | BF28: 4.09009e-06 | BG28: 4.09009e-06 | BH28: 0.002045047 | BI28: 0.000139063 | BJ28: 0.0021963803
A29: EG_WINDON | B29: 0 | C29: EG_WINDON | D29: 0 | E29: 0 | F29: 0 | G29: 0 | H29: 0 | I29: 0 | J29: 0 | K29: 0 | L29: 0 | M29: 0 | N29: 0 | O29: 0 | P29: 0 | Q29: 0 | R29: 0 | S29: 0 | T29: 0 | U29: 0 | V29: 0 | W29: EG_WINDON | X29: 0 | Y29: 0 | Z29: 0 | AA29: 0 | AB29: 0.013 | AC29: 0.013 | AD29: 0.013 | AE29: 0.013 | AF29: 0.015 | AG29: 0.015 | AH29: 0.015 | AI29: 0.015 | AJ29: 0.015 | AK29: 0.016 | AL29: 0.016 | AM29: 0.016 | AN29: 0.016 | AO29: 0.016 | AP29: 0.207 | AQ29: EG_WINDON | AR29: 0 | AS29: 0 | AT29: 0 | AU29: 0 | AV29: 0 | AW29: 0 | AX29: 0 | AY29: 0 | AZ29: 0 | BA29: 0 | BB29: 0 | BC29: 0 | BD29: 0 | BE29: 0 | BF29: 0 | BG29: 0 | BH29: 0 | BI29: 0 | BJ29: 0
A30: EG_WINDOFF | B30: 0 | C30: EG_WINDOFF | D30: 0 | E30: 0 | F30: 0 | G30: 0 | H30: 0 | I30: 0 | J30: 0 | K30: 0 | L30: 0 | M30: 0 | N30: 0 | O30: 0 | P30: 0 | Q30: 0 | R30: 0 | S30: 0 | T30: 0 | U30: 0 | V30: 0 | W30: EG_WINDOFF | X30: 0 | Y30: 0 | Z30: 0 | AA30: 0 | AB30: 0 | AC30: 0 | AD30: 0 | AE30: 0 | AF30: 0 | AG30: 0 | AH30: 0 | AI30: 0 | AJ30: 0 | AK30: 0 | AL30: 0 | AM30: 0 | AN30: 0 | AO30: 0 | AP30: 0
A31: GH_ELECTROLYSIS | B31: 0.005006256 | C31: GH_ELECTROLYSIS | D31: 2.1154e-05 | E31: 0.000182058 | F31: 0.000262565 | G31: 0.009700517 | H31: 0.00694169 | I31: 0.009185507 | J31: 0.008974035 | K31: 0.008588109 | L31: 0 | M31: 0 | N31: 0 | O31: 0 | P31: 0 | Q31: 0 | R31: 0 | S31: 0 | T31: 0 | U31: 0 | V31: 0.043855635 | W31: GH_ELECTROLYSIS | X31: 2.1154e-05 | Y31: 0.008790345 | Z31: 0.018580569 | AA31: 0.040544596 | AB31: 0.089135609 | AC31: 0.19126664 | AD31: 0.41081105 | AE31: 0.86431119 | AF31: 0.86431119 | AG31: 0.82975398 | AH31: 0.82975398 | AI31: 0.82975398 | AJ31: 0.79880808 | AK31: 0.79880808 | AL31: 0.79880808 | AM31: 0.79880808 | AN31: 0.79880808 | AO31: 0.79880808 | AP31: 9.7698828
A32: ER | C32: ER | D32: 0.2071059 | E32: 0.47761165 | F32: 3.9759269 | G32: 1.2753333 | H32: 0.85456888 | I32: 0.062789382 | J32: 1.4870609 | K32: 1.3858948 | L32: 0.03 | M32: 0 | N32: 0 | O32: 4 | P32: 1.6 | Q32: 0.8 | R32: 0 | S32: 0 | T32: 0 | U32: 0 | V32: 16.156292 | W32: ER | X32: 0.2071059 | Y32: 0.50653218 | Z32: 4.0405915 | AA32: 1.4575004 | AB32: 5.9794797 | AC32: 7.124762 | AD32: 9.3385645 | AE32: 10.732469 | AF32: 10.613469 | AG32: 10.616051 | AH32: 10.224051 | AI32: 13.541051 | AJ32: 11.675546 | AK32: 11.417546 | AL32: 11.077546 | AM32: 11.077546 | AN32: 11.077546 | AO32: 11.077546 | AP32: 151.7849 | AQ32: ER | AR32: 0 | AS32: 0 | AT32: 0 | AU32: 0 | AV32: 0.44 | AW32: 0 | AX32: 0.425 | AY32: 0.593 | AZ32: 0.643 | BA32: 0.91 | BB32: 0.92 | BC32: 0.63 | BD32: 0.63 | BE32: 0.43785 | BF32: 0.017850001 | BG32: 0.017850001 | BH32: 0.21142 | BI32: 0.46101 | BJ32: 6.33698
A33: EG_COAL | B33: 41.729904 | C33: EG_COAL | D33: 0 | E33: 0 | F33: 3.44 | G33: 0.66 | H33: 0.8 | I33: 0 | J33: 0.8 | K33: 1.32 | L33: 0 | M33: 0 | N33: 0 | O33: 4 | P33: 1.6 | Q33: 0.8 | R33: 0 | S33: 0 | T33: 0 | U33: 0 | V33: 13.42 | W33: EG_COAL | X33: 0 | Y33: 0 | Z33: 3.44 | AA33: 0.66 | AB33: 0.8 | AC33: 1.578 | AD33: 2.081 | AE33: 2.176 | AF33: 1.561 | AG33: 1.561 | AH33: 1.163 | AI33: 4.469 | AJ33: 2.697 | AK33: 2.031 | AL33: 1.578 | AM33: 1.578 | AN33: 1.578 | AO33: 1.578 | AP33: 30.529 | AQ33: EG_COAL | AR33: 0 | AS33: 0 | AT33: 0 | AU33: 0 | AV33: 0.44 | AW33: 0 | AX33: 0.425 | AY33: 0.593 | AZ33: 0.643 | BA33: 0.91 | BB33: 0.92 | BC33: 0.63 | BD33: 0.63 | BE33: 0.42 | BF33: 0 | BG33: 0 | BH33: 0.21 | BI33: 0.42 | BJ33: 6.241
A34: EG_CCGT | B34: 0.77080433 | C34: EG_CCGT | D34: 0 | E34: 0 | F34: 0 | G34: 0 | H34: 0 | I34: 0 | J34: 0 | K34: 0 | L34: 0 | M34: 0 | N34: 0 | O34: 0 | P34: 0 | Q34: 0 | R34: 0 | S34: 0 | T34: 0 | U34: 0 | V34: 0 | W34: EG_CCGT | X34: 0 | Y34: 0 | Z34: 0 | AA34: 0 | AB34: 0.025 | AC34: 0.025 | AD34: 0.025 | AE34: 0.025 | AF34: 0.025 | AG34: 0.025 | AH34: 0.025 | AI34: 0.025 | AJ34: 0.025 | AK34: 0.025 | AL34: 0.025 | AM34: 0.025 | AN34: 0.025 | AO34: 0.025 | AP34: 0.35 | AQ34: EG_CCGT | AR34: 0 | AS34: 0 | AT34: 0 | AU34: 0 | AV34: 0 | AW34: 0 | AX34: 0 | AY34: 0 | AZ34: 0 | BA34: 0 | BB34: 0 | BC34: 0 | BD34: 0 | BE34: 0 | BF34: 0 | BG34: 0 | BH34: 0 | BI34: 0 | BJ34: 0
A35: EG_OCGT | B35: 0 | C35: EG_OCGT | D35: 0 | E35: 0 | F35: 0 | G35: 0 | H35: 0 | I35: 0 | J35: 0 | K35: 0 | L35: 0 | M35: 0 | N35: 0 | O35: 0 | P35: 0 | Q35: 0 | R35: 0 | S35: 0 | T35: 0 | U35: 0 | V35: 0 | W35: EG_OCGT | X35: 0 | Y35: 0 | Z35: 0 | AA35: 0.073 | AB35: 0.073 | AC35: 0.073 | AD35: 0.073 | AE35: 0.073 | AF35: 0.073 | AG35: 0.073 | AH35: 0.073 | AI35: 0.073 | AJ35: 0.073 | AK35: 0.073 | AL35: 0.073 | AM35: 0.073 | AN35: 0.073 | AO35: 0.073 | AP35: 1.095
A36: EG_PHWR | B36: 0 | C36: EG_PHWR | D36: 0 | E36: 0 | F36: 0 | G36: 0 | H36: 0 | I36: 0 | J36: 0 | K36: 0 | L36: 0 | M36: 0 | N36: 0 | O36: 0 | P36: 0 | Q36: 0 | R36: 0 | S36: 0 | T36: 0 | U36: 0 | V36: 0 | W36: EG_PHWR | X36: 0 | Y36: 0 | Z36: 0 | AA36: 0 | AB36: 0 | AC36: 0 | AD36: 0 | AE36: 0 | AF36: 0 | AG36: 0 | AH36: 0 | AI36: 0 | AJ36: 0 | AK36: 0 | AL36: 0 | AM36: 0 | AN36: 0 | AO36: 0 | AP36: 0
A37: EG_SMR | B37: 0 | C37: EG_SMR | D37: 0 | E37: 0 | F37: 0 | G37: 0 | H37: 0 | I37: 0 | J37: 0 | K37: 0 | L37: 0 | M37: 0 | N37: 0 | O37: 0 | P37: 0 | Q37: 0 | R37: 0 | S37: 0 | T37: 0 | U37: 0 | V37: 0 | W37: EG_SMR | X37: 0 | Y37: 0 | Z37: 0 | AA37: 0 | AB37: 0 | AC37: 0 | AD37: 0 | AE37: 0 | AF37: 0 | AG37: 0 | AH37: 0 | AI37: 0 | AJ37: 0 | AK37: 0 | AL37: 0 | AM37: 0 | AN37: 0 | AO37: 0 | AP37: 0
A38: EG_LH | B38: 4.1988603 | C38: EG_LH | D38: 0 | E38: 0 | F38: 0 | G38: 0.12 | H38: 0 | I38: 0 | J38: 0.62 | K38: 0 | L38: 0 | M38: 0 | N38: 0 | O38: 0 | P38: 0 | Q38: 0 | R38: 0 | S38: 0 | T38: 0 | U38: 0 | V38: 0.74 | W38: EG_LH | X38: 0 | Y38: 0 | Z38: 0 | AA38: 0.12 | AB38: 0 | AC38: 0 | AD38: 0.62 | AE38: 0 | AF38: 0.02 | AG38: 0.096 | AH38: 0.102 | AI38: 0.113 | AJ38: 0.113 | AK38: 0 | AL38: 0.113 | AM38: 0.113 | AN38: 0.113 | AO38: 0.113 | AP38: 1.636
A39: EG_SH | B39: 0.34399 | C39: EG_SH | D39: 0.006 | E39: 0.006 | F39: 0.006 | G39: 0.006 | H39: 0.005 | I39: 0.005 | J39: 0.005 | K39: 0.005 | L39: 0.005 | M39: 0 | N39: 0 | O39: 0 | P39: 0 | Q39: 0 | R39: 0 | S39: 0 | T39: 0 | U39: 0 | V39: 0.049 | W39: EG_SH | X39: 0.006 | Y39: 0.006 | Z39: 0.006 | AA39: 0.006 | AB39: 0.005 | AC39: 0.005 | AD39: 0.082 | AE39: 0.082 | AF39: 0.082 | AG39: 0.082 | AH39: 0.082 | AI39: 0.082 | AJ39: 0.082 | AK39: 0.082 | AL39: 0.082 | AM39: 0.082 | AN39: 0.082 | AO39: 0.082 | AP39: 1.018
A40: EG_BIOMASS | B40: 0.56064 | C40: EG_BIOMASS | D40: 0.023 | E40: 0.023 | F40: 0.023 | G40: 0.023 | H40: 0.025 | I40: 0.025 | J40: 0.025 | K40: 0.025 | L40: 0.025 | M40: 0 | N40: 0 | O40: 0 | P40: 0 | Q40: 0 | R40: 0 | S40: 0 | T40: 0 | U40: 0 | V40: 0.217 | W40: EG_BIOMASS | X40: 0.023 | Y40: 0.023 | Z40: 0.023 | AA40: 0.023 | AB40: 0.025 | AC40: 0.025 | AD40: 0.025 | AE40: 0.028 | AF40: 0.031 | AG40: 0.062 | AH40: 0.062 | AI40: 0.062 | AJ40: 0.062 | AK40: 0.062 | AL40: 0.062 | AM40: 0.062 | AN40: 0.062 | AO40: 0.062 | AP40: 0.784 | AQ40: EG_BIOMASS | AR40: 0 | AS40: 0 | AT40: 0 | AU40: 0 | AV40: 0 | AW40: 0 | AX40: 0 | AY40: 0 | AZ40: 0 | BA40: 0 | BB40: 0 | BC40: 0 | BD40: 0 | BE40: 0 | BF40: 0 | BG40: 0 | BH40: 0 | BI40: 0 | BJ40: 0
A41: EG_SOLARGM | B41: 0.8477259 | C41: EG_SOLARGM | D41: 0.04 | E41: 0.04 | F41: 0.231 | G41: 0.285 | H41: 0 | I41: 0 | J41: 0 | K41: 0 | L41: 0 | M41: 0 | N41: 0 | O41: 0 | P41: 0 | Q41: 0 | R41: 0 | S41: 0 | T41: 0 | U41: 0 | V41: 0.596 | W41: EG_SOLARGM | X41: 0.04 | Y41: 0.04 | Z41: 0.231 | AA41: 0.285 | AB41: 3.548 | AC41: 3.548 | AD41: 3.548 | AE41: 3.548 | AF41: 3.903 | AG41: 3.903 | AH41: 3.903 | AI41: 3.903 | AJ41: 3.903 | AK41: 4.294 | AL41: 4.294 | AM41: 4.294 | AN41: 4.294 | AO41: 4.294 | AP41: 55.773 | AQ41: EG_SOLARGM | AR41: 0 | AS41: 0 | AT41: 0 | AU41: 0 | AV41: 0 | AW41: 0 | AX41: 0 | AY41: 0 | AZ41: 0 | BA41: 0 | BB41: 0 | BC41: 0 | BD41: 0 | BE41: 0.013022359 | BF41: 0.013022359 | BG41: 0.013022359 | BH41: 0.001304953 | BI41: 0.038006156 | BJ41: 0.078378187
A42: EG_SOLARRF | B42: 0.2000841 | C42: EG_SOLARRF | D42: 0.138 | E42: 0.408 | F42: 0.275 | G42: 0.147 | H42: 0 | I42: 0 | J42: 0 | K42: 0 | L42: 0 | M42: 0 | N42: 0 | O42: 0 | P42: 0 | Q42: 0 | R42: 0 | S42: 0 | T42: 0 | U42: 0 | V42: 0.968 | W42: EG_SOLARRF | X42: 0.138 | Y42: 0.408 | Z42: 0.275 | AA42: 0.147 | AB42: 0.888 | AC42: 0.888 | AD42: 0.888 | AE42: 0.888 | AF42: 0.976 | AG42: 0.976 | AH42: 0.976 | AI42: 0.976 | AJ42: 0.976 | AK42: 1.073 | AL42: 1.073 | AM42: 1.073 | AN42: 1.073 | AO42: 1.073 | AP42: 14.765 | AQ42: EG_SOLARRF | AR42: 0 | AS42: 0 | AT42: 0 | AU42: 0 | AV42: 0 | AW42: 0 | AX42: 0 | AY42: 0 | AZ42: 0 | BA42: 0 | BB42: 0 | BC42: 0 | BD42: 0 | BE42: 0.004827642 | BF42: 0.004827642 | BG42: 0.004827642 | BH42: 0.0001150478 | BI42: 0.003003844 | BJ42: 0.017601818
A43: EG_WINDON | B43: 0.046 | C43: EG_WINDON | D43: 0 | E43: 0 | F43: 0 | G43: 0 | H43: 0 | I43: 0 | J43: 0 | K43: 0 | L43: 0 | M43: 0 | N43: 0 | O43: 0 | P43: 0 | Q43: 0 | R43: 0 | S43: 0 | T43: 0 | U43: 0 | V43: 0 | W43: EG_WINDON | X43: 0 | Y43: 0 | Z43: 0 | AA43: 0 | AB43: 0.3 | AC43: 0.3 | AD43: 0.3 | AE43: 0.3 | AF43: 0.33 | AG43: 0.33 | AH43: 0.33 | AI43: 0.33 | AJ43: 0.33 | AK43: 0.363 | AL43: 0.363 | AM43: 0.363 | AN43: 0.363 | AO43: 0.363 | AP43: 4.665 | AQ43: EG_WINDON | AR43: 0 | AS43: 0 | AT43: 0 | AU43: 0 | AV43: 0 | AW43: 0 | AX43: 0 | AY43: 0 | AZ43: 0 | BA43: 0 | BB43: 0 | BC43: 0 | BD43: 0 | BE43: 0 | BF43: 0 | BG43: 0 | BH43: 0 | BI43: 0 | BJ43: 0
A44: EG_WINDOFF | B44: 0 | C44: EG_WINDOFF | D44: 0 | E44: 0 | F44: 0 | G44: 0 | H44: 0 | I44: 0 | J44: 0 | K44: 0 | L44: 0 | M44: 0 | N44: 0 | O44: 0 | P44: 0 | Q44: 0 | R44: 0 | S44: 0 | T44: 0 | U44: 0 | V44: 0 | W44: EG_WINDOFF | X44: 0 | Y44: 0 | Z44: 0 | AA44: 0 | AB44: 0 | AC44: 0 | AD44: 0 | AE44: 0 | AF44: 0 | AG44: 0 | AH44: 0 | AI44: 0 | AJ44: 0 | AK44: 0 | AL44: 0 | AM44: 0 | AN44: 0 | AO44: 0 | AP44: 0
A45: GH_ELECTROLYSIS | B45: 0.025503758 | C45: GH_ELECTROLYSIS | D45: 0.0001059036 | E45: 0.0006116463 | F45: 0.000926884 | G45: 0.034333257 | H45: 0.024568882 | I45: 0.032789382 | J45: 0.037060906 | K45: 0.035894795 | L45: 0 | M45: 0 | N45: 0 | O45: 0 | P45: 0 | Q45: 0 | R45: 0 | S45: 0 | T45: 0 | U45: 0 | V45: 0.16629166 | W45: GH_ELECTROLYSIS | X45: 0.0001059036 | Y45: 0.029532175 | Z45: 0.065591547 | AA45: 0.1435004 | AB45: 0.31547968 | AC45: 0.68276197 | AD45: 1.6965645 | AE45: 3.6124688 | AF45: 3.6124688 | AG45: 3.5080513 | AH45: 3.5080513 | AI45: 3.5080513 | AJ45: 3.4145457 | AK45: 3.4145457 | AL45: 3.4145457 | AM45: 3.4145457 | AN45: 3.4145457 | AO45: 3.4145457 | AP45: 41.169902
A46: WR | C46: WR | D46: 10.750448 | E46: 21.355624 | F46: 31.943782 | G46: 25.912054 | H46: 1.9002228 | I46: 0.99035872 | J46: 1.0881831 | K46: 1.0931743 | L46: 0.953 | M46: 1.3 | N46: 4 | O46: 0 | P46: 1.6 | Q46: 0 | R46: 0 | S46: 0 | T46: 0 | U46: 0 | V46: 102.88685 | W46: WR | X46: 10.750448 | Y46: 21.479714 | Z46: 32.207614 | AA46: 27.654375 | AB46: 22.858923 | AC46: 27.354173 | AD46: 30.735379 | AE46: 38.635202 | AF46: 41.252202 | AG46: 42.416124 | AH46: 44.369124 | AI46: 41.055124 | AJ46: 42.598341 | AK46: 44.579341 | AL46: 44.844341 | AM46: 44.844341 | AN46: 44.844341 | AO46: 44.844341 | AP46: 647.32345 | AQ46: WR | AR46: 0 | AS46: 0 | AT46: 0 | AU46: 0 | AV46: 0.92 | AW46: 0 | AX46: 3.64 | AY46: 1.251 | AZ46: 1.805 | BA46: 0.42 | BB46: 1.5240617 | BC46: 2.5650617 | BD46: 2.1540617 | BE46: 1.8207017 | BF46: 1.8957017 | BG46: 1.8207017 | BH46: 1.40453 | BI46: 2.313549 | BJ46: 23.534369
A47: EG_COAL | B47: 90.475826 | C47: EG_COAL | D47: 0 | E47: 0.66 | F47: 0 | G47: 0 | H47: 0 | I47: 0 | J47: 0.8 | K47: 0.8 | L47: 0.8 | M47: 0.8 | N47: 4 | O47: 0 | P47: 1.6 | Q47: 0 | R47: 0 | S47: 0 | T47: 0 | U47: 0 | V47: 9.46 | W47: EG_COAL | X47: 0 | Y47: 0.66 | Z47: 0 | AA47: 0 | AB47: 0 | AC47: 3.422 | AD47: 3.344 | AE47: 3.325 | AF47: 3.505 | AG47: 3.505 | AH47: 5.514 | AI47: 2.192 | AJ47: 3.335 | AK47: 3.245 | AL47: 3.422 | AM47: 3.422 | AN47: 3.422 | AO47: 3.422 | AP47: 45.735 | AQ47: EG_COAL | AR47: 0 | AS47: 0 | AT47: 0 | AU47: 0 | AV47: 0.92 | AW47: 0 | AX47: 3.64 | AY47: 1.251 | AZ47: 1.805 | BA47: 0.42 | BB47: 0.21 | BC47: 1.251 | BD47: 0.84 | BE47: 0 | BF47: 0.075 | BG47: 0 | BH47: 0 | BI47: 0 | BJ47: 10.412
A48: EG_CCGT | B48: 13.563175 | C48: EG_CCGT | D48: 0 | E48: 0 | F48: 0 | G48: 0 | H48: 0 | I48: 0 | J48: 0 | K48: 0 | L48: 0 | M48: 0 | N48: 0 | O48: 0 | P48: 0 | Q48: 0 | R48: 0 | S48: 0 | T48: 0 | U48: 0 | V48: 0 | W48: EG_CCGT | X48: 0 | Y48: 0 | Z48: 0 | AA48: 0 | AB48: 0.432 | AC48: 0.432 | AD48: 0.432 | AE48: 0.432 | AF48: 0.432 | AG48: 0.432 | AH48: 0.432 | AI48: 0.432 | AJ48: 0.432 | AK48: 0.432 | AL48: 0.432 | AM48: 0.432 | AN48: 0.432 | AO48: 0.432 | AP48: 6.048 | AQ48: EG_CCGT | AR48: 0 | AS48: 0 | AT48: 0 | AU48: 0 | AV48: 0 | AW48: 0 | AX48: 0 | AY48: 0 | AZ48: 0 | BA48: 0 | BB48: 0 | BC48: 0 | BD48: 0 | BE48: 0 | BF48: 0 | BG48: 0 | BH48: 0 | BI48: 0 | BJ48: 0
A49: EG_OCGT | B49: 0 | C49: EG_OCGT | D49: 0 | E49: 0 | F49: 0 | G49: 0 | H49: 0 | I49: 0 | J49: 0 | K49: 0 | L49: 0 | M49: 0 | N49: 0 | O49: 0 | P49: 0 | Q49: 0 | R49: 0 | S49: 0 | T49: 0 | U49: 0 | V49: 0 | W49: EG_OCGT | X49: 0 | Y49: 0 | Z49: 0 | AA49: 1.297 | AB49: 1.297 | AC49: 1.297 | AD49: 1.297 | AE49: 1.297 | AF49: 1.297 | AG49: 1.297 | AH49: 1.297 | AI49: 1.297 | AJ49: 1.297 | AK49: 1.297 | AL49: 1.297 | AM49: 1.297 | AN49: 1.297 | AO49: 1.297 | AP49: 19.455
A50: EG_PHWR | B50: 3.248824 | C50: EG_PHWR | D50: 1.4 | E50: 0 | F50: 0 | G50: 0 | H50: 0 | I50: 0 | J50: 0 | K50: 0 | L50: 0 | M50: 0 | N50: 0 | O50: 0 | P50: 0 | Q50: 0 | R50: 0 | S50: 0 | T50: 0 | U50: 0 | V50: 1.4 | W50: EG_PHWR | X50: 1.4 | Y50: 0 | Z50: 0 | AA50: 0 | AB50: 0 | AC50: 0 | AD50: 0 | AE50: 0 | AF50: 0 | AG50: 0 | AH50: 0.397 | AI50: 0.397 | AJ50: 0.397 | AK50: 0.397 | AL50: 0.397 | AM50: 0.397 | AN50: 0.397 | AO50: 0.397 | AP50: 4.576
A51: EG_SMR | B51: 0 | C51: EG_SMR | D51: 0 | E51: 0 | F51: 0 | G51: 0 | H51: 0 | I51: 0 | J51: 0 | K51: 0 | L51: 0 | M51: 0.5 | N51: 0 | O51: 0 | P51: 0 | Q51: 0 | R51: 0 | S51: 0 | T51: 0 | U51: 0 | V51: 0.5 | W51: EG_SMR | X51: 0 | Y51: 0 | Z51: 0 | AA51: 0 | AB51: 0 | AC51: 0 | AD51: 0 | AE51: 0 | AF51: 0 | AG51: 0.513 | AH51: 0.054 | AI51: 0.054 | AJ51: 0.054 | AK51: 0.054 | AL51: 0.054 | AM51: 0.054 | AN51: 0.054 | AO51: 0.054 | AP51: 0.945
A52: EG_LH | B52: 7.7532156 | C52: EG_LH | D52: 0 | E52: 0 | F52: 0 | G52: 0 | H52: 0 | I52: 0 | J52: 0 | K52: 0 | L52: 0 | M52: 0 | N52: 0 | O52: 0 | P52: 0 | Q52: 0 | R52: 0 | S52: 0 | T52: 0 | U52: 0 | V52: 0 | W52: EG_LH | X52: 0 | Y52: 0 | Z52: 0 | AA52: 0 | AB52: 0 | AC52: 0 | AD52: 0 | AE52: 0 | AF52: 0.015 | AG52: 0.074 | AH52: 0.08 | AI52: 0.088 | AJ52: 0.088 | AK52: 0 | AL52: 0.088 | AM52: 0.088 | AN52: 0.088 | AO52: 0.088 | AP52: 0.697
A53: EG_SH | B53: 0.67248 | C53: EG_SH | D53: 0.011 | E53: 0.011 | F53: 0.011 | G53: 0.011 | H53: 0.007 | I53: 0.007 | J53: 0.007 | K53: 0.007 | L53: 0.007 | M53: 0 | N53: 0 | O53: 0 | P53: 0 | Q53: 0 | R53: 0 | S53: 0 | T53: 0 | U53: 0 | V53: 0.079 | W53: EG_SH | X53: 0.011 | Y53: 0.011 | Z53: 0.011 | AA53: 0.011 | AB53: 0.007 | AC53: 0.007 | AD53: 0.138 | AE53: 0.138 | AF53: 0.138 | AG53: 0.138 | AH53: 0.138 | AI53: 0.138 | AJ53: 0.138 | AK53: 0.138 | AL53: 0.138 | AM53: 0.138 | AN53: 0.138 | AO53: 0.138 | AP53: 1.714
A54: EG_BIOMASS | B54: 3.1617 | C54: EG_BIOMASS | D54: 0.136 | E54: 0.136 | F54: 0.136 | G54: 0.136 | H54: 0.146 | I54: 0.146 | J54: 0.146 | K54: 0.146 | L54: 0.146 | M54: 0 | N54: 0 | O54: 0 | P54: 0 | Q54: 0 | R54: 0 | S54: 0 | T54: 0 | U54: 0 | V54: 1.274 | W54: EG_BIOMASS | X54: 0.136 | Y54: 0.136 | Z54: 0.136 | AA54: 0.136 | AB54: 0.146 | AC54: 0.146 | AD54: 0.146 | AE54: 0.146 | AF54: 0.146 | AG54: 0.291 | AH54: 0.291 | AI54: 0.291 | AJ54: 0.291 | AK54: 0.291 | AL54: 0.291 | AM54: 0.291 | AN54: 0.291 | AO54: 0.291 | AP54: 3.893 | AQ54: EG_BIOMASS | AR54: 0 | AS54: 0 | AT54: 0 | AU54: 0 | AV54: 0 | AW54: 0 | AX54: 0 | AY54: 0 | AZ54: 0 | BA54: 0 | BB54: 0 | BC54: 0 | BD54: 0 | BE54: 0 | BF54: 0 | BG54: 0 | BH54: 0 | BI54: 0 | BJ54: 0
A55: EG_SOLARGM | B55: 13.221936 | C55: EG_SOLARGM | D55: 5.56 | E55: 6.29 | F55: 13.882 | G55: 13.743 | H55: 0.362 | I55: 0.145 | J55: 0 | K55: 0 | L55: 0 | M55: 0 | N55: 0 | O55: 0 | P55: 0 | Q55: 0 | R55: 0 | S55: 0 | T55: 0 | U55: 0 | V55: 39.982 | W55: EG_SOLARGM | X55: 5.56 | Y55: 6.29 | Z55: 13.882 | AA55: 13.743 | AB55: 9.671 | AC55: 9.671 | AD55: 9.671 | AE55: 9.671 | AF55: 10.639 | AG55: 10.639 | AH55: 10.639 | AI55: 10.639 | AJ55: 10.639 | AK55: 11.703 | AL55: 11.703 | AM55: 11.703 | AN55: 11.703 | AO55: 11.703 | AP55: 189.869 | AQ55: EG_SOLARGM | AR55: 0 | AS55: 0 | AT55: 0 | AU55: 0 | AV55: 0 | AW55: 0 | AX55: 0 | AY55: 0 | AZ55: 0 | BA55: 0 | BB55: 0 | BC55: 0 | BD55: 0 | BE55: 0.38450579 | BF55: 0.38450579 | BG55: 0.38450579 | BH55: 0.32723512 | BI55: 0.38096527 | BJ55: 1.8617178
A56: EG_SOLARRF | B56: 4.503404 | C56: EG_SOLARRF | D56: 1.704 | E56: 12.197 | F56: 6.11 | G56: 6.239 | H56: 0.083 | I56: 0.055 | J56: 0 | K56: 0 | L56: 0 | M56: 0 | N56: 0 | O56: 0 | P56: 0 | Q56: 0 | R56: 0 | S56: 0 | T56: 0 | U56: 0 | V56: 26.388 | W56: EG_SOLARRF | X56: 1.704 | Y56: 12.197 | Z56: 6.11 | AA56: 6.239 | AB56: 2.418 | AC56: 2.418 | AD56: 2.418 | AE56: 2.418 | AF56: 2.661 | AG56: 2.661 | AH56: 2.661 | AI56: 2.661 | AJ56: 2.661 | AK56: 2.924 | AL56: 2.924 | AM56: 2.924 | AN56: 2.924 | AO56: 2.924 | AP56: 63.847 | AQ56: EG_SOLARRF | AR56: 0 | AS56: 0 | AT56: 0 | AU56: 0 | AV56: 0 | AW56: 0 | AX56: 0 | AY56: 0 | AZ56: 0 | BA56: 0 | BB56: 0 | BC56: 0 | BD56: 0 | BE56: 0.12213421 | BF56: 0.12213421 | BG56: 0.12213421 | BH56: 0.079824884 | BI56: 0.070933729 | BJ56: 0.51716124
A57: EG_WINDON | B57: 18.66104 | C57: EG_WINDON | D57: 1.939 | E57: 2.059 | F57: 11.801 | G57: 5.643 | H57: 0.702 | I57: 0.5 | J57: 0 | K57: 0 | L57: 0 | M57: 0 | N57: 0 | O57: 0 | P57: 0 | Q57: 0 | R57: 0 | S57: 0 | T57: 0 | U57: 0 | V57: 22.644 | W57: EG_WINDON | X57: 1.939 | Y57: 2.059 | Z57: 11.801 | AA57: 5.643 | AB57: 7.101 | AC57: 7.101 | AD57: 7.101 | AE57: 7.101 | AF57: 7.812 | AG57: 7.812 | AH57: 7.812 | AI57: 7.812 | AJ57: 7.812 | AK57: 8.594 | AL57: 8.594 | AM57: 8.594 | AN57: 8.594 | AO57: 8.594 | AP57: 131.876 | AQ57: EG_WINDON | AR57: 0 | AS57: 0 | AT57: 0 | AU57: 0 | AV57: 0 | AW57: 0 | AX57: 0 | AY57: 0 | AZ57: 0 | BA57: 0 | BB57: 1.3140617 | BC57: 1.3140617 | BD57: 1.3140617 | BE57: 1.3140617 | BF57: 1.3140617 | BG57: 1.3140617 | BH57: 0.99747 | BI57: 1.86165 | BJ57: 10.74349
A58: EG_WINDOFF | B58: 0 | C58: EG_WINDOFF | D58: 0 | E58: 0 | F58: 0 | G58: 0 | H58: 0.5 | I58: 0 | J58: 0 | K58: 0 | L58: 0 | M58: 0 | N58: 0 | O58: 0 | P58: 0 | Q58: 0 | R58: 0 | S58: 0 | T58: 0 | U58: 0 | V58: 0.5 | W58: EG_WINDOFF | X58: 0 | Y58: 0 | Z58: 0 | AA58: 0 | AB58: 0.5 | AC58: 0 | AD58: 0 | AE58: 0 | AF58: 0.5 | AG58: 0.5 | AH58: 0.5 | AI58: 0.5 | AJ58: 0.5 | AK58: 0.55 | AL58: 0.55 | AM58: 0.55 | AN58: 0.55 | AO58: 0.55 | AP58: 5.75
A59: GH_ELECTROLYSIS | B59: 0.10789067 | C59: GH_ELECTROLYSIS | D59: 0.00044800125 | E59: 0.0026243891 | F59: 0.0037816991 | G59: 0.14005422 | H59: 0.10022281 | I59: 0.13735872 | J59: 0.13518315 | K59: 0.14017426 | L59: 0 | M59: 0 | N59: 0 | O59: 0 | P59: 0 | Q59: 0 | R59: 0 | S59: 0 | T59: 0 | U59: 0 | V59: 0.65984725 | W59: GH_ELECTROLYSIS | X59: 0.00044800125 | Y59: 0.12671366 | Z59: 0.26761423 | AA59: 0.58537518 | AB59: 1.286923 | AC59: 2.8601732 | AD59: 6.188379 | AE59: 14.107202 | AF59: 14.107202 | AG59: 14.554124 | AH59: 14.554124 | AI59: 14.554124 | AJ59: 14.954341 | AK59: 14.954341 | AL59: 14.954341 | AM59: 14.954341 | AN59: 14.954341 | AO59: 14.954341 | AP59: 172.91845
A60: SR | C60: SR | D60: 4.0991399 | E60: 10.6679 | F60: 17.765275 | G60: 18.100121 | H60: 3.7907194 | I60: 0.35588626 | J60: 0.77985833 | K60: 0.86798239 | L60: 0.185 | M60: 2.04 | N60: 0 | O60: 0 | P60: 0 | Q60: 0 | R60: 0 | S60: 0 | T60: 0 | U60: 0 | V60: 58.651882 | W60: SR | X60: 4.0991399 | Y60: 10.710437 | Z60: 17.854231 | AA60: 18.988946 | AB60: 18.479979 | AC60: 19.381474 | AD60: 21.101513 | AE60: 23.491767 | AF60: 25.100767 | AG60: 27.17179 | AH60: 24.95979 | AI60: 24.74279 | AJ60: 25.086366 | AK60: 26.875366 | AL60: 27.144366 | AM60: 27.144366 | AN60: 27.144366 | AO60: 27.144366 | AP60: 396.62182 | AQ60: SR | AR60: 0 | AS60: 0 | AT60: 0 | AU60: 0 | AV60: 2.31 | AW60: 0 | AX60: 0.8925 | AY60: 1.04 | AZ60: 1.04 | BA60: 0.63 | BB60: 1.9381483 | BC60: 3.5681483 | BD60: 2.4381483 | BE60: 2.315235 | BF60: 2.315235 | BG60: 2.025235 | BH60: 1.26351 | BI60: 2.673085 | BJ60: 24.449245
A61: EG_COAL | B61: 63.929271 | C61: EG_COAL | D61: 0 | E61: 0 | F61: 0.8 | G61: 5.32 | H61: 1.32 | I61: 0 | J61: 0 | K61: 0 | L61: 0 | M61: 0 | N61: 0 | O61: 0 | P61: 0 | Q61: 0 | R61: 0 | S61: 0 | T61: 0 | U61: 0 | V61: 7.44 | W61: EG_COAL | X61: 0 | Y61: 0 | Z61: 0.8 | AA61: 5.32 | AB61: 1.32 | AC61: 2.419 | AD61: 2.244 | AE61: 2.228 | AF61: 2.39 | AG61: 2.39 | AH61: 1.781 | AI61: 1.549 | AJ61: 2.043 | AK61: 2.292 | AL61: 2.419 | AM61: 2.419 | AN61: 2.419 | AO61: 2.419 | AP61: 36.452 | AQ61: EG_COAL | AR61: 0 | AS61: 0 | AT61: 0 | AU61: 0 | AV61: 2.31 | AW61: 0 | AX61: 0.8925 | AY61: 1.04 | AZ61: 1.04 | BA61: 0.63 | BB61: 0.21 | BC61: 1.84 | BD61: 0.71 | BE61: 0.5 | BF61: 0.5 | BG61: 0.21 | BH61: 0.21 | BI61: 0 | BJ61: 10.0925
A62: EG_CCGT | B62: 7.7302171 | C62: EG_CCGT | D62: 0.37 | E62: 0 | F62: 0 | G62: 0 | H62: 0 | I62: 0 | J62: 0 | K62: 0 | L62: 0 | M62: 0 | N62: 0 | O62: 0 | P62: 0 | Q62: 0 | R62: 0 | S62: 0 | T62: 0 | U62: 0 | V62: 0.37 | W62: EG_CCGT | X62: 0.37 | Y62: 0 | Z62: 0 | AA62: 0 | AB62: 0.246 | AC62: 0.246 | AD62: 0.246 | AE62: 0.246 | AF62: 0.246 | AG62: 0.246 | AH62: 0.246 | AI62: 0.246 | AJ62: 0.246 | AK62: 0.246 | AL62: 0.246 | AM62: 0.246 | AN62: 0.246 | AO62: 0.246 | AP62: 3.814 | AQ62: EG_CCGT | AR62: 0 | AS62: 0 | AT62: 0 | AU62: 0 | AV62: 0 | AW62: 0 | AX62: 0 | AY62: 0 | AZ62: 0 | BA62: 0 | BB62: 0 | BC62: 0 | BD62: 0 | BE62: 0 | BF62: 0 | BG62: 0 | BH62: 0 | BI62: 0 | BJ62: 0
A63: EG_OCGT | B63: 0 | C63: EG_OCGT | D63: 0 | E63: 0 | F63: 0 | G63: 0 | H63: 0 | I63: 0 | J63: 0 | K63: 0 | L63: 0 | M63: 0 | N63: 0 | O63: 0 | P63: 0 | Q63: 0 | R63: 0 | S63: 0 | T63: 0 | U63: 0 | V63: 0 | W63: EG_OCGT | X63: 0 | Y63: 0 | Z63: 0 | AA63: 0.739 | AB63: 0.739 | AC63: 0.739 | AD63: 0.739 | AE63: 0.739 | AF63: 0.739 | AG63: 0.739 | AH63: 0.739 | AI63: 0.739 | AJ63: 0.739 | AK63: 0.739 | AL63: 0.739 | AM63: 0.739 | AN63: 0.739 | AO63: 0.739 | AP63: 11.085
A64: EG_PHWR | B64: 3.3276676 | C64: EG_PHWR | D64: 0 | E64: 0 | F64: 0 | G64: 2 | H64: 0 | I64: 0 | J64: 0 | K64: 0 | L64: 0 | M64: 2 | N64: 0 | O64: 0 | P64: 0 | Q64: 0 | R64: 0 | S64: 0 | T64: 0 | U64: 0 | V64: 4 | W64: EG_PHWR | X64: 0 | Y64: 0 | Z64: 0 | AA64: 2 | AB64: 0 | AC64: 0 | AD64: 0 | AE64: 0 | AF64: 0 | AG64: 2 | AH64: 0.406 | AI64: 0.406 | AJ64: 0.406 | AK64: 0.406 | AL64: 0.406 | AM64: 0.406 | AN64: 0.406 | AO64: 0.406 | AP64: 7.248
A65: EG_SMR | B65: 0 | C65: EG_SMR | D65: 0 | E65: 0 | F65: 0 | G65: 0 | H65: 0 | I65: 0 | J65: 0 | K65: 0 | L65: 0 | M65: 0 | N65: 0 | O65: 0 | P65: 0 | Q65: 0 | R65: 0 | S65: 0 | T65: 0 | U65: 0 | V65: 0 | W65: EG_SMR | X65: 0 | Y65: 0 | Z65: 0 | AA65: 0 | AB65: 0 | AC65: 0 | AD65: 0 | AE65: 0 | AF65: 0 | AG65: 0.098 | AH65: 0.098 | AI65: 0.098 | AJ65: 0.098 | AK65: 0.098 | AL65: 0.098 | AM65: 0.098 | AN65: 0.098 | AO65: 0.098 | AP65: 0.882
A66: EG_LH | B66: 12.168961 | C66: EG_LH | D66: 0 | E66: 0.1 | F66: 0 | G66: 0.98 | H66: 0.72 | I66: 0 | J66: 0.55 | K66: 0.64 | L66: 0 | M66: 0.04 | N66: 0 | O66: 0 | P66: 0 | Q66: 0 | R66: 0 | S66: 0 | T66: 0 | U66: 0 | V66: 3.03 | W66: EG_LH | X66: 0 | Y66: 0.1 | Z66: 0 | AA66: 0.98 | AB66: 0.72 | AC66: 0 | AD66: 0.55 | AE66: 0.64 | AF66: 0.023 | AG66: 0.136 | AH66: 0.127 | AI66: 0.142 | AJ66: 0.142 | AK66: 0 | AL66: 0.142 | AM66: 0.142 | AN66: 0.142 | AO66: 0.142 | AP66: 4.128
A67: EG_SH | B67: 1.92448 | C67: EG_SH | D67: 0.017 | E67: 0.017 | F67: 0.017 | G67: 0.017 | H67: 0.013 | I67: 0.013 | J67: 0.013 | K67: 0.013 | L67: 0.013 | M67: 0 | N67: 0 | O67: 0 | P67: 0 | Q67: 0 | R67: 0 | S67: 0 | T67: 0 | U67: 0 | V67: 0.133 | W67: EG_SH | X67: 0.017 | Y67: 0.017 | Z67: 0.017 | AA67: 0.017 | AB67: 0.013 | AC67: 0.013 | AD67: 0.26 | AE67: 0.26 | AF67: 0.26 | AG67: 0.26 | AH67: 0.26 | AI67: 0.26 | AJ67: 0.26 | AK67: 0.26 | AL67: 0.26 | AM67: 0.26 | AN67: 0.26 | AO67: 0.26 | AP67: 3.214
A68: EG_BIOMASS | B68: 3.73475 | C68: EG_BIOMASS | D68: 0.16 | E68: 0.16 | F68: 0.16 | G68: 0.16 | H68: 0.172 | I68: 0.172 | J68: 0.172 | K68: 0.172 | L68: 0.172 | M68: 0 | N68: 0 | O68: 0 | P68: 0 | Q68: 0 | R68: 0 | S68: 0 | T68: 0 | U68: 0 | V68: 1.5 | W68: EG_BIOMASS | X68: 0.16 | Y68: 0.16 | Z68: 0.16 | AA68: 0.16 | AB68: 0.172 | AC68: 0.172 | AD68: 0.172 | AE68: 0.216 | AF68: 0.298 | AG68: 0.326 | AH68: 0.326 | AI68: 0.326 | AJ68: 0.326 | AK68: 0.326 | AL68: 0.326 | AM68: 0.326 | AN68: 0.326 | AO68: 0.326 | AP68: 4.604 | AQ68: EG_BIOMASS | AR68: 0 | AS68: 0 | AT68: 0 | AU68: 0 | AV68: 0 | AW68: 0 | AX68: 0 | AY68: 0 | AZ68: 0 | BA68: 0 | BB68: 0 | BC68: 0 | BD68: 0 | BE68: 0 | BF68: 0 | BG68: 0 | BH68: 0 | BI68: 0 | BJ68: 0
A69: EG_SOLARGM | B69: 24.128917 | C69: EG_SOLARGM | D69: 1.622 | E69: 2.204 | F69: 5.578 | G69: 3.393 | H69: 0.17 | I69: 0 | J69: 0 | K69: 0 | L69: 0 | M69: 0 | N69: 0 | O69: 0 | P69: 0 | Q69: 0 | R69: 0 | S69: 0 | T69: 0 | U69: 0 | V69: 12.967 | W69: EG_SOLARGM | X69: 1.622 | Y69: 2.204 | Z69: 5.578 | AA69: 3.393 | AB69: 5.739 | AC69: 5.739 | AD69: 5.739 | AE69: 5.739 | AF69: 6.312 | AG69: 6.312 | AH69: 6.312 | AI69: 6.312 | AJ69: 6.312 | AK69: 6.943 | AL69: 6.943 | AM69: 6.943 | AN69: 6.943 | AO69: 6.943 | AP69: 102.028 | AQ69: EG_SOLARGM | AR69: 0 | AS69: 0 | AT69: 0 | AU69: 0 | AV69: 0 | AW69: 0 | AX69: 0 | AY69: 0 | AZ69: 0 | BA69: 0 | BB69: 0 | BC69: 0 | BD69: 0 | BE69: 0.082604207 | BF69: 0.082604207 | BG69: 0.082604207 | BH69: 0.24846537 | BI69: 1.6845571 | BJ69: 2.1808351
A70: EG_SOLARRF | B70: 2.0308232 | C70: EG_SOLARRF | D70: 0.618 | E70: 4.769 | F70: 1.492 | G70: 1.398 | H70: 0 | I70: 0 | J70: 0 | K70: 0 | L70: 0 | M70: 0 | N70: 0 | O70: 0 | P70: 0 | Q70: 0 | R70: 0 | S70: 0 | T70: 0 | U70: 0 | V70: 8.277 | W70: EG_SOLARRF | X70: 0.618 | Y70: 4.769 | Z70: 1.492 | AA70: 1.398 | AB70: 1.435 | AC70: 1.435 | AD70: 1.435 | AE70: 1.435 | AF70: 1.578 | AG70: 1.578 | AH70: 1.578 | AI70: 1.578 | AJ70: 1.578 | AK70: 1.736 | AL70: 1.736 | AM70: 1.736 | AN70: 1.736 | AO70: 1.736 | AP70: 30.587 | AQ70: EG_SOLARRF | AR70: 0 | AS70: 0 | AT70: 0 | AU70: 0 | AV70: 0 | AW70: 0 | AX70: 0 | AY70: 0 | AZ70: 0 | BA70: 0 | BB70: 0 | BC70: 0 | BD70: 0 | BE70: 0.0044824594 | BF70: 0.0044824594 | BG70: 0.0044824594 | BH70: 0.014244633 | BI70: 0.11262788 | BJ70: 0.14031989
A71: EG_WINDON | B71: 22.16137 | C71: EG_WINDON | D71: 1.312 | E71: 3.417 | F71: 9.717 | G71: 4.785 | H71: 1.362 | I71: 0.125 | J71: 0 | K71: 0 | L71: 0 | M71: 0 | N71: 0 | O71: 0 | P71: 0 | Q71: 0 | R71: 0 | S71: 0 | T71: 0 | U71: 0 | V71: 20.718 | W71: EG_WINDON | X71: 1.312 | Y71: 3.417 | Z71: 9.717 | AA71: 4.785 | AB71: 7.663 | AC71: 7.663 | AD71: 7.663 | AE71: 7.663 | AF71: 8.429 | AG71: 8.429 | AH71: 8.429 | AI71: 8.429 | AJ71: 8.429 | AK71: 9.272 | AL71: 9.272 | AM71: 9.272 | AN71: 9.272 | AO71: 9.272 | AP71: 138.388 | AQ71: EG_WINDON | AR71: 0 | AS71: 0 | AT71: 0 | AU71: 0 | AV71: 0 | AW71: 0 | AX71: 0 | AY71: 0 | AZ71: 0 | BA71: 0 | BB71: 1.7281483 | BC71: 1.7281483 | BD71: 1.7281483 | BE71: 1.7281483 | BF71: 1.7281483 | BG71: 1.7281483 | BH71: 0.7908 | BI71: 0.8759 | BJ71: 12.03559
A72: EG_WINDOFF | B72: 0 | C72: EG_WINDOFF | D72: 0 | E72: 0 | F72: 0 | G72: 0 | H72: 0 | I72: 0 | J72: 0 | K72: 0 | L72: 0 | M72: 0 | N72: 0 | O72: 0 | P72: 0 | Q72: 0 | R72: 0 | S72: 0 | T72: 0 | U72: 0 | V72: 0 | W72: EG_WINDOFF | X72: 0 | Y72: 0 | Z72: 0 | AA72: 0 | AB72: 0 | AC72: 0 | AD72: 0 | AE72: 0 | AF72: 0.5 | AG72: 0.5 | AH72: 0.5 | AI72: 0.5 | AJ72: 0.5 | AK72: 0.55 | AL72: 0.55 | AM72: 0.55 | AN72: 0.55 | AO72: 0.55 | AP72: 5.25
A73: GH_ELECTROLYSIS | B73: 0.033690705 | C73: GH_ELECTROLYSIS | D73: 0.000139876 | E73: 0.000899631 | F73: 0.001275071 | G73: 0.047120514 | H73: 0.033719444 | I73: 0.045886264 | J73: 0.044858327 | K73: 0.04298239 | L73: 0 | M73: 0 | N73: 0 | O73: 0 | P73: 0 | Q73: 0 | R73: 0 | S73: 0 | T73: 0 | U73: 0 | V73: 0.21688152 | W73: GH_ELECTROLYSIS | X73: 0.000139876 | Y73: 0.04343695 | Z73: 0.090231192 | AA73: 0.19694644 | AB73: 0.43297856 | AC73: 0.95547381 | AD73: 2.0535128 | AE73: 4.3257675 | AF73: 4.3257675 | AG73: 4.1577896 | AH73: 4.1577896 | AI73: 4.1577896 | AJ73: 4.0073658 | AK73: 4.0073658 | AL73: 4.0073658 | AM73: 4.0073658 | AN73: 4.0073658 | AO73: 4.0073658 | AP73: 48.941818
A74: (blank) | C74: (blank) | D74: 0.15610527 | E74: 16.078843 | F74: 17.444764 | G74: 1 | H74: 0 | I74: 7 | J74: 7 | K74: 15 | L74: 0 | M74: 15 | N74: 0 | O74: 0 | P74: 15 | Q74: 0 | R74: 0 | S74: 0 | T74: 0 | U74: 0 | V74: 93.679712 | W74: (blank) | X74: 0.15610527 | Y74: 16.078843 | Z74: 21.805955 | AA74: 4.0977634 | AB74: 21.1703 | AC74: 22.228815 | AD74: 23.340256 | AE74: 24.507269 | AF74: 25.732632 | AG74: 27.019264 | AH74: 28.370227 | AI74: 29.788738 | AJ74: 31.278175 | AK74: 32.842084 | AL74: 34.484188 | AM74: 36.208397 | AN74: 38.018817 | AO74: 39.919758 | AP74: 457.04759
A75: RF_ATF | B75: 15.039 | C75: RF_ATF | D75: 0.009768983 | E75: 1.0062052 | F75: 1.0916838 | G75: 0 | H75: 0 | I75: 0 | J75: 0 | K75: 1 | L75: 0 | M75: 1 | N75: 0 | O75: 0 | P75: 1 | Q75: 0 | R75: 0 | S75: 0 | T75: 0 | U75: 0 | V75: 5.1076581 | W75: RF_ATF | X75: 0.009768983 | Y75: 1.0062052 | Z75: 1.3646048 | AA75: 0.2564358 | AB75: 1.5039 | AC75: 1.579095 | AD75: 1.6580497 | AE75: 1.7409522 | AF75: 1.8279998 | AG75: 1.9193998 | AH75: 2.0153698 | AI75: 2.1161383 | AJ75: 2.2219452 | AK75: 2.3330425 | AL75: 2.4496946 | AM75: 2.5721794 | AN75: 2.7007883 | AO75: 2.8358277 | AP75: 32.111397
A76: RF_HSD | B76: 113.776 | C76: RF_HSD | D76: 0.084909669 | E76: 8.7456959 | F76: 9.4886555 | G76: 1 | H76: 0 | I76: 4 | J76: 4 | K76: 8 | L76: 0 | M76: 8 | N76: 0 | O76: 0 | P76: 8 | Q76: 0 | R76: 0 | S76: 0 | T76: 0 | U76: 0 | V76: 51.319261 | W76: RF_HSD | X76: 0.084909669 | Y76: 8.7456959 | Z76: 11.860819 | AA76: 2.2288788 | AB76: 11.3776 | AC76: 11.94648 | AD76: 12.543804 | AE76: 13.170994 | AF76: 13.829544 | AG76: 14.521021 | AH76: 15.247072 | AI76: 16.009426 | AJ76: 16.809897 | AK76: 17.650392 | AL76: 18.532912 | AM76: 19.459557 | AN76: 20.432535 | AO76: 21.454162 | AP76: 245.9057
A77: RF_LPG | B77: 12.831 | C77: RF_LPG | D77: 0.009818491 | E77: 1.0113046 | F77: 1.0972164 | G77: 0 | H77: 0 | I77: 0 | J77: 0 | K77: 1 | L77: 0 | M77: 1 | N77: 0 | O77: 0 | P77: 1 | Q77: 0 | R77: 0 | S77: 0 | T77: 0 | U77: 0 | V77: 5.1183395 | W77: RF_LPG | X77: 0.009818491 | Y77: 1.0113046 | Z77: 1.3715205 | AA77: 0.2577354 | AB77: 1.2831 | AC77: 1.347255 | AD77: 1.4146177 | AE77: 1.4853486 | AF77: 1.5596161 | AG77: 1.6375969 | AH77: 1.7194767 | AI77: 1.8054506 | AJ77: 1.8957231 | AK77: 1.9905092 | AL77: 2.0900347 | AM77: 2.1945364 | AN77: 2.3042633 | AO77: 2.4194764 | AP77: 27.797384
A78: RF_MS | B78: 42.817 | C78: RF_MS | D78: 0.030557553 | E78: 3.147428 | F78: 3.4148066 | G78: 0 | H78: 0 | I78: 2 | J78: 2 | K78: 3 | L78: 0 | M78: 3 | N78: 0 | O78: 0 | P78: 3 | Q78: 0 | R78: 0 | S78: 0 | T78: 0 | U78: 0 | V78: 19.592792 | W78: RF_MS | X78: 0.030557553 | Y78: 3.147428 | Z78: 4.2685082 | AA78: 0.80213577 | AB78: 4.2817 | AC78: 4.495785 | AD78: 4.7205743 | AE78: 4.956603 | AF78: 5.2044331 | AG78: 5.4646548 | AH78: 5.7378875 | AI78: 6.0247819 | AJ78: 6.326021 | AK78: 6.642322 | AL78: 6.9744381 | AM78: 7.32316 | AN78: 7.689318 | AO78: 8.0737839 | AP78: 92.164092
A79: RF_OTHERPP | B79: 11.85 | C79: RF_OTHERPP | D79: 0.009534187 | E79: 0.98202121 | F79: 1.0654453 | G79: 0 | H79: 0 | I79: 0 | J79: 0 | K79: 1 | L79: 0 | M79: 1 | N79: 0 | O79: 0 | P79: 1 | Q79: 0 | R79: 0 | S79: 0 | T79: 0 | U79: 0 | V79: 5.0570007 | W79: RF_OTHERPP | X79: 0.009534187 | Y79: 0.98202121 | Z79: 1.3318067 | AA79: 0.2502724 | AB79: 1.185 | AC79: 1.24425 | AD79: 1.3064625 | AE79: 1.3717856 | AF79: 1.4403749 | AG79: 1.5123937 | AH79: 1.5880133 | AI79: 1.667414 | AJ79: 1.7507847 | AK79: 1.8383239 | AL79: 1.9302401 | AM79: 2.0267521 | AN79: 2.1280897 | AO79: 2.2344942 | AP79: 25.798013
A80: RF_PETCOKE | B80: 15.39 | C80: RF_PETCOKE | D80: 0.011516389 | E80: 1.1861881 | F80: 1.2869565 | G80: 0 | H80: 0 | I80: 1 | J80: 1 | K80: 1 | L80: 0 | M80: 1 | N80: 0 | O80: 0 | P80: 1 | Q80: 0 | R80: 0 | S80: 0 | T80: 0 | U80: 0 | V80: 7.4846609 | W80: RF_PETCOKE | X80: 0.011516389 | Y80: 1.1861881 | Z80: 1.6086956 | AA80: 0.30230521 | AB80: 1.539 | AC80: 1.61595 | AD80: 1.6967475 | AE80: 1.7815849 | AF80: 1.8706641 | AG80: 1.9641973 | AH80: 2.0624072 | AI80: 2.1655276 | AJ80: 2.2738039 | AK80: 2.3874941 | AL80: 2.5068688 | AM80: 2.6322123 | AN80: 2.7638229 | AO80: 2.902014 | AP80: 33.271
