Workbook
Name Escalation_rate: [1]!COAL_TransitCost_Esc[#All]

Sheet Model_expectations_worksheet
N3: Reported Macro investments = Annual annuity * years in total model length
C4: legacy | D4: 2024 | E4: 2025 | T4: Not applying in the first year, as it should be
C5: P1 | D5: P2 | E5: P3 | G5: All | H5: All | I5: P1 | J5: P2 | K5: P3 | N5: Invest_multiplier | Q5: Total annualized investment (trillion) - coming from Macro / 2 | T5: Fixed | W5: PIER
B6: Tech | D6: MW | E6: MW | G6: FixedO&M | H6: CRP | J6: Investment | K6: Investment | L6: CRF | N6: P2 | O6: P3 | Q6: P2 | R6: P3 | T6: P2 | U6: P3 | W6: P2 | X6: P3
B7: EG_COAL | C7: 264152.47 | D7: 0 | E7: 1980 | G7: 3.7167527 | H7: 40 | J7: 93.522921 | K7: 93.522921 | L7: 0.10697141 | N7: 2 | O7: 1 | Q7: =J7*D7*L7*N7/1000000 -> 0 | R7: =E7*K7*L7*O7/1000000 -> 0.019808472 | T7: =C7*G7/1000000 -> 0.98178942 | U7: =(C7+D7)*G7/1000000 -> 0.98178942
B8: EG_CCGT | C8: 31397.2 | D8: 370 | E8: 370 | G8: 3.592861 | H8: 25 | J8: 42.99044 | K8: 42.99044 | L8: 0.11442932 | N8: 2 | O8: 1 | Q8: =J8*D8*L8*N8/1000000 -> 0.0036403314 | R8: =E8*K8*L8*O8/1000000 -> 0.0018201657 | T8: =C8*G8/1000000 -> 0.11280577 | U8: =(C8+D8)*G8/1000000 -> 0.11413513
B9: EG_OCGT | C9: 0 | D9: 0 | E9: 0 | G9: 0.86724231 | H9: 25 | J9: 50.795621 | K9: 50.795621 | L9: 0.11442932 | N9: 2 | O9: 1 | Q9: =J9*D9*L9*N9/1000000 -> 0 | R9: =E9*K9*L9*O9/1000000 -> 0 | T9: =C9*G9/1000000 -> 0 | U9: =(C9+D9)*G9/1000000 -> 0
B10: EG_PHWR | C10: 8180.01 | D10: 1400 | E10: 2100 | G10: 5.3273456 | H10: 40 | J10: 144.95336 | K10: 144.95336 | L10: 0.10697141 | N10: 2 | O10: 1 | Q10: =J10*D10*L10*N10/1000000 -> 0.043416421 | R10: =E10*K10*L10*O10/1000000 -> 0.032562316 | T10: =C10*G10/1000000 -> 0.04357774 | U10: =(C10+D10)*G10/1000000 -> 0.051036024
B11: EG_SMR | C11: 0 | D11: 0 | E11: 0 | G11: 6.1945879 | H11: 30 | J11: 263.23388 | K11: 263.23388 | L11: 0.11052848 | N11: 2 | O11: 1 | Q11: =J11*D11*L11*N11/1000000 -> 0 | R11: =E11*K11*L11*O11/1000000 -> 0 | T11: =C11*G11/1000000 -> 0 | U11: =(C11+D11)*G11/1000000 -> 0
B12: EG_LH | C12: 46491.18 | D12: 0 | E12: 1160 | G12: 5.4512374 | H12: 40 | J12: 132.56418 | K12: 132.56418 | L12: 0.10697141 | N12: 2 | O12: 1 | Q12: =J12*D12*L12*N12/1000000 -> 0 | R12: =E12*K12*L12*O12/1000000 -> 0.01644947 | T12: =C12*G12/1000000 -> 0.25343446 | U12: =(C12+D12)*G12/1000000 -> 0.25343446
B13: EG_SH | C13: 4939.05 | D13: 72 | E13: 144 | G13: 2.9734022 | H13: 35 | J13: 99.608974 | K13: 99.608974 | L13: 0.088866959 | N13: 2 | O13: 1 | Q13: =J13*D13*L13*N13/1000000 -> 0.0012746803 | R13: =E13*K13*L13*O13/1000000 -> 0.0012746803 | T13: =C13*G13/1000000 -> 0.014685782 | U13: =(C13+D13)*G13/1000000 -> 0.014899867
B14: EG_BIOMASS | C14: 10830.04 | D14: 463 | E14: 926 | G14: 1.2389176 | H14: 20 | J14: 61.945879 | K14: 61.945879 | L14: 0.1045193 | N14: 2 | O14: 1 | Q14: =J14*D14*L14*N14/1000000 -> 0.0059954237 | R14: =E14*K14*L14*O14/1000000 -> 0.0059954237 | T14: =C14*G14/1000000 -> 0.013417527 | U14: =(C14+D14)*G14/1000000 -> 0.013991146
B15: EG_SOLARGM | C15: 58366.793 | D15: 12020 | E15: 25411 | G15: 0.43362115 | H15: 25 | J15: 43.748269 | K15: 42.133466 | L15: 0.11442932 | N15: 2 | O15: 1 | Q15: =J15*D15*L15*N15/1000000 -> 0.12034628 | R15: =E15*K15*L15*O15/1000000 -> 0.12251415 | T15: =C15*G15/1000000 -> 0.025309076 | U15: =(C15+D15)*G15/1000000 -> 0.030521202
B16: EG_SOLARRF | C16: 9468.2674 | D16: 3234 | E16: 25392 | G16: 0.63184797 | H16: 25 | J16: 41.649738 | K16: 40.115885 | L16: 0.113573 | N16: 2 | O16: 1 | Q16: =J16*D16*L16*N16/1000000 -> 0.030595489 | R16: =E16*K16*L16*O16/1000000 -> 0.11568802 | T16: =C16*G16/1000000 -> 0.0059825055 | U16: =(C16+D16)*G16/1000000 -> 0.0080259018
B17: EG_WINDON | C17: 46169.83 | D17: 3253 | E17: 8758 | G17: 0.84246396 | H17: 25 | J17: 85.157375 | K17: 84.5284 | L17: 0.11442932 | N17: 2 | O17: 1 | Q17: =J17*D17*L17*N17/1000000 -> 0.06339772 | R17: =E17*K17*L17*O17/1000000 -> 0.084711994 | T17: =C17*G17/1000000 -> 0.038896418 | U17: =(C17+D17)*G17/1000000 -> 0.041636953
B18: EG_WINDOFF | C18: 0 | D18: 0 | E18: 0 | G18: 8.3007478 | H18: 25 | J18: 217.7961 | K18: 202.86445 | L18: 0.12047789 | N18: 2 | O18: 1 | Q18: =J18*D18*L18*N18/1000000 -> 0 | R18: =E18*K18*L18*O18/1000000 -> 0 | T18: =C18*G18/1000000 -> 0 | U18: =(C18+D18)*G18/1000000 -> 0
Q19: =SUM(Q7:Q18) -> 0.26866634 | R19: =SUM(R7:R18) -> 0.4008247 | T19: =SUM(T7:T18) -> 1.4898987 | U19: =SUM(U7:U18) -> 1.5094701
Q20: =Q19/2 -> 0.13433317

Sheet PeriodMap
A1: Period | B1: Year (FY) | C1: Constraint (s) | D1: Notes
A2: 1 | B2: 2023 | C2: Capacity forced , no retirements, no new-builds | D2: This period is inserted only so that all existing capacity can be built. Using demand from 2024, as PIER2.0 does not provide a demand for 2023
A3: 2 | B3: 2024 | C3: Pipeline capacity forced, no retirements, no new-builds | D3: Demand = PIER2.0 2024, Calibration year for constrained model operation and comparison between Rumi+PIER2.0 & Macro case build on PIER2.0
A4: 3 | B4: 2025 | D4: Demand = PIER2.0 2025, Calibration year for less constraned model operaration
A5: 4 | B5: 2029 | D5: Using demand from 2029, as selected year for period , which spans 2026 to 2031, using constraints from PIER2.0 "8_REF_Unconstr" scenario
A6: 5 | B6: 2034 | D6: Using demand from 2034, as selected year for period, which spans 2032 to 2036, using constraints from PIER2.0 "8_REF_Unconstr" scenario
A7: 6 | B7: 2039 | D7: Using demand from 2039, as selected year for period, which spans 2037 to 2041, using constraints from PIER2.0 "8_REF_Unconstr" scenario
A8: 7 | B8: 2045
A9: 8 | B9: 2055
A10: 9 | B10: 2065
A11: 10 | B11: 2071

Sheet nodes
A1: Source::File | B1: PIER2.0::PEC_ProdImpConstraints.csv | C1: PIER2.0::PEC_ProdImpConstraints.csv | D1: PIER2.0::PEC_ProdImpConstraints.csv | E1: PIER2.0::PEC_ProdImpConstraints.csv | F1: PIER2.0::PEC_ProdImpConstraints.csv | G1: PIER2.0::PEC_ProdImpConstraints.csv | H1: PIER2.0::PEC_Info.csv | I1: PIER2.0::PEC_Info.csv | J1: PIER2.0::PEC_Info.csv | K1: PIER2.0::PEC_Info.csv | L1: PIER2.0::PEC_Info.csv | M1: PIER2.0::PEC_Info.csv | N1: PIER2.0::PEC_Info.csv
A2: PIER2.0 var name | B2: EnergyCarrier | C2: ModelGeography | D2: SubGeography1 | E2: Year | F2: MaxDomesticProd | G2: MaxImport | H2: NonEnergyShare | I2: DomesticPrice (mRs/ktonne) | J2: AVTaxOHDom | K2: FixedTaxOHDom | L2: ImportPrice | M2: AVTaxOHImp | N2: FixedTaxOHImp
A3: Variable | F3: a | G3: b | H3: c | I3: d | J3: e | K3: f | L3: g | M3: h | N3: i | P3: aa | Q3: bb | R3: cc | S3: dd
A4: description | P4: Seg1 - domestic price with taxes applied | Q4: Seg 1 - domestic resource | R4: Seg 2 - import price with taxes applied | S4: Seg 2 - import resource
A5: Equation to Macro var | P5: = ( d * 1e3 * (1 + e) + f * 1e3 ) / conversion_if_not _MT / conversion from MT to PJ / conversion from PJ to MWh | Q5: = a * conversion_if_not _MT * conversion from MT to PJ * conversion from PJ to MWh | R5: = ( g * 1e3 * (1 + h) + i * 1e3 ) / conversion_if_not _MT / conversion from MT to PJ / conversion from PJ to MWh | S5: = b * conversion_if_not _MT * conversion from MT to PJ * conversion from PJ to MWh
A6: Macro variable | D6: location | P6: price | Q6: max | R6: price | S6: max
A7: period | F7: MT or BCM | G7: MT or BCF | H7: % | I7: mRs/mT or kRs/BCM | J7: % | K7: mRs/mT ork Rs/BCM | L7: mRs/mT or kRs/BCM | M7: % | N7: mRs/mT or kRs/BCM | P7: mRs/MWh | Q7: MWh | R7: mRs/mWh
A8: 1 | B8: BIOMASS | C8: INDIA | E8: =_xlfn.XLOOKUP(A8,PeriodMap!$A$2:$A$45,PeriodMap!$B$2:$B$45) -> 2023 | F8: =_xlfn.XLOOKUP(_xlfn.CONCAT($B8,$D8,$E8),PEC_ProdImpConstraints!$G$2:$G$286,PEC_ProdImpConstraints!$E$2:$E$286) -> 270 | G8: =_xlfn.XLOOKUP(_xlfn.CONCAT($B8,$D8,$E8),PEC_ProdImpConstraints!$G$2:$G$286,PEC_ProdImpConstraints!$F$2:$F$286) -> 0 | H8: =_xlfn.XLOOKUP(_xlfn.CONCAT($B8,$D8,$E8),PEC_Info!$L$2:$L$301,PEC_Info!$E$2:$E$301) -> 0 | I8: =_xlfn.XLOOKUP(_xlfn.CONCAT($B8,$D8,$E8),PEC_Info!$L$2:$L$301,PEC_Info!$F$2:$F$301) -> 5449.5727 | J8: =_xlfn.XLOOKUP(_xlfn.CONCAT($B8,$D8,$E8),PEC_Info!$L$2:$L$301,PEC_Info!$G$2:$G$301) -> 0 | K8: =_xlfn.XLOOKUP(_xlfn.CONCAT($B8,$D8,$E8),PEC_Info!$L$2:$L$301,PEC_Info!$H$2:$H$301) -> 0 | L8: =_xlfn.XLOOKUP(_xlfn.CONCAT($B8,$D8,$E8),PEC_Info!$L$2:$L$301,PEC_Info!$I$2:$I$301) -> 5449.5727 | M8: =_xlfn.XLOOKUP(_xlfn.CONCAT($B8,$D8,$E8),PEC_Info!$L$2:$L$301,PEC_Info!$J$2:$J$301) -> 0 | N8: =_xlfn.XLOOKUP(_xlfn.CONCAT($B8,$D8,$E8),PEC_Info!$L$2:$L$301,PEC_Info!$K$2:$K$301) -> 0 | P8: =(I8*(1+J8)+K8*1000)/_xlfn.XLOOKUP(B8,CarriersTech_characteristics!$B$2:$B$8,CarriersTech_characteristics!$G$2:$G$8)/Conversions!$D$2 -> 0.0012608266 | Q8: =F8*_xlfn.XLOOKUP(B8,CarriersTech_characteristics!$B$2:$B$8,CarriersTech_characteristics!$G$2:$G$8)*Conversions!$D$2*(1-H8) -> 1.167e+09 | R8: =(L8*(1+M8)+N8*1000)/_xlfn.XLOOKUP(B8,CarriersTech_characteristics!$B$2:$B$8,CarriersTech_characteristics!$J$2:$J$8)/Conversions!$D$2 -> 0.0012608266 | S8: =G8*_xlfn.XLOOKUP(B8,CarriersTech_characteristics!$B$2:$B$8,CarriersTech_characteristics!$J$2:$J$8)*Conversions!$D$2 -> 0
A9: 1 | B9: BIOMASS_WASTE | C9: INDIA | E9: =_xlfn.XLOOKUP(A9,PeriodMap!$A$2:$A$45,PeriodMap!$B$2:$B$45) -> 2023 | F9: =_xlfn.XLOOKUP(_xlfn.CONCAT($B9,$D9,$E9),PEC_ProdImpConstraints!$G$2:$G$286,PEC_ProdImpConstraints!$E$2:$E$286) -> 175 | G9: =_xlfn.XLOOKUP(_xlfn.CONCAT($B9,$D9,$E9),PEC_ProdImpConstraints!$G$2:$G$286,PEC_ProdImpConstraints!$F$2:$F$286) -> 0 | H9: =_xlfn.XLOOKUP(_xlfn.CONCAT($B9,$D9,$E9),PEC_Info!$L$2:$L$301,PEC_Info!$E$2:$E$301) -> 0 | I9: =_xlfn.XLOOKUP(_xlfn.CONCAT($B9,$D9,$E9),PEC_Info!$L$2:$L$301,PEC_Info!$F$2:$F$301) -> 9000 | J9: =_xlfn.XLOOKUP(_xlfn.CONCAT($B9,$D9,$E9),PEC_Info!$L$2:$L$301,PEC_Info!$G$2:$G$301) -> 0.05 | K9: =_xlfn.XLOOKUP(_xlfn.CONCAT($B9,$D9,$E9),PEC_Info!$L$2:$L$301,PEC_Info!$H$2:$H$301) -> 0 | L9: =_xlfn.XLOOKUP(_xlfn.CONCAT($B9,$D9,$E9),PEC_Info!$L$2:$L$301,PEC_Info!$I$2:$I$301) -> 9000 | M9: =_xlfn.XLOOKUP(_xlfn.CONCAT($B9,$D9,$E9),PEC_Info!$L$2:$L$301,PEC_Info!$J$2:$J$301) -> 0.05 | N9: =_xlfn.XLOOKUP(_xlfn.CONCAT($B9,$D9,$E9),PEC_Info!$L$2:$L$301,PEC_Info!$K$2:$K$301) -> 0 | P9: =(I9*(1+J9)+K9*1000)/_xlfn.XLOOKUP(B9,CarriersTech_characteristics!$B$2:$B$8,CarriersTech_characteristics!$G$2:$G$8)/Conversions!$D$2 -> 0.0024924961 | Q9: =F9*_xlfn.XLOOKUP(B9,CarriersTech_characteristics!$B$2:$B$8,CarriersTech_characteristics!$G$2:$G$8)*Conversions!$D$2*(1-H9) -> 6.6349151e+08 | R9: =(L9*(1+M9)+N9*1000)/_xlfn.XLOOKUP(B9,CarriersTech_characteristics!$B$2:$B$8,CarriersTech_characteristics!$J$2:$J$8)/Conversions!$D$2 -> 0.0024924961 | S9: =G9*_xlfn.XLOOKUP(B9,CarriersTech_characteristics!$B$2:$B$8,CarriersTech_characteristics!$J$2:$J$8)*Conversions!$D$2 -> 0
A10: 1 | B10: NATGAS | C10: INDIA | E10: =_xlfn.XLOOKUP(A10,PeriodMap!$A$2:$A$45,PeriodMap!$B$2:$B$45) -> 2023 | F10: =_xlfn.XLOOKUP(_xlfn.CONCAT($B10,$D10,$E10),PEC_ProdImpConstraints!$G$2:$G$286,PEC_ProdImpConstraints!$E$2:$E$286) -> 33.648 | G10: =_xlfn.XLOOKUP(_xlfn.CONCAT($B10,$D10,$E10),PEC_ProdImpConstraints!$G$2:$G$286,PEC_ProdImpConstraints!$F$2:$F$286) -> 200 | H10: =_xlfn.XLOOKUP(_xlfn.CONCAT($B10,$D10,$E10),PEC_Info!$L$2:$L$301,PEC_Info!$E$2:$E$301) -> 0.36749121 | I10: =_xlfn.XLOOKUP(_xlfn.CONCAT($B10,$D10,$E10),PEC_Info!$L$2:$L$301,PEC_Info!$F$2:$F$301) -> 23859.031 | J10: =_xlfn.XLOOKUP(_xlfn.CONCAT($B10,$D10,$E10),PEC_Info!$L$2:$L$301,PEC_Info!$G$2:$G$301) -> 0.24 | K10: =_xlfn.XLOOKUP(_xlfn.CONCAT($B10,$D10,$E10),PEC_Info!$L$2:$L$301,PEC_Info!$H$2:$H$301) -> 0 | L10: =_xlfn.XLOOKUP(_xlfn.CONCAT($B10,$D10,$E10),PEC_Info!$L$2:$L$301,PEC_Info!$I$2:$I$301) -> 54880.306 | M10: =_xlfn.XLOOKUP(_xlfn.CONCAT($B10,$D10,$E10),PEC_Info!$L$2:$L$301,PEC_Info!$J$2:$J$301) -> 0.349 | N10: =_xlfn.XLOOKUP(_xlfn.CONCAT($B10,$D10,$E10),PEC_Info!$L$2:$L$301,PEC_Info!$K$2:$K$301) -> 0 | P10: =(I10*(1+J10)+K10*1000)/Conversions!$D$3/_xlfn.XLOOKUP(B10,CarriersTech_characteristics!$B$2:$B$8,CarriersTech_characteristics!$G$2:$G$8)/Conversions!$D$2 -> 0.0034095552 | Q10: =F10*_xlfn.XLOOKUP(B10,CarriersTech_characteristics!$B$2:$B$8,CarriersTech_characteristics!$G$2:$G$8)*Conversions!$D$2*(1-H10) -> 2.2276556e+08 | R10: =(L10*(1+M10)+N10*1000)/Conversions!$D$3/_xlfn.XLOOKUP(B10,CarriersTech_characteristics!$B$2:$B$8,CarriersTech_characteristics!$J$2:$J$8)/Conversions!$D$2 -> 0.008532017 | S10: =G10*_xlfn.XLOOKUP(B10,CarriersTech_characteristics!$B$2:$B$8,CarriersTech_characteristics!$J$2:$J$8)*Conversions!$D$2 -> 2.0934e+09
A11: 1 | B11: THERMAL_COAL | C11: INDIA | D11: NR | E11: =_xlfn.XLOOKUP(A11,PeriodMap!$A$2:$A$45,PeriodMap!$B$2:$B$45) -> 2023 | F11: =_xlfn.XLOOKUP(_xlfn.CONCAT($B11,$D11,$E11),PEC_ProdImpConstraints!$G$2:$G$286,PEC_ProdImpConstraints!$E$2:$E$286) -> 30.747 | G11: =_xlfn.XLOOKUP(_xlfn.CONCAT($B11,$D11,$E11),PEC_ProdImpConstraints!$G$2:$G$286,PEC_ProdImpConstraints!$F$2:$F$286) -> 0 | H11: =_xlfn.XLOOKUP(_xlfn.CONCAT($B11,$D11,$E11),PEC_Info!$L$2:$L$301,PEC_Info!$E$2:$E$301) -> 0 | I11: =_xlfn.XLOOKUP(_xlfn.CONCAT($B11,$D11,$E11),PEC_Info!$L$2:$L$301,PEC_Info!$F$2:$F$301) -> 1156.3734 | J11: =_xlfn.XLOOKUP(_xlfn.CONCAT($B11,$D11,$E11),PEC_Info!$L$2:$L$301,PEC_Info!$G$2:$G$301) -> 0.3508 | K11: =_xlfn.XLOOKUP(_xlfn.CONCAT($B11,$D11,$E11),PEC_Info!$L$2:$L$301,PEC_Info!$H$2:$H$301) -> 0 | L11: =_xlfn.XLOOKUP(_xlfn.CONCAT($B11,$D11,$E11),PEC_Info!$L$2:$L$301,PEC_Info!$I$2:$I$301) -> 13197.141 | M11: =_xlfn.XLOOKUP(_xlfn.CONCAT($B11,$D11,$E11),PEC_Info!$L$2:$L$301,PEC_Info!$J$2:$J$301) -> 0.205 | N11: =_xlfn.XLOOKUP(_xlfn.CONCAT($B11,$D11,$E11),PEC_Info!$L$2:$L$301,PEC_Info!$K$2:$K$301) -> 0 | P11: =(I11*(1+J11)+K11*1000)/_xlfn.XLOOKUP(B11,CarriersTech_characteristics!$B$2:$B$8,CarriersTech_characteristics!$G$2:$G$8)/Conversions!$D$2 -> 0.00032679978 | Q11: =F11*_xlfn.XLOOKUP(B11,CarriersTech_characteristics!$B$2:$B$8,CarriersTech_characteristics!$G$2:$G$8)*Conversions!$D$2*(1-H11) -> 1.4696372e+08 | R11: =(L11*(1+M11)+N11*1000)/_xlfn.XLOOKUP(B11,CarriersTech_characteristics!$B$2:$B$8,CarriersTech_characteristics!$J$2:$J$8)/Conversions!$D$2 -> 0.0025321733 | S11: =G11*_xlfn.XLOOKUP(B11,CarriersTech_characteristics!$B$2:$B$8,CarriersTech_characteristics!$J$2:$J$8)*Conversions!$D$2 -> 0
A12: 1 | B12: THERMAL_COAL | C12: INDIA | D12: NER | E12: =_xlfn.XLOOKUP(A12,PeriodMap!$A$2:$A$45,PeriodMap!$B$2:$B$45) -> 2023 | F12: =_xlfn.XLOOKUP(_xlfn.CONCAT($B12,$D12,$E12),PEC_ProdImpConstraints!$G$2:$G$286,PEC_ProdImpConstraints!$E$2:$E$286) -> 0 | G12: =_xlfn.XLOOKUP(_xlfn.CONCAT($B12,$D12,$E12),PEC_ProdImpConstraints!$G$2:$G$286,PEC_ProdImpConstraints!$F$2:$F$286) -> 0 | H12: =_xlfn.XLOOKUP(_xlfn.CONCAT($B12,$D12,$E12),PEC_Info!$L$2:$L$301,PEC_Info!$E$2:$E$301) -> 0 | I12: =_xlfn.XLOOKUP(_xlfn.CONCAT($B12,$D12,$E12),PEC_Info!$L$2:$L$301,PEC_Info!$F$2:$F$301) -> 1156.3734 | J12: =_xlfn.XLOOKUP(_xlfn.CONCAT($B12,$D12,$E12),PEC_Info!$L$2:$L$301,PEC_Info!$G$2:$G$301) -> 0.3508 | K12: =_xlfn.XLOOKUP(_xlfn.CONCAT($B12,$D12,$E12),PEC_Info!$L$2:$L$301,PEC_Info!$H$2:$H$301) -> 0 | L12: =_xlfn.XLOOKUP(_xlfn.CONCAT($B12,$D12,$E12),PEC_Info!$L$2:$L$301,PEC_Info!$I$2:$I$301) -> 13197.141 | M12: =_xlfn.XLOOKUP(_xlfn.CONCAT($B12,$D12,$E12),PEC_Info!$L$2:$L$301,PEC_Info!$J$2:$J$301) -> 0.205 | N12: =_xlfn.XLOOKUP(_xlfn.CONCAT($B12,$D12,$E12),PEC_Info!$L$2:$L$301,PEC_Info!$K$2:$K$301) -> 0 | P12: =(I12*(1+J12)+K12*1000)/_xlfn.XLOOKUP(B12,CarriersTech_characteristics!$B$2:$B$8,CarriersTech_characteristics!$G$2:$G$8)/Conversions!$D$2 -> 0.00032679978 | Q12: =F12*_xlfn.XLOOKUP(B12,CarriersTech_characteristics!$B$2:$B$8,CarriersTech_characteristics!$G$2:$G$8)*Conversions!$D$2*(1-H12) -> 0 | R12: =(L12*(1+M12)+N12*1000)/_xlfn.XLOOKUP(B12,CarriersTech_characteristics!$B$2:$B$8,CarriersTech_characteristics!$J$2:$J$8)/Conversions!$D$2 -> 0.0025321733 | S12: =G12*_xlfn.XLOOKUP(B12,CarriersTech_characteristics!$B$2:$B$8,CarriersTech_characteristics!$J$2:$J$8)*Conversions!$D$2 -> 0
A13: 1 | B13: THERMAL_COAL | C13: INDIA | D13: ER | E13: =_xlfn.XLOOKUP(A13,PeriodMap!$A$2:$A$45,PeriodMap!$B$2:$B$45) -> 2023 | F13: =_xlfn.XLOOKUP(_xlfn.CONCAT($B13,$D13,$E13),PEC_ProdImpConstraints!$G$2:$G$286,PEC_ProdImpConstraints!$E$2:$E$286) -> 395.289 | G13: =_xlfn.XLOOKUP(_xlfn.CONCAT($B13,$D13,$E13),PEC_ProdImpConstraints!$G$2:$G$286,PEC_ProdImpConstraints!$F$2:$F$286) -> 150 | H13: =_xlfn.XLOOKUP(_xlfn.CONCAT($B13,$D13,$E13),PEC_Info!$L$2:$L$301,PEC_Info!$E$2:$E$301) -> 0 | I13: =_xlfn.XLOOKUP(_xlfn.CONCAT($B13,$D13,$E13),PEC_Info!$L$2:$L$301,PEC_Info!$F$2:$F$301) -> 1156.3734 | J13: =_xlfn.XLOOKUP(_xlfn.CONCAT($B13,$D13,$E13),PEC_Info!$L$2:$L$301,PEC_Info!$G$2:$G$301) -> 0.3508 | K13: =_xlfn.XLOOKUP(_xlfn.CONCAT($B13,$D13,$E13),PEC_Info!$L$2:$L$301,PEC_Info!$H$2:$H$301) -> 0 | L13: =_xlfn.XLOOKUP(_xlfn.CONCAT($B13,$D13,$E13),PEC_Info!$L$2:$L$301,PEC_Info!$I$2:$I$301) -> 13197.141 | M13: =_xlfn.XLOOKUP(_xlfn.CONCAT($B13,$D13,$E13),PEC_Info!$L$2:$L$301,PEC_Info!$J$2:$J$301) -> 0.205 | N13: =_xlfn.XLOOKUP(_xlfn.CONCAT($B13,$D13,$E13),PEC_Info!$L$2:$L$301,PEC_Info!$K$2:$K$301) -> 0 | P13: =(I13*(1+J13)+K13*1000)/_xlfn.XLOOKUP(B13,CarriersTech_characteristics!$B$2:$B$8,CarriersTech_characteristics!$G$2:$G$8)/Conversions!$D$2 -> 0.00032679978 | Q13: =F13*_xlfn.XLOOKUP(B13,CarriersTech_characteristics!$B$2:$B$8,CarriersTech_characteristics!$G$2:$G$8)*Conversions!$D$2*(1-H13) -> 1.8893922e+09 | R13: =(L13*(1+M13)+N13*1000)/_xlfn.XLOOKUP(B13,CarriersTech_characteristics!$B$2:$B$8,CarriersTech_characteristics!$J$2:$J$8)/Conversions!$D$2 -> 0.0025321733 | S13: =G13*_xlfn.XLOOKUP(B13,CarriersTech_characteristics!$B$2:$B$8,CarriersTech_characteristics!$J$2:$J$8)*Conversions!$D$2 -> 9.4203001e+08
A14: 1 | B14: THERMAL_COAL | C14: INDIA | D14: WR | E14: =_xlfn.XLOOKUP(A14,PeriodMap!$A$2:$A$45,PeriodMap!$B$2:$B$45) -> 2023 | F14: =_xlfn.XLOOKUP(_xlfn.CONCAT($B14,$D14,$E14),PEC_ProdImpConstraints!$G$2:$G$286,PEC_ProdImpConstraints!$E$2:$E$286) -> 406.857 | G14: =_xlfn.XLOOKUP(_xlfn.CONCAT($B14,$D14,$E14),PEC_ProdImpConstraints!$G$2:$G$286,PEC_ProdImpConstraints!$F$2:$F$286) -> 150 | H14: =_xlfn.XLOOKUP(_xlfn.CONCAT($B14,$D14,$E14),PEC_Info!$L$2:$L$301,PEC_Info!$E$2:$E$301) -> 0 | I14: =_xlfn.XLOOKUP(_xlfn.CONCAT($B14,$D14,$E14),PEC_Info!$L$2:$L$301,PEC_Info!$F$2:$F$301) -> 1156.3734 | J14: =_xlfn.XLOOKUP(_xlfn.CONCAT($B14,$D14,$E14),PEC_Info!$L$2:$L$301,PEC_Info!$G$2:$G$301) -> 0.3508 | K14: =_xlfn.XLOOKUP(_xlfn.CONCAT($B14,$D14,$E14),PEC_Info!$L$2:$L$301,PEC_Info!$H$2:$H$301) -> 0 | L14: =_xlfn.XLOOKUP(_xlfn.CONCAT($B14,$D14,$E14),PEC_Info!$L$2:$L$301,PEC_Info!$I$2:$I$301) -> 13197.141 | M14: =_xlfn.XLOOKUP(_xlfn.CONCAT($B14,$D14,$E14),PEC_Info!$L$2:$L$301,PEC_Info!$J$2:$J$301) -> 0.205 | N14: =_xlfn.XLOOKUP(_xlfn.CONCAT($B14,$D14,$E14),PEC_Info!$L$2:$L$301,PEC_Info!$K$2:$K$301) -> 0 | P14: =(I14*(1+J14)+K14*1000)/_xlfn.XLOOKUP(B14,CarriersTech_characteristics!$B$2:$B$8,CarriersTech_characteristics!$G$2:$G$8)/Conversions!$D$2 -> 0.00032679978 | Q14: =F14*_xlfn.XLOOKUP(B14,CarriersTech_characteristics!$B$2:$B$8,CarriersTech_characteristics!$G$2:$G$8)*Conversions!$D$2*(1-H14) -> 1.9446847e+09 | R14: =(L14*(1+M14)+N14*1000)/_xlfn.XLOOKUP(B14,CarriersTech_characteristics!$B$2:$B$8,CarriersTech_characteristics!$J$2:$J$8)/Conversions!$D$2 -> 0.0025321733 | S14: =G14*_xlfn.XLOOKUP(B14,CarriersTech_characteristics!$B$2:$B$8,CarriersTech_characteristics!$J$2:$J$8)*Conversions!$D$2 -> 9.4203001e+08
A15: 1 | B15: THERMAL_COAL | C15: INDIA | D15: SR | E15: =_xlfn.XLOOKUP(A15,PeriodMap!$A$2:$A$45,PeriodMap!$B$2:$B$45) -> 2023 | F15: =_xlfn.XLOOKUP(_xlfn.CONCAT($B15,$D15,$E15),PEC_ProdImpConstraints!$G$2:$G$286,PEC_ProdImpConstraints!$E$2:$E$286) -> 91.156 | G15: =_xlfn.XLOOKUP(_xlfn.CONCAT($B15,$D15,$E15),PEC_ProdImpConstraints!$G$2:$G$286,PEC_ProdImpConstraints!$F$2:$F$286) -> 150 | H15: =_xlfn.XLOOKUP(_xlfn.CONCAT($B15,$D15,$E15),PEC_Info!$L$2:$L$301,PEC_Info!$E$2:$E$301) -> 0 | I15: =_xlfn.XLOOKUP(_xlfn.CONCAT($B15,$D15,$E15),PEC_Info!$L$2:$L$301,PEC_Info!$F$2:$F$301) -> 1156.3734 | J15: =_xlfn.XLOOKUP(_xlfn.CONCAT($B15,$D15,$E15),PEC_Info!$L$2:$L$301,PEC_Info!$G$2:$G$301) -> 0.3508 | K15: =_xlfn.XLOOKUP(_xlfn.CONCAT($B15,$D15,$E15),PEC_Info!$L$2:$L$301,PEC_Info!$H$2:$H$301) -> 0 | L15: =_xlfn.XLOOKUP(_xlfn.CONCAT($B15,$D15,$E15),PEC_Info!$L$2:$L$301,PEC_Info!$I$2:$I$301) -> 13197.141 | M15: =_xlfn.XLOOKUP(_xlfn.CONCAT($B15,$D15,$E15),PEC_Info!$L$2:$L$301,PEC_Info!$J$2:$J$301) -> 0.205 | N15: =_xlfn.XLOOKUP(_xlfn.CONCAT($B15,$D15,$E15),PEC_Info!$L$2:$L$301,PEC_Info!$K$2:$K$301) -> 0 | P15: =(I15*(1+J15)+K15*1000)/_xlfn.XLOOKUP(B15,CarriersTech_characteristics!$B$2:$B$8,CarriersTech_characteristics!$G$2:$G$8)/Conversions!$D$2 -> 0.00032679978 | Q15: =F15*_xlfn.XLOOKUP(B15,CarriersTech_characteristics!$B$2:$B$8,CarriersTech_characteristics!$G$2:$G$8)*Conversions!$D$2*(1-H15) -> 4.3570511e+08 | R15: =(L15*(1+M15)+N15*1000)/_xlfn.XLOOKUP(B15,CarriersTech_characteristics!$B$2:$B$8,CarriersTech_characteristics!$J$2:$J$8)/Conversions!$D$2 -> 0.0025321733 | S15: =G15*_xlfn.XLOOKUP(B15,CarriersTech_characteristics!$B$2:$B$8,CarriersTech_characteristics!$J$2:$J$8)*Conversions!$D$2 -> 9.4203001e+08
A16: 1 | B16: THERMAL_COAL | C16: INDIA | D16: ALL | E16: =_xlfn.XLOOKUP(A16,PeriodMap!$A$2:$A$45,PeriodMap!$B$2:$B$45) -> 2023 | F16: =SUM(F11:F15) -> 924.049 | G16: =SUM(G11:G15) -> 450 | H16: =AVERAGE(H11:H15) -> 0 | I16: =AVERAGE(I11:I15) -> 1156.3734 | J16: =AVERAGE(J11:J15) -> 0.3508 | K16: =AVERAGE(K11:K15) -> 0 | L16: =AVERAGE(L11:L15) -> 13197.141 | M16: =AVERAGE(M11:M15) -> 0.205 | N16: =AVERAGE(N11:N15) -> 0 | P16: =AVERAGE(P11:P15) -> 0.00032679978 | Q16: =SUM(Q11:Q15) -> 4.4167457e+09 | R16: =AVERAGE(R11:R15) -> 0.0025321733 | S16: =SUM(S11:S15) -> 2.82609e+09
A17: 1 | B17: CRUDE | C17: INDIA | E17: =_xlfn.XLOOKUP(A17,PeriodMap!$A$2:$A$45,PeriodMap!$B$2:$B$45) -> 2023 | F17: =_xlfn.XLOOKUP(_xlfn.CONCAT($B17,$D17,$E17),PEC_ProdImpConstraints!$G$2:$G$286,PEC_ProdImpConstraints!$E$2:$E$286) -> 31.9035 | G17: =_xlfn.XLOOKUP(_xlfn.CONCAT($B17,$D17,$E17),PEC_ProdImpConstraints!$G$2:$G$286,PEC_ProdImpConstraints!$F$2:$F$286) -> 330 | H17: 0 | I17: =_xlfn.XLOOKUP(_xlfn.CONCAT($B17,$D17,$E17),PEC_Info!$L$2:$L$301,PEC_Info!$F$2:$F$301) -> 57833.373 | J17: =_xlfn.XLOOKUP(_xlfn.CONCAT($B17,$D17,$E17),PEC_Info!$L$2:$L$301,PEC_Info!$G$2:$G$301) -> 0 | K17: =_xlfn.XLOOKUP(_xlfn.CONCAT($B17,$D17,$E17),PEC_Info!$L$2:$L$301,PEC_Info!$H$2:$H$301) -> 51.2 | L17: =_xlfn.XLOOKUP(_xlfn.CONCAT($B17,$D17,$E17),PEC_Info!$L$2:$L$301,PEC_Info!$I$2:$I$301) -> 56505.275 | M17: =_xlfn.XLOOKUP(_xlfn.CONCAT($B17,$D17,$E17),PEC_Info!$L$2:$L$301,PEC_Info!$J$2:$J$301) -> 0 | N17: =_xlfn.XLOOKUP(_xlfn.CONCAT($B17,$D17,$E17),PEC_Info!$L$2:$L$301,PEC_Info!$K$2:$K$301) -> 57.2 | P17: =(I17*(1+J17)+K17*1000)/_xlfn.XLOOKUP(B17,CarriersTech_characteristics!$B$2:$B$8,CarriersTech_characteristics!$G$2:$G$8)/Conversions!$D$2 -> 0.0091021189 | Q17: =F17*_xlfn.XLOOKUP(B17,CarriersTech_characteristics!$B$2:$B$8,CarriersTech_characteristics!$G$2:$G$8)*Conversions!$D$2*(1-H17) -> 3.8216884e+08 | R17: =(L17*(1+M17)+N17*1000)/_xlfn.XLOOKUP(B17,CarriersTech_characteristics!$B$2:$B$8,CarriersTech_characteristics!$J$2:$J$8)/Conversions!$D$2 -> 0.0094921299 | S17: =G17*_xlfn.XLOOKUP(B17,CarriersTech_characteristics!$B$2:$B$8,CarriersTech_characteristics!$J$2:$J$8)*Conversions!$D$2 -> 3.953037e+09
A18: 1 | B18: BIOGAS | C18: INDIA | E18: =_xlfn.XLOOKUP(A18,PeriodMap!$A$2:$A$45,PeriodMap!$B$2:$B$45) -> 2023 | F18: =_xlfn.XLOOKUP(_xlfn.CONCAT($B18,$D18,$E18),PEC_ProdImpConstraints!$G$2:$G$286,PEC_ProdImpConstraints!$E$2:$E$286) -> 87 | G18: =_xlfn.XLOOKUP(_xlfn.CONCAT($B18,$D18,$E18),PEC_ProdImpConstraints!$G$2:$G$286,PEC_ProdImpConstraints!$F$2:$F$286) -> 0 | H18: 0 | I18: =_xlfn.XLOOKUP(_xlfn.CONCAT($B18,$D18,$E18),PEC_Info!$L$2:$L$301,PEC_Info!$F$2:$F$301) -> 49802.018 | J18: =_xlfn.XLOOKUP(_xlfn.CONCAT($B18,$D18,$E18),PEC_Info!$L$2:$L$301,PEC_Info!$G$2:$G$301) -> 0.05 | K18: =_xlfn.XLOOKUP(_xlfn.CONCAT($B18,$D18,$E18),PEC_Info!$L$2:$L$301,PEC_Info!$H$2:$H$301) -> 0 | L18: =_xlfn.XLOOKUP(_xlfn.CONCAT($B18,$D18,$E18),PEC_Info!$L$2:$L$301,PEC_Info!$I$2:$I$301) -> 49802.018 | M18: =_xlfn.XLOOKUP(_xlfn.CONCAT($B18,$D18,$E18),PEC_Info!$L$2:$L$301,PEC_Info!$J$2:$J$301) -> 0.05 | N18: =_xlfn.XLOOKUP(_xlfn.CONCAT($B18,$D18,$E18),PEC_Info!$L$2:$L$301,PEC_Info!$K$2:$K$301) -> 0 | P18: =(I18*(1+J18)+K18*1000)/Conversions!$D$3/_xlfn.XLOOKUP(B18,CarriersTech_characteristics!$B$2:$B$8,CarriersTech_characteristics!$G$2:$G$8)/Conversions!$D$2 -> 0.0099597712 | Q18: =F18*_xlfn.XLOOKUP(B18,CarriersTech_characteristics!$B$2:$B$8,CarriersTech_characteristics!$G$2:$G$8)*Conversions!$D$2*(1-H18) -> 5.51e+08 | R18: =(L18*(1+M18)+N18*1000)/Conversions!$D$3/_xlfn.XLOOKUP(B18,CarriersTech_characteristics!$B$2:$B$8,CarriersTech_characteristics!$J$2:$J$8)/Conversions!$D$2 -> 0.0099597712 | S18: =G18*_xlfn.XLOOKUP(B18,CarriersTech_characteristics!$B$2:$B$8,CarriersTech_characteristics!$J$2:$J$8)*Conversions!$D$2 -> 0
A19: 1 | B19: COKING_COAL | C19: INDIA | D19: ER | E19: =_xlfn.XLOOKUP(A19,PeriodMap!$A$2:$A$45,PeriodMap!$B$2:$B$45) -> 2023 | F19: =_xlfn.XLOOKUP(_xlfn.CONCAT($B19,$D19,$E19),PEC_ProdImpConstraints!$G$2:$G$286,PEC_ProdImpConstraints!$E$2:$E$286) -> 12.971 | G19: =_xlfn.XLOOKUP(_xlfn.CONCAT($B19,$D19,$E19),PEC_ProdImpConstraints!$G$2:$G$286,PEC_ProdImpConstraints!$F$2:$F$286) -> 100 | H19: 0 | I19: =_xlfn.XLOOKUP(_xlfn.CONCAT($B19,$D19,$E19),PEC_Info!$L$2:$L$301,PEC_Info!$F$2:$F$301) -> 2789.0369 | J19: =_xlfn.XLOOKUP(_xlfn.CONCAT($B19,$D19,$E19),PEC_Info!$L$2:$L$301,PEC_Info!$G$2:$G$301) -> 0.3508 | K19: =_xlfn.XLOOKUP(_xlfn.CONCAT($B19,$D19,$E19),PEC_Info!$L$2:$L$301,PEC_Info!$H$2:$H$301) -> 0 | L19: =_xlfn.XLOOKUP(_xlfn.CONCAT($B19,$D19,$E19),PEC_Info!$L$2:$L$301,PEC_Info!$I$2:$I$301) -> 28632.348 | M19: =_xlfn.XLOOKUP(_xlfn.CONCAT($B19,$D19,$E19),PEC_Info!$L$2:$L$301,PEC_Info!$J$2:$J$301) -> 0.205 | N19: =_xlfn.XLOOKUP(_xlfn.CONCAT($B19,$D19,$E19),PEC_Info!$L$2:$L$301,PEC_Info!$K$2:$K$301) -> 0 | P19: =(I19*(1+J19)+K19*1000)/_xlfn.XLOOKUP(B19,CarriersTech_characteristics!$B$2:$B$8,CarriersTech_characteristics!$G$2:$G$8)/Conversions!$D$2 -> 0.00065980588 | Q19: =F19*_xlfn.XLOOKUP(B19,CarriersTech_characteristics!$B$2:$B$8,CarriersTech_characteristics!$G$2:$G$8)*Conversions!$D$2*(1-H19) -> 74063219 | R19: =(L19*(1+M19)+N19*1000)/_xlfn.XLOOKUP(B19,CarriersTech_characteristics!$B$2:$B$8,CarriersTech_characteristics!$J$2:$J$8)/Conversions!$D$2 -> 0.0051369302 | S19: =G19*_xlfn.XLOOKUP(B19,CarriersTech_characteristics!$B$2:$B$8,CarriersTech_characteristics!$J$2:$J$8)*Conversions!$D$2 -> 6.7164587e+08
A20: 1 | B20: COKING_COAL | C20: INDIA | D20: WR | E20: =_xlfn.XLOOKUP(A20,PeriodMap!$A$2:$A$45,PeriodMap!$B$2:$B$45) -> 2023 | F20: =_xlfn.XLOOKUP(_xlfn.CONCAT($B20,$D20,$E20),PEC_ProdImpConstraints!$G$2:$G$286,PEC_ProdImpConstraints!$E$2:$E$286) -> 0 | G20: =_xlfn.XLOOKUP(_xlfn.CONCAT($B20,$D20,$E20),PEC_ProdImpConstraints!$G$2:$G$286,PEC_ProdImpConstraints!$F$2:$F$286) -> 100 | H20: 0 | I20: =_xlfn.XLOOKUP(_xlfn.CONCAT($B20,$D20,$E20),PEC_Info!$L$2:$L$301,PEC_Info!$F$2:$F$301) -> 2789.0369 | J20: =_xlfn.XLOOKUP(_xlfn.CONCAT($B20,$D20,$E20),PEC_Info!$L$2:$L$301,PEC_Info!$G$2:$G$301) -> 0.3508 | K20: =_xlfn.XLOOKUP(_xlfn.CONCAT($B20,$D20,$E20),PEC_Info!$L$2:$L$301,PEC_Info!$H$2:$H$301) -> 0 | L20: =_xlfn.XLOOKUP(_xlfn.CONCAT($B20,$D20,$E20),PEC_Info!$L$2:$L$301,PEC_Info!$I$2:$I$301) -> 28632.348 | M20: =_xlfn.XLOOKUP(_xlfn.CONCAT($B20,$D20,$E20),PEC_Info!$L$2:$L$301,PEC_Info!$J$2:$J$301) -> 0.205 | N20: =_xlfn.XLOOKUP(_xlfn.CONCAT($B20,$D20,$E20),PEC_Info!$L$2:$L$301,PEC_Info!$K$2:$K$301) -> 0 | P20: =(I20*(1+J20)+K20*1000)/_xlfn.XLOOKUP(B20,CarriersTech_characteristics!$B$2:$B$8,CarriersTech_characteristics!$G$2:$G$8)/Conversions!$D$2 -> 0.00065980588 | Q20: =F20*_xlfn.XLOOKUP(B20,CarriersTech_characteristics!$B$2:$B$8,CarriersTech_characteristics!$G$2:$G$8)*Conversions!$D$2*(1-H20) -> 0 | R20: =(L20*(1+M20)+N20*1000)/_xlfn.XLOOKUP(B20,CarriersTech_characteristics!$B$2:$B$8,CarriersTech_characteristics!$J$2:$J$8)/Conversions!$D$2 -> 0.0051369302 | S20: =G20*_xlfn.XLOOKUP(B20,CarriersTech_characteristics!$B$2:$B$8,CarriersTech_characteristics!$J$2:$J$8)*Conversions!$D$2 -> 6.7164587e+08
A21: 1 | B21: COKING_COAL | C21: INDIA | D21: NR | E21: =_xlfn.XLOOKUP(A21,PeriodMap!$A$2:$A$45,PeriodMap!$B$2:$B$45) -> 2023 | F21: =_xlfn.XLOOKUP(_xlfn.CONCAT($B21,$D21,$E21),PEC_ProdImpConstraints!$G$2:$G$286,PEC_ProdImpConstraints!$E$2:$E$286) -> 0 | G21: =_xlfn.XLOOKUP(_xlfn.CONCAT($B21,$D21,$E21),PEC_ProdImpConstraints!$G$2:$G$286,PEC_ProdImpConstraints!$F$2:$F$286) -> 0 | H21: 0 | I21: =_xlfn.XLOOKUP(_xlfn.CONCAT($B21,$D21,$E21),PEC_Info!$L$2:$L$301,PEC_Info!$F$2:$F$301) -> 2789.0369 | J21: =_xlfn.XLOOKUP(_xlfn.CONCAT($B21,$D21,$E21),PEC_Info!$L$2:$L$301,PEC_Info!$G$2:$G$301) -> 0.3508 | K21: =_xlfn.XLOOKUP(_xlfn.CONCAT($B21,$D21,$E21),PEC_Info!$L$2:$L$301,PEC_Info!$H$2:$H$301) -> 0 | L21: =_xlfn.XLOOKUP(_xlfn.CONCAT($B21,$D21,$E21),PEC_Info!$L$2:$L$301,PEC_Info!$I$2:$I$301) -> 28632.348 | M21: =_xlfn.XLOOKUP(_xlfn.CONCAT($B21,$D21,$E21),PEC_Info!$L$2:$L$301,PEC_Info!$J$2:$J$301) -> 0.205 | N21: =_xlfn.XLOOKUP(_xlfn.CONCAT($B21,$D21,$E21),PEC_Info!$L$2:$L$301,PEC_Info!$K$2:$K$301) -> 0 | P21: =(I21*(1+J21)+K21*1000)/_xlfn.XLOOKUP(B21,CarriersTech_characteristics!$B$2:$B$8,CarriersTech_characteristics!$G$2:$G$8)/Conversions!$D$2 -> 0.00065980588 | Q21: =F21*_xlfn.XLOOKUP(B21,CarriersTech_characteristics!$B$2:$B$8,CarriersTech_characteristics!$G$2:$G$8)*Conversions!$D$2*(1-H21) -> 0 | R21: =(L21*(1+M21)+N21*1000)/_xlfn.XLOOKUP(B21,CarriersTech_characteristics!$B$2:$B$8,CarriersTech_characteristics!$J$2:$J$8)/Conversions!$D$2 -> 0.0051369302 | S21: =G21*_xlfn.XLOOKUP(B21,CarriersTech_characteristics!$B$2:$B$8,CarriersTech_characteristics!$J$2:$J$8)*Conversions!$D$2 -> 0
A22: 1 | B22: COKING_COAL | C22: INDIA | D22: SR | E22: =_xlfn.XLOOKUP(A22,PeriodMap!$A$2:$A$45,PeriodMap!$B$2:$B$45) -> 2023 | F22: =_xlfn.XLOOKUP(_xlfn.CONCAT($B22,$D22,$E22),PEC_ProdImpConstraints!$G$2:$G$286,PEC_ProdImpConstraints!$E$2:$E$286) -> 0 | G22: =_xlfn.XLOOKUP(_xlfn.CONCAT($B22,$D22,$E22),PEC_ProdImpConstraints!$G$2:$G$286,PEC_ProdImpConstraints!$F$2:$F$286) -> 100 | H22: 0 | I22: =_xlfn.XLOOKUP(_xlfn.CONCAT($B22,$D22,$E22),PEC_Info!$L$2:$L$301,PEC_Info!$F$2:$F$301) -> 2789.0369 | J22: =_xlfn.XLOOKUP(_xlfn.CONCAT($B22,$D22,$E22),PEC_Info!$L$2:$L$301,PEC_Info!$G$2:$G$301) -> 0.3508 | K22: =_xlfn.XLOOKUP(_xlfn.CONCAT($B22,$D22,$E22),PEC_Info!$L$2:$L$301,PEC_Info!$H$2:$H$301) -> 0 | L22: =_xlfn.XLOOKUP(_xlfn.CONCAT($B22,$D22,$E22),PEC_Info!$L$2:$L$301,PEC_Info!$I$2:$I$301) -> 28632.348 | M22: =_xlfn.XLOOKUP(_xlfn.CONCAT($B22,$D22,$E22),PEC_Info!$L$2:$L$301,PEC_Info!$J$2:$J$301) -> 0.205 | N22: =_xlfn.XLOOKUP(_xlfn.CONCAT($B22,$D22,$E22),PEC_Info!$L$2:$L$301,PEC_Info!$K$2:$K$301) -> 0 | P22: =(I22*(1+J22)+K22*1000)/_xlfn.XLOOKUP(B22,CarriersTech_characteristics!$B$2:$B$8,CarriersTech_characteristics!$G$2:$G$8)/Conversions!$D$2 -> 0.00065980588 | Q22: =F22*_xlfn.XLOOKUP(B22,CarriersTech_characteristics!$B$2:$B$8,CarriersTech_characteristics!$G$2:$G$8)*Conversions!$D$2*(1-H22) -> 0 | R22: =(L22*(1+M22)+N22*1000)/_xlfn.XLOOKUP(B22,CarriersTech_characteristics!$B$2:$B$8,CarriersTech_characteristics!$J$2:$J$8)/Conversions!$D$2 -> 0.0051369302 | S22: =G22*_xlfn.XLOOKUP(B22,CarriersTech_characteristics!$B$2:$B$8,CarriersTech_characteristics!$J$2:$J$8)*Conversions!$D$2 -> 6.7164587e+08
A23: 1 | B23: COKING_COAL | C23: INDIA | D23: NER | E23: =_xlfn.XLOOKUP(A23,PeriodMap!$A$2:$A$45,PeriodMap!$B$2:$B$45) -> 2023 | F23: =_xlfn.XLOOKUP(_xlfn.CONCAT($B23,$D23,$E23),PEC_ProdImpConstraints!$G$2:$G$286,PEC_ProdImpConstraints!$E$2:$E$286) -> 0 | G23: =_xlfn.XLOOKUP(_xlfn.CONCAT($B23,$D23,$E23),PEC_ProdImpConstraints!$G$2:$G$286,PEC_ProdImpConstraints!$F$2:$F$286) -> 0 | H23: 0 | I23: =_xlfn.XLOOKUP(_xlfn.CONCAT($B23,$D23,$E23),PEC_Info!$L$2:$L$301,PEC_Info!$F$2:$F$301) -> 2789.0369 | J23: =_xlfn.XLOOKUP(_xlfn.CONCAT($B23,$D23,$E23),PEC_Info!$L$2:$L$301,PEC_Info!$G$2:$G$301) -> 0.3508 | K23: =_xlfn.XLOOKUP(_xlfn.CONCAT($B23,$D23,$E23),PEC_Info!$L$2:$L$301,PEC_Info!$H$2:$H$301) -> 0 | L23: =_xlfn.XLOOKUP(_xlfn.CONCAT($B23,$D23,$E23),PEC_Info!$L$2:$L$301,PEC_Info!$I$2:$I$301) -> 28632.348 | M23: =_xlfn.XLOOKUP(_xlfn.CONCAT($B23,$D23,$E23),PEC_Info!$L$2:$L$301,PEC_Info!$J$2:$J$301) -> 0.205 | N23: =_xlfn.XLOOKUP(_xlfn.CONCAT($B23,$D23,$E23),PEC_Info!$L$2:$L$301,PEC_Info!$K$2:$K$301) -> 0 | P23: =(I23*(1+J23)+K23*1000)/_xlfn.XLOOKUP(B23,CarriersTech_characteristics!$B$2:$B$8,CarriersTech_characteristics!$G$2:$G$8)/Conversions!$D$2 -> 0.00065980588 | Q23: =F23*_xlfn.XLOOKUP(B23,CarriersTech_characteristics!$B$2:$B$8,CarriersTech_characteristics!$G$2:$G$8)*Conversions!$D$2*(1-H23) -> 0 | R23: =(L23*(1+M23)+N23*1000)/_xlfn.XLOOKUP(B23,CarriersTech_characteristics!$B$2:$B$8,CarriersTech_characteristics!$J$2:$J$8)/Conversions!$D$2 -> 0.0051369302 | S23: =G23*_xlfn.XLOOKUP(B23,CarriersTech_characteristics!$B$2:$B$8,CarriersTech_characteristics!$J$2:$J$8)*Conversions!$D$2 -> 0
A24: 1 | B24: COKING_COAL | C24: INDIA | D24: ALL | E24: =_xlfn.XLOOKUP(A24,PeriodMap!$A$2:$A$45,PeriodMap!$B$2:$B$45) -> 2023 | F24: =SUM(F19:F23) -> 12.971 | G24: =SUM(G19:G23) -> 300 | H24: =AVERAGE(H19:H23) -> 0 | I24: =AVERAGE(I19:I23) -> 2789.0369 | J24: =AVERAGE(J19:J23) -> 0.3508 | K24: =AVERAGE(K19:K23) -> 0 | L24: =AVERAGE(L19:L23) -> 28632.348 | M24: =AVERAGE(M19:M23) -> 0.205 | N24: =AVERAGE(N19:N23) -> 0 | P24: =AVERAGE(P19:P23) -> 0.00065980588 | Q24: =SUM(Q19:Q23) -> 74063219 | R24: =AVERAGE(R19:R23) -> 0.0051369302 | S24: =SUM(S19:S23) -> 2.0149376e+09
A25: 2 | B25: BIOMASS | C25: INDIA | E25: =_xlfn.XLOOKUP(A25,PeriodMap!$A$2:$A$45,PeriodMap!$B$2:$B$45) -> 2024 | F25: =_xlfn.XLOOKUP(_xlfn.CONCAT($B25,$D25,$E25),PEC_ProdImpConstraints!$G$2:$G$286,PEC_ProdImpConstraints!$E$2:$E$286) -> 270 | G25: =_xlfn.XLOOKUP(_xlfn.CONCAT($B25,$D25,$E25),PEC_ProdImpConstraints!$G$2:$G$286,PEC_ProdImpConstraints!$F$2:$F$286) -> 0 | H25: =_xlfn.XLOOKUP(_xlfn.CONCAT($B25,$D25,$E25),PEC_Info!$L$2:$L$301,PEC_Info!$E$2:$E$301) -> 0 | I25: =_xlfn.XLOOKUP(_xlfn.CONCAT($B25,$D25,$E25),PEC_Info!$L$2:$L$301,PEC_Info!$F$2:$F$301) -> 5683.2536 | J25: =_xlfn.XLOOKUP(_xlfn.CONCAT($B25,$D25,$E25),PEC_Info!$L$2:$L$301,PEC_Info!$G$2:$G$301) -> 0 | K25: =_xlfn.XLOOKUP(_xlfn.CONCAT($B25,$D25,$E25),PEC_Info!$L$2:$L$301,PEC_Info!$H$2:$H$301) -> 0 | L25: =_xlfn.XLOOKUP(_xlfn.CONCAT($B25,$D25,$E25),PEC_Info!$L$2:$L$301,PEC_Info!$I$2:$I$301) -> 5683.2536 | M25: =_xlfn.XLOOKUP(_xlfn.CONCAT($B25,$D25,$E25),PEC_Info!$L$2:$L$301,PEC_Info!$J$2:$J$301) -> 0 | N25: =_xlfn.XLOOKUP(_xlfn.CONCAT($B25,$D25,$E25),PEC_Info!$L$2:$L$301,PEC_Info!$K$2:$K$301) -> 0 | P25: =(I25*(1+J25)+K25*1000)/_xlfn.XLOOKUP(B25,CarriersTech_characteristics!$B$2:$B$8,CarriersTech_characteristics!$G$2:$G$8)/Conversions!$D$2 -> 0.0013148916 | Q25: =F25*_xlfn.XLOOKUP(B25,CarriersTech_characteristics!$B$2:$B$8,CarriersTech_characteristics!$G$2:$G$8)*Conversions!$D$2*(1-H25) -> 1.167e+09 | R25: =(L25*(1+M25)+N25*1000)/_xlfn.XLOOKUP(B25,CarriersTech_characteristics!$B$2:$B$8,CarriersTech_characteristics!$J$2:$J$8)/Conversions!$D$2 -> 0.0013148916 | S25: =G25*_xlfn.XLOOKUP(B25,CarriersTech_characteristics!$B$2:$B$8,CarriersTech_characteristics!$J$2:$J$8)*Conversions!$D$2 -> 0
A26: 2 | B26: BIOMASS_WASTE | C26: INDIA | E26: =_xlfn.XLOOKUP(A26,PeriodMap!$A$2:$A$45,PeriodMap!$B$2:$B$45) -> 2024 | F26: =_xlfn.XLOOKUP(_xlfn.CONCAT($B26,$D26,$E26),PEC_ProdImpConstraints!$G$2:$G$286,PEC_ProdImpConstraints!$E$2:$E$286) -> 175 | G26: =_xlfn.XLOOKUP(_xlfn.CONCAT($B26,$D26,$E26),PEC_ProdImpConstraints!$G$2:$G$286,PEC_ProdImpConstraints!$F$2:$F$286) -> 0 | H26: =_xlfn.XLOOKUP(_xlfn.CONCAT($B26,$D26,$E26),PEC_Info!$L$2:$L$301,PEC_Info!$E$2:$E$301) -> 0 | I26: =_xlfn.XLOOKUP(_xlfn.CONCAT($B26,$D26,$E26),PEC_Info!$L$2:$L$301,PEC_Info!$F$2:$F$301) -> 9000 | J26: =_xlfn.XLOOKUP(_xlfn.CONCAT($B26,$D26,$E26),PEC_Info!$L$2:$L$301,PEC_Info!$G$2:$G$301) -> 0.05 | K26: =_xlfn.XLOOKUP(_xlfn.CONCAT($B26,$D26,$E26),PEC_Info!$L$2:$L$301,PEC_Info!$H$2:$H$301) -> 0 | L26: =_xlfn.XLOOKUP(_xlfn.CONCAT($B26,$D26,$E26),PEC_Info!$L$2:$L$301,PEC_Info!$I$2:$I$301) -> 9000 | M26: =_xlfn.XLOOKUP(_xlfn.CONCAT($B26,$D26,$E26),PEC_Info!$L$2:$L$301,PEC_Info!$J$2:$J$301) -> 0.05 | N26: =_xlfn.XLOOKUP(_xlfn.CONCAT($B26,$D26,$E26),PEC_Info!$L$2:$L$301,PEC_Info!$K$2:$K$301) -> 0 | P26: =(I26*(1+J26)+K26*1000)/_xlfn.XLOOKUP(B26,CarriersTech_characteristics!$B$2:$B$8,CarriersTech_characteristics!$G$2:$G$8)/Conversions!$D$2 -> 0.0024924961 | Q26: =F26*_xlfn.XLOOKUP(B26,CarriersTech_characteristics!$B$2:$B$8,CarriersTech_characteristics!$G$2:$G$8)*Conversions!$D$2*(1-H26) -> 6.6349151e+08 | R26: =(L26*(1+M26)+N26*1000)/_xlfn.XLOOKUP(B26,CarriersTech_characteristics!$B$2:$B$8,CarriersTech_characteristics!$J$2:$J$8)/Conversions!$D$2 -> 0.0024924961 | S26: =G26*_xlfn.XLOOKUP(B26,CarriersTech_characteristics!$B$2:$B$8,CarriersTech_characteristics!$J$2:$J$8)*Conversions!$D$2 -> 0
A27: 2 | B27: NATGAS | C27: INDIA | E27: =_xlfn.XLOOKUP(A27,PeriodMap!$A$2:$A$45,PeriodMap!$B$2:$B$45) -> 2024 | F27: =_xlfn.XLOOKUP(_xlfn.CONCAT($B27,$D27,$E27),PEC_ProdImpConstraints!$G$2:$G$286,PEC_ProdImpConstraints!$E$2:$E$286) -> 34.32096 | G27: =_xlfn.XLOOKUP(_xlfn.CONCAT($B27,$D27,$E27),PEC_ProdImpConstraints!$G$2:$G$286,PEC_ProdImpConstraints!$F$2:$F$286) -> 200 | H27: =_xlfn.XLOOKUP(_xlfn.CONCAT($B27,$D27,$E27),PEC_Info!$L$2:$L$301,PEC_Info!$E$2:$E$301) -> 0.36749121 | I27: =_xlfn.XLOOKUP(_xlfn.CONCAT($B27,$D27,$E27),PEC_Info!$L$2:$L$301,PEC_Info!$F$2:$F$301) -> 24102 | J27: =_xlfn.XLOOKUP(_xlfn.CONCAT($B27,$D27,$E27),PEC_Info!$L$2:$L$301,PEC_Info!$G$2:$G$301) -> 0.24 | K27: =_xlfn.XLOOKUP(_xlfn.CONCAT($B27,$D27,$E27),PEC_Info!$L$2:$L$301,PEC_Info!$H$2:$H$301) -> 0 | L27: =_xlfn.XLOOKUP(_xlfn.CONCAT($B27,$D27,$E27),PEC_Info!$L$2:$L$301,PEC_Info!$I$2:$I$301) -> 35195.967 | M27: =_xlfn.XLOOKUP(_xlfn.CONCAT($B27,$D27,$E27),PEC_Info!$L$2:$L$301,PEC_Info!$J$2:$J$301) -> 0.349 | N27: =_xlfn.XLOOKUP(_xlfn.CONCAT($B27,$D27,$E27),PEC_Info!$L$2:$L$301,PEC_Info!$K$2:$K$301) -> 0 | P27: =(I27*(1+J27)+K27*1000)/Conversions!$D$3/_xlfn.XLOOKUP(B27,CarriersTech_characteristics!$B$2:$B$8,CarriersTech_characteristics!$G$2:$G$8)/Conversions!$D$2 -> 0.0034442765 | Q27: =F27*_xlfn.XLOOKUP(B27,CarriersTech_characteristics!$B$2:$B$8,CarriersTech_characteristics!$G$2:$G$8)*Conversions!$D$2*(1-H27) -> 2.2722087e+08 | R27: =(L27*(1+M27)+N27*1000)/Conversions!$D$3/_xlfn.XLOOKUP(B27,CarriersTech_characteristics!$B$2:$B$8,CarriersTech_characteristics!$J$2:$J$8)/Conversions!$D$2 -> 0.0054717732 | S27: =G27*_xlfn.XLOOKUP(B27,CarriersTech_characteristics!$B$2:$B$8,CarriersTech_characteristics!$J$2:$J$8)*Conversions!$D$2 -> 2.0934e+09
A28: 2 | B28: THERMAL_COAL | C28: INDIA | D28: NR | E28: =_xlfn.XLOOKUP(A28,PeriodMap!$A$2:$A$45,PeriodMap!$B$2:$B$45) -> 2024 | F28: =_xlfn.XLOOKUP(_xlfn.CONCAT($B28,$D28,$E28),PEC_ProdImpConstraints!$G$2:$G$286,PEC_ProdImpConstraints!$E$2:$E$286) -> 31.9232 | G28: =_xlfn.XLOOKUP(_xlfn.CONCAT($B28,$D28,$E28),PEC_ProdImpConstraints!$G$2:$G$286,PEC_ProdImpConstraints!$F$2:$F$286) -> 0 | H28: =_xlfn.XLOOKUP(_xlfn.CONCAT($B28,$D28,$E28),PEC_Info!$L$2:$L$301,PEC_Info!$E$2:$E$301) -> 0 | I28: =_xlfn.XLOOKUP(_xlfn.CONCAT($B28,$D28,$E28),PEC_Info!$L$2:$L$301,PEC_Info!$F$2:$F$301) -> 1156.3734 | J28: =_xlfn.XLOOKUP(_xlfn.CONCAT($B28,$D28,$E28),PEC_Info!$L$2:$L$301,PEC_Info!$G$2:$G$301) -> 0.3508 | K28: =_xlfn.XLOOKUP(_xlfn.CONCAT($B28,$D28,$E28),PEC_Info!$L$2:$L$301,PEC_Info!$H$2:$H$301) -> 0 | L28: =_xlfn.XLOOKUP(_xlfn.CONCAT($B28,$D28,$E28),PEC_Info!$L$2:$L$301,PEC_Info!$I$2:$I$301) -> 10095.813 | M28: =_xlfn.XLOOKUP(_xlfn.CONCAT($B28,$D28,$E28),PEC_Info!$L$2:$L$301,PEC_Info!$J$2:$J$301) -> 0.205 | N28: =_xlfn.XLOOKUP(_xlfn.CONCAT($B28,$D28,$E28),PEC_Info!$L$2:$L$301,PEC_Info!$K$2:$K$301) -> 0 | P28: =(I28*(1+J28)+K28*1000)/_xlfn.XLOOKUP(B28,CarriersTech_characteristics!$B$2:$B$8,CarriersTech_characteristics!$G$2:$G$8)/Conversions!$D$2 -> 0.00032679978 | Q28: =F28*_xlfn.XLOOKUP(B28,CarriersTech_characteristics!$B$2:$B$8,CarriersTech_characteristics!$G$2:$G$8)*Conversions!$D$2*(1-H28) -> 1.5258569e+08 | R28: =(L28*(1+M28)+N28*1000)/_xlfn.XLOOKUP(B28,CarriersTech_characteristics!$B$2:$B$8,CarriersTech_characteristics!$J$2:$J$8)/Conversions!$D$2 -> 0.0019371126 | S28: =G28*_xlfn.XLOOKUP(B28,CarriersTech_characteristics!$B$2:$B$8,CarriersTech_characteristics!$J$2:$J$8)*Conversions!$D$2 -> 0
A29: 2 | B29: THERMAL_COAL | C29: INDIA | D29: NER | E29: =_xlfn.XLOOKUP(A29,PeriodMap!$A$2:$A$45,PeriodMap!$B$2:$B$45) -> 2024 | F29: =_xlfn.XLOOKUP(_xlfn.CONCAT($B29,$D29,$E29),PEC_ProdImpConstraints!$G$2:$G$286,PEC_ProdImpConstraints!$E$2:$E$286) -> 0 | G29: =_xlfn.XLOOKUP(_xlfn.CONCAT($B29,$D29,$E29),PEC_ProdImpConstraints!$G$2:$G$286,PEC_ProdImpConstraints!$F$2:$F$286) -> 0 | H29: =_xlfn.XLOOKUP(_xlfn.CONCAT($B29,$D29,$E29),PEC_Info!$L$2:$L$301,PEC_Info!$E$2:$E$301) -> 0 | I29: =_xlfn.XLOOKUP(_xlfn.CONCAT($B29,$D29,$E29),PEC_Info!$L$2:$L$301,PEC_Info!$F$2:$F$301) -> 1156.3734 | J29: =_xlfn.XLOOKUP(_xlfn.CONCAT($B29,$D29,$E29),PEC_Info!$L$2:$L$301,PEC_Info!$G$2:$G$301) -> 0.3508 | K29: =_xlfn.XLOOKUP(_xlfn.CONCAT($B29,$D29,$E29),PEC_Info!$L$2:$L$301,PEC_Info!$H$2:$H$301) -> 0 | L29: =_xlfn.XLOOKUP(_xlfn.CONCAT($B29,$D29,$E29),PEC_Info!$L$2:$L$301,PEC_Info!$I$2:$I$301) -> 10095.813 | M29: =_xlfn.XLOOKUP(_xlfn.CONCAT($B29,$D29,$E29),PEC_Info!$L$2:$L$301,PEC_Info!$J$2:$J$301) -> 0.205 | N29: =_xlfn.XLOOKUP(_xlfn.CONCAT($B29,$D29,$E29),PEC_Info!$L$2:$L$301,PEC_Info!$K$2:$K$301) -> 0 | P29: =(I29*(1+J29)+K29*1000)/_xlfn.XLOOKUP(B29,CarriersTech_characteristics!$B$2:$B$8,CarriersTech_characteristics!$G$2:$G$8)/Conversions!$D$2 -> 0.00032679978 | Q29: =F29*_xlfn.XLOOKUP(B29,CarriersTech_characteristics!$B$2:$B$8,CarriersTech_characteristics!$G$2:$G$8)*Conversions!$D$2*(1-H29) -> 0 | R29: =(L29*(1+M29)+N29*1000)/_xlfn.XLOOKUP(B29,CarriersTech_characteristics!$B$2:$B$8,CarriersTech_characteristics!$J$2:$J$8)/Conversions!$D$2 -> 0.0019371126 | S29: =G29*_xlfn.XLOOKUP(B29,CarriersTech_characteristics!$B$2:$B$8,CarriersTech_characteristics!$J$2:$J$8)*Conversions!$D$2 -> 0
A30: 2 | B30: THERMAL_COAL | C30: INDIA | D30: ER | E30: =_xlfn.XLOOKUP(A30,PeriodMap!$A$2:$A$45,PeriodMap!$B$2:$B$45) -> 2024 | F30: =_xlfn.XLOOKUP(_xlfn.CONCAT($B30,$D30,$E30),PEC_ProdImpConstraints!$G$2:$G$286,PEC_ProdImpConstraints!$E$2:$E$286) -> 417.84809 | G30: =_xlfn.XLOOKUP(_xlfn.CONCAT($B30,$D30,$E30),PEC_ProdImpConstraints!$G$2:$G$286,PEC_ProdImpConstraints!$F$2:$F$286) -> 150 | H30: =_xlfn.XLOOKUP(_xlfn.CONCAT($B30,$D30,$E30),PEC_Info!$L$2:$L$301,PEC_Info!$E$2:$E$301) -> 0 | I30: =_xlfn.XLOOKUP(_xlfn.CONCAT($B30,$D30,$E30),PEC_Info!$L$2:$L$301,PEC_Info!$F$2:$F$301) -> 1156.3734 | J30: =_xlfn.XLOOKUP(_xlfn.CONCAT($B30,$D30,$E30),PEC_Info!$L$2:$L$301,PEC_Info!$G$2:$G$301) -> 0.3508 | K30: =_xlfn.XLOOKUP(_xlfn.CONCAT($B30,$D30,$E30),PEC_Info!$L$2:$L$301,PEC_Info!$H$2:$H$301) -> 0 | L30: =_xlfn.XLOOKUP(_xlfn.CONCAT($B30,$D30,$E30),PEC_Info!$L$2:$L$301,PEC_Info!$I$2:$I$301) -> 10095.813 | M30: =_xlfn.XLOOKUP(_xlfn.CONCAT($B30,$D30,$E30),PEC_Info!$L$2:$L$301,PEC_Info!$J$2:$J$301) -> 0.205 | N30: =_xlfn.XLOOKUP(_xlfn.CONCAT($B30,$D30,$E30),PEC_Info!$L$2:$L$301,PEC_Info!$K$2:$K$301) -> 0 | P30: =(I30*(1+J30)+K30*1000)/_xlfn.XLOOKUP(B30,CarriersTech_characteristics!$B$2:$B$8,CarriersTech_characteristics!$G$2:$G$8)/Conversions!$D$2 -> 0.00032679978 | Q30: =F30*_xlfn.XLOOKUP(B30,CarriersTech_characteristics!$B$2:$B$8,CarriersTech_characteristics!$G$2:$G$8)*Conversions!$D$2*(1-H30) -> 1.9972196e+09 | R30: =(L30*(1+M30)+N30*1000)/_xlfn.XLOOKUP(B30,CarriersTech_characteristics!$B$2:$B$8,CarriersTech_characteristics!$J$2:$J$8)/Conversions!$D$2 -> 0.0019371126 | S30: =G30*_xlfn.XLOOKUP(B30,CarriersTech_characteristics!$B$2:$B$8,CarriersTech_characteristics!$J$2:$J$8)*Conversions!$D$2 -> 9.4203001e+08
A31: 2 | B31: THERMAL_COAL | C31: INDIA | D31: WR | E31: =_xlfn.XLOOKUP(A31,PeriodMap!$A$2:$A$45,PeriodMap!$B$2:$B$45) -> 2024 | F31: =_xlfn.XLOOKUP(_xlfn.CONCAT($B31,$D31,$E31),PEC_ProdImpConstraints!$G$2:$G$286,PEC_ProdImpConstraints!$E$2:$E$286) -> 429.33807 | G31: =_xlfn.XLOOKUP(_xlfn.CONCAT($B31,$D31,$E31),PEC_ProdImpConstraints!$G$2:$G$286,PEC_ProdImpConstraints!$F$2:$F$286) -> 150 | H31: =_xlfn.XLOOKUP(_xlfn.CONCAT($B31,$D31,$E31),PEC_Info!$L$2:$L$301,PEC_Info!$E$2:$E$301) -> 0 | I31: =_xlfn.XLOOKUP(_xlfn.CONCAT($B31,$D31,$E31),PEC_Info!$L$2:$L$301,PEC_Info!$F$2:$F$301) -> 1156.3734 | J31: =_xlfn.XLOOKUP(_xlfn.CONCAT($B31,$D31,$E31),PEC_Info!$L$2:$L$301,PEC_Info!$G$2:$G$301) -> 0.3508 | K31: =_xlfn.XLOOKUP(_xlfn.CONCAT($B31,$D31,$E31),PEC_Info!$L$2:$L$301,PEC_Info!$H$2:$H$301) -> 0 | L31: =_xlfn.XLOOKUP(_xlfn.CONCAT($B31,$D31,$E31),PEC_Info!$L$2:$L$301,PEC_Info!$I$2:$I$301) -> 10095.813 | M31: =_xlfn.XLOOKUP(_xlfn.CONCAT($B31,$D31,$E31),PEC_Info!$L$2:$L$301,PEC_Info!$J$2:$J$301) -> 0.205 | N31: =_xlfn.XLOOKUP(_xlfn.CONCAT($B31,$D31,$E31),PEC_Info!$L$2:$L$301,PEC_Info!$K$2:$K$301) -> 0 | P31: =(I31*(1+J31)+K31*1000)/_xlfn.XLOOKUP(B31,CarriersTech_characteristics!$B$2:$B$8,CarriersTech_characteristics!$G$2:$G$8)/Conversions!$D$2 -> 0.00032679978 | Q31: =F31*_xlfn.XLOOKUP(B31,CarriersTech_characteristics!$B$2:$B$8,CarriersTech_characteristics!$G$2:$G$8)*Conversions!$D$2*(1-H31) -> 2.0521391e+09 | R31: =(L31*(1+M31)+N31*1000)/_xlfn.XLOOKUP(B31,CarriersTech_characteristics!$B$2:$B$8,CarriersTech_characteristics!$J$2:$J$8)/Conversions!$D$2 -> 0.0019371126 | S31: =G31*_xlfn.XLOOKUP(B31,CarriersTech_characteristics!$B$2:$B$8,CarriersTech_characteristics!$J$2:$J$8)*Conversions!$D$2 -> 9.4203001e+08
A32: 2 | B32: THERMAL_COAL | C32: INDIA | D32: SR | E32: =_xlfn.XLOOKUP(A32,PeriodMap!$A$2:$A$45,PeriodMap!$B$2:$B$45) -> 2024 | F32: =_xlfn.XLOOKUP(_xlfn.CONCAT($B32,$D32,$E32),PEC_ProdImpConstraints!$G$2:$G$286,PEC_ProdImpConstraints!$E$2:$E$286) -> 91.773025 | G32: =_xlfn.XLOOKUP(_xlfn.CONCAT($B32,$D32,$E32),PEC_ProdImpConstraints!$G$2:$G$286,PEC_ProdImpConstraints!$F$2:$F$286) -> 150 | H32: =_xlfn.XLOOKUP(_xlfn.CONCAT($B32,$D32,$E32),PEC_Info!$L$2:$L$301,PEC_Info!$E$2:$E$301) -> 0 | I32: =_xlfn.XLOOKUP(_xlfn.CONCAT($B32,$D32,$E32),PEC_Info!$L$2:$L$301,PEC_Info!$F$2:$F$301) -> 1156.3734 | J32: =_xlfn.XLOOKUP(_xlfn.CONCAT($B32,$D32,$E32),PEC_Info!$L$2:$L$301,PEC_Info!$G$2:$G$301) -> 0.3508 | K32: =_xlfn.XLOOKUP(_xlfn.CONCAT($B32,$D32,$E32),PEC_Info!$L$2:$L$301,PEC_Info!$H$2:$H$301) -> 0 | L32: =_xlfn.XLOOKUP(_xlfn.CONCAT($B32,$D32,$E32),PEC_Info!$L$2:$L$301,PEC_Info!$I$2:$I$301) -> 10095.813 | M32: =_xlfn.XLOOKUP(_xlfn.CONCAT($B32,$D32,$E32),PEC_Info!$L$2:$L$301,PEC_Info!$J$2:$J$301) -> 0.205 | N32: =_xlfn.XLOOKUP(_xlfn.CONCAT($B32,$D32,$E32),PEC_Info!$L$2:$L$301,PEC_Info!$K$2:$K$301) -> 0 | P32: =(I32*(1+J32)+K32*1000)/_xlfn.XLOOKUP(B32,CarriersTech_characteristics!$B$2:$B$8,CarriersTech_characteristics!$G$2:$G$8)/Conversions!$D$2 -> 0.00032679978 | Q32: =F32*_xlfn.XLOOKUP(B32,CarriersTech_characteristics!$B$2:$B$8,CarriersTech_characteristics!$G$2:$G$8)*Conversions!$D$2*(1-H32) -> 4.3865435e+08 | R32: =(L32*(1+M32)+N32*1000)/_xlfn.XLOOKUP(B32,CarriersTech_characteristics!$B$2:$B$8,CarriersTech_characteristics!$J$2:$J$8)/Conversions!$D$2 -> 0.0019371126 | S32: =G32*_xlfn.XLOOKUP(B32,CarriersTech_characteristics!$B$2:$B$8,CarriersTech_characteristics!$J$2:$J$8)*Conversions!$D$2 -> 9.4203001e+08
A33: 2 | B33: THERMAL_COAL | C33: INDIA | D33: ALL | E33: =_xlfn.XLOOKUP(A33,PeriodMap!$A$2:$A$45,PeriodMap!$B$2:$B$45) -> 2024 | F33: =SUM(F28:F32) -> 970.88239 | G33: =SUM(G28:G32) -> 450 | H33: =AVERAGE(H28:H32) -> 0 | I33: =AVERAGE(I28:I32) -> 1156.3734 | J33: =AVERAGE(J28:J32) -> 0.3508 | K33: =AVERAGE(K28:K32) -> 0 | L33: =AVERAGE(L28:L32) -> 10095.813 | M33: =AVERAGE(M28:M32) -> 0.205 | N33: =AVERAGE(N28:N32) -> 0 | P33: =AVERAGE(P28:P32) -> 0.00032679978 | Q33: =SUM(Q28:Q32) -> 4.6405988e+09 | R33: =AVERAGE(R28:R32) -> 0.0019371126 | S33: =SUM(S28:S32) -> 2.82609e+09
A34: 2 | B34: CRUDE | C34: INDIA | E34: =_xlfn.XLOOKUP(A34,PeriodMap!$A$2:$A$45,PeriodMap!$B$2:$B$45) -> 2024 | F34: =_xlfn.XLOOKUP(_xlfn.CONCAT($B34,$D34,$E34),PEC_ProdImpConstraints!$G$2:$G$286,PEC_ProdImpConstraints!$E$2:$E$286) -> 31.9035 | G34: =_xlfn.XLOOKUP(_xlfn.CONCAT($B34,$D34,$E34),PEC_ProdImpConstraints!$G$2:$G$286,PEC_ProdImpConstraints!$F$2:$F$286) -> 330 | H34: 0 | I34: =_xlfn.XLOOKUP(_xlfn.CONCAT($B34,$D34,$E34),PEC_Info!$L$2:$L$301,PEC_Info!$F$2:$F$301) -> 47177.324 | J34: =_xlfn.XLOOKUP(_xlfn.CONCAT($B34,$D34,$E34),PEC_Info!$L$2:$L$301,PEC_Info!$G$2:$G$301) -> 0 | K34: =_xlfn.XLOOKUP(_xlfn.CONCAT($B34,$D34,$E34),PEC_Info!$L$2:$L$301,PEC_Info!$H$2:$H$301) -> 51.2 | L34: =_xlfn.XLOOKUP(_xlfn.CONCAT($B34,$D34,$E34),PEC_Info!$L$2:$L$301,PEC_Info!$I$2:$I$301) -> 47177.324 | M34: =_xlfn.XLOOKUP(_xlfn.CONCAT($B34,$D34,$E34),PEC_Info!$L$2:$L$301,PEC_Info!$J$2:$J$301) -> 0 | N34: =_xlfn.XLOOKUP(_xlfn.CONCAT($B34,$D34,$E34),PEC_Info!$L$2:$L$301,PEC_Info!$K$2:$K$301) -> 57.2 | P34: =(I34*(1+J34)+K34*1000)/_xlfn.XLOOKUP(B34,CarriersTech_characteristics!$B$2:$B$8,CarriersTech_characteristics!$G$2:$G$8)/Conversions!$D$2 -> 0.0082125507 | Q34: =F34*_xlfn.XLOOKUP(B34,CarriersTech_characteristics!$B$2:$B$8,CarriersTech_characteristics!$G$2:$G$8)*Conversions!$D$2*(1-H34) -> 3.8216884e+08 | R34: =(L34*(1+M34)+N34*1000)/_xlfn.XLOOKUP(B34,CarriersTech_characteristics!$B$2:$B$8,CarriersTech_characteristics!$J$2:$J$8)/Conversions!$D$2 -> 0.0087134314 | S34: =G34*_xlfn.XLOOKUP(B34,CarriersTech_characteristics!$B$2:$B$8,CarriersTech_characteristics!$J$2:$J$8)*Conversions!$D$2 -> 3.953037e+09
A35: 2 | B35: BIOGAS | C35: INDIA | E35: =_xlfn.XLOOKUP(A35,PeriodMap!$A$2:$A$45,PeriodMap!$B$2:$B$45) -> 2024 | F35: =_xlfn.XLOOKUP(_xlfn.CONCAT($B35,$D35,$E35),PEC_ProdImpConstraints!$G$2:$G$286,PEC_ProdImpConstraints!$E$2:$E$286) -> 87 | G35: =_xlfn.XLOOKUP(_xlfn.CONCAT($B35,$D35,$E35),PEC_ProdImpConstraints!$G$2:$G$286,PEC_ProdImpConstraints!$F$2:$F$286) -> 0 | H35: 0 | I35: =_xlfn.XLOOKUP(_xlfn.CONCAT($B35,$D35,$E35),PEC_Info!$L$2:$L$301,PEC_Info!$F$2:$F$301) -> 54962.757 | J35: =_xlfn.XLOOKUP(_xlfn.CONCAT($B35,$D35,$E35),PEC_Info!$L$2:$L$301,PEC_Info!$G$2:$G$301) -> 0.05 | K35: =_xlfn.XLOOKUP(_xlfn.CONCAT($B35,$D35,$E35),PEC_Info!$L$2:$L$301,PEC_Info!$H$2:$H$301) -> 0 | L35: =_xlfn.XLOOKUP(_xlfn.CONCAT($B35,$D35,$E35),PEC_Info!$L$2:$L$301,PEC_Info!$I$2:$I$301) -> 54962.757 | M35: =_xlfn.XLOOKUP(_xlfn.CONCAT($B35,$D35,$E35),PEC_Info!$L$2:$L$301,PEC_Info!$J$2:$J$301) -> 0.05 | N35: =_xlfn.XLOOKUP(_xlfn.CONCAT($B35,$D35,$E35),PEC_Info!$L$2:$L$301,PEC_Info!$K$2:$K$301) -> 0 | P35: =(I35*(1+J35)+K35*1000)/Conversions!$D$3/_xlfn.XLOOKUP(B35,CarriersTech_characteristics!$B$2:$B$8,CarriersTech_characteristics!$G$2:$G$8)/Conversions!$D$2 -> 0.010991853 | Q35: =F35*_xlfn.XLOOKUP(B35,CarriersTech_characteristics!$B$2:$B$8,CarriersTech_characteristics!$G$2:$G$8)*Conversions!$D$2*(1-H35) -> 5.51e+08 | R35: =(L35*(1+M35)+N35*1000)/Conversions!$D$3/_xlfn.XLOOKUP(B35,CarriersTech_characteristics!$B$2:$B$8,CarriersTech_characteristics!$J$2:$J$8)/Conversions!$D$2 -> 0.010991853 | S35: =G35*_xlfn.XLOOKUP(B35,CarriersTech_characteristics!$B$2:$B$8,CarriersTech_characteristics!$J$2:$J$8)*Conversions!$D$2 -> 0
A36: 2 | B36: COKING_COAL | C36: INDIA | D36: ER | E36: =_xlfn.XLOOKUP(A36,PeriodMap!$A$2:$A$45,PeriodMap!$B$2:$B$45) -> 2024 | F36: =_xlfn.XLOOKUP(_xlfn.CONCAT($B36,$D36,$E36),PEC_ProdImpConstraints!$G$2:$G$286,PEC_ProdImpConstraints!$E$2:$E$286) -> 13.516378 | G36: =_xlfn.XLOOKUP(_xlfn.CONCAT($B36,$D36,$E36),PEC_ProdImpConstraints!$G$2:$G$286,PEC_ProdImpConstraints!$F$2:$F$286) -> 100 | H36: 0 | I36: =_xlfn.XLOOKUP(_xlfn.CONCAT($B36,$D36,$E36),PEC_Info!$L$2:$L$301,PEC_Info!$F$2:$F$301) -> 2789.0369 | J36: =_xlfn.XLOOKUP(_xlfn.CONCAT($B36,$D36,$E36),PEC_Info!$L$2:$L$301,PEC_Info!$G$2:$G$301) -> 0.3508 | K36: =_xlfn.XLOOKUP(_xlfn.CONCAT($B36,$D36,$E36),PEC_Info!$L$2:$L$301,PEC_Info!$H$2:$H$301) -> 0 | L36: =_xlfn.XLOOKUP(_xlfn.CONCAT($B36,$D36,$E36),PEC_Info!$L$2:$L$301,PEC_Info!$I$2:$I$301) -> 21903.747 | M36: =_xlfn.XLOOKUP(_xlfn.CONCAT($B36,$D36,$E36),PEC_Info!$L$2:$L$301,PEC_Info!$J$2:$J$301) -> 0.205 | N36: =_xlfn.XLOOKUP(_xlfn.CONCAT($B36,$D36,$E36),PEC_Info!$L$2:$L$301,PEC_Info!$K$2:$K$301) -> 0 | P36: =(I36*(1+J36)+K36*1000)/_xlfn.XLOOKUP(B36,CarriersTech_characteristics!$B$2:$B$8,CarriersTech_characteristics!$G$2:$G$8)/Conversions!$D$2 -> 0.00065980588 | Q36: =F36*_xlfn.XLOOKUP(B36,CarriersTech_characteristics!$B$2:$B$8,CarriersTech_characteristics!$G$2:$G$8)*Conversions!$D$2*(1-H36) -> 77177275 | R36: =(L36*(1+M36)+N36*1000)/_xlfn.XLOOKUP(B36,CarriersTech_characteristics!$B$2:$B$8,CarriersTech_characteristics!$J$2:$J$8)/Conversions!$D$2 -> 0.0039297516 | S36: =G36*_xlfn.XLOOKUP(B36,CarriersTech_characteristics!$B$2:$B$8,CarriersTech_characteristics!$J$2:$J$8)*Conversions!$D$2 -> 6.7164587e+08
A37: 2 | B37: COKING_COAL | C37: INDIA | D37: WR | E37: =_xlfn.XLOOKUP(A37,PeriodMap!$A$2:$A$45,PeriodMap!$B$2:$B$45) -> 2024 | F37: =_xlfn.XLOOKUP(_xlfn.CONCAT($B37,$D37,$E37),PEC_ProdImpConstraints!$G$2:$G$286,PEC_ProdImpConstraints!$E$2:$E$286) -> 0 | G37: =_xlfn.XLOOKUP(_xlfn.CONCAT($B37,$D37,$E37),PEC_ProdImpConstraints!$G$2:$G$286,PEC_ProdImpConstraints!$F$2:$F$286) -> 100 | H37: 0 | I37: =_xlfn.XLOOKUP(_xlfn.CONCAT($B37,$D37,$E37),PEC_Info!$L$2:$L$301,PEC_Info!$F$2:$F$301) -> 2789.0369 | J37: =_xlfn.XLOOKUP(_xlfn.CONCAT($B37,$D37,$E37),PEC_Info!$L$2:$L$301,PEC_Info!$G$2:$G$301) -> 0.3508 | K37: =_xlfn.XLOOKUP(_xlfn.CONCAT($B37,$D37,$E37),PEC_Info!$L$2:$L$301,PEC_Info!$H$2:$H$301) -> 0 | L37: =_xlfn.XLOOKUP(_xlfn.CONCAT($B37,$D37,$E37),PEC_Info!$L$2:$L$301,PEC_Info!$I$2:$I$301) -> 21903.747 | M37: =_xlfn.XLOOKUP(_xlfn.CONCAT($B37,$D37,$E37),PEC_Info!$L$2:$L$301,PEC_Info!$J$2:$J$301) -> 0.205 | N37: =_xlfn.XLOOKUP(_xlfn.CONCAT($B37,$D37,$E37),PEC_Info!$L$2:$L$301,PEC_Info!$K$2:$K$301) -> 0 | P37: =(I37*(1+J37)+K37*1000)/_xlfn.XLOOKUP(B37,CarriersTech_characteristics!$B$2:$B$8,CarriersTech_characteristics!$G$2:$G$8)/Conversions!$D$2 -> 0.00065980588 | Q37: =F37*_xlfn.XLOOKUP(B37,CarriersTech_characteristics!$B$2:$B$8,CarriersTech_characteristics!$G$2:$G$8)*Conversions!$D$2*(1-H37) -> 0 | R37: =(L37*(1+M37)+N37*1000)/_xlfn.XLOOKUP(B37,CarriersTech_characteristics!$B$2:$B$8,CarriersTech_characteristics!$J$2:$J$8)/Conversions!$D$2 -> 0.0039297516 | S37: =G37*_xlfn.XLOOKUP(B37,CarriersTech_characteristics!$B$2:$B$8,CarriersTech_characteristics!$J$2:$J$8)*Conversions!$D$2 -> 6.7164587e+08
A38: 2 | B38: COKING_COAL | C38: INDIA | D38: NR | E38: =_xlfn.XLOOKUP(A38,PeriodMap!$A$2:$A$45,PeriodMap!$B$2:$B$45) -> 2024 | F38: =_xlfn.XLOOKUP(_xlfn.CONCAT($B38,$D38,$E38),PEC_ProdImpConstraints!$G$2:$G$286,PEC_ProdImpConstraints!$E$2:$E$286) -> 0 | G38: =_xlfn.XLOOKUP(_xlfn.CONCAT($B38,$D38,$E38),PEC_ProdImpConstraints!$G$2:$G$286,PEC_ProdImpConstraints!$F$2:$F$286) -> 0 | H38: 0 | I38: =_xlfn.XLOOKUP(_xlfn.CONCAT($B38,$D38,$E38),PEC_Info!$L$2:$L$301,PEC_Info!$F$2:$F$301) -> 2789.0369 | J38: =_xlfn.XLOOKUP(_xlfn.CONCAT($B38,$D38,$E38),PEC_Info!$L$2:$L$301,PEC_Info!$G$2:$G$301) -> 0.3508 | K38: =_xlfn.XLOOKUP(_xlfn.CONCAT($B38,$D38,$E38),PEC_Info!$L$2:$L$301,PEC_Info!$H$2:$H$301) -> 0 | L38: =_xlfn.XLOOKUP(_xlfn.CONCAT($B38,$D38,$E38),PEC_Info!$L$2:$L$301,PEC_Info!$I$2:$I$301) -> 21903.747 | M38: =_xlfn.XLOOKUP(_xlfn.CONCAT($B38,$D38,$E38),PEC_Info!$L$2:$L$301,PEC_Info!$J$2:$J$301) -> 0.205 | N38: =_xlfn.XLOOKUP(_xlfn.CONCAT($B38,$D38,$E38),PEC_Info!$L$2:$L$301,PEC_Info!$K$2:$K$301) -> 0 | P38: =(I38*(1+J38)+K38*1000)/_xlfn.XLOOKUP(B38,CarriersTech_characteristics!$B$2:$B$8,CarriersTech_characteristics!$G$2:$G$8)/Conversions!$D$2 -> 0.00065980588 | Q38: =F38*_xlfn.XLOOKUP(B38,CarriersTech_characteristics!$B$2:$B$8,CarriersTech_characteristics!$G$2:$G$8)*Conversions!$D$2*(1-H38) -> 0 | R38: =(L38*(1+M38)+N38*1000)/_xlfn.XLOOKUP(B38,CarriersTech_characteristics!$B$2:$B$8,CarriersTech_characteristics!$J$2:$J$8)/Conversions!$D$2 -> 0.0039297516 | S38: =G38*_xlfn.XLOOKUP(B38,CarriersTech_characteristics!$B$2:$B$8,CarriersTech_characteristics!$J$2:$J$8)*Conversions!$D$2 -> 0
A39: 2 | B39: COKING_COAL | C39: INDIA | D39: SR | E39: =_xlfn.XLOOKUP(A39,PeriodMap!$A$2:$A$45,PeriodMap!$B$2:$B$45) -> 2024 | F39: =_xlfn.XLOOKUP(_xlfn.CONCAT($B39,$D39,$E39),PEC_ProdImpConstraints!$G$2:$G$286,PEC_ProdImpConstraints!$E$2:$E$286) -> 0 | G39: =_xlfn.XLOOKUP(_xlfn.CONCAT($B39,$D39,$E39),PEC_ProdImpConstraints!$G$2:$G$286,PEC_ProdImpConstraints!$F$2:$F$286) -> 100 | H39: 0 | I39: =_xlfn.XLOOKUP(_xlfn.CONCAT($B39,$D39,$E39),PEC_Info!$L$2:$L$301,PEC_Info!$F$2:$F$301) -> 2789.0369 | J39: =_xlfn.XLOOKUP(_xlfn.CONCAT($B39,$D39,$E39),PEC_Info!$L$2:$L$301,PEC_Info!$G$2:$G$301) -> 0.3508 | K39: =_xlfn.XLOOKUP(_xlfn.CONCAT($B39,$D39,$E39),PEC_Info!$L$2:$L$301,PEC_Info!$H$2:$H$301) -> 0 | L39: =_xlfn.XLOOKUP(_xlfn.CONCAT($B39,$D39,$E39),PEC_Info!$L$2:$L$301,PEC_Info!$I$2:$I$301) -> 21903.747 | M39: =_xlfn.XLOOKUP(_xlfn.CONCAT($B39,$D39,$E39),PEC_Info!$L$2:$L$301,PEC_Info!$J$2:$J$301) -> 0.205 | N39: =_xlfn.XLOOKUP(_xlfn.CONCAT($B39,$D39,$E39),PEC_Info!$L$2:$L$301,PEC_Info!$K$2:$K$301) -> 0 | P39: =(I39*(1+J39)+K39*1000)/_xlfn.XLOOKUP(B39,CarriersTech_characteristics!$B$2:$B$8,CarriersTech_characteristics!$G$2:$G$8)/Conversions!$D$2 -> 0.00065980588 | Q39: =F39*_xlfn.XLOOKUP(B39,CarriersTech_characteristics!$B$2:$B$8,CarriersTech_characteristics!$G$2:$G$8)*Conversions!$D$2*(1-H39) -> 0 | R39: =(L39*(1+M39)+N39*1000)/_xlfn.XLOOKUP(B39,CarriersTech_characteristics!$B$2:$B$8,CarriersTech_characteristics!$J$2:$J$8)/Conversions!$D$2 -> 0.0039297516 | S39: =G39*_xlfn.XLOOKUP(B39,CarriersTech_characteristics!$B$2:$B$8,CarriersTech_characteristics!$J$2:$J$8)*Conversions!$D$2 -> 6.7164587e+08
A40: 2 | B40: COKING_COAL | C40: INDIA | D40: NER | E40: =_xlfn.XLOOKUP(A40,PeriodMap!$A$2:$A$45,PeriodMap!$B$2:$B$45) -> 2024 | F40: =_xlfn.XLOOKUP(_xlfn.CONCAT($B40,$D40,$E40),PEC_ProdImpConstraints!$G$2:$G$286,PEC_ProdImpConstraints!$E$2:$E$286) -> 0 | G40: =_xlfn.XLOOKUP(_xlfn.CONCAT($B40,$D40,$E40),PEC_ProdImpConstraints!$G$2:$G$286,PEC_ProdImpConstraints!$F$2:$F$286) -> 0 | H40: 0 | I40: =_xlfn.XLOOKUP(_xlfn.CONCAT($B40,$D40,$E40),PEC_Info!$L$2:$L$301,PEC_Info!$F$2:$F$301) -> 2789.0369 | J40: =_xlfn.XLOOKUP(_xlfn.CONCAT($B40,$D40,$E40),PEC_Info!$L$2:$L$301,PEC_Info!$G$2:$G$301) -> 0.3508 | K40: =_xlfn.XLOOKUP(_xlfn.CONCAT($B40,$D40,$E40),PEC_Info!$L$2:$L$301,PEC_Info!$H$2:$H$301) -> 0 | L40: =_xlfn.XLOOKUP(_xlfn.CONCAT($B40,$D40,$E40),PEC_Info!$L$2:$L$301,PEC_Info!$I$2:$I$301) -> 21903.747 | M40: =_xlfn.XLOOKUP(_xlfn.CONCAT($B40,$D40,$E40),PEC_Info!$L$2:$L$301,PEC_Info!$J$2:$J$301) -> 0.205 | N40: =_xlfn.XLOOKUP(_xlfn.CONCAT($B40,$D40,$E40),PEC_Info!$L$2:$L$301,PEC_Info!$K$2:$K$301) -> 0 | P40: =(I40*(1+J40)+K40*1000)/_xlfn.XLOOKUP(B40,CarriersTech_characteristics!$B$2:$B$8,CarriersTech_characteristics!$G$2:$G$8)/Conversions!$D$2 -> 0.00065980588 | Q40: =F40*_xlfn.XLOOKUP(B40,CarriersTech_characteristics!$B$2:$B$8,CarriersTech_characteristics!$G$2:$G$8)*Conversions!$D$2*(1-H40) -> 0 | R40: =(L40*(1+M40)+N40*1000)/_xlfn.XLOOKUP(B40,CarriersTech_characteristics!$B$2:$B$8,CarriersTech_characteristics!$J$2:$J$8)/Conversions!$D$2 -> 0.0039297516 | S40: =G40*_xlfn.XLOOKUP(B40,CarriersTech_characteristics!$B$2:$B$8,CarriersTech_characteristics!$J$2:$J$8)*Conversions!$D$2 -> 0
A41: 2 | B41: COKING_COAL | C41: INDIA | D41: ALL | E41: =_xlfn.XLOOKUP(A41,PeriodMap!$A$2:$A$45,PeriodMap!$B$2:$B$45) -> 2024 | F41: =SUM(F36:F40) -> 13.516378 | G41: =SUM(G36:G40) -> 300 | H41: =AVERAGE(H36:H40) -> 0 | I41: =AVERAGE(I36:I40) -> 2789.0369 | J41: =AVERAGE(J36:J40) -> 0.3508 | K41: =AVERAGE(K36:K40) -> 0 | L41: =AVERAGE(L36:L40) -> 21903.747 | M41: =AVERAGE(M36:M40) -> 0.205 | N41: =AVERAGE(N36:N40) -> 0 | P41: =AVERAGE(P36:P40) -> 0.00065980588 | Q41: =SUM(Q36:Q40) -> 77177275 | R41: =AVERAGE(R36:R40) -> 0.0039297516 | S41: =SUM(S36:S40) -> 2.0149376e+09
A42: 3 | B42: BIOMASS | C42: INDIA | E42: =_xlfn.XLOOKUP(A42,PeriodMap!$A$2:$A$45,PeriodMap!$B$2:$B$45) -> 2025 | F42: =_xlfn.XLOOKUP(_xlfn.CONCAT($B42,$D42,$E42),PEC_ProdImpConstraints!$G$2:$G$286,PEC_ProdImpConstraints!$E$2:$E$286) -> 270 | G42: =_xlfn.XLOOKUP(_xlfn.CONCAT($B42,$D42,$E42),PEC_ProdImpConstraints!$G$2:$G$286,PEC_ProdImpConstraints!$F$2:$F$286) -> 0 | H42: =_xlfn.XLOOKUP(_xlfn.CONCAT($B42,$D42,$E42),PEC_Info!$L$2:$L$301,PEC_Info!$E$2:$E$301) -> 0 | I42: =_xlfn.XLOOKUP(_xlfn.CONCAT($B42,$D42,$E42),PEC_Info!$L$2:$L$301,PEC_Info!$F$2:$F$301) -> 5683.2536 | J42: =_xlfn.XLOOKUP(_xlfn.CONCAT($B42,$D42,$E42),PEC_Info!$L$2:$L$301,PEC_Info!$G$2:$G$301) -> 0 | K42: =_xlfn.XLOOKUP(_xlfn.CONCAT($B42,$D42,$E42),PEC_Info!$L$2:$L$301,PEC_Info!$H$2:$H$301) -> 0 | L42: =_xlfn.XLOOKUP(_xlfn.CONCAT($B42,$D42,$E42),PEC_Info!$L$2:$L$301,PEC_Info!$I$2:$I$301) -> 5683.2536 | M42: =_xlfn.XLOOKUP(_xlfn.CONCAT($B42,$D42,$E42),PEC_Info!$L$2:$L$301,PEC_Info!$J$2:$J$301) -> 0 | N42: =_xlfn.XLOOKUP(_xlfn.CONCAT($B42,$D42,$E42),PEC_Info!$L$2:$L$301,PEC_Info!$K$2:$K$301) -> 0 | P42: =(I42*(1+J42)+K42*1000)/_xlfn.XLOOKUP(B42,CarriersTech_characteristics!$B$2:$B$8,CarriersTech_characteristics!$G$2:$G$8)/Conversions!$D$2 -> 0.0013148916 | Q42: =F42*_xlfn.XLOOKUP(B42,CarriersTech_characteristics!$B$2:$B$8,CarriersTech_characteristics!$G$2:$G$8)*Conversions!$D$2*(1-H42) -> 1.167e+09 | R42: =(L42*(1+M42)+N42*1000)/_xlfn.XLOOKUP(B42,CarriersTech_characteristics!$B$2:$B$8,CarriersTech_characteristics!$J$2:$J$8)/Conversions!$D$2 -> 0.0013148916 | S42: =G42*_xlfn.XLOOKUP(B42,CarriersTech_characteristics!$B$2:$B$8,CarriersTech_characteristics!$J$2:$J$8)*Conversions!$D$2 -> 0
A43: 3 | B43: BIOMASS_WASTE | C43: INDIA | E43: =_xlfn.XLOOKUP(A43,PeriodMap!$A$2:$A$45,PeriodMap!$B$2:$B$45) -> 2025 | F43: =_xlfn.XLOOKUP(_xlfn.CONCAT($B43,$D43,$E43),PEC_ProdImpConstraints!$G$2:$G$286,PEC_ProdImpConstraints!$E$2:$E$286) -> 175 | G43: =_xlfn.XLOOKUP(_xlfn.CONCAT($B43,$D43,$E43),PEC_ProdImpConstraints!$G$2:$G$286,PEC_ProdImpConstraints!$F$2:$F$286) -> 0 | H43: =_xlfn.XLOOKUP(_xlfn.CONCAT($B43,$D43,$E43),PEC_Info!$L$2:$L$301,PEC_Info!$E$2:$E$301) -> 0 | I43: =_xlfn.XLOOKUP(_xlfn.CONCAT($B43,$D43,$E43),PEC_Info!$L$2:$L$301,PEC_Info!$F$2:$F$301) -> 9000 | J43: =_xlfn.XLOOKUP(_xlfn.CONCAT($B43,$D43,$E43),PEC_Info!$L$2:$L$301,PEC_Info!$G$2:$G$301) -> 0.05 | K43: =_xlfn.XLOOKUP(_xlfn.CONCAT($B43,$D43,$E43),PEC_Info!$L$2:$L$301,PEC_Info!$H$2:$H$301) -> 0 | L43: =_xlfn.XLOOKUP(_xlfn.CONCAT($B43,$D43,$E43),PEC_Info!$L$2:$L$301,PEC_Info!$I$2:$I$301) -> 9000 | M43: =_xlfn.XLOOKUP(_xlfn.CONCAT($B43,$D43,$E43),PEC_Info!$L$2:$L$301,PEC_Info!$J$2:$J$301) -> 0.05 | N43: =_xlfn.XLOOKUP(_xlfn.CONCAT($B43,$D43,$E43),PEC_Info!$L$2:$L$301,PEC_Info!$K$2:$K$301) -> 0 | P43: =(I43*(1+J43)+K43*1000)/_xlfn.XLOOKUP(B43,CarriersTech_characteristics!$B$2:$B$8,CarriersTech_characteristics!$G$2:$G$8)/Conversions!$D$2 -> 0.0024924961 | Q43: =F43*_xlfn.XLOOKUP(B43,CarriersTech_characteristics!$B$2:$B$8,CarriersTech_characteristics!$G$2:$G$8)*Conversions!$D$2*(1-H43) -> 6.6349151e+08 | R43: =(L43*(1+M43)+N43*1000)/_xlfn.XLOOKUP(B43,CarriersTech_characteristics!$B$2:$B$8,CarriersTech_characteristics!$J$2:$J$8)/Conversions!$D$2 -> 0.0024924961 | S43: =G43*_xlfn.XLOOKUP(B43,CarriersTech_characteristics!$B$2:$B$8,CarriersTech_characteristics!$J$2:$J$8)*Conversions!$D$2 -> 0
A44: 3 | B44: NATGAS | C44: INDIA | E44: =_xlfn.XLOOKUP(A44,PeriodMap!$A$2:$A$45,PeriodMap!$B$2:$B$45) -> 2025 | F44: =_xlfn.XLOOKUP(_xlfn.CONCAT($B44,$D44,$E44),PEC_ProdImpConstraints!$G$2:$G$286,PEC_ProdImpConstraints!$E$2:$E$286) -> 35.007379 | G44: =_xlfn.XLOOKUP(_xlfn.CONCAT($B44,$D44,$E44),PEC_ProdImpConstraints!$G$2:$G$286,PEC_ProdImpConstraints!$F$2:$F$286) -> 200 | H44: =_xlfn.XLOOKUP(_xlfn.CONCAT($B44,$D44,$E44),PEC_Info!$L$2:$L$301,PEC_Info!$E$2:$E$301) -> 0.36749121 | I44: =_xlfn.XLOOKUP(_xlfn.CONCAT($B44,$D44,$E44),PEC_Info!$L$2:$L$301,PEC_Info!$F$2:$F$301) -> 21717.512 | J44: =_xlfn.XLOOKUP(_xlfn.CONCAT($B44,$D44,$E44),PEC_Info!$L$2:$L$301,PEC_Info!$G$2:$G$301) -> 0.24 | K44: =_xlfn.XLOOKUP(_xlfn.CONCAT($B44,$D44,$E44),PEC_Info!$L$2:$L$301,PEC_Info!$H$2:$H$301) -> 0 | L44: =_xlfn.XLOOKUP(_xlfn.CONCAT($B44,$D44,$E44),PEC_Info!$L$2:$L$301,PEC_Info!$I$2:$I$301) -> 38006.839 | M44: =_xlfn.XLOOKUP(_xlfn.CONCAT($B44,$D44,$E44),PEC_Info!$L$2:$L$301,PEC_Info!$J$2:$J$301) -> 0.349 | N44: =_xlfn.XLOOKUP(_xlfn.CONCAT($B44,$D44,$E44),PEC_Info!$L$2:$L$301,PEC_Info!$K$2:$K$301) -> 0 | P44: =(I44*(1+J44)+K44*1000)/Conversions!$D$3/_xlfn.XLOOKUP(B44,CarriersTech_characteristics!$B$2:$B$8,CarriersTech_characteristics!$G$2:$G$8)/Conversions!$D$2 -> 0.0031035233 | Q44: =F44*_xlfn.XLOOKUP(B44,CarriersTech_characteristics!$B$2:$B$8,CarriersTech_characteristics!$G$2:$G$8)*Conversions!$D$2*(1-H44) -> 2.3176529e+08 | R44: =(L44*(1+M44)+N44*1000)/Conversions!$D$3/_xlfn.XLOOKUP(B44,CarriersTech_characteristics!$B$2:$B$8,CarriersTech_characteristics!$J$2:$J$8)/Conversions!$D$2 -> 0.005908768 | S44: =G44*_xlfn.XLOOKUP(B44,CarriersTech_characteristics!$B$2:$B$8,CarriersTech_characteristics!$J$2:$J$8)*Conversions!$D$2 -> 2.0934e+09
A45: 3 | B45: THERMAL_COAL | C45: INDIA | D45: NR | E45: =_xlfn.XLOOKUP(A45,PeriodMap!$A$2:$A$45,PeriodMap!$B$2:$B$45) -> 2025 | F45: =_xlfn.XLOOKUP(_xlfn.CONCAT($B45,$D45,$E45),PEC_ProdImpConstraints!$G$2:$G$286,PEC_ProdImpConstraints!$E$2:$E$286) -> 33.144394 | G45: =_xlfn.XLOOKUP(_xlfn.CONCAT($B45,$D45,$E45),PEC_ProdImpConstraints!$G$2:$G$286,PEC_ProdImpConstraints!$F$2:$F$286) -> 0 | H45: =_xlfn.XLOOKUP(_xlfn.CONCAT($B45,$D45,$E45),PEC_Info!$L$2:$L$301,PEC_Info!$E$2:$E$301) -> 0 | I45: =_xlfn.XLOOKUP(_xlfn.CONCAT($B45,$D45,$E45),PEC_Info!$L$2:$L$301,PEC_Info!$F$2:$F$301) -> 1156.3734 | J45: =_xlfn.XLOOKUP(_xlfn.CONCAT($B45,$D45,$E45),PEC_Info!$L$2:$L$301,PEC_Info!$G$2:$G$301) -> 0.3508 | K45: =_xlfn.XLOOKUP(_xlfn.CONCAT($B45,$D45,$E45),PEC_Info!$L$2:$L$301,PEC_Info!$H$2:$H$301) -> 0 | L45: =_xlfn.XLOOKUP(_xlfn.CONCAT($B45,$D45,$E45),PEC_Info!$L$2:$L$301,PEC_Info!$I$2:$I$301) -> 9854.5983 | M45: =_xlfn.XLOOKUP(_xlfn.CONCAT($B45,$D45,$E45),PEC_Info!$L$2:$L$301,PEC_Info!$J$2:$J$301) -> 0.205 | N45: =_xlfn.XLOOKUP(_xlfn.CONCAT($B45,$D45,$E45),PEC_Info!$L$2:$L$301,PEC_Info!$K$2:$K$301) -> 0 | P45: =(I45*(1+J45)+K45*1000)/_xlfn.XLOOKUP(B45,CarriersTech_characteristics!$B$2:$B$8,CarriersTech_characteristics!$G$2:$G$8)/Conversions!$D$2 -> 0.00032679978 | Q45: =F45*_xlfn.XLOOKUP(B45,CarriersTech_characteristics!$B$2:$B$8,CarriersTech_characteristics!$G$2:$G$8)*Conversions!$D$2*(1-H45) -> 1.5842273e+08 | R45: =(L45*(1+M45)+N45*1000)/_xlfn.XLOOKUP(B45,CarriersTech_characteristics!$B$2:$B$8,CarriersTech_characteristics!$J$2:$J$8)/Conversions!$D$2 -> 0.00189083 | S45: =G45*_xlfn.XLOOKUP(B45,CarriersTech_characteristics!$B$2:$B$8,CarriersTech_characteristics!$J$2:$J$8)*Conversions!$D$2 -> 0
A46: 3 | B46: THERMAL_COAL | C46: INDIA | D46: NER | E46: =_xlfn.XLOOKUP(A46,PeriodMap!$A$2:$A$45,PeriodMap!$B$2:$B$45) -> 2025 | F46: =_xlfn.XLOOKUP(_xlfn.CONCAT($B46,$D46,$E46),PEC_ProdImpConstraints!$G$2:$G$286,PEC_ProdImpConstraints!$E$2:$E$286) -> 0 | G46: =_xlfn.XLOOKUP(_xlfn.CONCAT($B46,$D46,$E46),PEC_ProdImpConstraints!$G$2:$G$286,PEC_ProdImpConstraints!$F$2:$F$286) -> 0 | H46: =_xlfn.XLOOKUP(_xlfn.CONCAT($B46,$D46,$E46),PEC_Info!$L$2:$L$301,PEC_Info!$E$2:$E$301) -> 0 | I46: =_xlfn.XLOOKUP(_xlfn.CONCAT($B46,$D46,$E46),PEC_Info!$L$2:$L$301,PEC_Info!$F$2:$F$301) -> 1156.3734 | J46: =_xlfn.XLOOKUP(_xlfn.CONCAT($B46,$D46,$E46),PEC_Info!$L$2:$L$301,PEC_Info!$G$2:$G$301) -> 0.3508 | K46: =_xlfn.XLOOKUP(_xlfn.CONCAT($B46,$D46,$E46),PEC_Info!$L$2:$L$301,PEC_Info!$H$2:$H$301) -> 0 | L46: =_xlfn.XLOOKUP(_xlfn.CONCAT($B46,$D46,$E46),PEC_Info!$L$2:$L$301,PEC_Info!$I$2:$I$301) -> 9854.5983 | M46: =_xlfn.XLOOKUP(_xlfn.CONCAT($B46,$D46,$E46),PEC_Info!$L$2:$L$301,PEC_Info!$J$2:$J$301) -> 0.205 | N46: =_xlfn.XLOOKUP(_xlfn.CONCAT($B46,$D46,$E46),PEC_Info!$L$2:$L$301,PEC_Info!$K$2:$K$301) -> 0 | P46: =(I46*(1+J46)+K46*1000)/_xlfn.XLOOKUP(B46,CarriersTech_characteristics!$B$2:$B$8,CarriersTech_characteristics!$G$2:$G$8)/Conversions!$D$2 -> 0.00032679978 | Q46: =F46*_xlfn.XLOOKUP(B46,CarriersTech_characteristics!$B$2:$B$8,CarriersTech_characteristics!$G$2:$G$8)*Conversions!$D$2*(1-H46) -> 0 | R46: =(L46*(1+M46)+N46*1000)/_xlfn.XLOOKUP(B46,CarriersTech_characteristics!$B$2:$B$8,CarriersTech_characteristics!$J$2:$J$8)/Conversions!$D$2 -> 0.00189083 | S46: =G46*_xlfn.XLOOKUP(B46,CarriersTech_characteristics!$B$2:$B$8,CarriersTech_characteristics!$J$2:$J$8)*Conversions!$D$2 -> 0
A47: 3 | B47: THERMAL_COAL | C47: INDIA | D47: ER | E47: =_xlfn.XLOOKUP(A47,PeriodMap!$A$2:$A$45,PeriodMap!$B$2:$B$45) -> 2025 | F47: =_xlfn.XLOOKUP(_xlfn.CONCAT($B47,$D47,$E47),PEC_ProdImpConstraints!$G$2:$G$286,PEC_ProdImpConstraints!$E$2:$E$286) -> 441.69463 | G47: =_xlfn.XLOOKUP(_xlfn.CONCAT($B47,$D47,$E47),PEC_ProdImpConstraints!$G$2:$G$286,PEC_ProdImpConstraints!$F$2:$F$286) -> 150 | H47: =_xlfn.XLOOKUP(_xlfn.CONCAT($B47,$D47,$E47),PEC_Info!$L$2:$L$301,PEC_Info!$E$2:$E$301) -> 0 | I47: =_xlfn.XLOOKUP(_xlfn.CONCAT($B47,$D47,$E47),PEC_Info!$L$2:$L$301,PEC_Info!$F$2:$F$301) -> 1156.3734 | J47: =_xlfn.XLOOKUP(_xlfn.CONCAT($B47,$D47,$E47),PEC_Info!$L$2:$L$301,PEC_Info!$G$2:$G$301) -> 0.3508 | K47: =_xlfn.XLOOKUP(_xlfn.CONCAT($B47,$D47,$E47),PEC_Info!$L$2:$L$301,PEC_Info!$H$2:$H$301) -> 0 | L47: =_xlfn.XLOOKUP(_xlfn.CONCAT($B47,$D47,$E47),PEC_Info!$L$2:$L$301,PEC_Info!$I$2:$I$301) -> 9854.5983 | M47: =_xlfn.XLOOKUP(_xlfn.CONCAT($B47,$D47,$E47),PEC_Info!$L$2:$L$301,PEC_Info!$J$2:$J$301) -> 0.205 | N47: =_xlfn.XLOOKUP(_xlfn.CONCAT($B47,$D47,$E47),PEC_Info!$L$2:$L$301,PEC_Info!$K$2:$K$301) -> 0 | P47: =(I47*(1+J47)+K47*1000)/_xlfn.XLOOKUP(B47,CarriersTech_characteristics!$B$2:$B$8,CarriersTech_characteristics!$G$2:$G$8)/Conversions!$D$2 -> 0.00032679978 | Q47: =F47*_xlfn.XLOOKUP(B47,CarriersTech_characteristics!$B$2:$B$8,CarriersTech_characteristics!$G$2:$G$8)*Conversions!$D$2*(1-H47) -> 2.1112007e+09 | R47: =(L47*(1+M47)+N47*1000)/_xlfn.XLOOKUP(B47,CarriersTech_characteristics!$B$2:$B$8,CarriersTech_characteristics!$J$2:$J$8)/Conversions!$D$2 -> 0.00189083 | S47: =G47*_xlfn.XLOOKUP(B47,CarriersTech_characteristics!$B$2:$B$8,CarriersTech_characteristics!$J$2:$J$8)*Conversions!$D$2 -> 9.4203001e+08
A48: 3 | B48: THERMAL_COAL | C48: INDIA | D48: WR | E48: =_xlfn.XLOOKUP(A48,PeriodMap!$A$2:$A$45,PeriodMap!$B$2:$B$45) -> 2025 | F48: =_xlfn.XLOOKUP(_xlfn.CONCAT($B48,$D48,$E48),PEC_ProdImpConstraints!$G$2:$G$286,PEC_ProdImpConstraints!$E$2:$E$286) -> 453.06135 | G48: =_xlfn.XLOOKUP(_xlfn.CONCAT($B48,$D48,$E48),PEC_ProdImpConstraints!$G$2:$G$286,PEC_ProdImpConstraints!$F$2:$F$286) -> 150 | H48: =_xlfn.XLOOKUP(_xlfn.CONCAT($B48,$D48,$E48),PEC_Info!$L$2:$L$301,PEC_Info!$E$2:$E$301) -> 0 | I48: =_xlfn.XLOOKUP(_xlfn.CONCAT($B48,$D48,$E48),PEC_Info!$L$2:$L$301,PEC_Info!$F$2:$F$301) -> 1156.3734 | J48: =_xlfn.XLOOKUP(_xlfn.CONCAT($B48,$D48,$E48),PEC_Info!$L$2:$L$301,PEC_Info!$G$2:$G$301) -> 0.3508 | K48: =_xlfn.XLOOKUP(_xlfn.CONCAT($B48,$D48,$E48),PEC_Info!$L$2:$L$301,PEC_Info!$H$2:$H$301) -> 0 | L48: =_xlfn.XLOOKUP(_xlfn.CONCAT($B48,$D48,$E48),PEC_Info!$L$2:$L$301,PEC_Info!$I$2:$I$301) -> 9854.5983 | M48: =_xlfn.XLOOKUP(_xlfn.CONCAT($B48,$D48,$E48),PEC_Info!$L$2:$L$301,PEC_Info!$J$2:$J$301) -> 0.205 | N48: =_xlfn.XLOOKUP(_xlfn.CONCAT($B48,$D48,$E48),PEC_Info!$L$2:$L$301,PEC_Info!$K$2:$K$301) -> 0 | P48: =(I48*(1+J48)+K48*1000)/_xlfn.XLOOKUP(B48,CarriersTech_characteristics!$B$2:$B$8,CarriersTech_characteristics!$G$2:$G$8)/Conversions!$D$2 -> 0.00032679978 | Q48: =F48*_xlfn.XLOOKUP(B48,CarriersTech_characteristics!$B$2:$B$8,CarriersTech_characteristics!$G$2:$G$8)*Conversions!$D$2*(1-H48) -> 2.165531e+09 | R48: =(L48*(1+M48)+N48*1000)/_xlfn.XLOOKUP(B48,CarriersTech_characteristics!$B$2:$B$8,CarriersTech_characteristics!$J$2:$J$8)/Conversions!$D$2 -> 0.00189083 | S48: =G48*_xlfn.XLOOKUP(B48,CarriersTech_characteristics!$B$2:$B$8,CarriersTech_characteristics!$J$2:$J$8)*Conversions!$D$2 -> 9.4203001e+08
A49: 3 | B49: THERMAL_COAL | C49: INDIA | D49: SR | E49: =_xlfn.XLOOKUP(A49,PeriodMap!$A$2:$A$45,PeriodMap!$B$2:$B$45) -> 2025 | F49: =_xlfn.XLOOKUP(_xlfn.CONCAT($B49,$D49,$E49),PEC_ProdImpConstraints!$G$2:$G$286,PEC_ProdImpConstraints!$E$2:$E$286) -> 92.394226 | G49: =_xlfn.XLOOKUP(_xlfn.CONCAT($B49,$D49,$E49),PEC_ProdImpConstraints!$G$2:$G$286,PEC_ProdImpConstraints!$F$2:$F$286) -> 150 | H49: =_xlfn.XLOOKUP(_xlfn.CONCAT($B49,$D49,$E49),PEC_Info!$L$2:$L$301,PEC_Info!$E$2:$E$301) -> 0 | I49: =_xlfn.XLOOKUP(_xlfn.CONCAT($B49,$D49,$E49),PEC_Info!$L$2:$L$301,PEC_Info!$F$2:$F$301) -> 1156.3734 | J49: =_xlfn.XLOOKUP(_xlfn.CONCAT($B49,$D49,$E49),PEC_Info!$L$2:$L$301,PEC_Info!$G$2:$G$301) -> 0.3508 | K49: =_xlfn.XLOOKUP(_xlfn.CONCAT($B49,$D49,$E49),PEC_Info!$L$2:$L$301,PEC_Info!$H$2:$H$301) -> 0 | L49: =_xlfn.XLOOKUP(_xlfn.CONCAT($B49,$D49,$E49),PEC_Info!$L$2:$L$301,PEC_Info!$I$2:$I$301) -> 9854.5983 | M49: =_xlfn.XLOOKUP(_xlfn.CONCAT($B49,$D49,$E49),PEC_Info!$L$2:$L$301,PEC_Info!$J$2:$J$301) -> 0.205 | N49: =_xlfn.XLOOKUP(_xlfn.CONCAT($B49,$D49,$E49),PEC_Info!$L$2:$L$301,PEC_Info!$K$2:$K$301) -> 0 | P49: =(I49*(1+J49)+K49*1000)/_xlfn.XLOOKUP(B49,CarriersTech_characteristics!$B$2:$B$8,CarriersTech_characteristics!$G$2:$G$8)/Conversions!$D$2 -> 0.00032679978 | Q49: =F49*_xlfn.XLOOKUP(B49,CarriersTech_characteristics!$B$2:$B$8,CarriersTech_characteristics!$G$2:$G$8)*Conversions!$D$2*(1-H49) -> 4.4162356e+08 | R49: =(L49*(1+M49)+N49*1000)/_xlfn.XLOOKUP(B49,CarriersTech_characteristics!$B$2:$B$8,CarriersTech_characteristics!$J$2:$J$8)/Conversions!$D$2 -> 0.00189083 | S49: =G49*_xlfn.XLOOKUP(B49,CarriersTech_characteristics!$B$2:$B$8,CarriersTech_characteristics!$J$2:$J$8)*Conversions!$D$2 -> 9.4203001e+08
A50: 3 | B50: THERMAL_COAL | C50: INDIA | D50: ALL | E50: =_xlfn.XLOOKUP(A50,PeriodMap!$A$2:$A$45,PeriodMap!$B$2:$B$45) -> 2025 | F50: =SUM(F45:F49) -> 1020.2946 | G50: =SUM(G45:G49) -> 450 | H50: =AVERAGE(H45:H49) -> 0 | I50: =AVERAGE(I45:I49) -> 1156.3734 | J50: =AVERAGE(J45:J49) -> 0.3508 | K50: =AVERAGE(K45:K49) -> 0 | L50: =AVERAGE(L45:L49) -> 9854.5983 | M50: =AVERAGE(M45:M49) -> 0.205 | N50: =AVERAGE(N45:N49) -> 0 | P50: =AVERAGE(P45:P49) -> 0.00032679978 | Q50: =SUM(Q45:Q49) -> 4.876778e+09 | R50: =AVERAGE(R45:R49) -> 0.00189083 | S50: =SUM(S45:S49) -> 2.82609e+09
A51: 3 | B51: CRUDE | C51: INDIA | E51: =_xlfn.XLOOKUP(A51,PeriodMap!$A$2:$A$45,PeriodMap!$B$2:$B$45) -> 2025 | F51: =_xlfn.XLOOKUP(_xlfn.CONCAT($B51,$D51,$E51),PEC_ProdImpConstraints!$G$2:$G$286,PEC_ProdImpConstraints!$E$2:$E$286) -> 31.9035 | G51: =_xlfn.XLOOKUP(_xlfn.CONCAT($B51,$D51,$E51),PEC_ProdImpConstraints!$G$2:$G$286,PEC_ProdImpConstraints!$F$2:$F$286) -> 330 | H51: 0 | I51: =_xlfn.XLOOKUP(_xlfn.CONCAT($B51,$D51,$E51),PEC_Info!$L$2:$L$301,PEC_Info!$F$2:$F$301) -> 48276.56 | J51: =_xlfn.XLOOKUP(_xlfn.CONCAT($B51,$D51,$E51),PEC_Info!$L$2:$L$301,PEC_Info!$G$2:$G$301) -> 0 | K51: =_xlfn.XLOOKUP(_xlfn.CONCAT($B51,$D51,$E51),PEC_Info!$L$2:$L$301,PEC_Info!$H$2:$H$301) -> 51.2 | L51: =_xlfn.XLOOKUP(_xlfn.CONCAT($B51,$D51,$E51),PEC_Info!$L$2:$L$301,PEC_Info!$I$2:$I$301) -> 48276.56 | M51: =_xlfn.XLOOKUP(_xlfn.CONCAT($B51,$D51,$E51),PEC_Info!$L$2:$L$301,PEC_Info!$J$2:$J$301) -> 0 | N51: =_xlfn.XLOOKUP(_xlfn.CONCAT($B51,$D51,$E51),PEC_Info!$L$2:$L$301,PEC_Info!$K$2:$K$301) -> 57.2 | P51: =(I51*(1+J51)+K51*1000)/_xlfn.XLOOKUP(B51,CarriersTech_characteristics!$B$2:$B$8,CarriersTech_characteristics!$G$2:$G$8)/Conversions!$D$2 -> 0.008304315 | Q51: =F51*_xlfn.XLOOKUP(B51,CarriersTech_characteristics!$B$2:$B$8,CarriersTech_characteristics!$G$2:$G$8)*Conversions!$D$2*(1-H51) -> 3.8216884e+08 | R51: =(L51*(1+M51)+N51*1000)/_xlfn.XLOOKUP(B51,CarriersTech_characteristics!$B$2:$B$8,CarriersTech_characteristics!$J$2:$J$8)/Conversions!$D$2 -> 0.0088051957 | S51: =G51*_xlfn.XLOOKUP(B51,CarriersTech_characteristics!$B$2:$B$8,CarriersTech_characteristics!$J$2:$J$8)*Conversions!$D$2 -> 3.953037e+09
A52: 3 | B52: BIOGAS | C52: INDIA | E52: =_xlfn.XLOOKUP(A52,PeriodMap!$A$2:$A$45,PeriodMap!$B$2:$B$45) -> 2025 | F52: =_xlfn.XLOOKUP(_xlfn.CONCAT($B52,$D52,$E52),PEC_ProdImpConstraints!$G$2:$G$286,PEC_ProdImpConstraints!$E$2:$E$286) -> 87 | G52: =_xlfn.XLOOKUP(_xlfn.CONCAT($B52,$D52,$E52),PEC_ProdImpConstraints!$G$2:$G$286,PEC_ProdImpConstraints!$F$2:$F$286) -> 0 | H52: 0 | I52: =_xlfn.XLOOKUP(_xlfn.CONCAT($B52,$D52,$E52),PEC_Info!$L$2:$L$301,PEC_Info!$F$2:$F$301) -> 55747.637 | J52: =_xlfn.XLOOKUP(_xlfn.CONCAT($B52,$D52,$E52),PEC_Info!$L$2:$L$301,PEC_Info!$G$2:$G$301) -> 0.05 | K52: =_xlfn.XLOOKUP(_xlfn.CONCAT($B52,$D52,$E52),PEC_Info!$L$2:$L$301,PEC_Info!$H$2:$H$301) -> 0 | L52: =_xlfn.XLOOKUP(_xlfn.CONCAT($B52,$D52,$E52),PEC_Info!$L$2:$L$301,PEC_Info!$I$2:$I$301) -> 55747.637 | M52: =_xlfn.XLOOKUP(_xlfn.CONCAT($B52,$D52,$E52),PEC_Info!$L$2:$L$301,PEC_Info!$J$2:$J$301) -> 0.05 | N52: =_xlfn.XLOOKUP(_xlfn.CONCAT($B52,$D52,$E52),PEC_Info!$L$2:$L$301,PEC_Info!$K$2:$K$301) -> 0 | P52: =(I52*(1+J52)+K52*1000)/Conversions!$D$3/_xlfn.XLOOKUP(B52,CarriersTech_characteristics!$B$2:$B$8,CarriersTech_characteristics!$G$2:$G$8)/Conversions!$D$2 -> 0.011148819 | Q52: =F52*_xlfn.XLOOKUP(B52,CarriersTech_characteristics!$B$2:$B$8,CarriersTech_characteristics!$G$2:$G$8)*Conversions!$D$2*(1-H52) -> 5.51e+08 | R52: =(L52*(1+M52)+N52*1000)/Conversions!$D$3/_xlfn.XLOOKUP(B52,CarriersTech_characteristics!$B$2:$B$8,CarriersTech_characteristics!$J$2:$J$8)/Conversions!$D$2 -> 0.011148819 | S52: =G52*_xlfn.XLOOKUP(B52,CarriersTech_characteristics!$B$2:$B$8,CarriersTech_characteristics!$J$2:$J$8)*Conversions!$D$2 -> 0
A53: 3 | B53: COKING_COAL | C53: INDIA | D53: ER | E53: =_xlfn.XLOOKUP(A53,PeriodMap!$A$2:$A$45,PeriodMap!$B$2:$B$45) -> 2025 | F53: =_xlfn.XLOOKUP(_xlfn.CONCAT($B53,$D53,$E53),PEC_ProdImpConstraints!$G$2:$G$286,PEC_ProdImpConstraints!$E$2:$E$286) -> 14.084686 | G53: =_xlfn.XLOOKUP(_xlfn.CONCAT($B53,$D53,$E53),PEC_ProdImpConstraints!$G$2:$G$286,PEC_ProdImpConstraints!$F$2:$F$286) -> 100 | H53: 0 | I53: =_xlfn.XLOOKUP(_xlfn.CONCAT($B53,$D53,$E53),PEC_Info!$L$2:$L$301,PEC_Info!$F$2:$F$301) -> 2789.0369 | J53: =_xlfn.XLOOKUP(_xlfn.CONCAT($B53,$D53,$E53),PEC_Info!$L$2:$L$301,PEC_Info!$G$2:$G$301) -> 0.3508 | K53: =_xlfn.XLOOKUP(_xlfn.CONCAT($B53,$D53,$E53),PEC_Info!$L$2:$L$301,PEC_Info!$H$2:$H$301) -> 0 | L53: =_xlfn.XLOOKUP(_xlfn.CONCAT($B53,$D53,$E53),PEC_Info!$L$2:$L$301,PEC_Info!$I$2:$I$301) -> 21380.41 | M53: =_xlfn.XLOOKUP(_xlfn.CONCAT($B53,$D53,$E53),PEC_Info!$L$2:$L$301,PEC_Info!$J$2:$J$301) -> 0.205 | N53: =_xlfn.XLOOKUP(_xlfn.CONCAT($B53,$D53,$E53),PEC_Info!$L$2:$L$301,PEC_Info!$K$2:$K$301) -> 0 | P53: =(I53*(1+J53)+K53*1000)/_xlfn.XLOOKUP(B53,CarriersTech_characteristics!$B$2:$B$8,CarriersTech_characteristics!$G$2:$G$8)/Conversions!$D$2 -> 0.00065980588 | Q53: =F53*_xlfn.XLOOKUP(B53,CarriersTech_characteristics!$B$2:$B$8,CarriersTech_characteristics!$G$2:$G$8)*Conversions!$D$2*(1-H53) -> 80422265 | R53: =(L53*(1+M53)+N53*1000)/_xlfn.XLOOKUP(B53,CarriersTech_characteristics!$B$2:$B$8,CarriersTech_characteristics!$J$2:$J$8)/Conversions!$D$2 -> 0.0038358599 | S53: =G53*_xlfn.XLOOKUP(B53,CarriersTech_characteristics!$B$2:$B$8,CarriersTech_characteristics!$J$2:$J$8)*Conversions!$D$2 -> 6.7164587e+08
A54: 3 | B54: COKING_COAL | C54: INDIA | D54: WR | E54: =_xlfn.XLOOKUP(A54,PeriodMap!$A$2:$A$45,PeriodMap!$B$2:$B$45) -> 2025 | F54: =_xlfn.XLOOKUP(_xlfn.CONCAT($B54,$D54,$E54),PEC_ProdImpConstraints!$G$2:$G$286,PEC_ProdImpConstraints!$E$2:$E$286) -> 0 | G54: =_xlfn.XLOOKUP(_xlfn.CONCAT($B54,$D54,$E54),PEC_ProdImpConstraints!$G$2:$G$286,PEC_ProdImpConstraints!$F$2:$F$286) -> 100 | H54: 0 | I54: =_xlfn.XLOOKUP(_xlfn.CONCAT($B54,$D54,$E54),PEC_Info!$L$2:$L$301,PEC_Info!$F$2:$F$301) -> 2789.0369 | J54: =_xlfn.XLOOKUP(_xlfn.CONCAT($B54,$D54,$E54),PEC_Info!$L$2:$L$301,PEC_Info!$G$2:$G$301) -> 0.3508 | K54: =_xlfn.XLOOKUP(_xlfn.CONCAT($B54,$D54,$E54),PEC_Info!$L$2:$L$301,PEC_Info!$H$2:$H$301) -> 0 | L54: =_xlfn.XLOOKUP(_xlfn.CONCAT($B54,$D54,$E54),PEC_Info!$L$2:$L$301,PEC_Info!$I$2:$I$301) -> 21380.41 | M54: =_xlfn.XLOOKUP(_xlfn.CONCAT($B54,$D54,$E54),PEC_Info!$L$2:$L$301,PEC_Info!$J$2:$J$301) -> 0.205 | N54: =_xlfn.XLOOKUP(_xlfn.CONCAT($B54,$D54,$E54),PEC_Info!$L$2:$L$301,PEC_Info!$K$2:$K$301) -> 0 | P54: =(I54*(1+J54)+K54*1000)/_xlfn.XLOOKUP(B54,CarriersTech_characteristics!$B$2:$B$8,CarriersTech_characteristics!$G$2:$G$8)/Conversions!$D$2 -> 0.00065980588 | Q54: =F54*_xlfn.XLOOKUP(B54,CarriersTech_characteristics!$B$2:$B$8,CarriersTech_characteristics!$G$2:$G$8)*Conversions!$D$2*(1-H54) -> 0 | R54: =(L54*(1+M54)+N54*1000)/_xlfn.XLOOKUP(B54,CarriersTech_characteristics!$B$2:$B$8,CarriersTech_characteristics!$J$2:$J$8)/Conversions!$D$2 -> 0.0038358599 | S54: =G54*_xlfn.XLOOKUP(B54,CarriersTech_characteristics!$B$2:$B$8,CarriersTech_characteristics!$J$2:$J$8)*Conversions!$D$2 -> 6.7164587e+08
A55: 3 | B55: COKING_COAL | C55: INDIA | D55: NR | E55: =_xlfn.XLOOKUP(A55,PeriodMap!$A$2:$A$45,PeriodMap!$B$2:$B$45) -> 2025 | F55: =_xlfn.XLOOKUP(_xlfn.CONCAT($B55,$D55,$E55),PEC_ProdImpConstraints!$G$2:$G$286,PEC_ProdImpConstraints!$E$2:$E$286) -> 0 | G55: =_xlfn.XLOOKUP(_xlfn.CONCAT($B55,$D55,$E55),PEC_ProdImpConstraints!$G$2:$G$286,PEC_ProdImpConstraints!$F$2:$F$286) -> 0 | H55: 0 | I55: =_xlfn.XLOOKUP(_xlfn.CONCAT($B55,$D55,$E55),PEC_Info!$L$2:$L$301,PEC_Info!$F$2:$F$301) -> 2789.0369 | J55: =_xlfn.XLOOKUP(_xlfn.CONCAT($B55,$D55,$E55),PEC_Info!$L$2:$L$301,PEC_Info!$G$2:$G$301) -> 0.3508 | K55: =_xlfn.XLOOKUP(_xlfn.CONCAT($B55,$D55,$E55),PEC_Info!$L$2:$L$301,PEC_Info!$H$2:$H$301) -> 0 | L55: =_xlfn.XLOOKUP(_xlfn.CONCAT($B55,$D55,$E55),PEC_Info!$L$2:$L$301,PEC_Info!$I$2:$I$301) -> 21380.41 | M55: =_xlfn.XLOOKUP(_xlfn.CONCAT($B55,$D55,$E55),PEC_Info!$L$2:$L$301,PEC_Info!$J$2:$J$301) -> 0.205 | N55: =_xlfn.XLOOKUP(_xlfn.CONCAT($B55,$D55,$E55),PEC_Info!$L$2:$L$301,PEC_Info!$K$2:$K$301) -> 0 | P55: =(I55*(1+J55)+K55*1000)/_xlfn.XLOOKUP(B55,CarriersTech_characteristics!$B$2:$B$8,CarriersTech_characteristics!$G$2:$G$8)/Conversions!$D$2 -> 0.00065980588 | Q55: =F55*_xlfn.XLOOKUP(B55,CarriersTech_characteristics!$B$2:$B$8,CarriersTech_characteristics!$G$2:$G$8)*Conversions!$D$2*(1-H55) -> 0 | R55: =(L55*(1+M55)+N55*1000)/_xlfn.XLOOKUP(B55,CarriersTech_characteristics!$B$2:$B$8,CarriersTech_characteristics!$J$2:$J$8)/Conversions!$D$2 -> 0.0038358599 | S55: =G55*_xlfn.XLOOKUP(B55,CarriersTech_characteristics!$B$2:$B$8,CarriersTech_characteristics!$J$2:$J$8)*Conversions!$D$2 -> 0
A56: 3 | B56: COKING_COAL | C56: INDIA | D56: SR | E56: =_xlfn.XLOOKUP(A56,PeriodMap!$A$2:$A$45,PeriodMap!$B$2:$B$45) -> 2025 | F56: =_xlfn.XLOOKUP(_xlfn.CONCAT($B56,$D56,$E56),PEC_ProdImpConstraints!$G$2:$G$286,PEC_ProdImpConstraints!$E$2:$E$286) -> 0 | G56: =_xlfn.XLOOKUP(_xlfn.CONCAT($B56,$D56,$E56),PEC_ProdImpConstraints!$G$2:$G$286,PEC_ProdImpConstraints!$F$2:$F$286) -> 100 | H56: 0 | I56: =_xlfn.XLOOKUP(_xlfn.CONCAT($B56,$D56,$E56),PEC_Info!$L$2:$L$301,PEC_Info!$F$2:$F$301) -> 2789.0369 | J56: =_xlfn.XLOOKUP(_xlfn.CONCAT($B56,$D56,$E56),PEC_Info!$L$2:$L$301,PEC_Info!$G$2:$G$301) -> 0.3508 | K56: =_xlfn.XLOOKUP(_xlfn.CONCAT($B56,$D56,$E56),PEC_Info!$L$2:$L$301,PEC_Info!$H$2:$H$301) -> 0 | L56: =_xlfn.XLOOKUP(_xlfn.CONCAT($B56,$D56,$E56),PEC_Info!$L$2:$L$301,PEC_Info!$I$2:$I$301) -> 21380.41 | M56: =_xlfn.XLOOKUP(_xlfn.CONCAT($B56,$D56,$E56),PEC_Info!$L$2:$L$301,PEC_Info!$J$2:$J$301) -> 0.205 | N56: =_xlfn.XLOOKUP(_xlfn.CONCAT($B56,$D56,$E56),PEC_Info!$L$2:$L$301,PEC_Info!$K$2:$K$301) -> 0 | P56: =(I56*(1+J56)+K56*1000)/_xlfn.XLOOKUP(B56,CarriersTech_characteristics!$B$2:$B$8,CarriersTech_characteristics!$G$2:$G$8)/Conversions!$D$2 -> 0.00065980588 | Q56: =F56*_xlfn.XLOOKUP(B56,CarriersTech_characteristics!$B$2:$B$8,CarriersTech_characteristics!$G$2:$G$8)*Conversions!$D$2*(1-H56) -> 0 | R56: =(L56*(1+M56)+N56*1000)/_xlfn.XLOOKUP(B56,CarriersTech_characteristics!$B$2:$B$8,CarriersTech_characteristics!$J$2:$J$8)/Conversions!$D$2 -> 0.0038358599 | S56: =G56*_xlfn.XLOOKUP(B56,CarriersTech_characteristics!$B$2:$B$8,CarriersTech_characteristics!$J$2:$J$8)*Conversions!$D$2 -> 6.7164587e+08
A57: 3 | B57: COKING_COAL | C57: INDIA | D57: NER | E57: =_xlfn.XLOOKUP(A57,PeriodMap!$A$2:$A$45,PeriodMap!$B$2:$B$45) -> 2025 | F57: =_xlfn.XLOOKUP(_xlfn.CONCAT($B57,$D57,$E57),PEC_ProdImpConstraints!$G$2:$G$286,PEC_ProdImpConstraints!$E$2:$E$286) -> 0 | G57: =_xlfn.XLOOKUP(_xlfn.CONCAT($B57,$D57,$E57),PEC_ProdImpConstraints!$G$2:$G$286,PEC_ProdImpConstraints!$F$2:$F$286) -> 0 | H57: 0 | I57: =_xlfn.XLOOKUP(_xlfn.CONCAT($B57,$D57,$E57),PEC_Info!$L$2:$L$301,PEC_Info!$F$2:$F$301) -> 2789.0369 | J57: =_xlfn.XLOOKUP(_xlfn.CONCAT($B57,$D57,$E57),PEC_Info!$L$2:$L$301,PEC_Info!$G$2:$G$301) -> 0.3508 | K57: =_xlfn.XLOOKUP(_xlfn.CONCAT($B57,$D57,$E57),PEC_Info!$L$2:$L$301,PEC_Info!$H$2:$H$301) -> 0 | L57: =_xlfn.XLOOKUP(_xlfn.CONCAT($B57,$D57,$E57),PEC_Info!$L$2:$L$301,PEC_Info!$I$2:$I$301) -> 21380.41 | M57: =_xlfn.XLOOKUP(_xlfn.CONCAT($B57,$D57,$E57),PEC_Info!$L$2:$L$301,PEC_Info!$J$2:$J$301) -> 0.205 | N57: =_xlfn.XLOOKUP(_xlfn.CONCAT($B57,$D57,$E57),PEC_Info!$L$2:$L$301,PEC_Info!$K$2:$K$301) -> 0 | P57: =(I57*(1+J57)+K57*1000)/_xlfn.XLOOKUP(B57,CarriersTech_characteristics!$B$2:$B$8,CarriersTech_characteristics!$G$2:$G$8)/Conversions!$D$2 -> 0.00065980588 | Q57: =F57*_xlfn.XLOOKUP(B57,CarriersTech_characteristics!$B$2:$B$8,CarriersTech_characteristics!$G$2:$G$8)*Conversions!$D$2*(1-H57) -> 0 | R57: =(L57*(1+M57)+N57*1000)/_xlfn.XLOOKUP(B57,CarriersTech_characteristics!$B$2:$B$8,CarriersTech_characteristics!$J$2:$J$8)/Conversions!$D$2 -> 0.0038358599 | S57: =G57*_xlfn.XLOOKUP(B57,CarriersTech_characteristics!$B$2:$B$8,CarriersTech_characteristics!$J$2:$J$8)*Conversions!$D$2 -> 0
A58: 3 | B58: COKING_COAL | C58: INDIA | D58: ALL | E58: =_xlfn.XLOOKUP(A58,PeriodMap!$A$2:$A$45,PeriodMap!$B$2:$B$45) -> 2025 | F58: =SUM(F53:F57) -> 14.084686 | G58: =SUM(G53:G57) -> 300 | H58: =AVERAGE(H53:H57) -> 0 | I58: =AVERAGE(I53:I57) -> 2789.0369 | J58: =AVERAGE(J53:J57) -> 0.3508 | K58: =AVERAGE(K53:K57) -> 0 | L58: =AVERAGE(L53:L57) -> 21380.41 | M58: =AVERAGE(M53:M57) -> 0.205 | N58: =AVERAGE(N53:N57) -> 0 | P58: =AVERAGE(P53:P57) -> 0.00065980588 | Q58: =SUM(Q53:Q57) -> 80422265 | R58: =AVERAGE(R53:R57) -> 0.0038358599 | S58: =SUM(S53:S57) -> 2.0149376e+09
A59: 4 | B59: BIOMASS | C59: INDIA | E59: =_xlfn.XLOOKUP(A59,PeriodMap!$A$2:$A$45,PeriodMap!$B$2:$B$45) -> 2029 | F59: =_xlfn.XLOOKUP(_xlfn.CONCAT($B59,$D59,$E59),PEC_ProdImpConstraints!$G$2:$G$286,PEC_ProdImpConstraints!$E$2:$E$286) -> 270 | G59: =_xlfn.XLOOKUP(_xlfn.CONCAT($B59,$D59,$E59),PEC_ProdImpConstraints!$G$2:$G$286,PEC_ProdImpConstraints!$F$2:$F$286) -> 0 | H59: =_xlfn.XLOOKUP(_xlfn.CONCAT($B59,$D59,$E59),PEC_Info!$L$2:$L$301,PEC_Info!$E$2:$E$301) -> 0 | I59: =_xlfn.XLOOKUP(_xlfn.CONCAT($B59,$D59,$E59),PEC_Info!$L$2:$L$301,PEC_Info!$F$2:$F$301) -> 5683.2536 | J59: =_xlfn.XLOOKUP(_xlfn.CONCAT($B59,$D59,$E59),PEC_Info!$L$2:$L$301,PEC_Info!$G$2:$G$301) -> 0 | K59: =_xlfn.XLOOKUP(_xlfn.CONCAT($B59,$D59,$E59),PEC_Info!$L$2:$L$301,PEC_Info!$H$2:$H$301) -> 0 | L59: =_xlfn.XLOOKUP(_xlfn.CONCAT($B59,$D59,$E59),PEC_Info!$L$2:$L$301,PEC_Info!$I$2:$I$301) -> 5683.2536 | M59: =_xlfn.XLOOKUP(_xlfn.CONCAT($B59,$D59,$E59),PEC_Info!$L$2:$L$301,PEC_Info!$J$2:$J$301) -> 0 | N59: =_xlfn.XLOOKUP(_xlfn.CONCAT($B59,$D59,$E59),PEC_Info!$L$2:$L$301,PEC_Info!$K$2:$K$301) -> 0 | P59: =(I59*(1+J59)+K59*1000)/_xlfn.XLOOKUP(B59,CarriersTech_characteristics!$B$2:$B$8,CarriersTech_characteristics!$G$2:$G$8)/Conversions!$D$2 -> 0.0013148916 | Q59: =F59*_xlfn.XLOOKUP(B59,CarriersTech_characteristics!$B$2:$B$8,CarriersTech_characteristics!$G$2:$G$8)*Conversions!$D$2*(1-H59) -> 1.167e+09 | R59: =(L59*(1+M59)+N59*1000)/_xlfn.XLOOKUP(B59,CarriersTech_characteristics!$B$2:$B$8,CarriersTech_characteristics!$J$2:$J$8)/Conversions!$D$2 -> 0.0013148916 | S59: =G59*_xlfn.XLOOKUP(B59,CarriersTech_characteristics!$B$2:$B$8,CarriersTech_characteristics!$J$2:$J$8)*Conversions!$D$2 -> 0
A60: 4 | B60: BIOMASS_WASTE | C60: INDIA | E60: =_xlfn.XLOOKUP(A60,PeriodMap!$A$2:$A$45,PeriodMap!$B$2:$B$45) -> 2029 | F60: =_xlfn.XLOOKUP(_xlfn.CONCAT($B60,$D60,$E60),PEC_ProdImpConstraints!$G$2:$G$286,PEC_ProdImpConstraints!$E$2:$E$286) -> 175 | G60: =_xlfn.XLOOKUP(_xlfn.CONCAT($B60,$D60,$E60),PEC_ProdImpConstraints!$G$2:$G$286,PEC_ProdImpConstraints!$F$2:$F$286) -> 0 | H60: =_xlfn.XLOOKUP(_xlfn.CONCAT($B60,$D60,$E60),PEC_Info!$L$2:$L$301,PEC_Info!$E$2:$E$301) -> 0 | I60: =_xlfn.XLOOKUP(_xlfn.CONCAT($B60,$D60,$E60),PEC_Info!$L$2:$L$301,PEC_Info!$F$2:$F$301) -> 9000 | J60: =_xlfn.XLOOKUP(_xlfn.CONCAT($B60,$D60,$E60),PEC_Info!$L$2:$L$301,PEC_Info!$G$2:$G$301) -> 0.05 | K60: =_xlfn.XLOOKUP(_xlfn.CONCAT($B60,$D60,$E60),PEC_Info!$L$2:$L$301,PEC_Info!$H$2:$H$301) -> 0 | L60: =_xlfn.XLOOKUP(_xlfn.CONCAT($B60,$D60,$E60),PEC_Info!$L$2:$L$301,PEC_Info!$I$2:$I$301) -> 9000 | M60: =_xlfn.XLOOKUP(_xlfn.CONCAT($B60,$D60,$E60),PEC_Info!$L$2:$L$301,PEC_Info!$J$2:$J$301) -> 0.05 | N60: =_xlfn.XLOOKUP(_xlfn.CONCAT($B60,$D60,$E60),PEC_Info!$L$2:$L$301,PEC_Info!$K$2:$K$301) -> 0 | P60: =(I60*(1+J60)+K60*1000)/_xlfn.XLOOKUP(B60,CarriersTech_characteristics!$B$2:$B$8,CarriersTech_characteristics!$G$2:$G$8)/Conversions!$D$2 -> 0.0024924961 | Q60: =F60*_xlfn.XLOOKUP(B60,CarriersTech_characteristics!$B$2:$B$8,CarriersTech_characteristics!$G$2:$G$8)*Conversions!$D$2*(1-H60) -> 6.6349151e+08 | R60: =(L60*(1+M60)+N60*1000)/_xlfn.XLOOKUP(B60,CarriersTech_characteristics!$B$2:$B$8,CarriersTech_characteristics!$J$2:$J$8)/Conversions!$D$2 -> 0.0024924961 | S60: =G60*_xlfn.XLOOKUP(B60,CarriersTech_characteristics!$B$2:$B$8,CarriersTech_characteristics!$J$2:$J$8)*Conversions!$D$2 -> 0
A61: 4 | B61: NATGAS | C61: INDIA | E61: =_xlfn.XLOOKUP(A61,PeriodMap!$A$2:$A$45,PeriodMap!$B$2:$B$45) -> 2029 | F61: =_xlfn.XLOOKUP(_xlfn.CONCAT($B61,$D61,$E61),PEC_ProdImpConstraints!$G$2:$G$286,PEC_ProdImpConstraints!$E$2:$E$286) -> 37.893113 | G61: =_xlfn.XLOOKUP(_xlfn.CONCAT($B61,$D61,$E61),PEC_ProdImpConstraints!$G$2:$G$286,PEC_ProdImpConstraints!$F$2:$F$286) -> 200 | H61: =_xlfn.XLOOKUP(_xlfn.CONCAT($B61,$D61,$E61),PEC_Info!$L$2:$L$301,PEC_Info!$E$2:$E$301) -> 0.36749121 | I61: =_xlfn.XLOOKUP(_xlfn.CONCAT($B61,$D61,$E61),PEC_Info!$L$2:$L$301,PEC_Info!$F$2:$F$301) -> 23163.611 | J61: =_xlfn.XLOOKUP(_xlfn.CONCAT($B61,$D61,$E61),PEC_Info!$L$2:$L$301,PEC_Info!$G$2:$G$301) -> 0.24 | K61: =_xlfn.XLOOKUP(_xlfn.CONCAT($B61,$D61,$E61),PEC_Info!$L$2:$L$301,PEC_Info!$H$2:$H$301) -> 0 | L61: =_xlfn.XLOOKUP(_xlfn.CONCAT($B61,$D61,$E61),PEC_Info!$L$2:$L$301,PEC_Info!$I$2:$I$301) -> 29177.62 | M61: =_xlfn.XLOOKUP(_xlfn.CONCAT($B61,$D61,$E61),PEC_Info!$L$2:$L$301,PEC_Info!$J$2:$J$301) -> 0.349 | N61: =_xlfn.XLOOKUP(_xlfn.CONCAT($B61,$D61,$E61),PEC_Info!$L$2:$L$301,PEC_Info!$K$2:$K$301) -> 0 | P61: =(I61*(1+J61)+K61*1000)/Conversions!$D$3/_xlfn.XLOOKUP(B61,CarriersTech_characteristics!$B$2:$B$8,CarriersTech_characteristics!$G$2:$G$8)/Conversions!$D$2 -> 0.0033101768 | Q61: =F61*_xlfn.XLOOKUP(B61,CarriersTech_characteristics!$B$2:$B$8,CarriersTech_characteristics!$G$2:$G$8)*Conversions!$D$2*(1-H61) -> 2.508702e+08 | R61: =(L61*(1+M61)+N61*1000)/Conversions!$D$3/_xlfn.XLOOKUP(B61,CarriersTech_characteristics!$B$2:$B$8,CarriersTech_characteristics!$J$2:$J$8)/Conversions!$D$2 -> 0.0045361254 | S61: =G61*_xlfn.XLOOKUP(B61,CarriersTech_characteristics!$B$2:$B$8,CarriersTech_characteristics!$J$2:$J$8)*Conversions!$D$2 -> 2.0934e+09
A62: 4 | B62: THERMAL_COAL | C62: INDIA | D62: NR | E62: =_xlfn.XLOOKUP(A62,PeriodMap!$A$2:$A$45,PeriodMap!$B$2:$B$45) -> 2029 | F62: =_xlfn.XLOOKUP(_xlfn.CONCAT($B62,$D62,$E62),PEC_ProdImpConstraints!$G$2:$G$286,PEC_ProdImpConstraints!$E$2:$E$286) -> 38.514544 | G62: =_xlfn.XLOOKUP(_xlfn.CONCAT($B62,$D62,$E62),PEC_ProdImpConstraints!$G$2:$G$286,PEC_ProdImpConstraints!$F$2:$F$286) -> 0 | H62: =_xlfn.XLOOKUP(_xlfn.CONCAT($B62,$D62,$E62),PEC_Info!$L$2:$L$301,PEC_Info!$E$2:$E$301) -> 0 | I62: =_xlfn.XLOOKUP(_xlfn.CONCAT($B62,$D62,$E62),PEC_Info!$L$2:$L$301,PEC_Info!$F$2:$F$301) -> 1156.3734 | J62: =_xlfn.XLOOKUP(_xlfn.CONCAT($B62,$D62,$E62),PEC_Info!$L$2:$L$301,PEC_Info!$G$2:$G$301) -> 0.3508 | K62: =_xlfn.XLOOKUP(_xlfn.CONCAT($B62,$D62,$E62),PEC_Info!$L$2:$L$301,PEC_Info!$H$2:$H$301) -> 0 | L62: =_xlfn.XLOOKUP(_xlfn.CONCAT($B62,$D62,$E62),PEC_Info!$L$2:$L$301,PEC_Info!$I$2:$I$301) -> 8919.5272 | M62: =_xlfn.XLOOKUP(_xlfn.CONCAT($B62,$D62,$E62),PEC_Info!$L$2:$L$301,PEC_Info!$J$2:$J$301) -> 0.205 | N62: =_xlfn.XLOOKUP(_xlfn.CONCAT($B62,$D62,$E62),PEC_Info!$L$2:$L$301,PEC_Info!$K$2:$K$301) -> 0 | P62: =(I62*(1+J62)+K62*1000)/_xlfn.XLOOKUP(B62,CarriersTech_characteristics!$B$2:$B$8,CarriersTech_characteristics!$G$2:$G$8)/Conversions!$D$2 -> 0.00032679978 | Q62: =F62*_xlfn.XLOOKUP(B62,CarriersTech_characteristics!$B$2:$B$8,CarriersTech_characteristics!$G$2:$G$8)*Conversions!$D$2*(1-H62) -> 1.8409083e+08 | R62: =(L62*(1+M62)+N62*1000)/_xlfn.XLOOKUP(B62,CarriersTech_characteristics!$B$2:$B$8,CarriersTech_characteristics!$J$2:$J$8)/Conversions!$D$2 -> 0.0017114153 | S62: =G62*_xlfn.XLOOKUP(B62,CarriersTech_characteristics!$B$2:$B$8,CarriersTech_characteristics!$J$2:$J$8)*Conversions!$D$2 -> 0
A63: 4 | B63: THERMAL_COAL | C63: INDIA | D63: NER | E63: =_xlfn.XLOOKUP(A63,PeriodMap!$A$2:$A$45,PeriodMap!$B$2:$B$45) -> 2029 | F63: =_xlfn.XLOOKUP(_xlfn.CONCAT($B63,$D63,$E63),PEC_ProdImpConstraints!$G$2:$G$286,PEC_ProdImpConstraints!$E$2:$E$286) -> 0 | G63: =_xlfn.XLOOKUP(_xlfn.CONCAT($B63,$D63,$E63),PEC_ProdImpConstraints!$G$2:$G$286,PEC_ProdImpConstraints!$F$2:$F$286) -> 0 | H63: =_xlfn.XLOOKUP(_xlfn.CONCAT($B63,$D63,$E63),PEC_Info!$L$2:$L$301,PEC_Info!$E$2:$E$301) -> 0 | I63: =_xlfn.XLOOKUP(_xlfn.CONCAT($B63,$D63,$E63),PEC_Info!$L$2:$L$301,PEC_Info!$F$2:$F$301) -> 1156.3734 | J63: =_xlfn.XLOOKUP(_xlfn.CONCAT($B63,$D63,$E63),PEC_Info!$L$2:$L$301,PEC_Info!$G$2:$G$301) -> 0.3508 | K63: =_xlfn.XLOOKUP(_xlfn.CONCAT($B63,$D63,$E63),PEC_Info!$L$2:$L$301,PEC_Info!$H$2:$H$301) -> 0 | L63: =_xlfn.XLOOKUP(_xlfn.CONCAT($B63,$D63,$E63),PEC_Info!$L$2:$L$301,PEC_Info!$I$2:$I$301) -> 8919.5272 | M63: =_xlfn.XLOOKUP(_xlfn.CONCAT($B63,$D63,$E63),PEC_Info!$L$2:$L$301,PEC_Info!$J$2:$J$301) -> 0.205 | N63: =_xlfn.XLOOKUP(_xlfn.CONCAT($B63,$D63,$E63),PEC_Info!$L$2:$L$301,PEC_Info!$K$2:$K$301) -> 0 | P63: =(I63*(1+J63)+K63*1000)/_xlfn.XLOOKUP(B63,CarriersTech_characteristics!$B$2:$B$8,CarriersTech_characteristics!$G$2:$G$8)/Conversions!$D$2 -> 0.00032679978 | Q63: =F63*_xlfn.XLOOKUP(B63,CarriersTech_characteristics!$B$2:$B$8,CarriersTech_characteristics!$G$2:$G$8)*Conversions!$D$2*(1-H63) -> 0 | R63: =(L63*(1+M63)+N63*1000)/_xlfn.XLOOKUP(B63,CarriersTech_characteristics!$B$2:$B$8,CarriersTech_characteristics!$J$2:$J$8)/Conversions!$D$2 -> 0.0017114153 | S63: =G63*_xlfn.XLOOKUP(B63,CarriersTech_characteristics!$B$2:$B$8,CarriersTech_characteristics!$J$2:$J$8)*Conversions!$D$2 -> 0
A64: 4 | B64: THERMAL_COAL | C64: INDIA | D64: ER | E64: =_xlfn.XLOOKUP(A64,PeriodMap!$A$2:$A$45,PeriodMap!$B$2:$B$45) -> 2029 | F64: =_xlfn.XLOOKUP(_xlfn.CONCAT($B64,$D64,$E64),PEC_ProdImpConstraints!$G$2:$G$286,PEC_ProdImpConstraints!$E$2:$E$286) -> 551.48905 | G64: =_xlfn.XLOOKUP(_xlfn.CONCAT($B64,$D64,$E64),PEC_ProdImpConstraints!$G$2:$G$286,PEC_ProdImpConstraints!$F$2:$F$286) -> 150 | H64: =_xlfn.XLOOKUP(_xlfn.CONCAT($B64,$D64,$E64),PEC_Info!$L$2:$L$301,PEC_Info!$E$2:$E$301) -> 0 | I64: =_xlfn.XLOOKUP(_xlfn.CONCAT($B64,$D64,$E64),PEC_Info!$L$2:$L$301,PEC_Info!$F$2:$F$301) -> 1156.3734 | J64: =_xlfn.XLOOKUP(_xlfn.CONCAT($B64,$D64,$E64),PEC_Info!$L$2:$L$301,PEC_Info!$G$2:$G$301) -> 0.3508 | K64: =_xlfn.XLOOKUP(_xlfn.CONCAT($B64,$D64,$E64),PEC_Info!$L$2:$L$301,PEC_Info!$H$2:$H$301) -> 0 | L64: =_xlfn.XLOOKUP(_xlfn.CONCAT($B64,$D64,$E64),PEC_Info!$L$2:$L$301,PEC_Info!$I$2:$I$301) -> 8919.5272 | M64: =_xlfn.XLOOKUP(_xlfn.CONCAT($B64,$D64,$E64),PEC_Info!$L$2:$L$301,PEC_Info!$J$2:$J$301) -> 0.205 | N64: =_xlfn.XLOOKUP(_xlfn.CONCAT($B64,$D64,$E64),PEC_Info!$L$2:$L$301,PEC_Info!$K$2:$K$301) -> 0 | P64: =(I64*(1+J64)+K64*1000)/_xlfn.XLOOKUP(B64,CarriersTech_characteristics!$B$2:$B$8,CarriersTech_characteristics!$G$2:$G$8)/Conversions!$D$2 -> 0.00032679978 | Q64: =F64*_xlfn.XLOOKUP(B64,CarriersTech_characteristics!$B$2:$B$8,CarriersTech_characteristics!$G$2:$G$8)*Conversions!$D$2*(1-H64) -> 2.6359933e+09 | R64: =(L64*(1+M64)+N64*1000)/_xlfn.XLOOKUP(B64,CarriersTech_characteristics!$B$2:$B$8,CarriersTech_characteristics!$J$2:$J$8)/Conversions!$D$2 -> 0.0017114153 | S64: =G64*_xlfn.XLOOKUP(B64,CarriersTech_characteristics!$B$2:$B$8,CarriersTech_characteristics!$J$2:$J$8)*Conversions!$D$2 -> 9.4203001e+08
A65: 4 | B65: THERMAL_COAL | C65: INDIA | D65: WR | E65: =_xlfn.XLOOKUP(A65,PeriodMap!$A$2:$A$45,PeriodMap!$B$2:$B$45) -> 2029 | F65: =_xlfn.XLOOKUP(_xlfn.CONCAT($B65,$D65,$E65),PEC_ProdImpConstraints!$G$2:$G$286,PEC_ProdImpConstraints!$E$2:$E$286) -> 561.8074 | G65: =_xlfn.XLOOKUP(_xlfn.CONCAT($B65,$D65,$E65),PEC_ProdImpConstraints!$G$2:$G$286,PEC_ProdImpConstraints!$F$2:$F$286) -> 150 | H65: =_xlfn.XLOOKUP(_xlfn.CONCAT($B65,$D65,$E65),PEC_Info!$L$2:$L$301,PEC_Info!$E$2:$E$301) -> 0 | I65: =_xlfn.XLOOKUP(_xlfn.CONCAT($B65,$D65,$E65),PEC_Info!$L$2:$L$301,PEC_Info!$F$2:$F$301) -> 1156.3734 | J65: =_xlfn.XLOOKUP(_xlfn.CONCAT($B65,$D65,$E65),PEC_Info!$L$2:$L$301,PEC_Info!$G$2:$G$301) -> 0.3508 | K65: =_xlfn.XLOOKUP(_xlfn.CONCAT($B65,$D65,$E65),PEC_Info!$L$2:$L$301,PEC_Info!$H$2:$H$301) -> 0 | L65: =_xlfn.XLOOKUP(_xlfn.CONCAT($B65,$D65,$E65),PEC_Info!$L$2:$L$301,PEC_Info!$I$2:$I$301) -> 8919.5272 | M65: =_xlfn.XLOOKUP(_xlfn.CONCAT($B65,$D65,$E65),PEC_Info!$L$2:$L$301,PEC_Info!$J$2:$J$301) -> 0.205 | N65: =_xlfn.XLOOKUP(_xlfn.CONCAT($B65,$D65,$E65),PEC_Info!$L$2:$L$301,PEC_Info!$K$2:$K$301) -> 0 | P65: =(I65*(1+J65)+K65*1000)/_xlfn.XLOOKUP(B65,CarriersTech_characteristics!$B$2:$B$8,CarriersTech_characteristics!$G$2:$G$8)/Conversions!$D$2 -> 0.00032679978 | Q65: =F65*_xlfn.XLOOKUP(B65,CarriersTech_characteristics!$B$2:$B$8,CarriersTech_characteristics!$G$2:$G$8)*Conversions!$D$2*(1-H65) -> 2.6853126e+09 | R65: =(L65*(1+M65)+N65*1000)/_xlfn.XLOOKUP(B65,CarriersTech_characteristics!$B$2:$B$8,CarriersTech_characteristics!$J$2:$J$8)/Conversions!$D$2 -> 0.0017114153 | S65: =G65*_xlfn.XLOOKUP(B65,CarriersTech_characteristics!$B$2:$B$8,CarriersTech_characteristics!$J$2:$J$8)*Conversions!$D$2 -> 9.4203001e+08
A66: 4 | B66: THERMAL_COAL | C66: INDIA | D66: SR | E66: =_xlfn.XLOOKUP(A66,PeriodMap!$A$2:$A$45,PeriodMap!$B$2:$B$45) -> 2029 | F66: =_xlfn.XLOOKUP(_xlfn.CONCAT($B66,$D66,$E66),PEC_ProdImpConstraints!$G$2:$G$286,PEC_ProdImpConstraints!$E$2:$E$286) -> 94.921365 | G66: =_xlfn.XLOOKUP(_xlfn.CONCAT($B66,$D66,$E66),PEC_ProdImpConstraints!$G$2:$G$286,PEC_ProdImpConstraints!$F$2:$F$286) -> 150 | H66: =_xlfn.XLOOKUP(_xlfn.CONCAT($B66,$D66,$E66),PEC_Info!$L$2:$L$301,PEC_Info!$E$2:$E$301) -> 0 | I66: =_xlfn.XLOOKUP(_xlfn.CONCAT($B66,$D66,$E66),PEC_Info!$L$2:$L$301,PEC_Info!$F$2:$F$301) -> 1156.3734 | J66: =_xlfn.XLOOKUP(_xlfn.CONCAT($B66,$D66,$E66),PEC_Info!$L$2:$L$301,PEC_Info!$G$2:$G$301) -> 0.3508 | K66: =_xlfn.XLOOKUP(_xlfn.CONCAT($B66,$D66,$E66),PEC_Info!$L$2:$L$301,PEC_Info!$H$2:$H$301) -> 0 | L66: =_xlfn.XLOOKUP(_xlfn.CONCAT($B66,$D66,$E66),PEC_Info!$L$2:$L$301,PEC_Info!$I$2:$I$301) -> 8919.5272 | M66: =_xlfn.XLOOKUP(_xlfn.CONCAT($B66,$D66,$E66),PEC_Info!$L$2:$L$301,PEC_Info!$J$2:$J$301) -> 0.205 | N66: =_xlfn.XLOOKUP(_xlfn.CONCAT($B66,$D66,$E66),PEC_Info!$L$2:$L$301,PEC_Info!$K$2:$K$301) -> 0 | P66: =(I66*(1+J66)+K66*1000)/_xlfn.XLOOKUP(B66,CarriersTech_characteristics!$B$2:$B$8,CarriersTech_characteristics!$G$2:$G$8)/Conversions!$D$2 -> 0.00032679978 | Q66: =F66*_xlfn.XLOOKUP(B66,CarriersTech_characteristics!$B$2:$B$8,CarriersTech_characteristics!$G$2:$G$8)*Conversions!$D$2*(1-H66) -> 4.5370271e+08 | R66: =(L66*(1+M66)+N66*1000)/_xlfn.XLOOKUP(B66,CarriersTech_characteristics!$B$2:$B$8,CarriersTech_characteristics!$J$2:$J$8)/Conversions!$D$2 -> 0.0017114153 | S66: =G66*_xlfn.XLOOKUP(B66,CarriersTech_characteristics!$B$2:$B$8,CarriersTech_characteristics!$J$2:$J$8)*Conversions!$D$2 -> 9.4203001e+08
A67: 4 | B67: THERMAL_COAL | C67: INDIA | D67: ALL | E67: =_xlfn.XLOOKUP(A67,PeriodMap!$A$2:$A$45,PeriodMap!$B$2:$B$45) -> 2029 | F67: =SUM(F62:F66) -> 1246.7324 | G67: =SUM(G62:G66) -> 450 | H67: =AVERAGE(H62:H66) -> 0 | I67: =AVERAGE(I62:I66) -> 1156.3734 | J67: =AVERAGE(J62:J66) -> 0.3508 | K67: =AVERAGE(K62:K66) -> 0 | L67: =AVERAGE(L62:L66) -> 8919.5272 | M67: =AVERAGE(M62:M66) -> 0.205 | N67: =AVERAGE(N62:N66) -> 0 | P67: =AVERAGE(P62:P66) -> 0.00032679978 | Q67: =SUM(Q62:Q66) -> 5.9590994e+09 | R67: =AVERAGE(R62:R66) -> 0.0017114153 | S67: =SUM(S62:S66) -> 2.82609e+09
A68: 4 | B68: CRUDE | C68: INDIA | E68: =_xlfn.XLOOKUP(A68,PeriodMap!$A$2:$A$45,PeriodMap!$B$2:$B$45) -> 2029 | F68: =_xlfn.XLOOKUP(_xlfn.CONCAT($B68,$D68,$E68),PEC_ProdImpConstraints!$G$2:$G$286,PEC_ProdImpConstraints!$E$2:$E$286) -> 31.9035 | G68: =_xlfn.XLOOKUP(_xlfn.CONCAT($B68,$D68,$E68),PEC_ProdImpConstraints!$G$2:$G$286,PEC_ProdImpConstraints!$F$2:$F$286) -> 330 | H68: 0 | I68: =_xlfn.XLOOKUP(_xlfn.CONCAT($B68,$D68,$E68),PEC_Info!$L$2:$L$301,PEC_Info!$F$2:$F$301) -> 52778.948 | J68: =_xlfn.XLOOKUP(_xlfn.CONCAT($B68,$D68,$E68),PEC_Info!$L$2:$L$301,PEC_Info!$G$2:$G$301) -> 0 | K68: =_xlfn.XLOOKUP(_xlfn.CONCAT($B68,$D68,$E68),PEC_Info!$L$2:$L$301,PEC_Info!$H$2:$H$301) -> 51.2 | L68: =_xlfn.XLOOKUP(_xlfn.CONCAT($B68,$D68,$E68),PEC_Info!$L$2:$L$301,PEC_Info!$I$2:$I$301) -> 52778.948 | M68: =_xlfn.XLOOKUP(_xlfn.CONCAT($B68,$D68,$E68),PEC_Info!$L$2:$L$301,PEC_Info!$J$2:$J$301) -> 0 | N68: =_xlfn.XLOOKUP(_xlfn.CONCAT($B68,$D68,$E68),PEC_Info!$L$2:$L$301,PEC_Info!$K$2:$K$301) -> 57.2 | P68: =(I68*(1+J68)+K68*1000)/_xlfn.XLOOKUP(B68,CarriersTech_characteristics!$B$2:$B$8,CarriersTech_characteristics!$G$2:$G$8)/Conversions!$D$2 -> 0.0086801749 | Q68: =F68*_xlfn.XLOOKUP(B68,CarriersTech_characteristics!$B$2:$B$8,CarriersTech_characteristics!$G$2:$G$8)*Conversions!$D$2*(1-H68) -> 3.8216884e+08 | R68: =(L68*(1+M68)+N68*1000)/_xlfn.XLOOKUP(B68,CarriersTech_characteristics!$B$2:$B$8,CarriersTech_characteristics!$J$2:$J$8)/Conversions!$D$2 -> 0.0091810556 | S68: =G68*_xlfn.XLOOKUP(B68,CarriersTech_characteristics!$B$2:$B$8,CarriersTech_characteristics!$J$2:$J$8)*Conversions!$D$2 -> 3.953037e+09
A69: 4 | B69: BIOGAS | C69: INDIA | E69: =_xlfn.XLOOKUP(A69,PeriodMap!$A$2:$A$45,PeriodMap!$B$2:$B$45) -> 2029 | F69: =_xlfn.XLOOKUP(_xlfn.CONCAT($B69,$D69,$E69),PEC_ProdImpConstraints!$G$2:$G$286,PEC_ProdImpConstraints!$E$2:$E$286) -> 87 | G69: =_xlfn.XLOOKUP(_xlfn.CONCAT($B69,$D69,$E69),PEC_ProdImpConstraints!$G$2:$G$286,PEC_ProdImpConstraints!$F$2:$F$286) -> 0 | H69: 0 | I69: =_xlfn.XLOOKUP(_xlfn.CONCAT($B69,$D69,$E69),PEC_Info!$L$2:$L$301,PEC_Info!$F$2:$F$301) -> 55747.637 | J69: =_xlfn.XLOOKUP(_xlfn.CONCAT($B69,$D69,$E69),PEC_Info!$L$2:$L$301,PEC_Info!$G$2:$G$301) -> 0.05 | K69: =_xlfn.XLOOKUP(_xlfn.CONCAT($B69,$D69,$E69),PEC_Info!$L$2:$L$301,PEC_Info!$H$2:$H$301) -> 0 | L69: =_xlfn.XLOOKUP(_xlfn.CONCAT($B69,$D69,$E69),PEC_Info!$L$2:$L$301,PEC_Info!$I$2:$I$301) -> 55747.637 | M69: =_xlfn.XLOOKUP(_xlfn.CONCAT($B69,$D69,$E69),PEC_Info!$L$2:$L$301,PEC_Info!$J$2:$J$301) -> 0.05 | N69: =_xlfn.XLOOKUP(_xlfn.CONCAT($B69,$D69,$E69),PEC_Info!$L$2:$L$301,PEC_Info!$K$2:$K$301) -> 0 | P69: =(I69*(1+J69)+K69*1000)/Conversions!$D$3/_xlfn.XLOOKUP(B69,CarriersTech_characteristics!$B$2:$B$8,CarriersTech_characteristics!$G$2:$G$8)/Conversions!$D$2 -> 0.011148819 | Q69: =F69*_xlfn.XLOOKUP(B69,CarriersTech_characteristics!$B$2:$B$8,CarriersTech_characteristics!$G$2:$G$8)*Conversions!$D$2*(1-H69) -> 5.51e+08 | R69: =(L69*(1+M69)+N69*1000)/Conversions!$D$3/_xlfn.XLOOKUP(B69,CarriersTech_characteristics!$B$2:$B$8,CarriersTech_characteristics!$J$2:$J$8)/Conversions!$D$2 -> 0.011148819 | S69: =G69*_xlfn.XLOOKUP(B69,CarriersTech_characteristics!$B$2:$B$8,CarriersTech_characteristics!$J$2:$J$8)*Conversions!$D$2 -> 0
A70: 4 | B70: COKING_COAL | C70: INDIA | D70: ER | E70: =_xlfn.XLOOKUP(A70,PeriodMap!$A$2:$A$45,PeriodMap!$B$2:$B$45) -> 2029 | F70: =_xlfn.XLOOKUP(_xlfn.CONCAT($B70,$D70,$E70),PEC_ProdImpConstraints!$G$2:$G$286,PEC_ProdImpConstraints!$E$2:$E$286) -> 16.607131 | G70: =_xlfn.XLOOKUP(_xlfn.CONCAT($B70,$D70,$E70),PEC_ProdImpConstraints!$G$2:$G$286,PEC_ProdImpConstraints!$F$2:$F$286) -> 100 | H70: 0 | I70: =_xlfn.XLOOKUP(_xlfn.CONCAT($B70,$D70,$E70),PEC_Info!$L$2:$L$301,PEC_Info!$F$2:$F$301) -> 2789.0369 | J70: =_xlfn.XLOOKUP(_xlfn.CONCAT($B70,$D70,$E70),PEC_Info!$L$2:$L$301,PEC_Info!$G$2:$G$301) -> 0.3508 | K70: =_xlfn.XLOOKUP(_xlfn.CONCAT($B70,$D70,$E70),PEC_Info!$L$2:$L$301,PEC_Info!$H$2:$H$301) -> 0 | L70: =_xlfn.XLOOKUP(_xlfn.CONCAT($B70,$D70,$E70),PEC_Info!$L$2:$L$301,PEC_Info!$I$2:$I$301) -> 19351.692 | M70: =_xlfn.XLOOKUP(_xlfn.CONCAT($B70,$D70,$E70),PEC_Info!$L$2:$L$301,PEC_Info!$J$2:$J$301) -> 0.205 | N70: =_xlfn.XLOOKUP(_xlfn.CONCAT($B70,$D70,$E70),PEC_Info!$L$2:$L$301,PEC_Info!$K$2:$K$301) -> 0 | P70: =(I70*(1+J70)+K70*1000)/_xlfn.XLOOKUP(B70,CarriersTech_characteristics!$B$2:$B$8,CarriersTech_characteristics!$G$2:$G$8)/Conversions!$D$2 -> 0.00065980588 | Q70: =F70*_xlfn.XLOOKUP(B70,CarriersTech_characteristics!$B$2:$B$8,CarriersTech_characteristics!$G$2:$G$8)*Conversions!$D$2*(1-H70) -> 94825191 | R70: =(L70*(1+M70)+N70*1000)/_xlfn.XLOOKUP(B70,CarriersTech_characteristics!$B$2:$B$8,CarriersTech_characteristics!$J$2:$J$8)/Conversions!$D$2 -> 0.0034718875 | S70: =G70*_xlfn.XLOOKUP(B70,CarriersTech_characteristics!$B$2:$B$8,CarriersTech_characteristics!$J$2:$J$8)*Conversions!$D$2 -> 6.7164587e+08
A71: 4 | B71: COKING_COAL | C71: INDIA | D71: WR | E71: =_xlfn.XLOOKUP(A71,PeriodMap!$A$2:$A$45,PeriodMap!$B$2:$B$45) -> 2029 | F71: =_xlfn.XLOOKUP(_xlfn.CONCAT($B71,$D71,$E71),PEC_ProdImpConstraints!$G$2:$G$286,PEC_ProdImpConstraints!$E$2:$E$286) -> 0 | G71: =_xlfn.XLOOKUP(_xlfn.CONCAT($B71,$D71,$E71),PEC_ProdImpConstraints!$G$2:$G$286,PEC_ProdImpConstraints!$F$2:$F$286) -> 100 | H71: 0 | I71: =_xlfn.XLOOKUP(_xlfn.CONCAT($B71,$D71,$E71),PEC_Info!$L$2:$L$301,PEC_Info!$F$2:$F$301) -> 2789.0369 | J71: =_xlfn.XLOOKUP(_xlfn.CONCAT($B71,$D71,$E71),PEC_Info!$L$2:$L$301,PEC_Info!$G$2:$G$301) -> 0.3508 | K71: =_xlfn.XLOOKUP(_xlfn.CONCAT($B71,$D71,$E71),PEC_Info!$L$2:$L$301,PEC_Info!$H$2:$H$301) -> 0 | L71: =_xlfn.XLOOKUP(_xlfn.CONCAT($B71,$D71,$E71),PEC_Info!$L$2:$L$301,PEC_Info!$I$2:$I$301) -> 19351.692 | M71: =_xlfn.XLOOKUP(_xlfn.CONCAT($B71,$D71,$E71),PEC_Info!$L$2:$L$301,PEC_Info!$J$2:$J$301) -> 0.205 | N71: =_xlfn.XLOOKUP(_xlfn.CONCAT($B71,$D71,$E71),PEC_Info!$L$2:$L$301,PEC_Info!$K$2:$K$301) -> 0 | P71: =(I71*(1+J71)+K71*1000)/_xlfn.XLOOKUP(B71,CarriersTech_characteristics!$B$2:$B$8,CarriersTech_characteristics!$G$2:$G$8)/Conversions!$D$2 -> 0.00065980588 | Q71: =F71*_xlfn.XLOOKUP(B71,CarriersTech_characteristics!$B$2:$B$8,CarriersTech_characteristics!$G$2:$G$8)*Conversions!$D$2*(1-H71) -> 0 | R71: =(L71*(1+M71)+N71*1000)/_xlfn.XLOOKUP(B71,CarriersTech_characteristics!$B$2:$B$8,CarriersTech_characteristics!$J$2:$J$8)/Conversions!$D$2 -> 0.0034718875 | S71: =G71*_xlfn.XLOOKUP(B71,CarriersTech_characteristics!$B$2:$B$8,CarriersTech_characteristics!$J$2:$J$8)*Conversions!$D$2 -> 6.7164587e+08
A72: 4 | B72: COKING_COAL | C72: INDIA | D72: NR | E72: =_xlfn.XLOOKUP(A72,PeriodMap!$A$2:$A$45,PeriodMap!$B$2:$B$45) -> 2029 | F72: =_xlfn.XLOOKUP(_xlfn.CONCAT($B72,$D72,$E72),PEC_ProdImpConstraints!$G$2:$G$286,PEC_ProdImpConstraints!$E$2:$E$286) -> 0 | G72: =_xlfn.XLOOKUP(_xlfn.CONCAT($B72,$D72,$E72),PEC_ProdImpConstraints!$G$2:$G$286,PEC_ProdImpConstraints!$F$2:$F$286) -> 0 | H72: 0 | I72: =_xlfn.XLOOKUP(_xlfn.CONCAT($B72,$D72,$E72),PEC_Info!$L$2:$L$301,PEC_Info!$F$2:$F$301) -> 2789.0369 | J72: =_xlfn.XLOOKUP(_xlfn.CONCAT($B72,$D72,$E72),PEC_Info!$L$2:$L$301,PEC_Info!$G$2:$G$301) -> 0.3508 | K72: =_xlfn.XLOOKUP(_xlfn.CONCAT($B72,$D72,$E72),PEC_Info!$L$2:$L$301,PEC_Info!$H$2:$H$301) -> 0 | L72: =_xlfn.XLOOKUP(_xlfn.CONCAT($B72,$D72,$E72),PEC_Info!$L$2:$L$301,PEC_Info!$I$2:$I$301) -> 19351.692 | M72: =_xlfn.XLOOKUP(_xlfn.CONCAT($B72,$D72,$E72),PEC_Info!$L$2:$L$301,PEC_Info!$J$2:$J$301) -> 0.205 | N72: =_xlfn.XLOOKUP(_xlfn.CONCAT($B72,$D72,$E72),PEC_Info!$L$2:$L$301,PEC_Info!$K$2:$K$301) -> 0 | P72: =(I72*(1+J72)+K72*1000)/_xlfn.XLOOKUP(B72,CarriersTech_characteristics!$B$2:$B$8,CarriersTech_characteristics!$G$2:$G$8)/Conversions!$D$2 -> 0.00065980588 | Q72: =F72*_xlfn.XLOOKUP(B72,CarriersTech_characteristics!$B$2:$B$8,CarriersTech_characteristics!$G$2:$G$8)*Conversions!$D$2*(1-H72) -> 0 | R72: =(L72*(1+M72)+N72*1000)/_xlfn.XLOOKUP(B72,CarriersTech_characteristics!$B$2:$B$8,CarriersTech_characteristics!$J$2:$J$8)/Conversions!$D$2 -> 0.0034718875 | S72: =G72*_xlfn.XLOOKUP(B72,CarriersTech_characteristics!$B$2:$B$8,CarriersTech_characteristics!$J$2:$J$8)*Conversions!$D$2 -> 0
A73: 4 | B73: COKING_COAL | C73: INDIA | D73: SR | E73: =_xlfn.XLOOKUP(A73,PeriodMap!$A$2:$A$45,PeriodMap!$B$2:$B$45) -> 2029 | F73: =_xlfn.XLOOKUP(_xlfn.CONCAT($B73,$D73,$E73),PEC_ProdImpConstraints!$G$2:$G$286,PEC_ProdImpConstraints!$E$2:$E$286) -> 0 | G73: =_xlfn.XLOOKUP(_xlfn.CONCAT($B73,$D73,$E73),PEC_ProdImpConstraints!$G$2:$G$286,PEC_ProdImpConstraints!$F$2:$F$286) -> 100 | H73: 0 | I73: =_xlfn.XLOOKUP(_xlfn.CONCAT($B73,$D73,$E73),PEC_Info!$L$2:$L$301,PEC_Info!$F$2:$F$301) -> 2789.0369 | J73: =_xlfn.XLOOKUP(_xlfn.CONCAT($B73,$D73,$E73),PEC_Info!$L$2:$L$301,PEC_Info!$G$2:$G$301) -> 0.3508 | K73: =_xlfn.XLOOKUP(_xlfn.CONCAT($B73,$D73,$E73),PEC_Info!$L$2:$L$301,PEC_Info!$H$2:$H$301) -> 0 | L73: =_xlfn.XLOOKUP(_xlfn.CONCAT($B73,$D73,$E73),PEC_Info!$L$2:$L$301,PEC_Info!$I$2:$I$301) -> 19351.692 | M73: =_xlfn.XLOOKUP(_xlfn.CONCAT($B73,$D73,$E73),PEC_Info!$L$2:$L$301,PEC_Info!$J$2:$J$301) -> 0.205 | N73: =_xlfn.XLOOKUP(_xlfn.CONCAT($B73,$D73,$E73),PEC_Info!$L$2:$L$301,PEC_Info!$K$2:$K$301) -> 0 | P73: =(I73*(1+J73)+K73*1000)/_xlfn.XLOOKUP(B73,CarriersTech_characteristics!$B$2:$B$8,CarriersTech_characteristics!$G$2:$G$8)/Conversions!$D$2 -> 0.00065980588 | Q73: =F73*_xlfn.XLOOKUP(B73,CarriersTech_characteristics!$B$2:$B$8,CarriersTech_characteristics!$G$2:$G$8)*Conversions!$D$2*(1-H73) -> 0 | R73: =(L73*(1+M73)+N73*1000)/_xlfn.XLOOKUP(B73,CarriersTech_characteristics!$B$2:$B$8,CarriersTech_characteristics!$J$2:$J$8)/Conversions!$D$2 -> 0.0034718875 | S73: =G73*_xlfn.XLOOKUP(B73,CarriersTech_characteristics!$B$2:$B$8,CarriersTech_characteristics!$J$2:$J$8)*Conversions!$D$2 -> 6.7164587e+08
A74: 4 | B74: COKING_COAL | C74: INDIA | D74: NER | E74: =_xlfn.XLOOKUP(A74,PeriodMap!$A$2:$A$45,PeriodMap!$B$2:$B$45) -> 2029 | F74: =_xlfn.XLOOKUP(_xlfn.CONCAT($B74,$D74,$E74),PEC_ProdImpConstraints!$G$2:$G$286,PEC_ProdImpConstraints!$E$2:$E$286) -> 0 | G74: =_xlfn.XLOOKUP(_xlfn.CONCAT($B74,$D74,$E74),PEC_ProdImpConstraints!$G$2:$G$286,PEC_ProdImpConstraints!$F$2:$F$286) -> 0 | H74: 0 | I74: =_xlfn.XLOOKUP(_xlfn.CONCAT($B74,$D74,$E74),PEC_Info!$L$2:$L$301,PEC_Info!$F$2:$F$301) -> 2789.0369 | J74: =_xlfn.XLOOKUP(_xlfn.CONCAT($B74,$D74,$E74),PEC_Info!$L$2:$L$301,PEC_Info!$G$2:$G$301) -> 0.3508 | K74: =_xlfn.XLOOKUP(_xlfn.CONCAT($B74,$D74,$E74),PEC_Info!$L$2:$L$301,PEC_Info!$H$2:$H$301) -> 0 | L74: =_xlfn.XLOOKUP(_xlfn.CONCAT($B74,$D74,$E74),PEC_Info!$L$2:$L$301,PEC_Info!$I$2:$I$301) -> 19351.692 | M74: =_xlfn.XLOOKUP(_xlfn.CONCAT($B74,$D74,$E74),PEC_Info!$L$2:$L$301,PEC_Info!$J$2:$J$301) -> 0.205 | N74: =_xlfn.XLOOKUP(_xlfn.CONCAT($B74,$D74,$E74),PEC_Info!$L$2:$L$301,PEC_Info!$K$2:$K$301) -> 0 | P74: =(I74*(1+J74)+K74*1000)/_xlfn.XLOOKUP(B74,CarriersTech_characteristics!$B$2:$B$8,CarriersTech_characteristics!$G$2:$G$8)/Conversions!$D$2 -> 0.00065980588 | Q74: =F74*_xlfn.XLOOKUP(B74,CarriersTech_characteristics!$B$2:$B$8,CarriersTech_characteristics!$G$2:$G$8)*Conversions!$D$2*(1-H74) -> 0 | R74: =(L74*(1+M74)+N74*1000)/_xlfn.XLOOKUP(B74,CarriersTech_characteristics!$B$2:$B$8,CarriersTech_characteristics!$J$2:$J$8)/Conversions!$D$2 -> 0.0034718875 | S74: =G74*_xlfn.XLOOKUP(B74,CarriersTech_characteristics!$B$2:$B$8,CarriersTech_characteristics!$J$2:$J$8)*Conversions!$D$2 -> 0
A75: 4 | B75: COKING_COAL | C75: INDIA | D75: ALL | E75: =_xlfn.XLOOKUP(A75,PeriodMap!$A$2:$A$45,PeriodMap!$B$2:$B$45) -> 2029 | F75: =SUM(F70:F74) -> 16.607131 | G75: =SUM(G70:G74) -> 300 | H75: =AVERAGE(H70:H74) -> 0 | I75: =AVERAGE(I70:I74) -> 2789.0369 | J75: =AVERAGE(J70:J74) -> 0.3508 | K75: =AVERAGE(K70:K74) -> 0 | L75: =AVERAGE(L70:L74) -> 19351.692 | M75: =AVERAGE(M70:M74) -> 0.205 | N75: =AVERAGE(N70:N74) -> 0 | P75: =AVERAGE(P70:P74) -> 0.00065980588 | Q75: =SUM(Q70:Q74) -> 94825191 | R75: =AVERAGE(R70:R74) -> 0.0034718875 | S75: =SUM(S70:S74) -> 2.0149376e+09
A76: 5 | B76: BIOMASS | C76: INDIA | E76: =_xlfn.XLOOKUP(A76,PeriodMap!$A$2:$A$45,PeriodMap!$B$2:$B$45) -> 2034 | F76: =_xlfn.XLOOKUP(_xlfn.CONCAT($B76,$D76,$E76),PEC_ProdImpConstraints!$G$2:$G$286,PEC_ProdImpConstraints!$E$2:$E$286) -> 270 | G76: =_xlfn.XLOOKUP(_xlfn.CONCAT($B76,$D76,$E76),PEC_ProdImpConstraints!$G$2:$G$286,PEC_ProdImpConstraints!$F$2:$F$286) -> 0 | H76: =_xlfn.XLOOKUP(_xlfn.CONCAT($B76,$D76,$E76),PEC_Info!$L$2:$L$301,PEC_Info!$E$2:$E$301) -> 0 | I76: =_xlfn.XLOOKUP(_xlfn.CONCAT($B76,$D76,$E76),PEC_Info!$L$2:$L$301,PEC_Info!$F$2:$F$301) -> 5683.2536 | J76: =_xlfn.XLOOKUP(_xlfn.CONCAT($B76,$D76,$E76),PEC_Info!$L$2:$L$301,PEC_Info!$G$2:$G$301) -> 0 | K76: =_xlfn.XLOOKUP(_xlfn.CONCAT($B76,$D76,$E76),PEC_Info!$L$2:$L$301,PEC_Info!$H$2:$H$301) -> 0 | L76: =_xlfn.XLOOKUP(_xlfn.CONCAT($B76,$D76,$E76),PEC_Info!$L$2:$L$301,PEC_Info!$I$2:$I$301) -> 5683.2536 | M76: =_xlfn.XLOOKUP(_xlfn.CONCAT($B76,$D76,$E76),PEC_Info!$L$2:$L$301,PEC_Info!$J$2:$J$301) -> 0 | N76: =_xlfn.XLOOKUP(_xlfn.CONCAT($B76,$D76,$E76),PEC_Info!$L$2:$L$301,PEC_Info!$K$2:$K$301) -> 0 | P76: =(I76*(1+J76)+K76*1000)/_xlfn.XLOOKUP(B76,CarriersTech_characteristics!$B$2:$B$8,CarriersTech_characteristics!$G$2:$G$8)/Conversions!$D$2 -> 0.0013148916 | Q76: =F76*_xlfn.XLOOKUP(B76,CarriersTech_characteristics!$B$2:$B$8,CarriersTech_characteristics!$G$2:$G$8)*Conversions!$D$2*(1-H76) -> 1.167e+09 | R76: =(L76*(1+M76)+N76*1000)/_xlfn.XLOOKUP(B76,CarriersTech_characteristics!$B$2:$B$8,CarriersTech_characteristics!$J$2:$J$8)/Conversions!$D$2 -> 0.0013148916 | S76: =G76*_xlfn.XLOOKUP(B76,CarriersTech_characteristics!$B$2:$B$8,CarriersTech_characteristics!$J$2:$J$8)*Conversions!$D$2 -> 0
A77: 5 | B77: BIOMASS_WASTE | C77: INDIA | E77: =_xlfn.XLOOKUP(A77,PeriodMap!$A$2:$A$45,PeriodMap!$B$2:$B$45) -> 2034 | F77: =_xlfn.XLOOKUP(_xlfn.CONCAT($B77,$D77,$E77),PEC_ProdImpConstraints!$G$2:$G$286,PEC_ProdImpConstraints!$E$2:$E$286) -> 175 | G77: =_xlfn.XLOOKUP(_xlfn.CONCAT($B77,$D77,$E77),PEC_ProdImpConstraints!$G$2:$G$286,PEC_ProdImpConstraints!$F$2:$F$286) -> 0 | H77: =_xlfn.XLOOKUP(_xlfn.CONCAT($B77,$D77,$E77),PEC_Info!$L$2:$L$301,PEC_Info!$E$2:$E$301) -> 0 | I77: =_xlfn.XLOOKUP(_xlfn.CONCAT($B77,$D77,$E77),PEC_Info!$L$2:$L$301,PEC_Info!$F$2:$F$301) -> 9000 | J77: =_xlfn.XLOOKUP(_xlfn.CONCAT($B77,$D77,$E77),PEC_Info!$L$2:$L$301,PEC_Info!$G$2:$G$301) -> 0.05 | K77: =_xlfn.XLOOKUP(_xlfn.CONCAT($B77,$D77,$E77),PEC_Info!$L$2:$L$301,PEC_Info!$H$2:$H$301) -> 0 | L77: =_xlfn.XLOOKUP(_xlfn.CONCAT($B77,$D77,$E77),PEC_Info!$L$2:$L$301,PEC_Info!$I$2:$I$301) -> 9000 | M77: =_xlfn.XLOOKUP(_xlfn.CONCAT($B77,$D77,$E77),PEC_Info!$L$2:$L$301,PEC_Info!$J$2:$J$301) -> 0.05 | N77: =_xlfn.XLOOKUP(_xlfn.CONCAT($B77,$D77,$E77),PEC_Info!$L$2:$L$301,PEC_Info!$K$2:$K$301) -> 0 | P77: =(I77*(1+J77)+K77*1000)/_xlfn.XLOOKUP(B77,CarriersTech_characteristics!$B$2:$B$8,CarriersTech_characteristics!$G$2:$G$8)/Conversions!$D$2 -> 0.0024924961 | Q77: =F77*_xlfn.XLOOKUP(B77,CarriersTech_characteristics!$B$2:$B$8,CarriersTech_characteristics!$G$2:$G$8)*Conversions!$D$2*(1-H77) -> 6.6349151e+08 | R77: =(L77*(1+M77)+N77*1000)/_xlfn.XLOOKUP(B77,CarriersTech_characteristics!$B$2:$B$8,CarriersTech_characteristics!$J$2:$J$8)/Conversions!$D$2 -> 0.0024924961 | S77: =G77*_xlfn.XLOOKUP(B77,CarriersTech_characteristics!$B$2:$B$8,CarriersTech_characteristics!$J$2:$J$8)*Conversions!$D$2 -> 0
A78: 5 | B78: NATGAS | C78: INDIA | E78: =_xlfn.XLOOKUP(A78,PeriodMap!$A$2:$A$45,PeriodMap!$B$2:$B$45) -> 2034 | F78: =_xlfn.XLOOKUP(_xlfn.CONCAT($B78,$D78,$E78),PEC_ProdImpConstraints!$G$2:$G$286,PEC_ProdImpConstraints!$E$2:$E$286) -> 41.837059 | G78: =_xlfn.XLOOKUP(_xlfn.CONCAT($B78,$D78,$E78),PEC_ProdImpConstraints!$G$2:$G$286,PEC_ProdImpConstraints!$F$2:$F$286) -> 200 | H78: =_xlfn.XLOOKUP(_xlfn.CONCAT($B78,$D78,$E78),PEC_Info!$L$2:$L$301,PEC_Info!$E$2:$E$301) -> 0.36749121 | I78: =_xlfn.XLOOKUP(_xlfn.CONCAT($B78,$D78,$E78),PEC_Info!$L$2:$L$301,PEC_Info!$F$2:$F$301) -> 25324.749 | J78: =_xlfn.XLOOKUP(_xlfn.CONCAT($B78,$D78,$E78),PEC_Info!$L$2:$L$301,PEC_Info!$G$2:$G$301) -> 0.24 | K78: =_xlfn.XLOOKUP(_xlfn.CONCAT($B78,$D78,$E78),PEC_Info!$L$2:$L$301,PEC_Info!$H$2:$H$301) -> 0 | L78: =_xlfn.XLOOKUP(_xlfn.CONCAT($B78,$D78,$E78),PEC_Info!$L$2:$L$301,PEC_Info!$I$2:$I$301) -> 28005.568 | M78: =_xlfn.XLOOKUP(_xlfn.CONCAT($B78,$D78,$E78),PEC_Info!$L$2:$L$301,PEC_Info!$J$2:$J$301) -> 0.349 | N78: =_xlfn.XLOOKUP(_xlfn.CONCAT($B78,$D78,$E78),PEC_Info!$L$2:$L$301,PEC_Info!$K$2:$K$301) -> 0 | P78: =(I78*(1+J78)+K78*1000)/Conversions!$D$3/_xlfn.XLOOKUP(B78,CarriersTech_characteristics!$B$2:$B$8,CarriersTech_characteristics!$G$2:$G$8)/Conversions!$D$2 -> 0.0036190124 | Q78: =F78*_xlfn.XLOOKUP(B78,CarriersTech_characteristics!$B$2:$B$8,CarriersTech_characteristics!$G$2:$G$8)*Conversions!$D$2*(1-H78) -> 2.7698097e+08 | R78: =(L78*(1+M78)+N78*1000)/Conversions!$D$3/_xlfn.XLOOKUP(B78,CarriersTech_characteristics!$B$2:$B$8,CarriersTech_characteristics!$J$2:$J$8)/Conversions!$D$2 -> 0.0043539112 | S78: =G78*_xlfn.XLOOKUP(B78,CarriersTech_characteristics!$B$2:$B$8,CarriersTech_characteristics!$J$2:$J$8)*Conversions!$D$2 -> 2.0934e+09
A79: 5 | B79: THERMAL_COAL | C79: INDIA | D79: NR | E79: =_xlfn.XLOOKUP(A79,PeriodMap!$A$2:$A$45,PeriodMap!$B$2:$B$45) -> 2034 | F79: =_xlfn.XLOOKUP(_xlfn.CONCAT($B79,$D79,$E79),PEC_ProdImpConstraints!$G$2:$G$286,PEC_ProdImpConstraints!$E$2:$E$286) -> 46.466837 | G79: =_xlfn.XLOOKUP(_xlfn.CONCAT($B79,$D79,$E79),PEC_ProdImpConstraints!$G$2:$G$286,PEC_ProdImpConstraints!$F$2:$F$286) -> 0 | H79: =_xlfn.XLOOKUP(_xlfn.CONCAT($B79,$D79,$E79),PEC_Info!$L$2:$L$301,PEC_Info!$E$2:$E$301) -> 0 | I79: =_xlfn.XLOOKUP(_xlfn.CONCAT($B79,$D79,$E79),PEC_Info!$L$2:$L$301,PEC_Info!$F$2:$F$301) -> 1156.3734 | J79: =_xlfn.XLOOKUP(_xlfn.CONCAT($B79,$D79,$E79),PEC_Info!$L$2:$L$301,PEC_Info!$G$2:$G$301) -> 0.3508 | K79: =_xlfn.XLOOKUP(_xlfn.CONCAT($B79,$D79,$E79),PEC_Info!$L$2:$L$301,PEC_Info!$H$2:$H$301) -> 0 | L79: =_xlfn.XLOOKUP(_xlfn.CONCAT($B79,$D79,$E79),PEC_Info!$L$2:$L$301,PEC_Info!$I$2:$I$301) -> 7942.6264 | M79: =_xlfn.XLOOKUP(_xlfn.CONCAT($B79,$D79,$E79),PEC_Info!$L$2:$L$301,PEC_Info!$J$2:$J$301) -> 0.205 | N79: =_xlfn.XLOOKUP(_xlfn.CONCAT($B79,$D79,$E79),PEC_Info!$L$2:$L$301,PEC_Info!$K$2:$K$301) -> 0 | P79: =(I79*(1+J79)+K79*1000)/_xlfn.XLOOKUP(B79,CarriersTech_characteristics!$B$2:$B$8,CarriersTech_characteristics!$G$2:$G$8)/Conversions!$D$2 -> 0.00032679978 | Q79: =F79*_xlfn.XLOOKUP(B79,CarriersTech_characteristics!$B$2:$B$8,CarriersTech_characteristics!$G$2:$G$8)*Conversions!$D$2*(1-H79) -> 2.22101e+08 | R79: =(L79*(1+M79)+N79*1000)/_xlfn.XLOOKUP(B79,CarriersTech_characteristics!$B$2:$B$8,CarriersTech_characteristics!$J$2:$J$8)/Conversions!$D$2 -> 0.0015239745 | S79: =G79*_xlfn.XLOOKUP(B79,CarriersTech_characteristics!$B$2:$B$8,CarriersTech_characteristics!$J$2:$J$8)*Conversions!$D$2 -> 0
A80: 5 | B80: THERMAL_COAL | C80: INDIA | D80: NER | E80: =_xlfn.XLOOKUP(A80,PeriodMap!$A$2:$A$45,PeriodMap!$B$2:$B$45) -> 2034 | F80: =_xlfn.XLOOKUP(_xlfn.CONCAT($B80,$D80,$E80),PEC_ProdImpConstraints!$G$2:$G$286,PEC_ProdImpConstraints!$E$2:$E$286) -> 0 | G80: =_xlfn.XLOOKUP(_xlfn.CONCAT($B80,$D80,$E80),PEC_ProdImpConstraints!$G$2:$G$286,PEC_ProdImpConstraints!$F$2:$F$286) -> 0 | H80: =_xlfn.XLOOKUP(_xlfn.CONCAT($B80,$D80,$E80),PEC_Info!$L$2:$L$301,PEC_Info!$E$2:$E$301) -> 0 | I80: =_xlfn.XLOOKUP(_xlfn.CONCAT($B80,$D80,$E80),PEC_Info!$L$2:$L$301,PEC_Info!$F$2:$F$301) -> 1156.3734 | J80: =_xlfn.XLOOKUP(_xlfn.CONCAT($B80,$D80,$E80),PEC_Info!$L$2:$L$301,PEC_Info!$G$2:$G$301) -> 0.3508 | K80: =_xlfn.XLOOKUP(_xlfn.CONCAT($B80,$D80,$E80),PEC_Info!$L$2:$L$301,PEC_Info!$H$2:$H$301) -> 0 | L80: =_xlfn.XLOOKUP(_xlfn.CONCAT($B80,$D80,$E80),PEC_Info!$L$2:$L$301,PEC_Info!$I$2:$I$301) -> 7942.6264 | M80: =_xlfn.XLOOKUP(_xlfn.CONCAT($B80,$D80,$E80),PEC_Info!$L$2:$L$301,PEC_Info!$J$2:$J$301) -> 0.205 | N80: =_xlfn.XLOOKUP(_xlfn.CONCAT($B80,$D80,$E80),PEC_Info!$L$2:$L$301,PEC_Info!$K$2:$K$301) -> 0 | P80: =(I80*(1+J80)+K80*1000)/_xlfn.XLOOKUP(B80,CarriersTech_characteristics!$B$2:$B$8,CarriersTech_characteristics!$G$2:$G$8)/Conversions!$D$2 -> 0.00032679978 | Q80: =F80*_xlfn.XLOOKUP(B80,CarriersTech_characteristics!$B$2:$B$8,CarriersTech_characteristics!$G$2:$G$8)*Conversions!$D$2*(1-H80) -> 0 | R80: =(L80*(1+M80)+N80*1000)/_xlfn.XLOOKUP(B80,CarriersTech_characteristics!$B$2:$B$8,CarriersTech_characteristics!$J$2:$J$8)/Conversions!$D$2 -> 0.0015239745 | S80: =G80*_xlfn.XLOOKUP(B80,CarriersTech_characteristics!$B$2:$B$8,CarriersTech_characteristics!$J$2:$J$8)*Conversions!$D$2 -> 0
A81: 5 | B81: THERMAL_COAL | C81: INDIA | D81: ER | E81: =_xlfn.XLOOKUP(A81,PeriodMap!$A$2:$A$45,PeriodMap!$B$2:$B$45) -> 2034 | F81: =_xlfn.XLOOKUP(_xlfn.CONCAT($B81,$D81,$E81),PEC_ProdImpConstraints!$G$2:$G$286,PEC_ProdImpConstraints!$E$2:$E$286) -> 727.8726 | G81: =_xlfn.XLOOKUP(_xlfn.CONCAT($B81,$D81,$E81),PEC_ProdImpConstraints!$G$2:$G$286,PEC_ProdImpConstraints!$F$2:$F$286) -> 150 | H81: =_xlfn.XLOOKUP(_xlfn.CONCAT($B81,$D81,$E81),PEC_Info!$L$2:$L$301,PEC_Info!$E$2:$E$301) -> 0 | I81: =_xlfn.XLOOKUP(_xlfn.CONCAT($B81,$D81,$E81),PEC_Info!$L$2:$L$301,PEC_Info!$F$2:$F$301) -> 1156.3734 | J81: =_xlfn.XLOOKUP(_xlfn.CONCAT($B81,$D81,$E81),PEC_Info!$L$2:$L$301,PEC_Info!$G$2:$G$301) -> 0.3508 | K81: =_xlfn.XLOOKUP(_xlfn.CONCAT($B81,$D81,$E81),PEC_Info!$L$2:$L$301,PEC_Info!$H$2:$H$301) -> 0 | L81: =_xlfn.XLOOKUP(_xlfn.CONCAT($B81,$D81,$E81),PEC_Info!$L$2:$L$301,PEC_Info!$I$2:$I$301) -> 7942.6264 | M81: =_xlfn.XLOOKUP(_xlfn.CONCAT($B81,$D81,$E81),PEC_Info!$L$2:$L$301,PEC_Info!$J$2:$J$301) -> 0.205 | N81: =_xlfn.XLOOKUP(_xlfn.CONCAT($B81,$D81,$E81),PEC_Info!$L$2:$L$301,PEC_Info!$K$2:$K$301) -> 0 | P81: =(I81*(1+J81)+K81*1000)/_xlfn.XLOOKUP(B81,CarriersTech_characteristics!$B$2:$B$8,CarriersTech_characteristics!$G$2:$G$8)/Conversions!$D$2 -> 0.00032679978 | Q81: =F81*_xlfn.XLOOKUP(B81,CarriersTech_characteristics!$B$2:$B$8,CarriersTech_characteristics!$G$2:$G$8)*Conversions!$D$2*(1-H81) -> 3.4790668e+09 | R81: =(L81*(1+M81)+N81*1000)/_xlfn.XLOOKUP(B81,CarriersTech_characteristics!$B$2:$B$8,CarriersTech_characteristics!$J$2:$J$8)/Conversions!$D$2 -> 0.0015239745 | S81: =G81*_xlfn.XLOOKUP(B81,CarriersTech_characteristics!$B$2:$B$8,CarriersTech_characteristics!$J$2:$J$8)*Conversions!$D$2 -> 9.4203001e+08
A82: 5 | B82: THERMAL_COAL | C82: INDIA | D82: WR | E82: =_xlfn.XLOOKUP(A82,PeriodMap!$A$2:$A$45,PeriodMap!$B$2:$B$45) -> 2034 | F82: =_xlfn.XLOOKUP(_xlfn.CONCAT($B82,$D82,$E82),PEC_ProdImpConstraints!$G$2:$G$286,PEC_ProdImpConstraints!$E$2:$E$286) -> 735.14924 | G82: =_xlfn.XLOOKUP(_xlfn.CONCAT($B82,$D82,$E82),PEC_ProdImpConstraints!$G$2:$G$286,PEC_ProdImpConstraints!$F$2:$F$286) -> 150 | H82: =_xlfn.XLOOKUP(_xlfn.CONCAT($B82,$D82,$E82),PEC_Info!$L$2:$L$301,PEC_Info!$E$2:$E$301) -> 0 | I82: =_xlfn.XLOOKUP(_xlfn.CONCAT($B82,$D82,$E82),PEC_Info!$L$2:$L$301,PEC_Info!$F$2:$F$301) -> 1156.3734 | J82: =_xlfn.XLOOKUP(_xlfn.CONCAT($B82,$D82,$E82),PEC_Info!$L$2:$L$301,PEC_Info!$G$2:$G$301) -> 0.3508 | K82: =_xlfn.XLOOKUP(_xlfn.CONCAT($B82,$D82,$E82),PEC_Info!$L$2:$L$301,PEC_Info!$H$2:$H$301) -> 0 | L82: =_xlfn.XLOOKUP(_xlfn.CONCAT($B82,$D82,$E82),PEC_Info!$L$2:$L$301,PEC_Info!$I$2:$I$301) -> 7942.6264 | M82: =_xlfn.XLOOKUP(_xlfn.CONCAT($B82,$D82,$E82),PEC_Info!$L$2:$L$301,PEC_Info!$J$2:$J$301) -> 0.205 | N82: =_xlfn.XLOOKUP(_xlfn.CONCAT($B82,$D82,$E82),PEC_Info!$L$2:$L$301,PEC_Info!$K$2:$K$301) -> 0 | P82: =(I82*(1+J82)+K82*1000)/_xlfn.XLOOKUP(B82,CarriersTech_characteristics!$B$2:$B$8,CarriersTech_characteristics!$G$2:$G$8)/Conversions!$D$2 -> 0.00032679978 | Q82: =F82*_xlfn.XLOOKUP(B82,CarriersTech_characteristics!$B$2:$B$8,CarriersTech_characteristics!$G$2:$G$8)*Conversions!$D$2*(1-H82) -> 3.5138475e+09 | R82: =(L82*(1+M82)+N82*1000)/_xlfn.XLOOKUP(B82,CarriersTech_characteristics!$B$2:$B$8,CarriersTech_characteristics!$J$2:$J$8)/Conversions!$D$2 -> 0.0015239745 | S82: =G82*_xlfn.XLOOKUP(B82,CarriersTech_characteristics!$B$2:$B$8,CarriersTech_characteristics!$J$2:$J$8)*Conversions!$D$2 -> 9.4203001e+08
A83: 5 | B83: THERMAL_COAL | C83: INDIA | D83: SR | E83: =_xlfn.XLOOKUP(A83,PeriodMap!$A$2:$A$45,PeriodMap!$B$2:$B$45) -> 2034 | F83: =_xlfn.XLOOKUP(_xlfn.CONCAT($B83,$D83,$E83),PEC_ProdImpConstraints!$G$2:$G$286,PEC_ProdImpConstraints!$E$2:$E$286) -> 98.177712 | G83: =_xlfn.XLOOKUP(_xlfn.CONCAT($B83,$D83,$E83),PEC_ProdImpConstraints!$G$2:$G$286,PEC_ProdImpConstraints!$F$2:$F$286) -> 150 | H83: =_xlfn.XLOOKUP(_xlfn.CONCAT($B83,$D83,$E83),PEC_Info!$L$2:$L$301,PEC_Info!$E$2:$E$301) -> 0 | I83: =_xlfn.XLOOKUP(_xlfn.CONCAT($B83,$D83,$E83),PEC_Info!$L$2:$L$301,PEC_Info!$F$2:$F$301) -> 1156.3734 | J83: =_xlfn.XLOOKUP(_xlfn.CONCAT($B83,$D83,$E83),PEC_Info!$L$2:$L$301,PEC_Info!$G$2:$G$301) -> 0.3508 | K83: =_xlfn.XLOOKUP(_xlfn.CONCAT($B83,$D83,$E83),PEC_Info!$L$2:$L$301,PEC_Info!$H$2:$H$301) -> 0 | L83: =_xlfn.XLOOKUP(_xlfn.CONCAT($B83,$D83,$E83),PEC_Info!$L$2:$L$301,PEC_Info!$I$2:$I$301) -> 7942.6264 | M83: =_xlfn.XLOOKUP(_xlfn.CONCAT($B83,$D83,$E83),PEC_Info!$L$2:$L$301,PEC_Info!$J$2:$J$301) -> 0.205 | N83: =_xlfn.XLOOKUP(_xlfn.CONCAT($B83,$D83,$E83),PEC_Info!$L$2:$L$301,PEC_Info!$K$2:$K$301) -> 0 | P83: =(I83*(1+J83)+K83*1000)/_xlfn.XLOOKUP(B83,CarriersTech_characteristics!$B$2:$B$8,CarriersTech_characteristics!$G$2:$G$8)/Conversions!$D$2 -> 0.00032679978 | Q83: =F83*_xlfn.XLOOKUP(B83,CarriersTech_characteristics!$B$2:$B$8,CarriersTech_characteristics!$G$2:$G$8)*Conversions!$D$2*(1-H83) -> 4.6926731e+08 | R83: =(L83*(1+M83)+N83*1000)/_xlfn.XLOOKUP(B83,CarriersTech_characteristics!$B$2:$B$8,CarriersTech_characteristics!$J$2:$J$8)/Conversions!$D$2 -> 0.0015239745 | S83: =G83*_xlfn.XLOOKUP(B83,CarriersTech_characteristics!$B$2:$B$8,CarriersTech_characteristics!$J$2:$J$8)*Conversions!$D$2 -> 9.4203001e+08
A84: 5 | B84: THERMAL_COAL | C84: INDIA | D84: ALL | E84: =_xlfn.XLOOKUP(A84,PeriodMap!$A$2:$A$45,PeriodMap!$B$2:$B$45) -> 2034 | F84: =SUM(F79:F83) -> 1607.6664 | G84: =SUM(G79:G83) -> 450 | H84: =AVERAGE(H79:H83) -> 0 | I84: =AVERAGE(I79:I83) -> 1156.3734 | J84: =AVERAGE(J79:J83) -> 0.3508 | K84: =AVERAGE(K79:K83) -> 0 | L84: =AVERAGE(L79:L83) -> 7942.6264 | M84: =AVERAGE(M79:M83) -> 0.205 | N84: =AVERAGE(N79:N83) -> 0 | P84: =AVERAGE(P79:P83) -> 0.00032679978 | Q84: =SUM(Q79:Q83) -> 7.6842826e+09 | R84: =AVERAGE(R79:R83) -> 0.0015239745 | S84: =SUM(S79:S83) -> 2.82609e+09
A85: 5 | B85: CRUDE | C85: INDIA | E85: =_xlfn.XLOOKUP(A85,PeriodMap!$A$2:$A$45,PeriodMap!$B$2:$B$45) -> 2034 | F85: =_xlfn.XLOOKUP(_xlfn.CONCAT($B85,$D85,$E85),PEC_ProdImpConstraints!$G$2:$G$286,PEC_ProdImpConstraints!$E$2:$E$286) -> 31.9035 | G85: =_xlfn.XLOOKUP(_xlfn.CONCAT($B85,$D85,$E85),PEC_ProdImpConstraints!$G$2:$G$286,PEC_ProdImpConstraints!$F$2:$F$286) -> 330 | H85: 0 | I85: =_xlfn.XLOOKUP(_xlfn.CONCAT($B85,$D85,$E85),PEC_Info!$L$2:$L$301,PEC_Info!$F$2:$F$301) -> 59512.734 | J85: =_xlfn.XLOOKUP(_xlfn.CONCAT($B85,$D85,$E85),PEC_Info!$L$2:$L$301,PEC_Info!$G$2:$G$301) -> 0 | K85: =_xlfn.XLOOKUP(_xlfn.CONCAT($B85,$D85,$E85),PEC_Info!$L$2:$L$301,PEC_Info!$H$2:$H$301) -> 51.2 | L85: =_xlfn.XLOOKUP(_xlfn.CONCAT($B85,$D85,$E85),PEC_Info!$L$2:$L$301,PEC_Info!$I$2:$I$301) -> 59512.734 | M85: =_xlfn.XLOOKUP(_xlfn.CONCAT($B85,$D85,$E85),PEC_Info!$L$2:$L$301,PEC_Info!$J$2:$J$301) -> 0 | N85: =_xlfn.XLOOKUP(_xlfn.CONCAT($B85,$D85,$E85),PEC_Info!$L$2:$L$301,PEC_Info!$K$2:$K$301) -> 57.2 | P85: =(I85*(1+J85)+K85*1000)/_xlfn.XLOOKUP(B85,CarriersTech_characteristics!$B$2:$B$8,CarriersTech_characteristics!$G$2:$G$8)/Conversions!$D$2 -> 0.0092423121 | Q85: =F85*_xlfn.XLOOKUP(B85,CarriersTech_characteristics!$B$2:$B$8,CarriersTech_characteristics!$G$2:$G$8)*Conversions!$D$2*(1-H85) -> 3.8216884e+08 | R85: =(L85*(1+M85)+N85*1000)/_xlfn.XLOOKUP(B85,CarriersTech_characteristics!$B$2:$B$8,CarriersTech_characteristics!$J$2:$J$8)/Conversions!$D$2 -> 0.0097431929 | S85: =G85*_xlfn.XLOOKUP(B85,CarriersTech_characteristics!$B$2:$B$8,CarriersTech_characteristics!$J$2:$J$8)*Conversions!$D$2 -> 3.953037e+09
A86: 5 | B86: BIOGAS | C86: INDIA | E86: =_xlfn.XLOOKUP(A86,PeriodMap!$A$2:$A$45,PeriodMap!$B$2:$B$45) -> 2034 | F86: =_xlfn.XLOOKUP(_xlfn.CONCAT($B86,$D86,$E86),PEC_ProdImpConstraints!$G$2:$G$286,PEC_ProdImpConstraints!$E$2:$E$286) -> 87 | G86: =_xlfn.XLOOKUP(_xlfn.CONCAT($B86,$D86,$E86),PEC_ProdImpConstraints!$G$2:$G$286,PEC_ProdImpConstraints!$F$2:$F$286) -> 0 | H86: 0 | I86: =_xlfn.XLOOKUP(_xlfn.CONCAT($B86,$D86,$E86),PEC_Info!$L$2:$L$301,PEC_Info!$F$2:$F$301) -> 55747.637 | J86: =_xlfn.XLOOKUP(_xlfn.CONCAT($B86,$D86,$E86),PEC_Info!$L$2:$L$301,PEC_Info!$G$2:$G$301) -> 0.05 | K86: =_xlfn.XLOOKUP(_xlfn.CONCAT($B86,$D86,$E86),PEC_Info!$L$2:$L$301,PEC_Info!$H$2:$H$301) -> 0 | L86: =_xlfn.XLOOKUP(_xlfn.CONCAT($B86,$D86,$E86),PEC_Info!$L$2:$L$301,PEC_Info!$I$2:$I$301) -> 55747.637 | M86: =_xlfn.XLOOKUP(_xlfn.CONCAT($B86,$D86,$E86),PEC_Info!$L$2:$L$301,PEC_Info!$J$2:$J$301) -> 0.05 | N86: =_xlfn.XLOOKUP(_xlfn.CONCAT($B86,$D86,$E86),PEC_Info!$L$2:$L$301,PEC_Info!$K$2:$K$301) -> 0 | P86: =(I86*(1+J86)+K86*1000)/Conversions!$D$3/_xlfn.XLOOKUP(B86,CarriersTech_characteristics!$B$2:$B$8,CarriersTech_characteristics!$G$2:$G$8)/Conversions!$D$2 -> 0.011148819 | Q86: =F86*_xlfn.XLOOKUP(B86,CarriersTech_characteristics!$B$2:$B$8,CarriersTech_characteristics!$G$2:$G$8)*Conversions!$D$2*(1-H86) -> 5.51e+08 | R86: =(L86*(1+M86)+N86*1000)/Conversions!$D$3/_xlfn.XLOOKUP(B86,CarriersTech_characteristics!$B$2:$B$8,CarriersTech_characteristics!$J$2:$J$8)/Conversions!$D$2 -> 0.011148819 | S86: =G86*_xlfn.XLOOKUP(B86,CarriersTech_characteristics!$B$2:$B$8,CarriersTech_characteristics!$J$2:$J$8)*Conversions!$D$2 -> 0
A87: 5 | B87: COKING_COAL | C87: INDIA | D87: ER | E87: =_xlfn.XLOOKUP(A87,PeriodMap!$A$2:$A$45,PeriodMap!$B$2:$B$45) -> 2034 | F87: =_xlfn.XLOOKUP(_xlfn.CONCAT($B87,$D87,$E87),PEC_ProdImpConstraints!$G$2:$G$286,PEC_ProdImpConstraints!$E$2:$E$286) -> 20.404638 | G87: =_xlfn.XLOOKUP(_xlfn.CONCAT($B87,$D87,$E87),PEC_ProdImpConstraints!$G$2:$G$286,PEC_ProdImpConstraints!$F$2:$F$286) -> 100 | H87: 0 | I87: =_xlfn.XLOOKUP(_xlfn.CONCAT($B87,$D87,$E87),PEC_Info!$L$2:$L$301,PEC_Info!$F$2:$F$301) -> 2789.0369 | J87: =_xlfn.XLOOKUP(_xlfn.CONCAT($B87,$D87,$E87),PEC_Info!$L$2:$L$301,PEC_Info!$G$2:$G$301) -> 0.3508 | K87: =_xlfn.XLOOKUP(_xlfn.CONCAT($B87,$D87,$E87),PEC_Info!$L$2:$L$301,PEC_Info!$H$2:$H$301) -> 0 | L87: =_xlfn.XLOOKUP(_xlfn.CONCAT($B87,$D87,$E87),PEC_Info!$L$2:$L$301,PEC_Info!$I$2:$I$301) -> 17232.221 | M87: =_xlfn.XLOOKUP(_xlfn.CONCAT($B87,$D87,$E87),PEC_Info!$L$2:$L$301,PEC_Info!$J$2:$J$301) -> 0.205 | N87: =_xlfn.XLOOKUP(_xlfn.CONCAT($B87,$D87,$E87),PEC_Info!$L$2:$L$301,PEC_Info!$K$2:$K$301) -> 0 | P87: =(I87*(1+J87)+K87*1000)/_xlfn.XLOOKUP(B87,CarriersTech_characteristics!$B$2:$B$8,CarriersTech_characteristics!$G$2:$G$8)/Conversions!$D$2 -> 0.00065980588 | Q87: =F87*_xlfn.XLOOKUP(B87,CarriersTech_characteristics!$B$2:$B$8,CarriersTech_characteristics!$G$2:$G$8)*Conversions!$D$2*(1-H87) -> 1.1650861e+08 | R87: =(L87*(1+M87)+N87*1000)/_xlfn.XLOOKUP(B87,CarriersTech_characteristics!$B$2:$B$8,CarriersTech_characteristics!$J$2:$J$8)/Conversions!$D$2 -> 0.0030916331 | S87: =G87*_xlfn.XLOOKUP(B87,CarriersTech_characteristics!$B$2:$B$8,CarriersTech_characteristics!$J$2:$J$8)*Conversions!$D$2 -> 6.7164587e+08
A88: 5 | B88: COKING_COAL | C88: INDIA | D88: WR | E88: =_xlfn.XLOOKUP(A88,PeriodMap!$A$2:$A$45,PeriodMap!$B$2:$B$45) -> 2034 | F88: =_xlfn.XLOOKUP(_xlfn.CONCAT($B88,$D88,$E88),PEC_ProdImpConstraints!$G$2:$G$286,PEC_ProdImpConstraints!$E$2:$E$286) -> 0 | G88: =_xlfn.XLOOKUP(_xlfn.CONCAT($B88,$D88,$E88),PEC_ProdImpConstraints!$G$2:$G$286,PEC_ProdImpConstraints!$F$2:$F$286) -> 100 | H88: 0 | I88: =_xlfn.XLOOKUP(_xlfn.CONCAT($B88,$D88,$E88),PEC_Info!$L$2:$L$301,PEC_Info!$F$2:$F$301) -> 2789.0369 | J88: =_xlfn.XLOOKUP(_xlfn.CONCAT($B88,$D88,$E88),PEC_Info!$L$2:$L$301,PEC_Info!$G$2:$G$301) -> 0.3508 | K88: =_xlfn.XLOOKUP(_xlfn.CONCAT($B88,$D88,$E88),PEC_Info!$L$2:$L$301,PEC_Info!$H$2:$H$301) -> 0 | L88: =_xlfn.XLOOKUP(_xlfn.CONCAT($B88,$D88,$E88),PEC_Info!$L$2:$L$301,PEC_Info!$I$2:$I$301) -> 17232.221 | M88: =_xlfn.XLOOKUP(_xlfn.CONCAT($B88,$D88,$E88),PEC_Info!$L$2:$L$301,PEC_Info!$J$2:$J$301) -> 0.205 | N88: =_xlfn.XLOOKUP(_xlfn.CONCAT($B88,$D88,$E88),PEC_Info!$L$2:$L$301,PEC_Info!$K$2:$K$301) -> 0 | P88: =(I88*(1+J88)+K88*1000)/_xlfn.XLOOKUP(B88,CarriersTech_characteristics!$B$2:$B$8,CarriersTech_characteristics!$G$2:$G$8)/Conversions!$D$2 -> 0.00065980588 | Q88: =F88*_xlfn.XLOOKUP(B88,CarriersTech_characteristics!$B$2:$B$8,CarriersTech_characteristics!$G$2:$G$8)*Conversions!$D$2*(1-H88) -> 0 | R88: =(L88*(1+M88)+N88*1000)/_xlfn.XLOOKUP(B88,CarriersTech_characteristics!$B$2:$B$8,CarriersTech_characteristics!$J$2:$J$8)/Conversions!$D$2 -> 0.0030916331 | S88: =G88*_xlfn.XLOOKUP(B88,CarriersTech_characteristics!$B$2:$B$8,CarriersTech_characteristics!$J$2:$J$8)*Conversions!$D$2 -> 6.7164587e+08
A89: 5 | B89: COKING_COAL | C89: INDIA | D89: NR | E89: =_xlfn.XLOOKUP(A89,PeriodMap!$A$2:$A$45,PeriodMap!$B$2:$B$45) -> 2034 | F89: =_xlfn.XLOOKUP(_xlfn.CONCAT($B89,$D89,$E89),PEC_ProdImpConstraints!$G$2:$G$286,PEC_ProdImpConstraints!$E$2:$E$286) -> 0 | G89: =_xlfn.XLOOKUP(_xlfn.CONCAT($B89,$D89,$E89),PEC_ProdImpConstraints!$G$2:$G$286,PEC_ProdImpConstraints!$F$2:$F$286) -> 0 | H89: 0 | I89: =_xlfn.XLOOKUP(_xlfn.CONCAT($B89,$D89,$E89),PEC_Info!$L$2:$L$301,PEC_Info!$F$2:$F$301) -> 2789.0369 | J89: =_xlfn.XLOOKUP(_xlfn.CONCAT($B89,$D89,$E89),PEC_Info!$L$2:$L$301,PEC_Info!$G$2:$G$301) -> 0.3508 | K89: =_xlfn.XLOOKUP(_xlfn.CONCAT($B89,$D89,$E89),PEC_Info!$L$2:$L$301,PEC_Info!$H$2:$H$301) -> 0 | L89: =_xlfn.XLOOKUP(_xlfn.CONCAT($B89,$D89,$E89),PEC_Info!$L$2:$L$301,PEC_Info!$I$2:$I$301) -> 17232.221 | M89: =_xlfn.XLOOKUP(_xlfn.CONCAT($B89,$D89,$E89),PEC_Info!$L$2:$L$301,PEC_Info!$J$2:$J$301) -> 0.205 | N89: =_xlfn.XLOOKUP(_xlfn.CONCAT($B89,$D89,$E89),PEC_Info!$L$2:$L$301,PEC_Info!$K$2:$K$301) -> 0 | P89: =(I89*(1+J89)+K89*1000)/_xlfn.XLOOKUP(B89,CarriersTech_characteristics!$B$2:$B$8,CarriersTech_characteristics!$G$2:$G$8)/Conversions!$D$2 -> 0.00065980588 | Q89: =F89*_xlfn.XLOOKUP(B89,CarriersTech_characteristics!$B$2:$B$8,CarriersTech_characteristics!$G$2:$G$8)*Conversions!$D$2*(1-H89) -> 0 | R89: =(L89*(1+M89)+N89*1000)/_xlfn.XLOOKUP(B89,CarriersTech_characteristics!$B$2:$B$8,CarriersTech_characteristics!$J$2:$J$8)/Conversions!$D$2 -> 0.0030916331 | S89: =G89*_xlfn.XLOOKUP(B89,CarriersTech_characteristics!$B$2:$B$8,CarriersTech_characteristics!$J$2:$J$8)*Conversions!$D$2 -> 0
A90: 5 | B90: COKING_COAL | C90: INDIA | D90: SR | E90: =_xlfn.XLOOKUP(A90,PeriodMap!$A$2:$A$45,PeriodMap!$B$2:$B$45) -> 2034 | F90: =_xlfn.XLOOKUP(_xlfn.CONCAT($B90,$D90,$E90),PEC_ProdImpConstraints!$G$2:$G$286,PEC_ProdImpConstraints!$E$2:$E$286) -> 0 | G90: =_xlfn.XLOOKUP(_xlfn.CONCAT($B90,$D90,$E90),PEC_ProdImpConstraints!$G$2:$G$286,PEC_ProdImpConstraints!$F$2:$F$286) -> 100 | H90: 0 | I90: =_xlfn.XLOOKUP(_xlfn.CONCAT($B90,$D90,$E90),PEC_Info!$L$2:$L$301,PEC_Info!$F$2:$F$301) -> 2789.0369 | J90: =_xlfn.XLOOKUP(_xlfn.CONCAT($B90,$D90,$E90),PEC_Info!$L$2:$L$301,PEC_Info!$G$2:$G$301) -> 0.3508 | K90: =_xlfn.XLOOKUP(_xlfn.CONCAT($B90,$D90,$E90),PEC_Info!$L$2:$L$301,PEC_Info!$H$2:$H$301) -> 0 | L90: =_xlfn.XLOOKUP(_xlfn.CONCAT($B90,$D90,$E90),PEC_Info!$L$2:$L$301,PEC_Info!$I$2:$I$301) -> 17232.221 | M90: =_xlfn.XLOOKUP(_xlfn.CONCAT($B90,$D90,$E90),PEC_Info!$L$2:$L$301,PEC_Info!$J$2:$J$301) -> 0.205 | N90: =_xlfn.XLOOKUP(_xlfn.CONCAT($B90,$D90,$E90),PEC_Info!$L$2:$L$301,PEC_Info!$K$2:$K$301) -> 0 | P90: =(I90*(1+J90)+K90*1000)/_xlfn.XLOOKUP(B90,CarriersTech_characteristics!$B$2:$B$8,CarriersTech_characteristics!$G$2:$G$8)/Conversions!$D$2 -> 0.00065980588 | Q90: =F90*_xlfn.XLOOKUP(B90,CarriersTech_characteristics!$B$2:$B$8,CarriersTech_characteristics!$G$2:$G$8)*Conversions!$D$2*(1-H90) -> 0 | R90: =(L90*(1+M90)+N90*1000)/_xlfn.XLOOKUP(B90,CarriersTech_characteristics!$B$2:$B$8,CarriersTech_characteristics!$J$2:$J$8)/Conversions!$D$2 -> 0.0030916331 | S90: =G90*_xlfn.XLOOKUP(B90,CarriersTech_characteristics!$B$2:$B$8,CarriersTech_characteristics!$J$2:$J$8)*Conversions!$D$2 -> 6.7164587e+08
A91: 5 | B91: COKING_COAL | C91: INDIA | D91: NER | E91: =_xlfn.XLOOKUP(A91,PeriodMap!$A$2:$A$45,PeriodMap!$B$2:$B$45) -> 2034 | F91: =_xlfn.XLOOKUP(_xlfn.CONCAT($B91,$D91,$E91),PEC_ProdImpConstraints!$G$2:$G$286,PEC_ProdImpConstraints!$E$2:$E$286) -> 0 | G91: =_xlfn.XLOOKUP(_xlfn.CONCAT($B91,$D91,$E91),PEC_ProdImpConstraints!$G$2:$G$286,PEC_ProdImpConstraints!$F$2:$F$286) -> 0 | H91: 0 | I91: =_xlfn.XLOOKUP(_xlfn.CONCAT($B91,$D91,$E91),PEC_Info!$L$2:$L$301,PEC_Info!$F$2:$F$301) -> 2789.0369 | J91: =_xlfn.XLOOKUP(_xlfn.CONCAT($B91,$D91,$E91),PEC_Info!$L$2:$L$301,PEC_Info!$G$2:$G$301) -> 0.3508 | K91: =_xlfn.XLOOKUP(_xlfn.CONCAT($B91,$D91,$E91),PEC_Info!$L$2:$L$301,PEC_Info!$H$2:$H$301) -> 0 | L91: =_xlfn.XLOOKUP(_xlfn.CONCAT($B91,$D91,$E91),PEC_Info!$L$2:$L$301,PEC_Info!$I$2:$I$301) -> 17232.221 | M91: =_xlfn.XLOOKUP(_xlfn.CONCAT($B91,$D91,$E91),PEC_Info!$L$2:$L$301,PEC_Info!$J$2:$J$301) -> 0.205 | N91: =_xlfn.XLOOKUP(_xlfn.CONCAT($B91,$D91,$E91),PEC_Info!$L$2:$L$301,PEC_Info!$K$2:$K$301) -> 0 | P91: =(I91*(1+J91)+K91*1000)/_xlfn.XLOOKUP(B91,CarriersTech_characteristics!$B$2:$B$8,CarriersTech_characteristics!$G$2:$G$8)/Conversions!$D$2 -> 0.00065980588 | Q91: =F91*_xlfn.XLOOKUP(B91,CarriersTech_characteristics!$B$2:$B$8,CarriersTech_characteristics!$G$2:$G$8)*Conversions!$D$2*(1-H91) -> 0 | R91: =(L91*(1+M91)+N91*1000)/_xlfn.XLOOKUP(B91,CarriersTech_characteristics!$B$2:$B$8,CarriersTech_characteristics!$J$2:$J$8)/Conversions!$D$2 -> 0.0030916331 | S91: =G91*_xlfn.XLOOKUP(B91,CarriersTech_characteristics!$B$2:$B$8,CarriersTech_characteristics!$J$2:$J$8)*Conversions!$D$2 -> 0
A92: 5 | B92: COKING_COAL | C92: INDIA | D92: ALL | E92: =_xlfn.XLOOKUP(A92,PeriodMap!$A$2:$A$45,PeriodMap!$B$2:$B$45) -> 2034 | F92: =SUM(F87:F91) -> 20.404638 | G92: =SUM(G87:G91) -> 300 | H92: =AVERAGE(H87:H91) -> 0 | I92: =AVERAGE(I87:I91) -> 2789.0369 | J92: =AVERAGE(J87:J91) -> 0.3508 | K92: =AVERAGE(K87:K91) -> 0 | L92: =AVERAGE(L87:L91) -> 17232.221 | M92: =AVERAGE(M87:M91) -> 0.205 | N92: =AVERAGE(N87:N91) -> 0 | P92: =AVERAGE(P87:P91) -> 0.00065980588 | Q92: =SUM(Q87:Q91) -> 1.1650861e+08 | R92: =AVERAGE(R87:R91) -> 0.0030916331 | S92: =SUM(S87:S91) -> 2.0149376e+09
A93: 6 | B93: BIOMASS | C93: INDIA | E93: =_xlfn.XLOOKUP(A93,PeriodMap!$A$2:$A$45,PeriodMap!$B$2:$B$45) -> 2039 | F93: =_xlfn.XLOOKUP(_xlfn.CONCAT($B93,$D93,$E93),PEC_ProdImpConstraints!$G$2:$G$286,PEC_ProdImpConstraints!$E$2:$E$286) -> 270 | G93: =_xlfn.XLOOKUP(_xlfn.CONCAT($B93,$D93,$E93),PEC_ProdImpConstraints!$G$2:$G$286,PEC_ProdImpConstraints!$F$2:$F$286) -> 0 | H93: =_xlfn.XLOOKUP(_xlfn.CONCAT($B93,$D93,$E93),PEC_Info!$L$2:$L$301,PEC_Info!$E$2:$E$301) -> 0 | I93: =_xlfn.XLOOKUP(_xlfn.CONCAT($B93,$D93,$E93),PEC_Info!$L$2:$L$301,PEC_Info!$F$2:$F$301) -> 5683.2536 | J93: =_xlfn.XLOOKUP(_xlfn.CONCAT($B93,$D93,$E93),PEC_Info!$L$2:$L$301,PEC_Info!$G$2:$G$301) -> 0 | K93: =_xlfn.XLOOKUP(_xlfn.CONCAT($B93,$D93,$E93),PEC_Info!$L$2:$L$301,PEC_Info!$H$2:$H$301) -> 0 | L93: =_xlfn.XLOOKUP(_xlfn.CONCAT($B93,$D93,$E93),PEC_Info!$L$2:$L$301,PEC_Info!$I$2:$I$301) -> 5683.2536 | M93: =_xlfn.XLOOKUP(_xlfn.CONCAT($B93,$D93,$E93),PEC_Info!$L$2:$L$301,PEC_Info!$J$2:$J$301) -> 0 | N93: =_xlfn.XLOOKUP(_xlfn.CONCAT($B93,$D93,$E93),PEC_Info!$L$2:$L$301,PEC_Info!$K$2:$K$301) -> 0 | P93: =(I93*(1+J93)+K93*1000)/_xlfn.XLOOKUP(B93,CarriersTech_characteristics!$B$2:$B$8,CarriersTech_characteristics!$G$2:$G$8)/Conversions!$D$2 -> 0.0013148916 | Q93: =F93*_xlfn.XLOOKUP(B93,CarriersTech_characteristics!$B$2:$B$8,CarriersTech_characteristics!$G$2:$G$8)*Conversions!$D$2*(1-H93) -> 1.167e+09 | R93: =(L93*(1+M93)+N93*1000)/_xlfn.XLOOKUP(B93,CarriersTech_characteristics!$B$2:$B$8,CarriersTech_characteristics!$J$2:$J$8)/Conversions!$D$2 -> 0.0013148916 | S93: =G93*_xlfn.XLOOKUP(B93,CarriersTech_characteristics!$B$2:$B$8,CarriersTech_characteristics!$J$2:$J$8)*Conversions!$D$2 -> 0
A94: 6 | B94: BIOMASS_WASTE | C94: INDIA | E94: =_xlfn.XLOOKUP(A94,PeriodMap!$A$2:$A$45,PeriodMap!$B$2:$B$45) -> 2039 | F94: =_xlfn.XLOOKUP(_xlfn.CONCAT($B94,$D94,$E94),PEC_ProdImpConstraints!$G$2:$G$286,PEC_ProdImpConstraints!$E$2:$E$286) -> 175 | G94: =_xlfn.XLOOKUP(_xlfn.CONCAT($B94,$D94,$E94),PEC_ProdImpConstraints!$G$2:$G$286,PEC_ProdImpConstraints!$F$2:$F$286) -> 0 | H94: =_xlfn.XLOOKUP(_xlfn.CONCAT($B94,$D94,$E94),PEC_Info!$L$2:$L$301,PEC_Info!$E$2:$E$301) -> 0 | I94: =_xlfn.XLOOKUP(_xlfn.CONCAT($B94,$D94,$E94),PEC_Info!$L$2:$L$301,PEC_Info!$F$2:$F$301) -> 9000 | J94: =_xlfn.XLOOKUP(_xlfn.CONCAT($B94,$D94,$E94),PEC_Info!$L$2:$L$301,PEC_Info!$G$2:$G$301) -> 0.05 | K94: =_xlfn.XLOOKUP(_xlfn.CONCAT($B94,$D94,$E94),PEC_Info!$L$2:$L$301,PEC_Info!$H$2:$H$301) -> 0 | L94: =_xlfn.XLOOKUP(_xlfn.CONCAT($B94,$D94,$E94),PEC_Info!$L$2:$L$301,PEC_Info!$I$2:$I$301) -> 9000 | M94: =_xlfn.XLOOKUP(_xlfn.CONCAT($B94,$D94,$E94),PEC_Info!$L$2:$L$301,PEC_Info!$J$2:$J$301) -> 0.05 | N94: =_xlfn.XLOOKUP(_xlfn.CONCAT($B94,$D94,$E94),PEC_Info!$L$2:$L$301,PEC_Info!$K$2:$K$301) -> 0 | P94: =(I94*(1+J94)+K94*1000)/_xlfn.XLOOKUP(B94,CarriersTech_characteristics!$B$2:$B$8,CarriersTech_characteristics!$G$2:$G$8)/Conversions!$D$2 -> 0.0024924961 | Q94: =F94*_xlfn.XLOOKUP(B94,CarriersTech_characteristics!$B$2:$B$8,CarriersTech_characteristics!$G$2:$G$8)*Conversions!$D$2*(1-H94) -> 6.6349151e+08 | R94: =(L94*(1+M94)+N94*1000)/_xlfn.XLOOKUP(B94,CarriersTech_characteristics!$B$2:$B$8,CarriersTech_characteristics!$J$2:$J$8)/Conversions!$D$2 -> 0.0024924961 | S94: =G94*_xlfn.XLOOKUP(B94,CarriersTech_characteristics!$B$2:$B$8,CarriersTech_characteristics!$J$2:$J$8)*Conversions!$D$2 -> 0
A95: 6 | B95: NATGAS | C95: INDIA | E95: =_xlfn.XLOOKUP(A95,PeriodMap!$A$2:$A$45,PeriodMap!$B$2:$B$45) -> 2039 | F95: =_xlfn.XLOOKUP(_xlfn.CONCAT($B95,$D95,$E95),PEC_ProdImpConstraints!$G$2:$G$286,PEC_ProdImpConstraints!$E$2:$E$286) -> 46.191493 | G95: =_xlfn.XLOOKUP(_xlfn.CONCAT($B95,$D95,$E95),PEC_ProdImpConstraints!$G$2:$G$286,PEC_ProdImpConstraints!$F$2:$F$286) -> 200 | H95: =_xlfn.XLOOKUP(_xlfn.CONCAT($B95,$D95,$E95),PEC_Info!$L$2:$L$301,PEC_Info!$E$2:$E$301) -> 0.36749121 | I95: =_xlfn.XLOOKUP(_xlfn.CONCAT($B95,$D95,$E95),PEC_Info!$L$2:$L$301,PEC_Info!$F$2:$F$301) -> 27687.519 | J95: =_xlfn.XLOOKUP(_xlfn.CONCAT($B95,$D95,$E95),PEC_Info!$L$2:$L$301,PEC_Info!$G$2:$G$301) -> 0.24 | K95: =_xlfn.XLOOKUP(_xlfn.CONCAT($B95,$D95,$E95),PEC_Info!$L$2:$L$301,PEC_Info!$H$2:$H$301) -> 0 | L95: =_xlfn.XLOOKUP(_xlfn.CONCAT($B95,$D95,$E95),PEC_Info!$L$2:$L$301,PEC_Info!$I$2:$I$301) -> 32349.616 | M95: =_xlfn.XLOOKUP(_xlfn.CONCAT($B95,$D95,$E95),PEC_Info!$L$2:$L$301,PEC_Info!$J$2:$J$301) -> 0.349 | N95: =_xlfn.XLOOKUP(_xlfn.CONCAT($B95,$D95,$E95),PEC_Info!$L$2:$L$301,PEC_Info!$K$2:$K$301) -> 0 | P95: =(I95*(1+J95)+K95*1000)/Conversions!$D$3/_xlfn.XLOOKUP(B95,CarriersTech_characteristics!$B$2:$B$8,CarriersTech_characteristics!$G$2:$G$8)/Conversions!$D$2 -> 0.0039566621 | Q95: =F95*_xlfn.XLOOKUP(B95,CarriersTech_characteristics!$B$2:$B$8,CarriersTech_characteristics!$G$2:$G$8)*Conversions!$D$2*(1-H95) -> 3.0580937e+08 | R95: =(L95*(1+M95)+N95*1000)/Conversions!$D$3/_xlfn.XLOOKUP(B95,CarriersTech_characteristics!$B$2:$B$8,CarriersTech_characteristics!$J$2:$J$8)/Conversions!$D$2 -> 0.0050292627 | S95: =G95*_xlfn.XLOOKUP(B95,CarriersTech_characteristics!$B$2:$B$8,CarriersTech_characteristics!$J$2:$J$8)*Conversions!$D$2 -> 2.0934e+09
A96: 6 | B96: THERMAL_COAL | C96: INDIA | D96: NR | E96: =_xlfn.XLOOKUP(A96,PeriodMap!$A$2:$A$45,PeriodMap!$B$2:$B$45) -> 2039 | F96: =_xlfn.XLOOKUP(_xlfn.CONCAT($B96,$D96,$E96),PEC_ProdImpConstraints!$G$2:$G$286,PEC_ProdImpConstraints!$E$2:$E$286) -> 56.06108 | G96: =_xlfn.XLOOKUP(_xlfn.CONCAT($B96,$D96,$E96),PEC_ProdImpConstraints!$G$2:$G$286,PEC_ProdImpConstraints!$F$2:$F$286) -> 0 | H96: =_xlfn.XLOOKUP(_xlfn.CONCAT($B96,$D96,$E96),PEC_Info!$L$2:$L$301,PEC_Info!$E$2:$E$301) -> 0 | I96: =_xlfn.XLOOKUP(_xlfn.CONCAT($B96,$D96,$E96),PEC_Info!$L$2:$L$301,PEC_Info!$F$2:$F$301) -> 1156.3734 | J96: =_xlfn.XLOOKUP(_xlfn.CONCAT($B96,$D96,$E96),PEC_Info!$L$2:$L$301,PEC_Info!$G$2:$G$301) -> 0.3508 | K96: =_xlfn.XLOOKUP(_xlfn.CONCAT($B96,$D96,$E96),PEC_Info!$L$2:$L$301,PEC_Info!$H$2:$H$301) -> 0 | L96: =_xlfn.XLOOKUP(_xlfn.CONCAT($B96,$D96,$E96),PEC_Info!$L$2:$L$301,PEC_Info!$I$2:$I$301) -> 7072.7195 | M96: =_xlfn.XLOOKUP(_xlfn.CONCAT($B96,$D96,$E96),PEC_Info!$L$2:$L$301,PEC_Info!$J$2:$J$301) -> 0.205 | N96: =_xlfn.XLOOKUP(_xlfn.CONCAT($B96,$D96,$E96),PEC_Info!$L$2:$L$301,PEC_Info!$K$2:$K$301) -> 0 | P96: =(I96*(1+J96)+K96*1000)/_xlfn.XLOOKUP(B96,CarriersTech_characteristics!$B$2:$B$8,CarriersTech_characteristics!$G$2:$G$8)/Conversions!$D$2 -> 0.00032679978 | Q96: =F96*_xlfn.XLOOKUP(B96,CarriersTech_characteristics!$B$2:$B$8,CarriersTech_characteristics!$G$2:$G$8)*Conversions!$D$2*(1-H96) -> 2.6795932e+08 | R96: =(L96*(1+M96)+N96*1000)/_xlfn.XLOOKUP(B96,CarriersTech_characteristics!$B$2:$B$8,CarriersTech_characteristics!$J$2:$J$8)/Conversions!$D$2 -> 0.001357063 | S96: =G96*_xlfn.XLOOKUP(B96,CarriersTech_characteristics!$B$2:$B$8,CarriersTech_characteristics!$J$2:$J$8)*Conversions!$D$2 -> 0
A97: 6 | B97: THERMAL_COAL | C97: INDIA | D97: NER | E97: =_xlfn.XLOOKUP(A97,PeriodMap!$A$2:$A$45,PeriodMap!$B$2:$B$45) -> 2039 | F97: =_xlfn.XLOOKUP(_xlfn.CONCAT($B97,$D97,$E97),PEC_ProdImpConstraints!$G$2:$G$286,PEC_ProdImpConstraints!$E$2:$E$286) -> 0 | G97: =_xlfn.XLOOKUP(_xlfn.CONCAT($B97,$D97,$E97),PEC_ProdImpConstraints!$G$2:$G$286,PEC_ProdImpConstraints!$F$2:$F$286) -> 0 | H97: =_xlfn.XLOOKUP(_xlfn.CONCAT($B97,$D97,$E97),PEC_Info!$L$2:$L$301,PEC_Info!$E$2:$E$301) -> 0 | I97: =_xlfn.XLOOKUP(_xlfn.CONCAT($B97,$D97,$E97),PEC_Info!$L$2:$L$301,PEC_Info!$F$2:$F$301) -> 1156.3734 | J97: =_xlfn.XLOOKUP(_xlfn.CONCAT($B97,$D97,$E97),PEC_Info!$L$2:$L$301,PEC_Info!$G$2:$G$301) -> 0.3508 | K97: =_xlfn.XLOOKUP(_xlfn.CONCAT($B97,$D97,$E97),PEC_Info!$L$2:$L$301,PEC_Info!$H$2:$H$301) -> 0 | L97: =_xlfn.XLOOKUP(_xlfn.CONCAT($B97,$D97,$E97),PEC_Info!$L$2:$L$301,PEC_Info!$I$2:$I$301) -> 7072.7195 | M97: =_xlfn.XLOOKUP(_xlfn.CONCAT($B97,$D97,$E97),PEC_Info!$L$2:$L$301,PEC_Info!$J$2:$J$301) -> 0.205 | N97: =_xlfn.XLOOKUP(_xlfn.CONCAT($B97,$D97,$E97),PEC_Info!$L$2:$L$301,PEC_Info!$K$2:$K$301) -> 0 | P97: =(I97*(1+J97)+K97*1000)/_xlfn.XLOOKUP(B97,CarriersTech_characteristics!$B$2:$B$8,CarriersTech_characteristics!$G$2:$G$8)/Conversions!$D$2 -> 0.00032679978 | Q97: =F97*_xlfn.XLOOKUP(B97,CarriersTech_characteristics!$B$2:$B$8,CarriersTech_characteristics!$G$2:$G$8)*Conversions!$D$2*(1-H97) -> 0 | R97: =(L97*(1+M97)+N97*1000)/_xlfn.XLOOKUP(B97,CarriersTech_characteristics!$B$2:$B$8,CarriersTech_characteristics!$J$2:$J$8)/Conversions!$D$2 -> 0.001357063 | S97: =G97*_xlfn.XLOOKUP(B97,CarriersTech_characteristics!$B$2:$B$8,CarriersTech_characteristics!$J$2:$J$8)*Conversions!$D$2 -> 0
A98: 6 | B98: THERMAL_COAL | C98: INDIA | D98: ER | E98: =_xlfn.XLOOKUP(A98,PeriodMap!$A$2:$A$45,PeriodMap!$B$2:$B$45) -> 2039 | F98: =_xlfn.XLOOKUP(_xlfn.CONCAT($B98,$D98,$E98),PEC_ProdImpConstraints!$G$2:$G$286,PEC_ProdImpConstraints!$E$2:$E$286) -> 960.66915 | G98: =_xlfn.XLOOKUP(_xlfn.CONCAT($B98,$D98,$E98),PEC_ProdImpConstraints!$G$2:$G$286,PEC_ProdImpConstraints!$F$2:$F$286) -> 150 | H98: =_xlfn.XLOOKUP(_xlfn.CONCAT($B98,$D98,$E98),PEC_Info!$L$2:$L$301,PEC_Info!$E$2:$E$301) -> 0 | I98: =_xlfn.XLOOKUP(_xlfn.CONCAT($B98,$D98,$E98),PEC_Info!$L$2:$L$301,PEC_Info!$F$2:$F$301) -> 1156.3734 | J98: =_xlfn.XLOOKUP(_xlfn.CONCAT($B98,$D98,$E98),PEC_Info!$L$2:$L$301,PEC_Info!$G$2:$G$301) -> 0.3508 | K98: =_xlfn.XLOOKUP(_xlfn.CONCAT($B98,$D98,$E98),PEC_Info!$L$2:$L$301,PEC_Info!$H$2:$H$301) -> 0 | L98: =_xlfn.XLOOKUP(_xlfn.CONCAT($B98,$D98,$E98),PEC_Info!$L$2:$L$301,PEC_Info!$I$2:$I$301) -> 7072.7195 | M98: =_xlfn.XLOOKUP(_xlfn.CONCAT($B98,$D98,$E98),PEC_Info!$L$2:$L$301,PEC_Info!$J$2:$J$301) -> 0.205 | N98: =_xlfn.XLOOKUP(_xlfn.CONCAT($B98,$D98,$E98),PEC_Info!$L$2:$L$301,PEC_Info!$K$2:$K$301) -> 0 | P98: =(I98*(1+J98)+K98*1000)/_xlfn.XLOOKUP(B98,CarriersTech_characteristics!$B$2:$B$8,CarriersTech_characteristics!$G$2:$G$8)/Conversions!$D$2 -> 0.00032679978 | Q98: =F98*_xlfn.XLOOKUP(B98,CarriersTech_characteristics!$B$2:$B$8,CarriersTech_characteristics!$G$2:$G$8)*Conversions!$D$2*(1-H98) -> 4.5917818e+09 | R98: =(L98*(1+M98)+N98*1000)/_xlfn.XLOOKUP(B98,CarriersTech_characteristics!$B$2:$B$8,CarriersTech_characteristics!$J$2:$J$8)/Conversions!$D$2 -> 0.001357063 | S98: =G98*_xlfn.XLOOKUP(B98,CarriersTech_characteristics!$B$2:$B$8,CarriersTech_characteristics!$J$2:$J$8)*Conversions!$D$2 -> 9.4203001e+08
A99: 6 | B99: THERMAL_COAL | C99: INDIA | D99: WR | E99: =_xlfn.XLOOKUP(A99,PeriodMap!$A$2:$A$45,PeriodMap!$B$2:$B$45) -> 2039 | F99: =_xlfn.XLOOKUP(_xlfn.CONCAT($B99,$D99,$E99),PEC_ProdImpConstraints!$G$2:$G$286,PEC_ProdImpConstraints!$E$2:$E$286) -> 961.97451 | G99: =_xlfn.XLOOKUP(_xlfn.CONCAT($B99,$D99,$E99),PEC_ProdImpConstraints!$G$2:$G$286,PEC_ProdImpConstraints!$F$2:$F$286) -> 150 | H99: =_xlfn.XLOOKUP(_xlfn.CONCAT($B99,$D99,$E99),PEC_Info!$L$2:$L$301,PEC_Info!$E$2:$E$301) -> 0 | I99: =_xlfn.XLOOKUP(_xlfn.CONCAT($B99,$D99,$E99),PEC_Info!$L$2:$L$301,PEC_Info!$F$2:$F$301) -> 1156.3734 | J99: =_xlfn.XLOOKUP(_xlfn.CONCAT($B99,$D99,$E99),PEC_Info!$L$2:$L$301,PEC_Info!$G$2:$G$301) -> 0.3508 | K99: =_xlfn.XLOOKUP(_xlfn.CONCAT($B99,$D99,$E99),PEC_Info!$L$2:$L$301,PEC_Info!$H$2:$H$301) -> 0 | L99: =_xlfn.XLOOKUP(_xlfn.CONCAT($B99,$D99,$E99),PEC_Info!$L$2:$L$301,PEC_Info!$I$2:$I$301) -> 7072.7195 | M99: =_xlfn.XLOOKUP(_xlfn.CONCAT($B99,$D99,$E99),PEC_Info!$L$2:$L$301,PEC_Info!$J$2:$J$301) -> 0.205 | N99: =_xlfn.XLOOKUP(_xlfn.CONCAT($B99,$D99,$E99),PEC_Info!$L$2:$L$301,PEC_Info!$K$2:$K$301) -> 0 | P99: =(I99*(1+J99)+K99*1000)/_xlfn.XLOOKUP(B99,CarriersTech_characteristics!$B$2:$B$8,CarriersTech_characteristics!$G$2:$G$8)/Conversions!$D$2 -> 0.00032679978 | Q99: =F99*_xlfn.XLOOKUP(B99,CarriersTech_characteristics!$B$2:$B$8,CarriersTech_characteristics!$G$2:$G$8)*Conversions!$D$2*(1-H99) -> 4.5980211e+09 | R99: =(L99*(1+M99)+N99*1000)/_xlfn.XLOOKUP(B99,CarriersTech_characteristics!$B$2:$B$8,CarriersTech_characteristics!$J$2:$J$8)/Conversions!$D$2 -> 0.001357063 | S99: =G99*_xlfn.XLOOKUP(B99,CarriersTech_characteristics!$B$2:$B$8,CarriersTech_characteristics!$J$2:$J$8)*Conversions!$D$2 -> 9.4203001e+08
A100: 6 | B100: THERMAL_COAL | C100: INDIA | D100: SR | E100: =_xlfn.XLOOKUP(A100,PeriodMap!$A$2:$A$45,PeriodMap!$B$2:$B$45) -> 2039 | F100: =_xlfn.XLOOKUP(_xlfn.CONCAT($B100,$D100,$E100),PEC_ProdImpConstraints!$G$2:$G$286,PEC_ProdImpConstraints!$E$2:$E$286) -> 101.54577 | G100: =_xlfn.XLOOKUP(_xlfn.CONCAT($B100,$D100,$E100),PEC_ProdImpConstraints!$G$2:$G$286,PEC_ProdImpConstraints!$F$2:$F$286) -> 150 | H100: =_xlfn.XLOOKUP(_xlfn.CONCAT($B100,$D100,$E100),PEC_Info!$L$2:$L$301,PEC_Info!$E$2:$E$301) -> 0 | I100: =_xlfn.XLOOKUP(_xlfn.CONCAT($B100,$D100,$E100),PEC_Info!$L$2:$L$301,PEC_Info!$F$2:$F$301) -> 1156.3734 | J100: =_xlfn.XLOOKUP(_xlfn.CONCAT($B100,$D100,$E100),PEC_Info!$L$2:$L$301,PEC_Info!$G$2:$G$301) -> 0.3508 | K100: =_xlfn.XLOOKUP(_xlfn.CONCAT($B100,$D100,$E100),PEC_Info!$L$2:$L$301,PEC_Info!$H$2:$H$301) -> 0 | L100: =_xlfn.XLOOKUP(_xlfn.CONCAT($B100,$D100,$E100),PEC_Info!$L$2:$L$301,PEC_Info!$I$2:$I$301) -> 7072.7195 | M100: =_xlfn.XLOOKUP(_xlfn.CONCAT($B100,$D100,$E100),PEC_Info!$L$2:$L$301,PEC_Info!$J$2:$J$301) -> 0.205 | N100: =_xlfn.XLOOKUP(_xlfn.CONCAT($B100,$D100,$E100),PEC_Info!$L$2:$L$301,PEC_Info!$K$2:$K$301) -> 0 | P100: =(I100*(1+J100)+K100*1000)/_xlfn.XLOOKUP(B100,CarriersTech_characteristics!$B$2:$B$8,CarriersTech_characteristics!$G$2:$G$8)/Conversions!$D$2 -> 0.00032679978 | Q100: =F100*_xlfn.XLOOKUP(B100,CarriersTech_characteristics!$B$2:$B$8,CarriersTech_characteristics!$G$2:$G$8)*Conversions!$D$2*(1-H100) -> 4.8536587e+08 | R100: =(L100*(1+M100)+N100*1000)/_xlfn.XLOOKUP(B100,CarriersTech_characteristics!$B$2:$B$8,CarriersTech_characteristics!$J$2:$J$8)/Conversions!$D$2 -> 0.001357063 | S100: =G100*_xlfn.XLOOKUP(B100,CarriersTech_characteristics!$B$2:$B$8,CarriersTech_characteristics!$J$2:$J$8)*Conversions!$D$2 -> 9.4203001e+08
...

Sheet assetsEG
A1: Source::File | H1: PIER::EnergyConvTechnologies.csv | I1: PIER::EnergyConvTechnologies.csv | J1: PIER::EnergyConvTechnologies.csv | K1: PIER::EnergyConvTechnologies.csv | L1: PIER2.0_ECT::EfficiencyCostMaxAnnual.csv | M1: PIER2.0_ECT::EfficiencyCostMaxAnnual.csv | N1: PIER2.0_ECT::EfficiencyCostMaxAnnual.csv | O1: PIER2.0_ECT::EfficiencyCostMaxAnnual.csv | P1: PIER2.0::ECT_Lifetime.csv | Q1: PIER2.0::ECT_OperationalInfo.csv | R1: PIER2.0::ECT_OperationalInfo.csv | S1: PIER2.0::ECT_OperationalInfo.csv | T1: PIER2.0::ECT_LegacyCapacity.csv - PIER2.0::ECT_LegacyRetirement.csv | U1: PIER2.0::ECT_CapAddBounds.csv | V1: PIER2.0::ECT_CapAddBounds.csv | W1: PIER2.0::PhysicalDerivedCarriers.csv | X1: PIER2.0::PhysicalCarrierEmissions.csv or for coal, PIER2.0::ECT_EmissionDetails.csv | Y1: PIER2.0::ECT_EfficiencyCostMaxAnnualUF.xlsx | Z1: PIER2.0::ECT_EfficiencyCostMaxAnnualUF.xlsx
A2: PIER2.0 var name | B2: EnergyConvTech | C2: SubGeography1 | G2: ModelGeography | H2: CapacityUnit | I2: InputEC | J2: OutputDEC | K2: AnnualOutputPerUnitCapacity | L2: ConvEff | M2: MaxAnnualUF | N2: FixedCost | O2: VarCost | P2: Lifetime | Q2: SelfCons | R2: MaxRampUpRate | S2: MaxRampDownRate | T2: LegacyCapacity & RetCapacity | U2: MinCapacity | V2: MaxCapacity | W2: DomEnergyDensity | X2: DomEmissionFactor
A3: Variable | L3: a | M3: b | N3: c | O3: d | P3: e | Q3: f | R3: g | S3: h | T3: i | U3: k | V3: l | W3: m | X3: n | Y3: o | Z3: p | AB3: aa | AC3: bb | AD3: cc | AE3: dd | AF3: ee | AG3: ff | AH3: gg | AI3: hh | AJ3: ii
A4: description | C4: model geography | H4: all units in macro are given in the selected value | I4: energy carrier | J4: energy carrier | K4: model granularity | L4: efficiency of conversion of energy input to output | M4: max utilization factor (over whole year) ** this must be considered alongside availability for technology provided in ECT_Max_CUF.csv to arrive at more granular availability profiles (see code) | N4: annuity on existiting capacity | O4: variable cost per Mt of input energy carrier | P4: lifetime of asset | Q4: % of energy input consumed by technology (not part of output) | T4: legacy/existing | U4: pipeline builds | V4: maximum additions | W4: given | X4: given | Y4: given Fixed O&M (PIER or assumed), adjusted to 2024Rs from 2020Rs | Z4: given discount rate from PIER2.0 workbook, No adjustment made | AB4: self-consumption adjsuted fuel consumption of generating unit | AC4: self-consumption adjusted efficiency | AD4: doemstic only, need imported ! | AG4: This is without fixed O&M as expected by Macro | AH4: For existing infrastructure this is half operational lifetime, rounded to integer as Macro will fail if given decimal
A5: Equation to Macro var | H5: given / 1000 | I5: given | N5: given/1000 | P5: given | R5: given | S5: given | T5: = given legacy cap * 1000 - given retirement *1000 | U5: = given*1000 | V5: = given*1000 | Y5: = given fixed o&m | Z5: = given | AB5: = 1 / a / (1 -f) | AC5: = a - f | AD5: = ( m * conversion_if_not _MT) / (n * conversion_PJ_to_MWh) | AE5: = d / m/ conversion_PJ_to_MWh * aa | AF5: = o * 2020 to 2024 inflator | AG5: = c - ee | AH5: = round ( fe/ 2 , 0) | AI5: = p / ( 1-(1+p)^(-gg)) | AJ5: = ff / hh
A6: Macro variable | C6: location | E6: type | F6: id | I6: fuel_commodity | N6: annualized_investment_cost | P6: lifetime of asset | R6: ramp_up_fraction | S6: ramp_down_fraction | T6: min & max_capacity | U6: min_capcity | V6: max_capacity | Z6: wacc | AB6: fuel_consumption | AC6: discharge_efficiency | AD6: emission_rate | AE6: variable_om_cost | AF6: fixed_om_cost | AG6: annualized_investment_cost | AH6: capital_recovery_period | AI6: CRF | AJ6: investment_cost
A7: period | D7: year | L7: % | M7: % | N7: million Rs2024/MW | O7: million Rs / Mt | P7: years | Q7: % | R7: fraction of capacity | S7: fraction of capacity | T7: MW | U7: MW | V7: MW | W7: PJ/MT or PJ/BCM | X7: tonnes CO2/MT (no BCM) | Y7: million 2020Rs/year | Z7: % | AB7: MWin per Mwout | AC7: % | AD7: tCO2/MWh input | AE7: millionRs/MWh-elec | AF7: million 2024Rs/year | AG7: million 2024Rs/year | AH7: years | AI7: % total investment per capital recovery year | AJ7: million 2024Rs
A8: 1 | B8: EG_COAL | C8: NR | D8: =_xlfn.XLOOKUP(A8,PeriodMap!$A$2:$A$45,PeriodMap!$B$2:$B$45) -> 2023 | E8: ThermalPower | F8: coal_legacy | G8: INDIA | H8: MW | I8: THERMAL_COAL | J8: ELECTRICITY | K8: 8760 | L8: =_xlfn.XLOOKUP(_xlfn.CONCAT($B8,$C8,$D8),ECT_EfficiencyCostMaxAnnualUF!$J$2:$J$12484,ECT_EfficiencyCostMaxAnnualUF!$F$2:$F$12484) -> 0.3664022 | M8: =_xlfn.XLOOKUP(_xlfn.CONCAT($B8,$C8,$D8),ECT_EfficiencyCostMaxAnnualUF!$J$2:$J$12484,ECT_EfficiencyCostMaxAnnualUF!$I$2:$I$12484) -> 0.85 | N8: =_xlfn.XLOOKUP(_xlfn.CONCAT($B8,$C8,$D8),ECT_EfficiencyCostMaxAnnualUF!$J$2:$J$12484,ECT_EfficiencyCostMaxAnnualUF!$G$2:$G$12484)/1000 -> 11.751599 | O8: =_xlfn.XLOOKUP(_xlfn.CONCAT($B8,$C8,$D8),ECT_EfficiencyCostMaxAnnualUF!$J$2:$J$12484,ECT_EfficiencyCostMaxAnnualUF!$H$2:$H$12484) -> 133.52302 | P8: =_xlfn.XLOOKUP(_xlfn.CONCAT($B8,$D8+1),ECT_Lifetime!$D$2:$D$1000,ECT_Lifetime!$C$2:$C$1000) -> 40 | Q8: =_xlfn.XLOOKUP(_xlfn.CONCAT($B8,$D8),ECT_OperationalInfo!$G$2:$G$362,ECT_OperationalInfo!$D$2:$D$362) -> 0.0745 | R8: =_xlfn.XLOOKUP(_xlfn.CONCAT($B8,$D8),ECT_OperationalInfo!$G$2:$G$362,ECT_OperationalInfo!$E$2:$E$362) -> 0.3 | S8: =_xlfn.XLOOKUP(_xlfn.CONCAT($B8,$D8),ECT_OperationalInfo!$G$2:$G$362,ECT_OperationalInfo!$F$2:$F$362) -> 0.3 | T8: =SUMIF(ECT_LegacyCapacity!$F$2:$F$257,_xlfn.CONCAT($C8,$B8),ECT_LegacyCapacity!$E$2:$E$257)*1000-IFERROR(SUMIFS(ECT_LegacyRetirement!$F$2:$F$2701,ECT_LegacyRetirement!$G$2:$G$2701,_xlfn.CONCAT($B8,$C8),ECT_LegacyRetirement!$E$2:$E$2701,"<="&D8)*1000,0) -> 67226.539 | U8: =IFERROR(SUMIFS(ECT_CapAddBounds!$F$2:$F$5959,ECT_CapAddBounds!$H$2:$H$5959,_xlfn.CONCAT($B8,$C8),ECT_CapAddBounds!$E$2:$E$5959,"<="&D8)*1000,0) -> 0 | V8: =IFERROR(SUMIFS(ECT_CapAddBounds!$G$2:$G$5959,ECT_CapAddBounds!$H$2:$H$5959,_xlfn.CONCAT($B8,$C8),ECT_CapAddBounds!$E$2:$E$5959,"<="&D8)*1000,0) -> 0 | W8: =CarriersTech_characteristics!$G$2 -> 17.207188 | X8: =CarriersTech_characteristics!$H$28*1000 -> 1942097.6 | Y8: 3 | Z8: 0.105 | AB8: =1/L8/(1-Q8) -> 2.9489371 | AD8: =X8/(W8*Conversions!$D$2) -> 0.40631575 | AE8: =O8/W8/Conversions!$D$2*AB8 -> 8.237857e-05 | AF8: =Y8*Conversions!$D$4 -> 3.7167527 | AG8: =N8-AF8 -> 8.0348465 | AH8: =ROUND(P8/2,0) -> 20 | AI8: =Z8/(1-(1+Z8)^-AH8) -> 0.12149327 | AJ8: =AG8/AI8 -> 66.13409
A9: 1 | B9: EG_CCGT | C9: NR | D9: =_xlfn.XLOOKUP(A9,PeriodMap!$A$2:$A$45,PeriodMap!$B$2:$B$45) -> 2023 | E9: ThermalPower | F9: NG_CCGT_legacy | G9: INDIA | H9: MW | I9: NATGAS | J9: ELECTRICITY | K9: 8760 | L9: =_xlfn.XLOOKUP(_xlfn.CONCAT($B9,$C9,$D9),ECT_EfficiencyCostMaxAnnualUF!$J$2:$J$12484,ECT_EfficiencyCostMaxAnnualUF!$F$2:$F$12484) -> 0.40444272 | M9: =_xlfn.XLOOKUP(_xlfn.CONCAT($B9,$C9,$D9),ECT_EfficiencyCostMaxAnnualUF!$J$2:$J$12484,ECT_EfficiencyCostMaxAnnualUF!$I$2:$I$12484) -> 0.85 | N9: =_xlfn.XLOOKUP(_xlfn.CONCAT($B9,$C9,$D9),ECT_EfficiencyCostMaxAnnualUF!$J$2:$J$12484,ECT_EfficiencyCostMaxAnnualUF!$G$2:$G$12484)/1000 -> 8.5122278 | O9: =_xlfn.XLOOKUP(_xlfn.CONCAT($B9,$C9,$D9),ECT_EfficiencyCostMaxAnnualUF!$J$2:$J$12484,ECT_EfficiencyCostMaxAnnualUF!$H$2:$H$12484) -> 0 | P9: =_xlfn.XLOOKUP(_xlfn.CONCAT($B9,$D9+1),ECT_Lifetime!$D$2:$D$1000,ECT_Lifetime!$C$2:$C$1000) -> 25 | Q9: =_xlfn.XLOOKUP(_xlfn.CONCAT($B9,$D9),ECT_OperationalInfo!$G$2:$G$362,ECT_OperationalInfo!$D$2:$D$362) -> 0.02 | R9: =_xlfn.XLOOKUP(_xlfn.CONCAT($B9,$D9),ECT_OperationalInfo!$G$2:$G$362,ECT_OperationalInfo!$E$2:$E$362) -> 0.9 | S9: =_xlfn.XLOOKUP(_xlfn.CONCAT($B9,$D9),ECT_OperationalInfo!$G$2:$G$362,ECT_OperationalInfo!$F$2:$F$362) -> 0.9 | T9: =SUMIF(ECT_LegacyCapacity!$F$2:$F$257,_xlfn.CONCAT($C9,$B9),ECT_LegacyCapacity!$E$2:$E$257)*1000-IFERROR(SUMIFS(ECT_LegacyRetirement!$F$2:$F$2701,ECT_LegacyRetirement!$G$2:$G$2701,_xlfn.CONCAT($B9,$C9),ECT_LegacyRetirement!$E$2:$E$2701,"<="&D9)*1000,0) -> 7330.5467 | U9: =IFERROR(SUMIFS(ECT_CapAddBounds!$F$2:$F$5959,ECT_CapAddBounds!$H$2:$H$5959,_xlfn.CONCAT($B9,$C9),ECT_CapAddBounds!$E$2:$E$5959,"<="&D9)*1000,0) -> 0 | V9: =IFERROR(SUMIFS(ECT_CapAddBounds!$G$2:$G$5959,ECT_CapAddBounds!$H$2:$H$5959,_xlfn.CONCAT($B9,$C9),ECT_CapAddBounds!$E$2:$E$5959,"<="&D9)*1000,0) -> 0 | W9: =CarriersTech_characteristics!$G$3 -> 37.6812 | X9: =CarriersTech_characteristics!$H$3*1000 -> 3025024.5 | Y9: 2.9 | Z9: 0.105 | AB9: =1/L9/(1-Q9) -> 2.522998 | AD9: =(X9*Conversions!$D$3)/(W9*Conversions!$D$2) -> 0.23958587 | AE9: 0 | AF9: =Y9*Conversions!$D$4 -> 3.592861 | AG9: =N9-AF9 -> 4.9193668 | AH9: =ROUND(P9/2,0) -> 13 | AI9: =Z9/(1-(1+Z9)^-AH9) -> 0.14444512 | AJ9: =AG9/AI9 -> 34.056996
A10: 1 | B10: EG_OCGT | C10: NR | D10: =_xlfn.XLOOKUP(A10,PeriodMap!$A$2:$A$45,PeriodMap!$B$2:$B$45) -> 2023 | E10: ThermalPower | G10: INDIA | H10: MW | I10: NATGAS | J10: ELECTRICITY | K10: 8760 | L10: =_xlfn.XLOOKUP(_xlfn.CONCAT($B10,$C10,$D10),ECT_EfficiencyCostMaxAnnualUF!$J$2:$J$12484,ECT_EfficiencyCostMaxAnnualUF!$F$2:$F$12484) -> 0.28070163 | M10: =_xlfn.XLOOKUP(_xlfn.CONCAT($B10,$C10,$D10),ECT_EfficiencyCostMaxAnnualUF!$J$2:$J$12484,ECT_EfficiencyCostMaxAnnualUF!$I$2:$I$12484) -> 0.85 | N10: =_xlfn.XLOOKUP(_xlfn.CONCAT($B10,$C10,$D10),ECT_EfficiencyCostMaxAnnualUF!$J$2:$J$12484,ECT_EfficiencyCostMaxAnnualUF!$G$2:$G$12484)/1000 -> 6.6797506 | O10: =_xlfn.XLOOKUP(_xlfn.CONCAT($B10,$C10,$D10),ECT_EfficiencyCostMaxAnnualUF!$J$2:$J$12484,ECT_EfficiencyCostMaxAnnualUF!$H$2:$H$12484) -> 0 | P10: =_xlfn.XLOOKUP(_xlfn.CONCAT($B10,$D10+1),ECT_Lifetime!$D$2:$D$1000,ECT_Lifetime!$C$2:$C$1000) -> 25 | Q10: =_xlfn.XLOOKUP(_xlfn.CONCAT($B10,$D10),ECT_OperationalInfo!$G$2:$G$362,ECT_OperationalInfo!$D$2:$D$362) -> 0.01 | R10: =_xlfn.XLOOKUP(_xlfn.CONCAT($B10,$D10),ECT_OperationalInfo!$G$2:$G$362,ECT_OperationalInfo!$E$2:$E$362) -> 1 | S10: =_xlfn.XLOOKUP(_xlfn.CONCAT($B10,$D10),ECT_OperationalInfo!$G$2:$G$362,ECT_OperationalInfo!$F$2:$F$362) -> 1 | T10: =SUMIF(ECT_LegacyCapacity!$F$2:$F$257,_xlfn.CONCAT($C10,$B10),ECT_LegacyCapacity!$E$2:$E$257)*1000-IFERROR(SUMIFS(ECT_LegacyRetirement!$F$2:$F$2701,ECT_LegacyRetirement!$G$2:$G$2701,_xlfn.CONCAT($B10,$C10),ECT_LegacyRetirement!$E$2:$E$2701,"<="&D10)*1000,0) -> 0 | U10: =IFERROR(SUMIFS(ECT_CapAddBounds!$F$2:$F$5959,ECT_CapAddBounds!$H$2:$H$5959,_xlfn.CONCAT($B10,$C10),ECT_CapAddBounds!$E$2:$E$5959,"<="&D10)*1000,0) -> 0 | V10: =IFERROR(SUMIFS(ECT_CapAddBounds!$G$2:$G$5959,ECT_CapAddBounds!$H$2:$H$5959,_xlfn.CONCAT($B10,$C10),ECT_CapAddBounds!$E$2:$E$5959,"<="&D10)*1000,0) -> 0 | W10: =CarriersTech_characteristics!$G$3 -> 37.6812 | X10: =CarriersTech_characteristics!$H$3*1000 -> 3025024.5 | Y10: 0.7 | Z10: 0.105 | AB10: =1/L10/(1-Q10) -> 3.5984865 | AD10: =(X10*Conversions!$D$3)/(W10*Conversions!$D$2) -> 0.23958587 | AE10: 0 | AF10: =Y10*Conversions!$D$4 -> 0.86724231 | AG10: =N10-AF10 -> 5.8125083 | AH10: =ROUND(P10/2,0) -> 13 | AI10: =Z10/(1-(1+Z10)^-AH10) -> 0.14444512 | AJ10: =AG10/AI10 -> 40.240255
A11: 1 | B11: EG_PHWR | C11: NR | D11: =_xlfn.XLOOKUP(A11,PeriodMap!$A$2:$A$45,PeriodMap!$B$2:$B$45) -> 2023 | E11: ThermalPower | F11: nuclear_PHWR_legacy | G11: INDIA | H11: MW | I11: ATOMIC | J11: ELECTRICITY | K11: 8760 | L11: =_xlfn.XLOOKUP(_xlfn.CONCAT($B11,$C11,$D11),ECT_EfficiencyCostMaxAnnualUF!$J$2:$J$12484,ECT_EfficiencyCostMaxAnnualUF!$F$2:$F$12484) -> 1 | M11: =_xlfn.XLOOKUP(_xlfn.CONCAT($B11,$C11,$D11),ECT_EfficiencyCostMaxAnnualUF!$J$2:$J$12484,ECT_EfficiencyCostMaxAnnualUF!$I$2:$I$12484) -> 0.70916667 | N11: =_xlfn.XLOOKUP(_xlfn.CONCAT($B11,$C11,$D11),ECT_EfficiencyCostMaxAnnualUF!$J$2:$J$12484,ECT_EfficiencyCostMaxAnnualUF!$G$2:$G$12484)/1000 -> 20.83321 | O11: =_xlfn.XLOOKUP(_xlfn.CONCAT($B11,$C11,$D11),ECT_EfficiencyCostMaxAnnualUF!$J$2:$J$12484,ECT_EfficiencyCostMaxAnnualUF!$H$2:$H$12484) -> 0 | P11: =_xlfn.XLOOKUP(_xlfn.CONCAT($B11,$D11+1),ECT_Lifetime!$D$2:$D$1000,ECT_Lifetime!$C$2:$C$1000) -> 40 | Q11: =_xlfn.XLOOKUP(_xlfn.CONCAT($B11,$D11),ECT_OperationalInfo!$G$2:$G$362,ECT_OperationalInfo!$D$2:$D$362) -> 0.1078 | R11: =_xlfn.XLOOKUP(_xlfn.CONCAT($B11,$D11),ECT_OperationalInfo!$G$2:$G$362,ECT_OperationalInfo!$E$2:$E$362) -> 0.01 | S11: =_xlfn.XLOOKUP(_xlfn.CONCAT($B11,$D11),ECT_OperationalInfo!$G$2:$G$362,ECT_OperationalInfo!$F$2:$F$362) -> 0.01 | T11: =SUMIF(ECT_LegacyCapacity!$F$2:$F$257,_xlfn.CONCAT($C11,$B11),ECT_LegacyCapacity!$E$2:$E$257)*1000-IFERROR(SUMIFS(ECT_LegacyRetirement!$F$2:$F$2701,ECT_LegacyRetirement!$G$2:$G$2701,_xlfn.CONCAT($B11,$C11),ECT_LegacyRetirement!$E$2:$E$2701,"<="&D11)*1000,0) -> 1603.5184 | U11: =IFERROR(SUMIFS(ECT_CapAddBounds!$F$2:$F$5959,ECT_CapAddBounds!$H$2:$H$5959,_xlfn.CONCAT($B11,$C11),ECT_CapAddBounds!$E$2:$E$5959,"<="&D11)*1000,0) -> 0 | V11: =IFERROR(SUMIFS(ECT_CapAddBounds!$G$2:$G$5959,ECT_CapAddBounds!$H$2:$H$5959,_xlfn.CONCAT($B11,$C11),ECT_CapAddBounds!$E$2:$E$5959,"<="&D11)*1000,0) -> 0 | Y11: 4.3 | Z11: 0.105 | AB11: =1/L11/(1-Q11) -> 1.1208249 | AE11: 0 | AF11: =Y11*Conversions!$D$4 -> 5.3273456 | AG11: =N11-AF11 -> 15.505865 | AH11: =ROUND(P11/2,0) -> 20 | AI11: =Z11/(1-(1+Z11)^-AH11) -> 0.12149327 | AJ11: =AG11/AI11 -> 127.62736
A12: 1 | B12: EG_SMR | C12: NR | D12: =_xlfn.XLOOKUP(A12,PeriodMap!$A$2:$A$45,PeriodMap!$B$2:$B$45) -> 2023 | E12: ThermalPower | G12: INDIA | H12: MW | I12: ATOMIC | J12: ELECTRICITY | K12: 8760 | L12: =_xlfn.XLOOKUP(_xlfn.CONCAT($B12,$C12,$D12),ECT_EfficiencyCostMaxAnnualUF!$J$2:$J$12484,ECT_EfficiencyCostMaxAnnualUF!$F$2:$F$12484) -> #N/A | M12: =_xlfn.XLOOKUP(_xlfn.CONCAT($B12,$C12,$D12),ECT_EfficiencyCostMaxAnnualUF!$J$2:$J$12484,ECT_EfficiencyCostMaxAnnualUF!$I$2:$I$12484) -> #N/A | N12: =_xlfn.XLOOKUP(_xlfn.CONCAT($B12,$C12,$D12),ECT_EfficiencyCostMaxAnnualUF!$J$2:$J$12484,ECT_EfficiencyCostMaxAnnualUF!$G$2:$G$12484)/1000 -> #N/A | O12: =_xlfn.XLOOKUP(_xlfn.CONCAT($B12,$C12,$D12),ECT_EfficiencyCostMaxAnnualUF!$J$2:$J$12484,ECT_EfficiencyCostMaxAnnualUF!$H$2:$H$12484) -> #N/A | P12: =_xlfn.XLOOKUP(_xlfn.CONCAT($B12,$D12+1),ECT_Lifetime!$D$2:$D$1000,ECT_Lifetime!$C$2:$C$1000) -> 30 | Q12: =_xlfn.XLOOKUP(_xlfn.CONCAT($B12,$D12),ECT_OperationalInfo!$G$2:$G$362,ECT_OperationalInfo!$D$2:$D$362) -> 0.05 | R12: =_xlfn.XLOOKUP(_xlfn.CONCAT($B12,$D12),ECT_OperationalInfo!$G$2:$G$362,ECT_OperationalInfo!$E$2:$E$362) -> 0.01 | S12: =_xlfn.XLOOKUP(_xlfn.CONCAT($B12,$D12),ECT_OperationalInfo!$G$2:$G$362,ECT_OperationalInfo!$F$2:$F$362) -> 0.01 | T12: =SUMIF(ECT_LegacyCapacity!$F$2:$F$257,_xlfn.CONCAT($C12,$B12),ECT_LegacyCapacity!$E$2:$E$257)*1000-IFERROR(SUMIFS(ECT_LegacyRetirement!$F$2:$F$2701,ECT_LegacyRetirement!$G$2:$G$2701,_xlfn.CONCAT($B12,$C12),ECT_LegacyRetirement!$E$2:$E$2701,"<="&D12)*1000,0) -> 0 | U12: =IFERROR(SUMIFS(ECT_CapAddBounds!$F$2:$F$5959,ECT_CapAddBounds!$H$2:$H$5959,_xlfn.CONCAT($B12,$C12),ECT_CapAddBounds!$E$2:$E$5959,"<="&D12)*1000,0) -> 0 | V12: =IFERROR(SUMIFS(ECT_CapAddBounds!$G$2:$G$5959,ECT_CapAddBounds!$H$2:$H$5959,_xlfn.CONCAT($B12,$C12),ECT_CapAddBounds!$E$2:$E$5959,"<="&D12)*1000,0) -> 0 | Y12: 5 | Z12: 0.105 | AB12: =1/L12/(1-Q12) -> #N/A | AE12: 0 | AF12: =Y12*Conversions!$D$4 -> 6.1945879 | AG12: =N12-AF12 -> #N/A | AH12: =ROUND(P12/2,0) -> 15 | AI12: =Z12/(1-(1+Z12)^-AH12) -> 0.135248 | AJ12: =AG12/AI12 -> #N/A
A13: 1 | B13: EG_LH | C13: NR | D13: =_xlfn.XLOOKUP(A13,PeriodMap!$A$2:$A$45,PeriodMap!$B$2:$B$45) -> 2023 | E13: HydroRes | F13: conventional_hydroelectric_legacy | G13: INDIA | H13: MW | I13: HYDEL | J13: ELECTRICITY | K13: 8760 | L13: =_xlfn.XLOOKUP(_xlfn.CONCAT($B13,$C13,$D13),ECT_EfficiencyCostMaxAnnualUF!$J$2:$J$12484,ECT_EfficiencyCostMaxAnnualUF!$F$2:$F$12484) -> 1 | M13: =_xlfn.XLOOKUP(_xlfn.CONCAT($B13,$C13,$D13),ECT_EfficiencyCostMaxAnnualUF!$J$2:$J$12484,ECT_EfficiencyCostMaxAnnualUF!$I$2:$I$12484) -> 1 | N13: =_xlfn.XLOOKUP(_xlfn.CONCAT($B13,$C13,$D13),ECT_EfficiencyCostMaxAnnualUF!$J$2:$J$12484,ECT_EfficiencyCostMaxAnnualUF!$G$2:$G$12484)/1000 -> 19.631815 | O13: =_xlfn.XLOOKUP(_xlfn.CONCAT($B13,$C13,$D13),ECT_EfficiencyCostMaxAnnualUF!$J$2:$J$12484,ECT_EfficiencyCostMaxAnnualUF!$H$2:$H$12484) -> 0 | P13: =_xlfn.XLOOKUP(_xlfn.CONCAT($B13,$D13+1),ECT_Lifetime!$D$2:$D$1000,ECT_Lifetime!$C$2:$C$1000) -> 40 | Q13: =_xlfn.XLOOKUP(_xlfn.CONCAT($B13,$D13),ECT_OperationalInfo!$G$2:$G$362,ECT_OperationalInfo!$D$2:$D$362) -> 0.006 | R13: =_xlfn.XLOOKUP(_xlfn.CONCAT($B13,$D13),ECT_OperationalInfo!$G$2:$G$362,ECT_OperationalInfo!$E$2:$E$362) -> 1 | S13: =_xlfn.XLOOKUP(_xlfn.CONCAT($B13,$D13),ECT_OperationalInfo!$G$2:$G$362,ECT_OperationalInfo!$F$2:$F$362) -> 1 | T13: =SUMIF(ECT_LegacyCapacity!$F$2:$F$257,_xlfn.CONCAT($C13,$B13),ECT_LegacyCapacity!$E$2:$E$257)*1000-IFERROR(SUMIFS(ECT_LegacyRetirement!$F$2:$F$2701,ECT_LegacyRetirement!$G$2:$G$2701,_xlfn.CONCAT($B13,$C13),ECT_LegacyRetirement!$E$2:$E$2701,"<="&D13)*1000,0) -> 20527.317 | U13: =IFERROR(SUMIFS(ECT_CapAddBounds!$F$2:$F$5959,ECT_CapAddBounds!$H$2:$H$5959,_xlfn.CONCAT($B13,$C13),ECT_CapAddBounds!$E$2:$E$5959,"<="&D13)*1000,0) -> 0 | V13: =IFERROR(SUMIFS(ECT_CapAddBounds!$G$2:$G$5959,ECT_CapAddBounds!$H$2:$H$5959,_xlfn.CONCAT($B13,$C13),ECT_CapAddBounds!$E$2:$E$5959,"<="&D13)*1000,0) -> 0 | Y13: 4.4 | Z13: 0.105 | AC13: =L13-Q13 -> 0.994 | AE13: 0 | AF13: =Y13*Conversions!$D$4 -> 5.4512374 | AG13: =N13-AF13 -> 14.180577 | AH13: =ROUND(P13/2,0) -> 20 | AI13: =Z13/(1-(1+Z13)^-AH13) -> 0.12149327 | AJ13: =AG13/AI13 -> 116.71904
A14: 1 | B14: EG_SH | C14: NR | D14: =_xlfn.XLOOKUP(A14,PeriodMap!$A$2:$A$45,PeriodMap!$B$2:$B$45) -> 2023 | E14: HydroRes | F14: conventional_hydroelectric_small_legacy | G14: INDIA | H14: MW | I14: HYDEL | J14: ELECTRICITY | K14: 8760 | L14: =_xlfn.XLOOKUP(_xlfn.CONCAT($B14,$C14,$D14),ECT_EfficiencyCostMaxAnnualUF!$J$2:$J$12484,ECT_EfficiencyCostMaxAnnualUF!$F$2:$F$12484) -> 1 | M14: =_xlfn.XLOOKUP(_xlfn.CONCAT($B14,$C14,$D14),ECT_EfficiencyCostMaxAnnualUF!$J$2:$J$12484,ECT_EfficiencyCostMaxAnnualUF!$I$2:$I$12484) -> 1 | N14: =_xlfn.XLOOKUP(_xlfn.CONCAT($B14,$C14,$D14),ECT_EfficiencyCostMaxAnnualUF!$J$2:$J$12484,ECT_EfficiencyCostMaxAnnualUF!$G$2:$G$12484)/1000 -> 11.825349 | O14: =_xlfn.XLOOKUP(_xlfn.CONCAT($B14,$C14,$D14),ECT_EfficiencyCostMaxAnnualUF!$J$2:$J$12484,ECT_EfficiencyCostMaxAnnualUF!$H$2:$H$12484) -> 0 | P14: =_xlfn.XLOOKUP(_xlfn.CONCAT($B14,$D14+1),ECT_Lifetime!$D$2:$D$1000,ECT_Lifetime!$C$2:$C$1000) -> 35 | Q14: =_xlfn.XLOOKUP(_xlfn.CONCAT($B14,$D14),ECT_OperationalInfo!$G$2:$G$362,ECT_OperationalInfo!$D$2:$D$362) -> 0.01 | R14: =_xlfn.XLOOKUP(_xlfn.CONCAT($B14,$D14),ECT_OperationalInfo!$G$2:$G$362,ECT_OperationalInfo!$E$2:$E$362) -> 1 | S14: =_xlfn.XLOOKUP(_xlfn.CONCAT($B14,$D14),ECT_OperationalInfo!$G$2:$G$362,ECT_OperationalInfo!$F$2:$F$362) -> 1 | T14: =SUMIF(ECT_LegacyCapacity!$F$2:$F$257,_xlfn.CONCAT($C14,$B14),ECT_LegacyCapacity!$E$2:$E$257)*1000-IFERROR(SUMIFS(ECT_LegacyRetirement!$F$2:$F$2701,ECT_LegacyRetirement!$G$2:$G$2701,_xlfn.CONCAT($B14,$C14),ECT_LegacyRetirement!$E$2:$E$2701,"<="&D14)*1000,0) -> 1698.75 | U14: =IFERROR(SUMIFS(ECT_CapAddBounds!$F$2:$F$5959,ECT_CapAddBounds!$H$2:$H$5959,_xlfn.CONCAT($B14,$C14),ECT_CapAddBounds!$E$2:$E$5959,"<="&D14)*1000,0) -> 0 | V14: =IFERROR(SUMIFS(ECT_CapAddBounds!$G$2:$G$5959,ECT_CapAddBounds!$H$2:$H$5959,_xlfn.CONCAT($B14,$C14),ECT_CapAddBounds!$E$2:$E$5959,"<="&D14)*1000,0) -> 0 | Y14: =2.4 -> 2.4 | Z14: 0.0835 | AC14: =L14-Q14 -> 0.99 | AE14: 0 | AF14: =Y14*Conversions!$D$4 -> 2.9734022 | AG14: =N14-AF14 -> 8.8519466 | AH14: =ROUND(P14/2,0) -> 18 | AI14: =Z14/(1-(1+Z14)^-AH14) -> 0.10930622 | AJ14: =AG14/AI14 -> 80.983009
A15: 1 | B15: EG_BIOMASS | C15: NR | D15: =_xlfn.XLOOKUP(A15,PeriodMap!$A$2:$A$45,PeriodMap!$B$2:$B$45) -> 2023 | E15: ThermalPower | F15: biomass_legacy | G15: INDIA | H15: MW | I15: BIOMASS_WASTE | J15: ELECTRICITY | K15: 8760 | L15: =_xlfn.XLOOKUP(_xlfn.CONCAT($B15,$C15,$D15),ECT_EfficiencyCostMaxAnnualUF!$J$2:$J$12484,ECT_EfficiencyCostMaxAnnualUF!$F$2:$F$12484) -> 0.2388459 | M15: =_xlfn.XLOOKUP(_xlfn.CONCAT($B15,$C15,$D15),ECT_EfficiencyCostMaxAnnualUF!$J$2:$J$12484,ECT_EfficiencyCostMaxAnnualUF!$I$2:$I$12484) -> 1 | N15: =_xlfn.XLOOKUP(_xlfn.CONCAT($B15,$C15,$D15),ECT_EfficiencyCostMaxAnnualUF!$J$2:$J$12484,ECT_EfficiencyCostMaxAnnualUF!$G$2:$G$12484)/1000 -> 7.7134572 | O15: =_xlfn.XLOOKUP(_xlfn.CONCAT($B15,$C15,$D15),ECT_EfficiencyCostMaxAnnualUF!$J$2:$J$12484,ECT_EfficiencyCostMaxAnnualUF!$H$2:$H$12484) -> 0 | P15: =_xlfn.XLOOKUP(_xlfn.CONCAT($B15,$D15+1),ECT_Lifetime!$D$2:$D$1000,ECT_Lifetime!$C$2:$C$1000) -> 20 | Q15: =_xlfn.XLOOKUP(_xlfn.CONCAT($B15,$D15),ECT_OperationalInfo!$G$2:$G$362,ECT_OperationalInfo!$D$2:$D$362) -> 0.1 | R15: =_xlfn.XLOOKUP(_xlfn.CONCAT($B15,$D15),ECT_OperationalInfo!$G$2:$G$362,ECT_OperationalInfo!$E$2:$E$362) -> 0.06 | S15: =_xlfn.XLOOKUP(_xlfn.CONCAT($B15,$D15),ECT_OperationalInfo!$G$2:$G$362,ECT_OperationalInfo!$F$2:$F$362) -> 0.06 | T15: =SUMIF(ECT_LegacyCapacity!$F$2:$F$257,_xlfn.CONCAT($C15,$B15),ECT_LegacyCapacity!$E$2:$E$257)*1000-IFERROR(SUMIFS(ECT_LegacyRetirement!$F$2:$F$2701,ECT_LegacyRetirement!$G$2:$G$2701,_xlfn.CONCAT($B15,$C15),ECT_LegacyRetirement!$E$2:$E$2701,"<="&D15)*1000,0) -> 3357.15 | U15: =IFERROR(SUMIFS(ECT_CapAddBounds!$F$2:$F$5959,ECT_CapAddBounds!$H$2:$H$5959,_xlfn.CONCAT($B15,$C15),ECT_CapAddBounds!$E$2:$E$5959,"<="&D15)*1000,0) -> 0 | V15: =IFERROR(SUMIFS(ECT_CapAddBounds!$G$2:$G$5959,ECT_CapAddBounds!$H$2:$H$5959,_xlfn.CONCAT($B15,$C15),ECT_CapAddBounds!$E$2:$E$5959,"<="&D15)*1000,0) -> 0 | W15: =CarriersTech_characteristics!$G$7 -> 13.648968 | X15: =CarriersTech_characteristics!$H$5*1000 -> 1656436.7 | Y15: 1 | Z15: 0.0835 | AB15: =1/L15/(1-Q15) -> 4.652 | AD15: =X15/(W15*Conversions!$D$2) -> 0.43689545 | AE15: 0 | AF15: =Y15*Conversions!$D$4 -> 1.2389176 | AG15: =N15-AF15 -> 6.4745397 | AH15: =ROUND(P15/2,0) -> 10 | AI15: =Z15/(1-(1+Z15)^-AH15) -> 0.15139063 | AJ15: =AG15/AI15 -> 42.767109
A16: 1 | B16: EG_SOLARGM | C16: NR | D16: =_xlfn.XLOOKUP(A16,PeriodMap!$A$2:$A$45,PeriodMap!$B$2:$B$45) -> 2023 | E16: VRE | F16: solar_GM_legacy | G16: INDIA | H16: MW | I16: SUNLIGHT | J16: ELECTRICITY | K16: 8760 | L16: =_xlfn.XLOOKUP(_xlfn.CONCAT($B16,$C16,$D16),ECT_EfficiencyCostMaxAnnualUF!$J$2:$J$12484,ECT_EfficiencyCostMaxAnnualUF!$F$2:$F$12484) -> 1 | M16: =_xlfn.XLOOKUP(_xlfn.CONCAT($B16,$C16,$D16),ECT_EfficiencyCostMaxAnnualUF!$J$2:$J$12484,ECT_EfficiencyCostMaxAnnualUF!$I$2:$I$12484) -> 1 | N16: =_xlfn.XLOOKUP(_xlfn.CONCAT($B16,$C16,$D16),ECT_EfficiencyCostMaxAnnualUF!$J$2:$J$12484,ECT_EfficiencyCostMaxAnnualUF!$G$2:$G$12484)/1000 -> 5.6309842 | O16: =_xlfn.XLOOKUP(_xlfn.CONCAT($B16,$C16,$D16),ECT_EfficiencyCostMaxAnnualUF!$J$2:$J$12484,ECT_EfficiencyCostMaxAnnualUF!$H$2:$H$12484) -> 0 | P16: =_xlfn.XLOOKUP(_xlfn.CONCAT($B16,$D16+1),ECT_Lifetime!$D$2:$D$1000,ECT_Lifetime!$C$2:$C$1000) -> 25 | Q16: =_xlfn.XLOOKUP(_xlfn.CONCAT($B16,$D16),ECT_OperationalInfo!$G$2:$G$362,ECT_OperationalInfo!$D$2:$D$362) -> 0.01 | R16: =_xlfn.XLOOKUP(_xlfn.CONCAT($B16,$D16),ECT_OperationalInfo!$G$2:$G$362,ECT_OperationalInfo!$E$2:$E$362) -> 1 | S16: =_xlfn.XLOOKUP(_xlfn.CONCAT($B16,$D16),ECT_OperationalInfo!$G$2:$G$362,ECT_OperationalInfo!$F$2:$F$362) -> 1 | T16: =SUMIF(ECT_LegacyCapacity!$F$2:$F$257,_xlfn.CONCAT($C16,$B16),ECT_LegacyCapacity!$E$2:$E$257)*1000-IFERROR(SUMIFS(ECT_LegacyRetirement!$F$2:$F$2701,ECT_LegacyRetirement!$G$2:$G$2701,_xlfn.CONCAT($B16,$C16),ECT_LegacyRetirement!$E$2:$E$2701,"<="&D16)*1000,0) -> 19996.724 | U16: =IFERROR(SUMIFS(ECT_CapAddBounds!$F$2:$F$5959,ECT_CapAddBounds!$H$2:$H$5959,_xlfn.CONCAT($B16,$C16),ECT_CapAddBounds!$E$2:$E$5959,"<="&D16)*1000,0) -> 0 | V16: =IFERROR(SUMIFS(ECT_CapAddBounds!$G$2:$G$5959,ECT_CapAddBounds!$H$2:$H$5959,_xlfn.CONCAT($B16,$C16),ECT_CapAddBounds!$E$2:$E$5959,"<="&D16)*1000,0) -> 0 | Y16: 0.35 | Z16: 0.105 | AB16: 1 | AE16: 0 | AF16: =Y16*Conversions!$D$4 -> 0.43362115 | AG16: =N16-AF16 -> 5.197363 | AH16: =ROUND(P16/2,0) -> 13 | AI16: =Z16/(1-(1+Z16)^-AH16) -> 0.14444512 | AJ16: =AG16/AI16 -> 35.981577
A17: 1 | B17: EG_SOLARRF | C17: NR | D17: =_xlfn.XLOOKUP(A17,PeriodMap!$A$2:$A$45,PeriodMap!$B$2:$B$45) -> 2023 | E17: VRE | F17: solar_RT_legacy | G17: INDIA | H17: MW | I17: SUNLIGHT | J17: ELECTRICITY | K17: 8760 | L17: =_xlfn.XLOOKUP(_xlfn.CONCAT($B17,$C17,$D17),ECT_EfficiencyCostMaxAnnualUF!$J$2:$J$12484,ECT_EfficiencyCostMaxAnnualUF!$F$2:$F$12484) -> 1 | M17: =_xlfn.XLOOKUP(_xlfn.CONCAT($B17,$C17,$D17),ECT_EfficiencyCostMaxAnnualUF!$J$2:$J$12484,ECT_EfficiencyCostMaxAnnualUF!$I$2:$I$12484) -> 1 | N17: =_xlfn.XLOOKUP(_xlfn.CONCAT($B17,$C17,$D17),ECT_EfficiencyCostMaxAnnualUF!$J$2:$J$12484,ECT_EfficiencyCostMaxAnnualUF!$G$2:$G$12484)/1000 -> 5.5421877 | O17: =_xlfn.XLOOKUP(_xlfn.CONCAT($B17,$C17,$D17),ECT_EfficiencyCostMaxAnnualUF!$J$2:$J$12484,ECT_EfficiencyCostMaxAnnualUF!$H$2:$H$12484) -> 0 | P17: =_xlfn.XLOOKUP(_xlfn.CONCAT($B17,$D17+1),ECT_Lifetime!$D$2:$D$1000,ECT_Lifetime!$C$2:$C$1000) -> 25 | Q17: =_xlfn.XLOOKUP(_xlfn.CONCAT($B17,$D17),ECT_OperationalInfo!$G$2:$G$362,ECT_OperationalInfo!$D$2:$D$362) -> 0.01 | R17: =_xlfn.XLOOKUP(_xlfn.CONCAT($B17,$D17),ECT_OperationalInfo!$G$2:$G$362,ECT_OperationalInfo!$E$2:$E$362) -> 1 | S17: =_xlfn.XLOOKUP(_xlfn.CONCAT($B17,$D17),ECT_OperationalInfo!$G$2:$G$362,ECT_OperationalInfo!$F$2:$F$362) -> 1 | T17: =SUMIF(ECT_LegacyCapacity!$F$2:$F$257,_xlfn.CONCAT($C17,$B17),ECT_LegacyCapacity!$E$2:$E$257)*1000-IFERROR(SUMIFS(ECT_LegacyRetirement!$F$2:$F$2701,ECT_LegacyRetirement!$G$2:$G$2701,_xlfn.CONCAT($B17,$C17),ECT_LegacyRetirement!$E$2:$E$2701,"<="&D17)*1000,0) -> 2666.3458 | U17: =IFERROR(SUMIFS(ECT_CapAddBounds!$F$2:$F$5959,ECT_CapAddBounds!$H$2:$H$5959,_xlfn.CONCAT($B17,$C17),ECT_CapAddBounds!$E$2:$E$5959,"<="&D17)*1000,0) -> 0 | V17: =IFERROR(SUMIFS(ECT_CapAddBounds!$G$2:$G$5959,ECT_CapAddBounds!$H$2:$H$5959,_xlfn.CONCAT($B17,$C17),ECT_CapAddBounds!$E$2:$E$5959,"<="&D17)*1000,0) -> 0 | Y17: 0.51 | Z17: 0.104 | AB17: 1 | AE17: 0 | AF17: =Y17*Conversions!$D$4 -> 0.63184797 | AG17: =N17-AF17 -> 4.9103397 | AH17: =ROUND(P17/2,0) -> 13 | AI17: =Z17/(1-(1+Z17)^-AH17) -> 0.14370863 | AJ17: =AG17/AI17 -> 34.168719
A18: 1 | B18: EG_WINDON | C18: NR | D18: =_xlfn.XLOOKUP(A18,PeriodMap!$A$2:$A$45,PeriodMap!$B$2:$B$45) -> 2023 | E18: VRE | F18: onshore_wind_legacy | G18: INDIA | H18: MW | I18: WIND | J18: ELECTRICITY | K18: 8760 | L18: =_xlfn.XLOOKUP(_xlfn.CONCAT($B18,$C18,$D18),ECT_EfficiencyCostMaxAnnualUF!$J$2:$J$12484,ECT_EfficiencyCostMaxAnnualUF!$F$2:$F$12484) -> 1 | M18: =_xlfn.XLOOKUP(_xlfn.CONCAT($B18,$C18,$D18),ECT_EfficiencyCostMaxAnnualUF!$J$2:$J$12484,ECT_EfficiencyCostMaxAnnualUF!$I$2:$I$12484) -> 1 | N18: =_xlfn.XLOOKUP(_xlfn.CONCAT($B18,$C18,$D18),ECT_EfficiencyCostMaxAnnualUF!$J$2:$J$12484,ECT_EfficiencyCostMaxAnnualUF!$G$2:$G$12484)/1000 -> 10.65943 | O18: =_xlfn.XLOOKUP(_xlfn.CONCAT($B18,$C18,$D18),ECT_EfficiencyCostMaxAnnualUF!$J$2:$J$12484,ECT_EfficiencyCostMaxAnnualUF!$H$2:$H$12484) -> 0 | P18: =_xlfn.XLOOKUP(_xlfn.CONCAT($B18,$D18+1),ECT_Lifetime!$D$2:$D$1000,ECT_Lifetime!$C$2:$C$1000) -> 25 | Q18: =_xlfn.XLOOKUP(_xlfn.CONCAT($B18,$D18),ECT_OperationalInfo!$G$2:$G$362,ECT_OperationalInfo!$D$2:$D$362) -> 0.005 | R18: =_xlfn.XLOOKUP(_xlfn.CONCAT($B18,$D18),ECT_OperationalInfo!$G$2:$G$362,ECT_OperationalInfo!$E$2:$E$362) -> 1 | S18: =_xlfn.XLOOKUP(_xlfn.CONCAT($B18,$D18),ECT_OperationalInfo!$G$2:$G$362,ECT_OperationalInfo!$F$2:$F$362) -> 1 | T18: =SUMIF(ECT_LegacyCapacity!$F$2:$F$257,_xlfn.CONCAT($C18,$B18),ECT_LegacyCapacity!$E$2:$E$257)*1000-IFERROR(SUMIFS(ECT_LegacyRetirement!$F$2:$F$2701,ECT_LegacyRetirement!$G$2:$G$2701,_xlfn.CONCAT($B18,$C18),ECT_LegacyRetirement!$E$2:$E$2701,"<="&D18)*1000,0) -> 5301.42 | U18: =IFERROR(SUMIFS(ECT_CapAddBounds!$F$2:$F$5959,ECT_CapAddBounds!$H$2:$H$5959,_xlfn.CONCAT($B18,$C18),ECT_CapAddBounds!$E$2:$E$5959,"<="&D18)*1000,0) -> 0 | V18: =IFERROR(SUMIFS(ECT_CapAddBounds!$G$2:$G$5959,ECT_CapAddBounds!$H$2:$H$5959,_xlfn.CONCAT($B18,$C18),ECT_CapAddBounds!$E$2:$E$5959,"<="&D18)*1000,0) -> 0 | Y18: 0.68 | Z18: 0.105 | AB18: 1 | AE18: 0 | AF18: =Y18*Conversions!$D$4 -> 0.84246396 | AG18: =N18-AF18 -> 9.8169663 | AH18: =ROUND(P18/2,0) -> 13 | AI18: =Z18/(1-(1+Z18)^-AH18) -> 0.14444512 | AJ18: =AG18/AI18 -> 67.963296
A19: 1 | B19: EG_WINDOFF | C19: NR | D19: =_xlfn.XLOOKUP(A19,PeriodMap!$A$2:$A$45,PeriodMap!$B$2:$B$45) -> 2023 | E19: VRE | G19: INDIA | H19: MW | I19: WIND | J19: ELECTRICITY | K19: 8760 | L19: =_xlfn.XLOOKUP(_xlfn.CONCAT($B19,$C19,$D19),ECT_EfficiencyCostMaxAnnualUF!$J$2:$J$12484,ECT_EfficiencyCostMaxAnnualUF!$F$2:$F$12484) -> #N/A | M19: =_xlfn.XLOOKUP(_xlfn.CONCAT($B19,$C19,$D19),ECT_EfficiencyCostMaxAnnualUF!$J$2:$J$12484,ECT_EfficiencyCostMaxAnnualUF!$I$2:$I$12484) -> #N/A | N19: =_xlfn.XLOOKUP(_xlfn.CONCAT($B19,$C19,$D19),ECT_EfficiencyCostMaxAnnualUF!$J$2:$J$12484,ECT_EfficiencyCostMaxAnnualUF!$G$2:$G$12484)/1000 -> #N/A | O19: =_xlfn.XLOOKUP(_xlfn.CONCAT($B19,$C19,$D19),ECT_EfficiencyCostMaxAnnualUF!$J$2:$J$12484,ECT_EfficiencyCostMaxAnnualUF!$H$2:$H$12484) -> #N/A | P19: =_xlfn.XLOOKUP(_xlfn.CONCAT($B19,$D19+1),ECT_Lifetime!$D$2:$D$1000,ECT_Lifetime!$C$2:$C$1000) -> 25 | Q19: =_xlfn.XLOOKUP(_xlfn.CONCAT($B19,$D19),ECT_OperationalInfo!$G$2:$G$362,ECT_OperationalInfo!$D$2:$D$362) -> 0.005 | R19: =_xlfn.XLOOKUP(_xlfn.CONCAT($B19,$D19),ECT_OperationalInfo!$G$2:$G$362,ECT_OperationalInfo!$E$2:$E$362) -> 1 | S19: =_xlfn.XLOOKUP(_xlfn.CONCAT($B19,$D19),ECT_OperationalInfo!$G$2:$G$362,ECT_OperationalInfo!$F$2:$F$362) -> 1 | T19: =SUMIF(ECT_LegacyCapacity!$F$2:$F$257,_xlfn.CONCAT($C19,$B19),ECT_LegacyCapacity!$E$2:$E$257)*1000-IFERROR(SUMIFS(ECT_LegacyRetirement!$F$2:$F$2701,ECT_LegacyRetirement!$G$2:$G$2701,_xlfn.CONCAT($B19,$C19),ECT_LegacyRetirement!$E$2:$E$2701,"<="&D19)*1000,0) -> 0 | U19: =IFERROR(SUMIFS(ECT_CapAddBounds!$F$2:$F$5959,ECT_CapAddBounds!$H$2:$H$5959,_xlfn.CONCAT($B19,$C19),ECT_CapAddBounds!$E$2:$E$5959,"<="&D19)*1000,0) -> 0 | V19: =IFERROR(SUMIFS(ECT_CapAddBounds!$G$2:$G$5959,ECT_CapAddBounds!$H$2:$H$5959,_xlfn.CONCAT($B19,$C19),ECT_CapAddBounds!$E$2:$E$5959,"<="&D19)*1000,0) -> 0 | Y19: 6.7 | Z19: 0.112 | AB19: 1 | AE19: 0 | AF19: =Y19*Conversions!$D$4 -> 8.3007478 | AG19: =N19-AF19 -> #N/A | AH19: =ROUND(P19/2,0) -> 13 | AI19: =Z19/(1-(1+Z19)^-AH19) -> 0.14964415 | AJ19: =AG19/AI19 -> #N/A
A20: 1 | B20: EG_COAL | C20: NER | D20: =_xlfn.XLOOKUP(A20,PeriodMap!$A$2:$A$45,PeriodMap!$B$2:$B$45) -> 2023 | E20: ThermalPower | F20: coal_legacy | G20: INDIA | H20: MW | I20: THERMAL_COAL | J20: ELECTRICITY | K20: 8760 | L20: =_xlfn.XLOOKUP(_xlfn.CONCAT($B20,$C20,$D20),ECT_EfficiencyCostMaxAnnualUF!$J$2:$J$12484,ECT_EfficiencyCostMaxAnnualUF!$F$2:$F$12484) -> 0.3664022 | M20: =_xlfn.XLOOKUP(_xlfn.CONCAT($B20,$C20,$D20),ECT_EfficiencyCostMaxAnnualUF!$J$2:$J$12484,ECT_EfficiencyCostMaxAnnualUF!$I$2:$I$12484) -> 0.85 | N20: =_xlfn.XLOOKUP(_xlfn.CONCAT($B20,$C20,$D20),ECT_EfficiencyCostMaxAnnualUF!$J$2:$J$12484,ECT_EfficiencyCostMaxAnnualUF!$G$2:$G$12484)/1000 -> 26.148846 | O20: =_xlfn.XLOOKUP(_xlfn.CONCAT($B20,$C20,$D20),ECT_EfficiencyCostMaxAnnualUF!$J$2:$J$12484,ECT_EfficiencyCostMaxAnnualUF!$H$2:$H$12484) -> 133.52302 | P20: =_xlfn.XLOOKUP(_xlfn.CONCAT($B20,$D20+1),ECT_Lifetime!$D$2:$D$1000,ECT_Lifetime!$C$2:$C$1000) -> 40 | Q20: =_xlfn.XLOOKUP(_xlfn.CONCAT($B20,$D20),ECT_OperationalInfo!$G$2:$G$362,ECT_OperationalInfo!$D$2:$D$362) -> 0.0745 | R20: =_xlfn.XLOOKUP(_xlfn.CONCAT($B20,$D20),ECT_OperationalInfo!$G$2:$G$362,ECT_OperationalInfo!$E$2:$E$362) -> 0.3 | S20: =_xlfn.XLOOKUP(_xlfn.CONCAT($B20,$D20),ECT_OperationalInfo!$G$2:$G$362,ECT_OperationalInfo!$F$2:$F$362) -> 0.3 | T20: =SUMIF(ECT_LegacyCapacity!$F$2:$F$257,_xlfn.CONCAT($C20,$B20),ECT_LegacyCapacity!$E$2:$E$257)*1000-IFERROR(SUMIFS(ECT_LegacyRetirement!$F$2:$F$2701,ECT_LegacyRetirement!$G$2:$G$2701,_xlfn.CONCAT($B20,$C20),ECT_LegacyRetirement!$E$2:$E$2701,"<="&D20)*1000,0) -> 1010.9297 | U20: =IFERROR(SUMIFS(ECT_CapAddBounds!$F$2:$F$5959,ECT_CapAddBounds!$H$2:$H$5959,_xlfn.CONCAT($B20,$C20),ECT_CapAddBounds!$E$2:$E$5959,"<="&D20)*1000,0) -> 0 | V20: =IFERROR(SUMIFS(ECT_CapAddBounds!$G$2:$G$5959,ECT_CapAddBounds!$H$2:$H$5959,_xlfn.CONCAT($B20,$C20),ECT_CapAddBounds!$E$2:$E$5959,"<="&D20)*1000,0) -> 0 | W20: =CarriersTech_characteristics!$G$2 -> 17.207188 | X20: =CarriersTech_characteristics!$H$28*1000 -> 1942097.6 | Y20: 3 | Z20: 0.105 | AB20: =1/L20/(1-Q20) -> 2.9489371 | AD20: =X20/(W20*Conversions!$D$2) -> 0.40631575 | AE20: =O20/CarriersTech_characteristics!$G$2/Conversions!$D$2*AB20 -> 8.237857e-05 | AF20: =Y20*Conversions!$D$4 -> 3.7167527 | AG20: =N20-AF20 -> 22.432094 | AH20: =ROUND(P20/2,0) -> 20 | AI20: =Z20/(1-(1+Z20)^-AH20) -> 0.12149327 | AJ20: =AG20/AI20 -> 184.63652
A21: 1 | B21: EG_CCGT | C21: NER | D21: =_xlfn.XLOOKUP(A21,PeriodMap!$A$2:$A$45,PeriodMap!$B$2:$B$45) -> 2023 | E21: ThermalPower | F21: NG_CCGT_legacy | G21: INDIA | H21: MW | I21: NATGAS | J21: ELECTRICITY | K21: 8760 | L21: =_xlfn.XLOOKUP(_xlfn.CONCAT($B21,$C21,$D21),ECT_EfficiencyCostMaxAnnualUF!$J$2:$J$12484,ECT_EfficiencyCostMaxAnnualUF!$F$2:$F$12484) -> 0.40444272 | M21: =_xlfn.XLOOKUP(_xlfn.CONCAT($B21,$C21,$D21),ECT_EfficiencyCostMaxAnnualUF!$J$2:$J$12484,ECT_EfficiencyCostMaxAnnualUF!$I$2:$I$12484) -> 0.85 | N21: =_xlfn.XLOOKUP(_xlfn.CONCAT($B21,$C21,$D21),ECT_EfficiencyCostMaxAnnualUF!$J$2:$J$12484,ECT_EfficiencyCostMaxAnnualUF!$G$2:$G$12484)/1000 -> 8.5122278 | O21: =_xlfn.XLOOKUP(_xlfn.CONCAT($B21,$C21,$D21),ECT_EfficiencyCostMaxAnnualUF!$J$2:$J$12484,ECT_EfficiencyCostMaxAnnualUF!$H$2:$H$12484) -> 0 | P21: =_xlfn.XLOOKUP(_xlfn.CONCAT($B21,$D21+1),ECT_Lifetime!$D$2:$D$1000,ECT_Lifetime!$C$2:$C$1000) -> 25 | Q21: =_xlfn.XLOOKUP(_xlfn.CONCAT($B21,$D21),ECT_OperationalInfo!$G$2:$G$362,ECT_OperationalInfo!$D$2:$D$362) -> 0.02 | R21: =_xlfn.XLOOKUP(_xlfn.CONCAT($B21,$D21),ECT_OperationalInfo!$G$2:$G$362,ECT_OperationalInfo!$E$2:$E$362) -> 0.9 | S21: =_xlfn.XLOOKUP(_xlfn.CONCAT($B21,$D21),ECT_OperationalInfo!$G$2:$G$362,ECT_OperationalInfo!$F$2:$F$362) -> 0.9 | T21: =SUMIF(ECT_LegacyCapacity!$F$2:$F$257,_xlfn.CONCAT($C21,$B21),ECT_LegacyCapacity!$E$2:$E$257)*1000-IFERROR(SUMIFS(ECT_LegacyRetirement!$F$2:$F$2701,ECT_LegacyRetirement!$G$2:$G$2701,_xlfn.CONCAT($B21,$C21),ECT_LegacyRetirement!$E$2:$E$2701,"<="&D21)*1000,0) -> 2002.4569 | U21: =IFERROR(SUMIFS(ECT_CapAddBounds!$F$2:$F$5959,ECT_CapAddBounds!$H$2:$H$5959,_xlfn.CONCAT($B21,$C21),ECT_CapAddBounds!$E$2:$E$5959,"<="&D21)*1000,0) -> 0 | V21: =IFERROR(SUMIFS(ECT_CapAddBounds!$G$2:$G$5959,ECT_CapAddBounds!$H$2:$H$5959,_xlfn.CONCAT($B21,$C21),ECT_CapAddBounds!$E$2:$E$5959,"<="&D21)*1000,0) -> 0 | W21: =CarriersTech_characteristics!$G$3 -> 37.6812 | X21: =CarriersTech_characteristics!$H$3*1000 -> 3025024.5 | Y21: 2.9 | Z21: 0.105 | AB21: =1/L21/(1-Q21) -> 2.522998 | AD21: =(X21*Conversions!$D$3)/(W21*Conversions!$D$2) -> 0.23958587 | AE21: 0 | AF21: =Y21*Conversions!$D$4 -> 3.592861 | AG21: =N21-AF21 -> 4.9193668 | AH21: =ROUND(P21/2,0) -> 13 | AI21: =Z21/(1-(1+Z21)^-AH21) -> 0.14444512 | AJ21: =AG21/AI21 -> 34.056996
A22: 1 | B22: EG_OCGT | C22: NER | D22: =_xlfn.XLOOKUP(A22,PeriodMap!$A$2:$A$45,PeriodMap!$B$2:$B$45) -> 2023 | E22: ThermalPower | G22: INDIA | H22: MW | I22: NATGAS | J22: ELECTRICITY | K22: 8760 | L22: =_xlfn.XLOOKUP(_xlfn.CONCAT($B22,$C22,$D22),ECT_EfficiencyCostMaxAnnualUF!$J$2:$J$12484,ECT_EfficiencyCostMaxAnnualUF!$F$2:$F$12484) -> 0.28070163 | M22: =_xlfn.XLOOKUP(_xlfn.CONCAT($B22,$C22,$D22),ECT_EfficiencyCostMaxAnnualUF!$J$2:$J$12484,ECT_EfficiencyCostMaxAnnualUF!$I$2:$I$12484) -> 0.85 | N22: =_xlfn.XLOOKUP(_xlfn.CONCAT($B22,$C22,$D22),ECT_EfficiencyCostMaxAnnualUF!$J$2:$J$12484,ECT_EfficiencyCostMaxAnnualUF!$G$2:$G$12484)/1000 -> 6.6797506 | O22: =_xlfn.XLOOKUP(_xlfn.CONCAT($B22,$C22,$D22),ECT_EfficiencyCostMaxAnnualUF!$J$2:$J$12484,ECT_EfficiencyCostMaxAnnualUF!$H$2:$H$12484) -> 0 | P22: =_xlfn.XLOOKUP(_xlfn.CONCAT($B22,$D22+1),ECT_Lifetime!$D$2:$D$1000,ECT_Lifetime!$C$2:$C$1000) -> 25 | Q22: =_xlfn.XLOOKUP(_xlfn.CONCAT($B22,$D22),ECT_OperationalInfo!$G$2:$G$362,ECT_OperationalInfo!$D$2:$D$362) -> 0.01 | R22: =_xlfn.XLOOKUP(_xlfn.CONCAT($B22,$D22),ECT_OperationalInfo!$G$2:$G$362,ECT_OperationalInfo!$E$2:$E$362) -> 1 | S22: =_xlfn.XLOOKUP(_xlfn.CONCAT($B22,$D22),ECT_OperationalInfo!$G$2:$G$362,ECT_OperationalInfo!$F$2:$F$362) -> 1 | T22: =SUMIF(ECT_LegacyCapacity!$F$2:$F$257,_xlfn.CONCAT($C22,$B22),ECT_LegacyCapacity!$E$2:$E$257)*1000-IFERROR(SUMIFS(ECT_LegacyRetirement!$F$2:$F$2701,ECT_LegacyRetirement!$G$2:$G$2701,_xlfn.CONCAT($B22,$C22),ECT_LegacyRetirement!$E$2:$E$2701,"<="&D22)*1000,0) -> 0 | U22: =IFERROR(SUMIFS(ECT_CapAddBounds!$F$2:$F$5959,ECT_CapAddBounds!$H$2:$H$5959,_xlfn.CONCAT($B22,$C22),ECT_CapAddBounds!$E$2:$E$5959,"<="&D22)*1000,0) -> 0 | V22: =IFERROR(SUMIFS(ECT_CapAddBounds!$G$2:$G$5959,ECT_CapAddBounds!$H$2:$H$5959,_xlfn.CONCAT($B22,$C22),ECT_CapAddBounds!$E$2:$E$5959,"<="&D22)*1000,0) -> 0 | W22: =CarriersTech_characteristics!$G$3 -> 37.6812 | X22: =CarriersTech_characteristics!$H$3*1000 -> 3025024.5 | Y22: 0.7 | Z22: 0.105 | AB22: =1/L22/(1-Q22) -> 3.5984865 | AD22: =(X22*Conversions!$D$3)/(W22*Conversions!$D$2) -> 0.23958587 | AE22: 0 | AF22: =Y22*Conversions!$D$4 -> 0.86724231 | AG22: =N22-AF22 -> 5.8125083 | AH22: =ROUND(P22/2,0) -> 13 | AI22: =Z22/(1-(1+Z22)^-AH22) -> 0.14444512 | AJ22: =AG22/AI22 -> 40.240255
A23: 1 | B23: EG_PHWR | C23: NER | D23: =_xlfn.XLOOKUP(A23,PeriodMap!$A$2:$A$45,PeriodMap!$B$2:$B$45) -> 2023 | E23: ThermalPower | F23: nuclear_PHWR_legacy | G23: INDIA | H23: MW | I23: ATOMIC | J23: ELECTRICITY | K23: 8760 | L23: =_xlfn.XLOOKUP(_xlfn.CONCAT($B23,$C23,$D23),ECT_EfficiencyCostMaxAnnualUF!$J$2:$J$12484,ECT_EfficiencyCostMaxAnnualUF!$F$2:$F$12484) -> 1 | M23: =_xlfn.XLOOKUP(_xlfn.CONCAT($B23,$C23,$D23),ECT_EfficiencyCostMaxAnnualUF!$J$2:$J$12484,ECT_EfficiencyCostMaxAnnualUF!$I$2:$I$12484) -> 0.70916667 | N23: =_xlfn.XLOOKUP(_xlfn.CONCAT($B23,$C23,$D23),ECT_EfficiencyCostMaxAnnualUF!$J$2:$J$12484,ECT_EfficiencyCostMaxAnnualUF!$G$2:$G$12484)/1000 -> 20.83321 | O23: =_xlfn.XLOOKUP(_xlfn.CONCAT($B23,$C23,$D23),ECT_EfficiencyCostMaxAnnualUF!$J$2:$J$12484,ECT_EfficiencyCostMaxAnnualUF!$H$2:$H$12484) -> 0 | P23: =_xlfn.XLOOKUP(_xlfn.CONCAT($B23,$D23+1),ECT_Lifetime!$D$2:$D$1000,ECT_Lifetime!$C$2:$C$1000) -> 40 | Q23: =_xlfn.XLOOKUP(_xlfn.CONCAT($B23,$D23),ECT_OperationalInfo!$G$2:$G$362,ECT_OperationalInfo!$D$2:$D$362) -> 0.1078 | R23: =_xlfn.XLOOKUP(_xlfn.CONCAT($B23,$D23),ECT_OperationalInfo!$G$2:$G$362,ECT_OperationalInfo!$E$2:$E$362) -> 0.01 | S23: =_xlfn.XLOOKUP(_xlfn.CONCAT($B23,$D23),ECT_OperationalInfo!$G$2:$G$362,ECT_OperationalInfo!$F$2:$F$362) -> 0.01 | T23: =SUMIF(ECT_LegacyCapacity!$F$2:$F$257,_xlfn.CONCAT($C23,$B23),ECT_LegacyCapacity!$E$2:$E$257)*1000-IFERROR(SUMIFS(ECT_LegacyRetirement!$F$2:$F$2701,ECT_LegacyRetirement!$G$2:$G$2701,_xlfn.CONCAT($B23,$C23),ECT_LegacyRetirement!$E$2:$E$2701,"<="&D23)*1000,0) -> 0 | U23: =IFERROR(SUMIFS(ECT_CapAddBounds!$F$2:$F$5959,ECT_CapAddBounds!$H$2:$H$5959,_xlfn.CONCAT($B23,$C23),ECT_CapAddBounds!$E$2:$E$5959,"<="&D23)*1000,0) -> 0 | V23: =IFERROR(SUMIFS(ECT_CapAddBounds!$G$2:$G$5959,ECT_CapAddBounds!$H$2:$H$5959,_xlfn.CONCAT($B23,$C23),ECT_CapAddBounds!$E$2:$E$5959,"<="&D23)*1000,0) -> 0 | Y23: 4.3 | Z23: 0.105 | AB23: =1/L23/(1-Q23) -> 1.1208249 | AE23: 0 | AF23: =Y23*Conversions!$D$4 -> 5.3273456 | AG23: =N23-AF23 -> 15.505865 | AH23: =ROUND(P23/2,0) -> 20 | AI23: =Z23/(1-(1+Z23)^-AH23) -> 0.12149327 | AJ23: =AG23/AI23 -> 127.62736
A24: 1 | B24: EG_SMR | C24: NER | D24: =_xlfn.XLOOKUP(A24,PeriodMap!$A$2:$A$45,PeriodMap!$B$2:$B$45) -> 2023 | E24: ThermalPower | G24: INDIA | H24: MW | I24: ATOMIC | J24: ELECTRICITY | K24: 8760 | L24: =_xlfn.XLOOKUP(_xlfn.CONCAT($B24,$C24,$D24),ECT_EfficiencyCostMaxAnnualUF!$J$2:$J$12484,ECT_EfficiencyCostMaxAnnualUF!$F$2:$F$12484) -> #N/A | M24: =_xlfn.XLOOKUP(_xlfn.CONCAT($B24,$C24,$D24),ECT_EfficiencyCostMaxAnnualUF!$J$2:$J$12484,ECT_EfficiencyCostMaxAnnualUF!$I$2:$I$12484) -> #N/A | N24: =_xlfn.XLOOKUP(_xlfn.CONCAT($B24,$C24,$D24),ECT_EfficiencyCostMaxAnnualUF!$J$2:$J$12484,ECT_EfficiencyCostMaxAnnualUF!$G$2:$G$12484)/1000 -> #N/A | O24: =_xlfn.XLOOKUP(_xlfn.CONCAT($B24,$C24,$D24),ECT_EfficiencyCostMaxAnnualUF!$J$2:$J$12484,ECT_EfficiencyCostMaxAnnualUF!$H$2:$H$12484) -> #N/A | P24: =_xlfn.XLOOKUP(_xlfn.CONCAT($B24,$D24+1),ECT_Lifetime!$D$2:$D$1000,ECT_Lifetime!$C$2:$C$1000) -> 30 | Q24: =_xlfn.XLOOKUP(_xlfn.CONCAT($B24,$D24),ECT_OperationalInfo!$G$2:$G$362,ECT_OperationalInfo!$D$2:$D$362) -> 0.05 | R24: =_xlfn.XLOOKUP(_xlfn.CONCAT($B24,$D24),ECT_OperationalInfo!$G$2:$G$362,ECT_OperationalInfo!$E$2:$E$362) -> 0.01 | S24: =_xlfn.XLOOKUP(_xlfn.CONCAT($B24,$D24),ECT_OperationalInfo!$G$2:$G$362,ECT_OperationalInfo!$F$2:$F$362) -> 0.01 | T24: =SUMIF(ECT_LegacyCapacity!$F$2:$F$257,_xlfn.CONCAT($C24,$B24),ECT_LegacyCapacity!$E$2:$E$257)*1000-IFERROR(SUMIFS(ECT_LegacyRetirement!$F$2:$F$2701,ECT_LegacyRetirement!$G$2:$G$2701,_xlfn.CONCAT($B24,$C24),ECT_LegacyRetirement!$E$2:$E$2701,"<="&D24)*1000,0) -> 0 | U24: =IFERROR(SUMIFS(ECT_CapAddBounds!$F$2:$F$5959,ECT_CapAddBounds!$H$2:$H$5959,_xlfn.CONCAT($B24,$C24),ECT_CapAddBounds!$E$2:$E$5959,"<="&D24)*1000,0) -> 0 | V24: =IFERROR(SUMIFS(ECT_CapAddBounds!$G$2:$G$5959,ECT_CapAddBounds!$H$2:$H$5959,_xlfn.CONCAT($B24,$C24),ECT_CapAddBounds!$E$2:$E$5959,"<="&D24)*1000,0) -> 0 | Y24: 5 | Z24: 0.105 | AB24: =1/L24/(1-Q24) -> #N/A | AE24: 0 | AF24: =Y24*Conversions!$D$4 -> 6.1945879 | AG24: =N24-AF24 -> #N/A | AH24: =ROUND(P24/2,0) -> 15 | AI24: =Z24/(1-(1+Z24)^-AH24) -> 0.135248 | AJ24: =AG24/AI24 -> #N/A
A25: 1 | B25: EG_LH | C25: NER | D25: =_xlfn.XLOOKUP(A25,PeriodMap!$A$2:$A$45,PeriodMap!$B$2:$B$45) -> 2023 | E25: HydroRes | F25: conventional_hydroelectric_legacy | G25: INDIA | H25: MW | I25: HYDEL | J25: ELECTRICITY | K25: 8760 | L25: =_xlfn.XLOOKUP(_xlfn.CONCAT($B25,$C25,$D25),ECT_EfficiencyCostMaxAnnualUF!$J$2:$J$12484,ECT_EfficiencyCostMaxAnnualUF!$F$2:$F$12484) -> 1 | M25: =_xlfn.XLOOKUP(_xlfn.CONCAT($B25,$C25,$D25),ECT_EfficiencyCostMaxAnnualUF!$J$2:$J$12484,ECT_EfficiencyCostMaxAnnualUF!$I$2:$I$12484) -> 1 | N25: =_xlfn.XLOOKUP(_xlfn.CONCAT($B25,$C25,$D25),ECT_EfficiencyCostMaxAnnualUF!$J$2:$J$12484,ECT_EfficiencyCostMaxAnnualUF!$G$2:$G$12484)/1000 -> 19.631815 | O25: =_xlfn.XLOOKUP(_xlfn.CONCAT($B25,$C25,$D25),ECT_EfficiencyCostMaxAnnualUF!$J$2:$J$12484,ECT_EfficiencyCostMaxAnnualUF!$H$2:$H$12484) -> 0 | P25: =_xlfn.XLOOKUP(_xlfn.CONCAT($B25,$D25+1),ECT_Lifetime!$D$2:$D$1000,ECT_Lifetime!$C$2:$C$1000) -> 40 | Q25: =_xlfn.XLOOKUP(_xlfn.CONCAT($B25,$D25),ECT_OperationalInfo!$G$2:$G$362,ECT_OperationalInfo!$D$2:$D$362) -> 0.006 | R25: =_xlfn.XLOOKUP(_xlfn.CONCAT($B25,$D25),ECT_OperationalInfo!$G$2:$G$362,ECT_OperationalInfo!$E$2:$E$362) -> 1 | S25: =_xlfn.XLOOKUP(_xlfn.CONCAT($B25,$D25),ECT_OperationalInfo!$G$2:$G$362,ECT_OperationalInfo!$F$2:$F$362) -> 1 | T25: =SUMIF(ECT_LegacyCapacity!$F$2:$F$257,_xlfn.CONCAT($C25,$B25),ECT_LegacyCapacity!$E$2:$E$257)*1000-IFERROR(SUMIFS(ECT_LegacyRetirement!$F$2:$F$2701,ECT_LegacyRetirement!$G$2:$G$2701,_xlfn.CONCAT($B25,$C25),ECT_LegacyRetirement!$E$2:$E$2701,"<="&D25)*1000,0) -> 1842.8253 | U25: =IFERROR(SUMIFS(ECT_CapAddBounds!$F$2:$F$5959,ECT_CapAddBounds!$H$2:$H$5959,_xlfn.CONCAT($B25,$C25),ECT_CapAddBounds!$E$2:$E$5959,"<="&D25)*1000,0) -> 0 | V25: =IFERROR(SUMIFS(ECT_CapAddBounds!$G$2:$G$5959,ECT_CapAddBounds!$H$2:$H$5959,_xlfn.CONCAT($B25,$C25),ECT_CapAddBounds!$E$2:$E$5959,"<="&D25)*1000,0) -> 0 | Y25: 4.4 | Z25: 0.105 | AC25: =L25-Q25 -> 0.994 | AE25: 0 | AF25: =Y25*Conversions!$D$4 -> 5.4512374 | AG25: =N25-AF25 -> 14.180577 | AH25: =ROUND(P25/2,0) -> 20 | AI25: =Z25/(1-(1+Z25)^-AH25) -> 0.12149327 | AJ25: =AG25/AI25 -> 116.71904
A26: 1 | B26: EG_SH | C26: NER | D26: =_xlfn.XLOOKUP(A26,PeriodMap!$A$2:$A$45,PeriodMap!$B$2:$B$45) -> 2023 | E26: HydroRes | F26: conventional_hydroelectric_small_legacy | G26: INDIA | H26: MW | I26: HYDEL | J26: ELECTRICITY | K26: 8760 | L26: =_xlfn.XLOOKUP(_xlfn.CONCAT($B26,$C26,$D26),ECT_EfficiencyCostMaxAnnualUF!$J$2:$J$12484,ECT_EfficiencyCostMaxAnnualUF!$F$2:$F$12484) -> 1 | M26: =_xlfn.XLOOKUP(_xlfn.CONCAT($B26,$C26,$D26),ECT_EfficiencyCostMaxAnnualUF!$J$2:$J$12484,ECT_EfficiencyCostMaxAnnualUF!$I$2:$I$12484) -> 1 | N26: =_xlfn.XLOOKUP(_xlfn.CONCAT($B26,$C26,$D26),ECT_EfficiencyCostMaxAnnualUF!$J$2:$J$12484,ECT_EfficiencyCostMaxAnnualUF!$G$2:$G$12484)/1000 -> 11.825349 | O26: =_xlfn.XLOOKUP(_xlfn.CONCAT($B26,$C26,$D26),ECT_EfficiencyCostMaxAnnualUF!$J$2:$J$12484,ECT_EfficiencyCostMaxAnnualUF!$H$2:$H$12484) -> 0 | P26: =_xlfn.XLOOKUP(_xlfn.CONCAT($B26,$D26+1),ECT_Lifetime!$D$2:$D$1000,ECT_Lifetime!$C$2:$C$1000) -> 35 | Q26: =_xlfn.XLOOKUP(_xlfn.CONCAT($B26,$D26),ECT_OperationalInfo!$G$2:$G$362,ECT_OperationalInfo!$D$2:$D$362) -> 0.01 | R26: =_xlfn.XLOOKUP(_xlfn.CONCAT($B26,$D26),ECT_OperationalInfo!$G$2:$G$362,ECT_OperationalInfo!$E$2:$E$362) -> 1 | S26: =_xlfn.XLOOKUP(_xlfn.CONCAT($B26,$D26),ECT_OperationalInfo!$G$2:$G$362,ECT_OperationalInfo!$F$2:$F$362) -> 1 | T26: =SUMIF(ECT_LegacyCapacity!$F$2:$F$257,_xlfn.CONCAT($C26,$B26),ECT_LegacyCapacity!$E$2:$E$257)*1000-IFERROR(SUMIFS(ECT_LegacyRetirement!$F$2:$F$2701,ECT_LegacyRetirement!$G$2:$G$2701,_xlfn.CONCAT($B26,$C26),ECT_LegacyRetirement!$E$2:$E$2701,"<="&D26)*1000,0) -> 299.35 | U26: =IFERROR(SUMIFS(ECT_CapAddBounds!$F$2:$F$5959,ECT_CapAddBounds!$H$2:$H$5959,_xlfn.CONCAT($B26,$C26),ECT_CapAddBounds!$E$2:$E$5959,"<="&D26)*1000,0) -> 0 | V26: =IFERROR(SUMIFS(ECT_CapAddBounds!$G$2:$G$5959,ECT_CapAddBounds!$H$2:$H$5959,_xlfn.CONCAT($B26,$C26),ECT_CapAddBounds!$E$2:$E$5959,"<="&D26)*1000,0) -> 0 | Y26: =2.4 -> 2.4 | Z26: 0.0835 | AC26: =L26-Q26 -> 0.99 | AE26: 0 | AF26: =Y26*Conversions!$D$4 -> 2.9734022 | AG26: =N26-AF26 -> 8.8519466 | AH26: =ROUND(P26/2,0) -> 18 | AI26: =Z26/(1-(1+Z26)^-AH26) -> 0.10930622 | AJ26: =AG26/AI26 -> 80.983009
A27: 1 | B27: EG_BIOMASS | C27: NER | D27: =_xlfn.XLOOKUP(A27,PeriodMap!$A$2:$A$45,PeriodMap!$B$2:$B$45) -> 2023 | E27: ThermalPower | F27: biomass_legacy | G27: INDIA | H27: MW | I27: BIOMASS_WASTE | J27: ELECTRICITY | K27: 8760 | L27: =_xlfn.XLOOKUP(_xlfn.CONCAT($B27,$C27,$D27),ECT_EfficiencyCostMaxAnnualUF!$J$2:$J$12484,ECT_EfficiencyCostMaxAnnualUF!$F$2:$F$12484) -> 0.2388459 | M27: =_xlfn.XLOOKUP(_xlfn.CONCAT($B27,$C27,$D27),ECT_EfficiencyCostMaxAnnualUF!$J$2:$J$12484,ECT_EfficiencyCostMaxAnnualUF!$I$2:$I$12484) -> 1 | N27: =_xlfn.XLOOKUP(_xlfn.CONCAT($B27,$C27,$D27),ECT_EfficiencyCostMaxAnnualUF!$J$2:$J$12484,ECT_EfficiencyCostMaxAnnualUF!$G$2:$G$12484)/1000 -> 7.7134572 | O27: =_xlfn.XLOOKUP(_xlfn.CONCAT($B27,$C27,$D27),ECT_EfficiencyCostMaxAnnualUF!$J$2:$J$12484,ECT_EfficiencyCostMaxAnnualUF!$H$2:$H$12484) -> 0 | P27: =_xlfn.XLOOKUP(_xlfn.CONCAT($B27,$D27+1),ECT_Lifetime!$D$2:$D$1000,ECT_Lifetime!$C$2:$C$1000) -> 20 | Q27: =_xlfn.XLOOKUP(_xlfn.CONCAT($B27,$D27),ECT_OperationalInfo!$G$2:$G$362,ECT_OperationalInfo!$D$2:$D$362) -> 0.1 | R27: =_xlfn.XLOOKUP(_xlfn.CONCAT($B27,$D27),ECT_OperationalInfo!$G$2:$G$362,ECT_OperationalInfo!$E$2:$E$362) -> 0.06 | S27: =_xlfn.XLOOKUP(_xlfn.CONCAT($B27,$D27),ECT_OperationalInfo!$G$2:$G$362,ECT_OperationalInfo!$F$2:$F$362) -> 0.06 | T27: =SUMIF(ECT_LegacyCapacity!$F$2:$F$257,_xlfn.CONCAT($C27,$B27),ECT_LegacyCapacity!$E$2:$E$257)*1000-IFERROR(SUMIFS(ECT_LegacyRetirement!$F$2:$F$2701,ECT_LegacyRetirement!$G$2:$G$2701,_xlfn.CONCAT($B27,$C27),ECT_LegacyRetirement!$E$2:$E$2701,"<="&D27)*1000,0) -> 15.8 | U27: =IFERROR(SUMIFS(ECT_CapAddBounds!$F$2:$F$5959,ECT_CapAddBounds!$H$2:$H$5959,_xlfn.CONCAT($B27,$C27),ECT_CapAddBounds!$E$2:$E$5959,"<="&D27)*1000,0) -> 0 | V27: =IFERROR(SUMIFS(ECT_CapAddBounds!$G$2:$G$5959,ECT_CapAddBounds!$H$2:$H$5959,_xlfn.CONCAT($B27,$C27),ECT_CapAddBounds!$E$2:$E$5959,"<="&D27)*1000,0) -> 0 | W27: =CarriersTech_characteristics!$G$7 -> 13.648968 | X27: =CarriersTech_characteristics!$H$5*1000 -> 1656436.7 | Y27: 1 | Z27: 0.0835 | AB27: =1/L27/(1-Q27) -> 4.652 | AD27: =X27/(W27*Conversions!$D$2) -> 0.43689545 | AE27: 0 | AF27: =Y27*Conversions!$D$4 -> 1.2389176 | AG27: =N27-AF27 -> 6.4745397 | AH27: =ROUND(P27/2,0) -> 10 | AI27: =Z27/(1-(1+Z27)^-AH27) -> 0.15139063 | AJ27: =AG27/AI27 -> 42.767109
